Workbook

Sheet Read me
A1: TrustLedger analyst workbook (P07-ART-05)
A3: What it is | B3: A formula-driven recomputation of the TrustLedger quality ledger over the published synthetic snapshot tl-20261026-20261026 (dataset hash a9f7a3321b102752dd7aa95b76df14c1d9372103e685e10222959fd6438f27ff, code revision 0b5d686, as-of 2026-10-05T00:00:00Z): 40 datasets, 60 rules (55 active), 574 issues, 160 lineage edges, 30 published metrics, 400 match candidates.
A4: The decision | B4: Which data issues should be fixed first and who is accountable? The workbook shows each dataset's score under both weight versions with the critical override beside it, the issues by class (a claim is not a resolution), mean resolution by team, ownership coverage, lineage, definitions, match precision and timeliness.
A5: Synthetic data | B5: Everything is synthetic (a seeded generator). Observed = what this one draw shows; constructed = what the generator built in on purpose (its designed relationships and injected defects); hypothetical benefits are not claimed.
A6: How to use it | B6: Open the .xlsx in any spreadsheet application. Controls!B3 switches the weight version; Checks!B2 is TRUE when every figure agrees with the Python domain and the golden hand answer. Nothing needs installing to read the cached values.
A7: Recalculation status | B7: openpyxl wrote formulas only; LibreOffice (headless) recalculated the delivered file. Microsoft Excel was NOT run: nothing here was opened or recalculated by Excel (docs/workbook.md).
A8: Sheets | B8: Controls, Checks, Portfolio, Dataset scores, Golden case, Assumptions (read-this-first limits), data sheets (Rule results, Issues, Owners, Datasets, Lineage, Definitions, Matching, Timeliness, Weights), Domain reference (pasted values), SQL results (pasted).
A9: Colour | B9: Blue = typed input or pasted value; black = formula.

Sheet Controls
A1: Controls
A2: Change B3 (w1 or w2): the Selected column of `Dataset scores` follows it. Blue cells are inputs.
A3: Weight version (switch) | B3: w2
A4: As-of (UTC) | B4: 46300
A6: Weights of the selected version
A7: completeness | B7: =INDEX(Weights!$C$4:$C$5,MATCH($B$3,Weights!$A$4:$A$5,0)) -> 0.25
A8: validity | B8: =INDEX(Weights!$D$4:$D$5,MATCH($B$3,Weights!$A$4:$A$5,0)) -> 0.25
A9: uniqueness | B9: =INDEX(Weights!$E$4:$E$5,MATCH($B$3,Weights!$A$4:$A$5,0)) -> 0.25
A10: relationship | B10: =INDEX(Weights!$F$4:$F$5,MATCH($B$3,Weights!$A$4:$A$5,0)) -> 0.15
A11: timeliness | B11: =INDEX(Weights!$G$4:$G$5,MATCH($B$3,Weights!$A$4:$A$5,0)) -> 0.1
A13: Sum of the five weights (must be 1) | B13: =SUM(B7:B11) -> 1
A15: All checks pass (Checks!B2) | B15: =Checks!B2 -> TRUE

Sheet Checks
A1: Checks: TRUE when every comparison with the Python domain and the golden hand answer holds
A2: All checks pass | B2: =AND(Portfolio!E4:E38,'Dataset scores'!U4:U43,'Golden case'!E4:E24,B5,B6) -> TRUE
A4: check | B4: result
A5: Selected column equals the domain's score under the version chosen at Controls!B3 (every dataset) | B5: =SUMPRODUCT(--ISNUMBER('Dataset scores'!L4:L43))=SUMPRODUCT(--ISNUMBER(IF(Controls!B3="w1",'Dataset scores'!S4:S43,'Dataset scores'!T4:T43))) -> TRUE
A6: Every dataset-by-version row of Dataset scores agrees with the domain (rounded to 6 places) | B6: =COUNTIF('Dataset scores'!U4:U43,TRUE())=ROWS('Dataset scores'!U4:U43) -> TRUE

Sheet Portfolio
A1: Portfolio metrics, live formulas against the domain's values
A2: Column B is a formula over the data sheets; C is the domain's value pasted from `Domain reference`; D is the tolerance; E is TRUE when they agree.
A3: measure | B3: workbook (formula) | C3: domain (pasted) | D3: tolerance | E3: check
A4: datasets | B4: =COUNTA(Datasets!A4:A43) -> 40 | C4: 40 | D4: 0 | E4: =ABS(B4-C4)<=D4 -> TRUE
A5: datasets with an accountable owner | B5: =COUNTIF(Datasets!D4:D43,TRUE()) -> 35 | C5: 35 | D5: 0 | E5: =ABS(B5-C5)<=D5 -> TRUE
A6: ownership coverage | B6: =COUNTIF(Datasets!D4:D43,TRUE())/COUNTA(Datasets!A4:A43) -> 0.875 | C6: 0.875 | D6: 5e-07 | E6: =ABS(B6-C6)<=D6 -> TRUE
A7: issues resolved (a successful rerun of the same rule version) | B7: =COUNTIF(Issues!$U$4:$U$577,"resolved") -> 315 | C7: 315 | D7: 0 | E7: =ABS(B7-C7)<=D7 -> TRUE
A8: issues claimed (closed without one) | B8: =COUNTIF(Issues!$U$4:$U$577,"claimed") -> 99 | C8: 99 | D8: 0 | E8: =ABS(B8-C8)<=D8 -> TRUE
A9: issues open | B9: =COUNTIF(Issues!$U$4:$U$577,"open") -> 160 | C9: 160 | D9: 0 | E9: =ABS(B9-C9)<=D9 -> TRUE
A10: mean resolution hours (resolved only) | B10: =AVERAGEIFS(Issues!$V$4:$V$577,Issues!$U$4:$U$577,"resolved") -> 68.271587 | C10: 68.2716 | D10: 5e-05 | E10: =ABS(B10-C10)<=D10 -> TRUE
A11: mean resolution hours, Data Platform | B11: =AVERAGEIFS(Issues!$V$4:$V$577,Issues!$U$4:$U$577,"resolved",Issues!$R$4:$R$577,"Data Platform") -> 34.42018 | C11: 34.4202 | D11: 5e-05 | E11: =ABS(B11-C11)<=D11 -> TRUE
A12: mean resolution hours, all other teams | B12: =AVERAGEIFS(Issues!$V$4:$V$577,Issues!$U$4:$U$577,"resolved",Issues!$R$4:$R$577,"<>Data Platform") -> 86.183254 | C12: 86.1833 | D12: 5e-05 | E12: =ABS(B12-C12)<=D12 -> TRUE
A13: fast team ratio (Data Platform / others) | B13: =AVERAGEIFS(Issues!$V$4:$V$577,Issues!$U$4:$U$577,"resolved",Issues!$R$4:$R$577,"Data Platform")/AVERAGEIFS(Issues!$V$4:$V$577,Issues!$U$4:$U$577,"resolved",Issues!$R$4:$R$577,"<>Data Platform") -> 0.39938362 | C13: 0.399384 | D13: 5e-07 | E13: =ABS(B13-C13)<=D13 -> TRUE
A14: unresolved critical issues | B14: =COUNTIFS(Issues!$E$4:$E$577,"critical",Issues!$U$4:$U$577,"<>resolved") -> 1 | C14: 1 | D14: 0 | E14: =ABS(B14-C14)<=D14 -> TRUE
A15: unresolved high issues | B15: =COUNTIFS(Issues!$E$4:$E$577,"high",Issues!$U$4:$U$577,"<>resolved") -> 171 | C15: 171 | D15: 0 | E15: =ABS(B15-C15)<=D15 -> TRUE
A16: unresolved medium issues | B16: =COUNTIFS(Issues!$E$4:$E$577,"medium",Issues!$U$4:$U$577,"<>resolved") -> 70 | C16: 70 | D16: 0 | E16: =ABS(B16-C16)<=D16 -> TRUE
A17: unresolved low issues | B17: =COUNTIFS(Issues!$E$4:$E$577,"low",Issues!$U$4:$U$577,"<>resolved") -> 17 | C17: 17 | D17: 0 | E17: =ABS(B17-C17)<=D17 -> TRUE
A18: declared lineage edges | B18: =COUNTIF(Lineage!D4:D163,"declared") -> 80 | C18: 80 | D18: 0 | E18: =ABS(B18-C18)<=D18 -> TRUE
A19: observed edges matching a declared pair | B19: =COUNTIF(Lineage!I4:I163,TRUE()) -> 58 | C19: 58 | D19: 0 | E19: =ABS(B19-C19)<=D19 -> TRUE
A20: lineage coverage | B20: =COUNTIF(Lineage!I4:I163,TRUE())/COUNTIF(Lineage!D4:D163,"declared") -> 0.725 | C20: 0.725 | D20: 5e-07 | E20: =ABS(B20-C20)<=D20 -> TRUE
A21: undeclared observed edges | B21: =COUNTIFS(Lineage!D4:D163,"observed",Lineage!G4:G163,FALSE()) -> 12 | C21: 12 | D21: 0 | E21: =ABS(B21-C21)<=D21 -> TRUE
A22: inferred edges (never observed) | B22: =COUNTIF(Lineage!D4:D163,"inferred") -> 10 | C22: 10 | D22: 0 | E22: =ABS(B22-C22)<=D22 -> TRUE
A23: published metrics | B23: =COUNTA(Definitions!A4:A33) -> 30 | C23: 30 | D23: 0 | E23: =ABS(B23-C23)<=D23 -> TRUE
A24: metrics with a complete checklist | B24: =COUNTIF(Definitions!N4:N33,TRUE()) -> 23 | C24: 23 | D24: 0 | E24: =ABS(B24-C24)<=D24 -> TRUE
A25: definition coverage | B25: =COUNTIF(Definitions!N4:N33,TRUE())/COUNTA(Definitions!A4:A33) -> 0.76666667 | C25: 0.766667 | D25: 5e-07 | E25: =ABS(B25-C25)<=D25 -> TRUE
A26: approved merge decisions | B26: =COUNTIF(Matching!B4:B403,"approve") -> 174 | C26: 174 | D26: 0 | E26: =ABS(B26-C26)<=D26 -> TRUE
A27: approved decisions the truth confirms | B27: =COUNTIFS(Matching!B4:B403,"approve",Matching!E4:E403,TRUE()) -> 172 | C27: 172 | D27: 0 | E27: =ABS(B27-C27)<=D27 -> TRUE
A28: match precision (over approvals) | B28: =COUNTIFS(Matching!B4:B403,"approve",Matching!E4:E403,TRUE())/COUNTIF(Matching!B4:B403,"approve") -> 0.98850575 | C28: 0.988506 | D28: 5e-07 | E28: =ABS(B28-C28)<=D28 -> TRUE
A29: reviewed candidates (approved or rejected) | B29: =COUNTIF(Matching!B4:B403,"approve")+COUNTIF(Matching!B4:B403,"reject") -> 220 | C29: 220 | D29: 0 | E29: =ABS(B29-C29)<=D29 -> TRUE
A30: review-correct share (reviewed candidates that are the same entity) | B30: =(COUNTIFS(Matching!B4:B403,"approve",Matching!E4:E403,TRUE())+COUNTIFS(Matching!B4:B403,"reject",Matching!E4:E403,TRUE()))/(COUNTIF(Matching!B4:B403,"approve")+COUNTIF(Matching!B4:B403,"reject")) -> 0.84090909 | C30: 0.840909 | D30: 5e-07 | E30: =ABS(B30-C30)<=D30 -> TRUE
A31: decision-agreement share (reviews that agree with the truth; the analysis's own) | B31: =COUNTIF(Matching!F4:F403,TRUE())/COUNT(Matching!F4:F403) -> 0.93181818 | C31: (no domain value: the contract does not publish it; see the SQL investigation 07)
A32: monitored datasets | B32: =COUNTA(Timeliness!A4:A18) -> 15 | C32: 15 | D32: 0 | E32: =ABS(B32-C32)<=D32 -> TRUE
A33: on time | B33: =COUNTIF(Timeliness!H4:H18,"on_time") -> 10 | C33: 10 | D33: 0 | E33: =ABS(B33-C33)<=D33 -> TRUE
A34: pending (outside the denominator) | B34: =COUNTIF(Timeliness!H4:H18,"pending") -> 0 | C34: 0 | D34: 0 | E34: =ABS(B34-C34)<=D34 -> TRUE
A35: timeliness | B35: =COUNTIF(Timeliness!H4:H18,"on_time")/(COUNTA(Timeliness!A4:A18)-COUNTIF(Timeliness!H4:H18,"pending")) -> 0.66666667 | C35: 0.666667 | D35: 5e-07 | E35: =ABS(B35-C35)<=D35 -> TRUE
A36: critical failures (failing rows of active critical rules) | B36: ='Dataset scores'!B53 -> 2 | C36: 2 | D36: 0 | E36: =ABS(B36-C36)<=D36 -> TRUE
A37: datasets carrying the critical override | B37: ='Dataset scores'!B52 -> 1 | C37: 1 | D37: 0 | E37: =ABS(B37-C37)<=D37 -> TRUE
A38: open critical issues | B38: ='Dataset scores'!B54 -> 1 | C38: 1 | D38: 0 | E38: =ABS(B38-C38)<=D38 -> TRUE

Sheet Dataset scores
A1: Weighted score of every dataset under both weight versions, with the critical override beside it
A2: Dimension score = mean of the dataset's measured rules; weighted = sum(weight x score) / sum(weights of the MEASURED dimensions); a dataset that measures nothing is empty, never 0. Selected = the version chosen at Controls!B3.
A3: dataset_id | B3: completeness | C3: validity | D3: uniqueness | E3: relationship | F3: timeliness | G3: weight_sum_w1 | H3: weighted_w1 | I3: weight_sum_w2 | J3: weighted_w2 | K3: shift (w2 - w1) | L3: selected | M3: critical_failures | N3: open_critical_issues | O3: critical_override | P3: differs | Q3: moved_at_least_0_005 | R3: abs_shift | S3: ref_w1 (domain) | T3: ref_w2 (domain) | U3: check
A4: ds-accounts | B4: =IFERROR(AVERAGEIFS('Rule results'!$I$4:$I$58,'Rule results'!$B$4:$B$58,$A4,'Rule results'!$C$4:$C$58,B$3),"") | C4: =IFERROR(AVERAGEIFS('Rule results'!$I$4:$I$58,'Rule results'!$B$4:$B$58,$A4,'Rule results'!$C$4:$C$58,C$3),"") | D4: =IFERROR(AVERAGEIFS('Rule results'!$I$4:$I$58,'Rule results'!$B$4:$B$58,$A4,'Rule results'!$C$4:$C$58,D$3),"") -> 1 | E4: =IFERROR(AVERAGEIFS('Rule results'!$I$4:$I$58,'Rule results'!$B$4:$B$58,$A4,'Rule results'!$C$4:$C$58,E$3),"") -> 0.95 | F4: =IFERROR(AVERAGEIFS('Rule results'!$I$4:$I$58,'Rule results'!$B$4:$B$58,$A4,'Rule results'!$C$4:$C$58,F$3),"") | G4: =IF(ISNUMBER(B4),Weights!$C$4,0)+IF(ISNUMBER(C4),Weights!$D$4,0)+IF(ISNUMBER(D4),Weights!$E$4,0)+IF(ISNUMBER(E4),Weights!$F$4,0)+IF(ISNUMBER(F4),Weights!$G$4,0) -> 0.25 | H4: =IF(G4=0,"",(IF(ISNUMBER(B4),Weights!$C$4*B4,0)+IF(ISNUMBER(C4),Weights!$D$4*C4,0)+IF(ISNUMBER(D4),Weights!$E$4*D4,0)+IF(ISNUMBER(E4),Weights!$F$4*E4,0)+IF(ISNUMBER(F4),Weights!$G$4*F4,0))/G4) -> 0.99 | I4: =IF(ISNUMBER(B4),Weights!$C$5,0)+IF(ISNUMBER(C4),Weights!$D$5,0)+IF(ISNUMBER(D4),Weights!$E$5,0)+IF(ISNUMBER(E4),Weights!$F$5,0)+IF(ISNUMBER(F4),Weights!$G$5,0) -> 0.4 | J4: =IF(I4=0,"",(IF(ISNUMBER(B4),Weights!$C$5*B4,0)+IF(ISNUMBER(C4),Weights!$D$5*C4,0)+IF(ISNUMBER(D4),Weights!$E$5*D4,0)+IF(ISNUMBER(E4),Weights!$F$5*E4,0)+IF(ISNUMBER(F4),Weights!$G$5*F4,0))/I4) -> 0.98125 | K4: =IF(AND(ISNUMBER(H4),ISNUMBER(J4)),J4-H4,"") -> -0.00875 | L4: =IF(Controls!$B$3="w1",H4,J4) -> 0.98125 | M4: =SUMIFS('Rule results'!$G$4:$G$58,'Rule results'!$B$4:$B$58,$A4,'Rule results'!$D$4:$D$58,"critical") -> 0 | N4: =COUNTIFS(Issues!$B$4:$B$577,$A4,Issues!$E$4:$E$577,"critical",Issues!$U$4:$U$577,"<>resolved") -> 0 | O4: =OR(M4>0,N4>0) -> FALSE | P4: =IF(ISNUMBER(K4),IF(ABS(K4)>0.000000000001,1,0),"") -> 1 | Q4: =IF(ISNUMBER(K4),IF(ABS(K4)>=0.005,1,0),"") -> 1 | R4: =IF(ISNUMBER(K4),ABS(K4),"") -> 0.00875 | S4: ='Domain reference'!B4 -> 0.99 | T4: ='Domain reference'!C4 -> 0.98125 | U4: =AND(IF(ISNUMBER(H4),ISNUMBER(S4),NOT(ISNUMBER(S4))),IF(ISNUMBER(J4),ISNUMBER(T4),NOT(ISNUMBER(T4))),IF(ISNUMBER(H4),ABS(ROUND(H4,6)-S4)<0.0000005,TRUE()),IF(ISNUMBER(J4),ABS(ROUND(J4,6)-T4)<0.0000005,TRUE())) -> TRUE
A5: ds-billing-accounts | B5: =IFERROR(AVERAGEIFS('Rule results'!$I$4:$I$58,'Rule results'!$B$4:$B$58,$A5,'Rule results'!$C$4:$C$58,B$3),"") | C5: =IFERROR(AVERAGEIFS('Rule results'!$I$4:$I$58,'Rule results'!$B$4:$B$58,$A5,'Rule results'!$C$4:$C$58,C$3),"") | D5: =IFERROR(AVERAGEIFS('Rule results'!$I$4:$I$58,'Rule results'!$B$4:$B$58,$A5,'Rule results'!$C$4:$C$58,D$3),"") | E5: =IFERROR(AVERAGEIFS('Rule results'!$I$4:$I$58,'Rule results'!$B$4:$B$58,$A5,'Rule results'!$C$4:$C$58,E$3),"") | F5: =IFERROR(AVERAGEIFS('Rule results'!$I$4:$I$58,'Rule results'!$B$4:$B$58,$A5,'Rule results'!$C$4:$C$58,F$3),"") | G5: =IF(ISNUMBER(B5),Weights!$C$4,0)+IF(ISNUMBER(C5),Weights!$D$4,0)+IF(ISNUMBER(D5),Weights!$E$4,0)+IF(ISNUMBER(E5),Weights!$F$4,0)+IF(ISNUMBER(F5),Weights!$G$4,0) -> 0 | H5: =IF(G5=0,"",(IF(ISNUMBER(B5),Weights!$C$4*B5,0)+IF(ISNUMBER(C5),Weights!$D$4*C5,0)+IF(ISNUMBER(D5),Weights!$E$4*D5,0)+IF(ISNUMBER(E5),Weights!$F$4*E5,0)+IF(ISNUMBER(F5),Weights!$G$4*F5,0))/G5) | I5: =IF(ISNUMBER(B5),Weights!$C$5,0)+IF(ISNUMBER(C5),Weights!$D$5,0)+IF(ISNUMBER(D5),Weights!$E$5,0)+IF(ISNUMBER(E5),Weights!$F$5,0)+IF(ISNUMBER(F5),Weights!$G$5,0) -> 0 | J5: =IF(I5=0,"",(IF(ISNUMBER(B5),Weights!$C$5*B5,0)+IF(ISNUMBER(C5),Weights!$D$5*C5,0)+IF(ISNUMBER(D5),Weights!$E$5*D5,0)+IF(ISNUMBER(E5),Weights!$F$5*E5,0)+IF(ISNUMBER(F5),Weights!$G$5*F5,0))/I5) | K5: =IF(AND(ISNUMBER(H5),ISNUMBER(J5)),J5-H5,"") | L5: =IF(Controls!$B$3="w1",H5,J5) | M5: =SUMIFS('Rule results'!$G$4:$G$58,'Rule results'!$B$4:$B$58,$A5,'Rule results'!$D$4:$D$58,"critical") -> 0 | N5: =COUNTIFS(Issues!$B$4:$B$577,$A5,Issues!$E$4:$E$577,"critical",Issues!$U$4:$U$577,"<>resolved") -> 0 | O5: =OR(M5>0,N5>0) -> FALSE | P5: =IF(ISNUMBER(K5),IF(ABS(K5)>0.000000000001,1,0),"") | Q5: =IF(ISNUMBER(K5),IF(ABS(K5)>=0.005,1,0),"") | R5: =IF(ISNUMBER(K5),ABS(K5),"") | S5: ='Domain reference'!B5 -> not measured | T5: ='Domain reference'!C5 -> not measured | U5: =AND(IF(ISNUMBER(H5),ISNUMBER(S5),NOT(ISNUMBER(S5))),IF(ISNUMBER(J5),ISNUMBER(T5),NOT(ISNUMBER(T5))),IF(ISNUMBER(H5),ABS(ROUND(H5,6)-S5)<0.0000005,TRUE()),IF(ISNUMBER(J5),ABS(ROUND(J5,6)-T5)<0.0000005,TRUE())) -> TRUE
A6: ds-campaigns | B6: =IFERROR(AVERAGEIFS('Rule results'!$I$4:$I$58,'Rule results'!$B$4:$B$58,$A6,'Rule results'!$C$4:$C$58,B$3),"") | C6: =IFERROR(AVERAGEIFS('Rule results'!$I$4:$I$58,'Rule results'!$B$4:$B$58,$A6,'Rule results'!$C$4:$C$58,C$3),"") | D6: =IFERROR(AVERAGEIFS('Rule results'!$I$4:$I$58,'Rule results'!$B$4:$B$58,$A6,'Rule results'!$C$4:$C$58,D$3),"") | E6: =IFERROR(AVERAGEIFS('Rule results'!$I$4:$I$58,'Rule results'!$B$4:$B$58,$A6,'Rule results'!$C$4:$C$58,E$3),"") | F6: =IFERROR(AVERAGEIFS('Rule results'!$I$4:$I$58,'Rule results'!$B$4:$B$58,$A6,'Rule results'!$C$4:$C$58,F$3),"") | G6: =IF(ISNUMBER(B6),Weights!$C$4,0)+IF(ISNUMBER(C6),Weights!$D$4,0)+IF(ISNUMBER(D6),Weights!$E$4,0)+IF(ISNUMBER(E6),Weights!$F$4,0)+IF(ISNUMBER(F6),Weights!$G$4,0) -> 0 | H6: =IF(G6=0,"",(IF(ISNUMBER(B6),Weights!$C$4*B6,0)+IF(ISNUMBER(C6),Weights!$D$4*C6,0)+IF(ISNUMBER(D6),Weights!$E$4*D6,0)+IF(ISNUMBER(E6),Weights!$F$4*E6,0)+IF(ISNUMBER(F6),Weights!$G$4*F6,0))/G6) | I6: =IF(ISNUMBER(B6),Weights!$C$5,0)+IF(ISNUMBER(C6),Weights!$D$5,0)+IF(ISNUMBER(D6),Weights!$E$5,0)+IF(ISNUMBER(E6),Weights!$F$5,0)+IF(ISNUMBER(F6),Weights!$G$5,0) -> 0 | J6: =IF(I6=0,"",(IF(ISNUMBER(B6),Weights!$C$5*B6,0)+IF(ISNUMBER(C6),Weights!$D$5*C6,0)+IF(ISNUMBER(D6),Weights!$E$5*D6,0)+IF(ISNUMBER(E6),Weights!$F$5*E6,0)+IF(ISNUMBER(F6),Weights!$G$5*F6,0))/I6) | K6: =IF(AND(ISNUMBER(H6),ISNUMBER(J6)),J6-H6,"") | L6: =IF(Controls!$B$3="w1",H6,J6) | M6: =SUMIFS('Rule results'!$G$4:$G$58,'Rule results'!$B$4:$B$58,$A6,'Rule results'!$D$4:$D$58,"critical") -> 0 | N6: =COUNTIFS(Issues!$B$4:$B$577,$A6,Issues!$E$4:$E$577,"critical",Issues!$U$4:$U$577,"<>resolved") -> 0 | O6: =OR(M6>0,N6>0) -> FALSE | P6: =IF(ISNUMBER(K6),IF(ABS(K6)>0.000000000001,1,0),"") | Q6: =IF(ISNUMBER(K6),IF(ABS(K6)>=0.005,1,0),"") | R6: =IF(ISNUMBER(K6),ABS(K6),"") | S6: ='Domain reference'!B6 -> not measured | T6: ='Domain reference'!C6 -> not measured | U6: =AND(IF(ISNUMBER(H6),ISNUMBER(S6),NOT(ISNUMBER(S6))),IF(ISNUMBER(J6),ISNUMBER(T6),NOT(ISNUMBER(T6))),IF(ISNUMBER(H6),ABS(ROUND(H6,6)-S6)<0.0000005,TRUE()),IF(ISNUMBER(J6),ABS(ROUND(J6,6)-T6)<0.0000005,TRUE())) -> TRUE
A7: ds-carriers | B7: =IFERROR(AVERAGEIFS('Rule results'!$I$4:$I$58,'Rule results'!$B$4:$B$58,$A7,'Rule results'!$C$4:$C$58,B$3),"") | C7: =IFERROR(AVERAGEIFS('Rule results'!$I$4:$I$58,'Rule results'!$B$4:$B$58,$A7,'Rule results'!$C$4:$C$58,C$3),"") -> 0.96638655 | D7: =IFERROR(AVERAGEIFS('Rule results'!$I$4:$I$58,'Rule results'!$B$4:$B$58,$A7,'Rule results'!$C$4:$C$58,D$3),"") | E7: =IFERROR(AVERAGEIFS('Rule results'!$I$4:$I$58,'Rule results'!$B$4:$B$58,$A7,'Rule results'!$C$4:$C$58,E$3),"") | F7: =IFERROR(AVERAGEIFS('Rule results'!$I$4:$I$58,'Rule results'!$B$4:$B$58,$A7,'Rule results'!$C$4:$C$58,F$3),"") | G7: =IF(ISNUMBER(B7),Weights!$C$4,0)+IF(ISNUMBER(C7),Weights!$D$4,0)+IF(ISNUMBER(D7),Weights!$E$4,0)+IF(ISNUMBER(E7),Weights!$F$4,0)+IF(ISNUMBER(F7),Weights!$G$4,0) -> 0.3 | H7: =IF(G7=0,"",(IF(ISNUMBER(B7),Weights!$C$4*B7,0)+IF(ISNUMBER(C7),Weights!$D$4*C7,0)+IF(ISNUMBER(D7),Weights!$E$4*D7,0)+IF(ISNUMBER(E7),Weights!$F$4*E7,0)+IF(ISNUMBER(F7),Weights!$G$4*F7,0))/G7) -> 0.96638655 | I7: =IF(ISNUMBER(B7),Weights!$C$5,0)+IF(ISNUMBER(C7),Weights!$D$5,0)+IF(ISNUMBER(D7),Weights!$E$5,0)+IF(ISNUMBER(E7),Weights!$F$5,0)+IF(ISNUMBER(F7),Weights!$G$5,0) -> 0.25 | J7: =IF(I7=0,"",(IF(ISNUMBER(B7),Weights!$C$5*B7,0)+IF(ISNUMBER(C7),Weights!$D$5*C7,0)+IF(ISNUMBER(D7),Weights!$E$5*D7,0)+IF(ISNUMBER(E7),Weights!$F$5*E7,0)+IF(ISNUMBER(F7),Weights!$G$5*F7,0))/I7) -> 0.96638655 | K7: =IF(AND(ISNUMBER(H7),ISNUMBER(J7)),J7-H7,"") -> 0 | L7: =IF(Controls!$B$3="w1",H7,J7) -> 0.96638655 | M7: =SUMIFS('Rule results'!$G$4:$G$58,'Rule results'!$B$4:$B$58,$A7,'Rule results'!$D$4:$D$58,"critical") -> 0 | N7: =COUNTIFS(Issues!$B$4:$B$577,$A7,Issues!$E$4:$E$577,"critical",Issues!$U$4:$U$577,"<>resolved") -> 0 | O7: =OR(M7>0,N7>0) -> FALSE | P7: =IF(ISNUMBER(K7),IF(ABS(K7)>0.000000000001,1,0),"") -> 0 | Q7: =IF(ISNUMBER(K7),IF(ABS(K7)>=0.005,1,0),"") -> 0 | R7: =IF(ISNUMBER(K7),ABS(K7),"") -> 0 | S7: ='Domain reference'!B7 -> 0.966387 | T7: ='Domain reference'!C7 -> 0.966387 | U7: =AND(IF(ISNUMBER(H7),ISNUMBER(S7),NOT(ISNUMBER(S7))),IF(ISNUMBER(J7),ISNUMBER(T7),NOT(ISNUMBER(T7))),IF(ISNUMBER(H7),ABS(ROUND(H7,6)-S7)<0.0000005,TRUE()),IF(ISNUMBER(J7),ABS(ROUND(J7,6)-T7)<0.0000005,TRUE())) -> TRUE
A8: ds-consent-records | B8: =IFERROR(AVERAGEIFS('Rule results'!$I$4:$I$58,'Rule results'!$B$4:$B$58,$A8,'Rule results'!$C$4:$C$58,B$3),"") -> 0.90588235 | C8: =IFERROR(AVERAGEIFS('Rule results'!$I$4:$I$58,'Rule results'!$B$4:$B$58,$A8,'Rule results'!$C$4:$C$58,C$3),"") | D8: =IFERROR(AVERAGEIFS('Rule results'!$I$4:$I$58,'Rule results'!$B$4:$B$58,$A8,'Rule results'!$C$4:$C$58,D$3),"") | E8: =IFERROR(AVERAGEIFS('Rule results'!$I$4:$I$58,'Rule results'!$B$4:$B$58,$A8,'Rule results'!$C$4:$C$58,E$3),"") | F8: =IFERROR(AVERAGEIFS('Rule results'!$I$4:$I$58,'Rule results'!$B$4:$B$58,$A8,'Rule results'!$C$4:$C$58,F$3),"") -> 1 | G8: =IF(ISNUMBER(B8),Weights!$C$4,0)+IF(ISNUMBER(C8),Weights!$D$4,0)+IF(ISNUMBER(D8),Weights!$E$4,0)+IF(ISNUMBER(E8),Weights!$F$4,0)+IF(ISNUMBER(F8),Weights!$G$4,0) -> 0.45 | H8: =IF(G8=0,"",(IF(ISNUMBER(B8),Weights!$C$4*B8,0)+IF(ISNUMBER(C8),Weights!$D$4*C8,0)+IF(ISNUMBER(D8),Weights!$E$4*D8,0)+IF(ISNUMBER(E8),Weights!$F$4*E8,0)+IF(ISNUMBER(F8),Weights!$G$4*F8,0))/G8) -> 0.91633987 | I8: =IF(ISNUMBER(B8),Weights!$C$5,0)+IF(ISNUMBER(C8),Weights!$D$5,0)+IF(ISNUMBER(D8),Weights!$E$5,0)+IF(ISNUMBER(E8),Weights!$F$5,0)+IF(ISNUMBER(F8),Weights!$G$5,0) -> 0.35 | J8: =IF(I8=0,"",(IF(ISNUMBER(B8),Weights!$C$5*B8,0)+IF(ISNUMBER(C8),Weights!$D$5*C8,0)+IF(ISNUMBER(D8),Weights!$E$5*D8,0)+IF(ISNUMBER(E8),Weights!$F$5*E8,0)+IF(ISNUMBER(F8),Weights!$G$5*F8,0))/I8) -> 0.93277311 | K8: =IF(AND(ISNUMBER(H8),ISNUMBER(J8)),J8-H8,"") -> 0.01643324 | L8: =IF(Controls!$B$3="w1",H8,J8) -> 0.93277311 | M8: =SUMIFS('Rule results'!$G$4:$G$58,'Rule results'!$B$4:$B$58,$A8,'Rule results'!$D$4:$D$58,"critical") -> 0 | N8: =COUNTIFS(Issues!$B$4:$B$577,$A8,Issues!$E$4:$E$577,"critical",Issues!$U$4:$U$577,"<>resolved") -> 0 | O8: =OR(M8>0,N8>0) -> FALSE | P8: =IF(ISNUMBER(K8),IF(ABS(K8)>0.000000000001,1,0),"") -> 1 | Q8: =IF(ISNUMBER(K8),IF(ABS(K8)>=0.005,1,0),"") -> 1 | R8: =IF(ISNUMBER(K8),ABS(K8),"") -> 0.01643324 | S8: ='Domain reference'!B8 -> 0.91634 | T8: ='Domain reference'!C8 -> 0.932773 | U8: =AND(IF(ISNUMBER(H8),ISNUMBER(S8),NOT(ISNUMBER(S8))),IF(ISNUMBER(J8),ISNUMBER(T8),NOT(ISNUMBER(T8))),IF(ISNUMBER(H8),ABS(ROUND(H8,6)-S8)<0.0000005,TRUE()),IF(ISNUMBER(J8),ABS(ROUND(J8,6)-T8)<0.0000005,TRUE())) -> TRUE
A9: ds-contacts | B9: =IFERROR(AVERAGEIFS('Rule results'!$I$4:$I$58,'Rule results'!$B$4:$B$58,$A9,'Rule results'!$C$4:$C$58,B$3),"") -> 0.98214286 | C9: =IFERROR(AVERAGEIFS('Rule results'!$I$4:$I$58,'Rule results'!$B$4:$B$58,$A9,'Rule results'!$C$4:$C$58,C$3),"") | D9: =IFERROR(AVERAGEIFS('Rule results'!$I$4:$I$58,'Rule results'!$B$4:$B$58,$A9,'Rule results'!$C$4:$C$58,D$3),"") | E9: =IFERROR(AVERAGEIFS('Rule results'!$I$4:$I$58,'Rule results'!$B$4:$B$58,$A9,'Rule results'!$C$4:$C$58,E$3),"") -> 1 | F9: =IFERROR(AVERAGEIFS('Rule results'!$I$4:$I$58,'Rule results'!$B$4:$B$58,$A9,'Rule results'!$C$4:$C$58,F$3),"") | G9: =IF(ISNUMBER(B9),Weights!$C$4,0)+IF(ISNUMBER(C9),Weights!$D$4,0)+IF(ISNUMBER(D9),Weights!$E$4,0)+IF(ISNUMBER(E9),Weights!$F$4,0)+IF(ISNUMBER(F9),Weights!$G$4,0) -> 0.45 | H9: =IF(G9=0,"",(IF(ISNUMBER(B9),Weights!$C$4*B9,0)+IF(ISNUMBER(C9),Weights!$D$4*C9,0)+IF(ISNUMBER(D9),Weights!$E$4*D9,0)+IF(ISNUMBER(E9),Weights!$F$4*E9,0)+IF(ISNUMBER(F9),Weights!$G$4*F9,0))/G9) -> 0.98412698 | I9: =IF(ISNUMBER(B9),Weights!$C$5,0)+IF(ISNUMBER(C9),Weights!$D$5,0)+IF(ISNUMBER(D9),Weights!$E$5,0)+IF(ISNUMBER(E9),Weights!$F$5,0)+IF(ISNUMBER(F9),Weights!$G$5,0) -> 0.4 | J9: =IF(I9=0,"",(IF(ISNUMBER(B9),Weights!$C$5*B9,0)+IF(ISNUMBER(C9),Weights!$D$5*C9,0)+IF(ISNUMBER(D9),Weights!$E$5*D9,0)+IF(ISNUMBER(E9),Weights!$F$5*E9,0)+IF(ISNUMBER(F9),Weights!$G$5*F9,0))/I9) -> 0.98883929 | K9: =IF(AND(ISNUMBER(H9),ISNUMBER(J9)),J9-H9,"") -> 0.0047123016 | L9: =IF(Controls!$B$3="w1",H9,J9) -> 0.98883929 | M9: =SUMIFS('Rule results'!$G$4:$G$58,'Rule results'!$B$4:$B$58,$A9,'Rule results'!$D$4:$D$58,"critical") -> 0 | N9: =COUNTIFS(Issues!$B$4:$B$577,$A9,Issues!$E$4:$E$577,"critical",Issues!$U$4:$U$577,"<>resolved") -> 0 | O9: =OR(M9>0,N9>0) -> FALSE | P9: =IF(ISNUMBER(K9),IF(ABS(K9)>0.000000000001,1,0),"") -> 1 | Q9: =IF(ISNUMBER(K9),IF(ABS(K9)>=0.005,1,0),"") -> 0 | R9: =IF(ISNUMBER(K9),ABS(K9),"") -> 0.0047123016 | S9: ='Domain reference'!B9 -> 0.984127 | T9: ='Domain reference'!C9 -> 0.988839 | U9: =AND(IF(ISNUMBER(H9),ISNUMBER(S9),NOT(ISNUMBER(S9))),IF(ISNUMBER(J9),ISNUMBER(T9),NOT(ISNUMBER(T9))),IF(ISNUMBER(H9),ABS(ROUND(H9,6)-S9)<0.0000005,TRUE()),IF(ISNUMBER(J9),ABS(ROUND(J9,6)-T9)<0.0000005,TRUE())) -> TRUE
A10: ds-cost-centres | B10: =IFERROR(AVERAGEIFS('Rule results'!$I$4:$I$58,'Rule results'!$B$4:$B$58,$A10,'Rule results'!$C$4:$C$58,B$3),"") | C10: =IFERROR(AVERAGEIFS('Rule results'!$I$4:$I$58,'Rule results'!$B$4:$B$58,$A10,'Rule results'!$C$4:$C$58,C$3),"") | D10: =IFERROR(AVERAGEIFS('Rule results'!$I$4:$I$58,'Rule results'!$B$4:$B$58,$A10,'Rule results'!$C$4:$C$58,D$3),"") -> 0.97435897 | E10: =IFERROR(AVERAGEIFS('Rule results'!$I$4:$I$58,'Rule results'!$B$4:$B$58,$A10,'Rule results'!$C$4:$C$58,E$3),"") | F10: =IFERROR(AVERAGEIFS('Rule results'!$I$4:$I$58,'Rule results'!$B$4:$B$58,$A10,'Rule results'!$C$4:$C$58,F$3),"") | G10: =IF(ISNUMBER(B10),Weights!$C$4,0)+IF(ISNUMBER(C10),Weights!$D$4,0)+IF(ISNUMBER(D10),Weights!$E$4,0)+IF(ISNUMBER(E10),Weights!$F$4,0)+IF(ISNUMBER(F10),Weights!$G$4,0) -> 0.2 | H10: =IF(G10=0,"",(IF(ISNUMBER(B10),Weights!$C$4*B10,0)+IF(ISNUMBER(C10),Weights!$D$4*C10,0)+IF(ISNUMBER(D10),Weights!$E$4*D10,0)+IF(ISNUMBER(E10),Weights!$F$4*E10,0)+IF(ISNUMBER(F10),Weights!$G$4*F10,0))/G10) -> 0.97435897 | I10: =IF(ISNUMBER(B10),Weights!$C$5,0)+IF(ISNUMBER(C10),Weights!$D$5,0)+IF(ISNUMBER(D10),Weights!$E$5,0)+IF(ISNUMBER(E10),Weights!$F$5,0)+IF(ISNUMBER(F10),Weights!$G$5,0) -> 0.25 | J10: =IF(I10=0,"",(IF(ISNUMBER(B10),Weights!$C$5*B10,0)+IF(ISNUMBER(C10),Weights!$D$5*C10,0)+IF(ISNUMBER(D10),Weights!$E$5*D10,0)+IF(ISNUMBER(E10),Weights!$F$5*E10,0)+IF(ISNUMBER(F10),Weights!$G$5*F10,0))/I10) -> 0.97435897 | K10: =IF(AND(ISNUMBER(H10),ISNUMBER(J10)),J10-H10,"") -> 0 | L10: =IF(Controls!$B$3="w1",H10,J10) -> 0.97435897 | M10: =SUMIFS('Rule results'!$G$4:$G$58,'Rule results'!$B$4:$B$58,$A10,'Rule results'!$D$4:$D$58,"critical") -> 0 | N10: =COUNTIFS(Issues!$B$4:$B$577,$A10,Issues!$E$4:$E$577,"critical",Issues!$U$4:$U$577,"<>resolved") -> 0 | O10: =OR(M10>0,N10>0) -> FALSE | P10: =IF(ISNUMBER(K10),IF(ABS(K10)>0.000000000001,1,0),"") -> 0 | Q10: =IF(ISNUMBER(K10),IF(ABS(K10)>=0.005,1,0),"") -> 0 | R10: =IF(ISNUMBER(K10),ABS(K10),"") -> 0 | S10: ='Domain reference'!B10 -> 0.974359 | T10: ='Domain reference'!C10 -> 0.974359 | U10: =AND(IF(ISNUMBER(H10),ISNUMBER(S10),NOT(ISNUMBER(S10))),IF(ISNUMBER(J10),ISNUMBER(T10),NOT(ISNUMBER(T10))),IF(ISNUMBER(H10),ABS(ROUND(H10,6)-S10)<0.0000005,TRUE()),IF(ISNUMBER(J10),ABS(ROUND(J10,6)-T10)<0.0000005,TRUE())) -> TRUE
A11: ds-credit-notes | B11: =IFERROR(AVERAGEIFS('Rule results'!$I$4:$I$58,'Rule results'!$B$4:$B$58,$A11,'Rule results'!$C$4:$C$58,B$3),"") | C11: =IFERROR(AVERAGEIFS('Rule results'!$I$4:$I$58,'Rule results'!$B$4:$B$58,$A11,'Rule results'!$C$4:$C$58,C$3),"") | D11: =IFERROR(AVERAGEIFS('Rule results'!$I$4:$I$58,'Rule results'!$B$4:$B$58,$A11,'Rule results'!$C$4:$C$58,D$3),"") | E11: =IFERROR(AVERAGEIFS('Rule results'!$I$4:$I$58,'Rule results'!$B$4:$B$58,$A11,'Rule results'!$C$4:$C$58,E$3),"") | F11: =IFERROR(AVERAGEIFS('Rule results'!$I$4:$I$58,'Rule results'!$B$4:$B$58,$A11,'Rule results'!$C$4:$C$58,F$3),"") | G11: =IF(ISNUMBER(B11),Weights!$C$4,0)+IF(ISNUMBER(C11),Weights!$D$4,0)+IF(ISNUMBER(D11),Weights!$E$4,0)+IF(ISNUMBER(E11),Weights!$F$4,0)+IF(ISNUMBER(F11),Weights!$G$4,0) -> 0 | H11: =IF(G11=0,"",(IF(ISNUMBER(B11),Weights!$C$4*B11,0)+IF(ISNUMBER(C11),Weights!$D$4*C11,0)+IF(ISNUMBER(D11),Weights!$E$4*D11,0)+IF(ISNUMBER(E11),Weights!$F$4*E11,0)+IF(ISNUMBER(F11),Weights!$G$4*F11,0))/G11) | I11: =IF(ISNUMBER(B11),Weights!$C$5,0)+IF(ISNUMBER(C11),Weights!$D$5,0)+IF(ISNUMBER(D11),Weights!$E$5,0)+IF(ISNUMBER(E11),Weights!$F$5,0)+IF(ISNUMBER(F11),Weights!$G$5,0) -> 0 | J11: =IF(I11=0,"",(IF(ISNUMBER(B11),Weights!$C$5*B11,0)+IF(ISNUMBER(C11),Weights!$D$5*C11,0)+IF(ISNUMBER(D11),Weights!$E$5*D11,0)+IF(ISNUMBER(E11),Weights!$F$5*E11,0)+IF(ISNUMBER(F11),Weights!$G$5*F11,0))/I11) | K11: =IF(AND(ISNUMBER(H11),ISNUMBER(J11)),J11-H11,"") | L11: =IF(Controls!$B$3="w1",H11,J11) | M11: =SUMIFS('Rule results'!$G$4:$G$58,'Rule results'!$B$4:$B$58,$A11,'Rule results'!$D$4:$D$58,"critical") -> 0 | N11: =COUNTIFS(Issues!$B$4:$B$577,$A11,Issues!$E$4:$E$577,"critical",Issues!$U$4:$U$577,"<>resolved") -> 0 | O11: =OR(M11>0,N11>0) -> FALSE | P11: =IF(ISNUMBER(K11),IF(ABS(K11)>0.000000000001,1,0),"") | Q11: =IF(ISNUMBER(K11),IF(ABS(K11)>=0.005,1,0),"") | R11: =IF(ISNUMBER(K11),ABS(K11),"") | S11: ='Domain reference'!B11 -> not measured | T11: ='Domain reference'!C11 -> not measured | U11: =AND(IF(ISNUMBER(H11),ISNUMBER(S11),NOT(ISNUMBER(S11))),IF(ISNUMBER(J11),ISNUMBER(T11),NOT(ISNUMBER(T11))),IF(ISNUMBER(H11),ABS(ROUND(H11,6)-S11)<0.0000005,TRUE()),IF(ISNUMBER(J11),ABS(ROUND(J11,6)-T11)<0.0000005,TRUE())) -> TRUE
A12: ds-crm-activities | B12: =IFERROR(AVERAGEIFS('Rule results'!$I$4:$I$58,'Rule results'!$B$4:$B$58,$A12,'Rule results'!$C$4:$C$58,B$3),"") | C12: =IFERROR(AVERAGEIFS('Rule results'!$I$4:$I$58,'Rule results'!$B$4:$B$58,$A12,'Rule results'!$C$4:$C$58,C$3),"") | D12: =IFERROR(AVERAGEIFS('Rule results'!$I$4:$I$58,'Rule results'!$B$4:$B$58,$A12,'Rule results'!$C$4:$C$58,D$3),"") | E12: =IFERROR(AVERAGEIFS('Rule results'!$I$4:$I$58,'Rule results'!$B$4:$B$58,$A12,'Rule results'!$C$4:$C$58,E$3),"") | F12: =IFERROR(AVERAGEIFS('Rule results'!$I$4:$I$58,'Rule results'!$B$4:$B$58,$A12,'Rule results'!$C$4:$C$58,F$3),"") | G12: =IF(ISNUMBER(B12),Weights!$C$4,0)+IF(ISNUMBER(C12),Weights!$D$4,0)+IF(ISNUMBER(D12),Weights!$E$4,0)+IF(ISNUMBER(E12),Weights!$F$4,0)+IF(ISNUMBER(F12),Weights!$G$4,0) -> 0 | H12: =IF(G12=0,"",(IF(ISNUMBER(B12),Weights!$C$4*B12,0)+IF(ISNUMBER(C12),Weights!$D$4*C12,0)+IF(ISNUMBER(D12),Weights!$E$4*D12,0)+IF(ISNUMBER(E12),Weights!$F$4*E12,0)+IF(ISNUMBER(F12),Weights!$G$4*F12,0))/G12) | I12: =IF(ISNUMBER(B12),Weights!$C$5,0)+IF(ISNUMBER(C12),Weights!$D$5,0)+IF(ISNUMBER(D12),Weights!$E$5,0)+IF(ISNUMBER(E12),Weights!$F$5,0)+IF(ISNUMBER(F12),Weights!$G$5,0) -> 0 | J12: =IF(I12=0,"",(IF(ISNUMBER(B12),Weights!$C$5*B12,0)+IF(ISNUMBER(C12),Weights!$D$5*C12,0)+IF(ISNUMBER(D12),Weights!$E$5*D12,0)+IF(ISNUMBER(E12),Weights!$F$5*E12,0)+IF(ISNUMBER(F12),Weights!$G$5*F12,0))/I12) | K12: =IF(AND(ISNUMBER(H12),ISNUMBER(J12)),J12-H12,"") | L12: =IF(Controls!$B$3="w1",H12,J12) | M12: =SUMIFS('Rule results'!$G$4:$G$58,'Rule results'!$B$4:$B$58,$A12,'Rule results'!$D$4:$D$58,"critical") -> 0 | N12: =COUNTIFS(Issues!$B$4:$B$577,$A12,Issues!$E$4:$E$577,"critical",Issues!$U$4:$U$577,"<>resolved") -> 0 | O12: =OR(M12>0,N12>0) -> FALSE | P12: =IF(ISNUMBER(K12),IF(ABS(K12)>0.000000000001,1,0),"") | Q12: =IF(ISNUMBER(K12),IF(ABS(K12)>=0.005,1,0),"") | R12: =IF(ISNUMBER(K12),ABS(K12),"") | S12: ='Domain reference'!B12 -> not measured | T12: ='Domain reference'!C12 -> not measured | U12: =AND(IF(ISNUMBER(H12),ISNUMBER(S12),NOT(ISNUMBER(S12))),IF(ISNUMBER(J12),ISNUMBER(T12),NOT(ISNUMBER(T12))),IF(ISNUMBER(H12),ABS(ROUND(H12,6)-S12)<0.0000005,TRUE()),IF(ISNUMBER(J12),ABS(ROUND(J12,6)-T12)<0.0000005,TRUE())) -> TRUE
A13: ds-csat-surveys | B13: =IFERROR(AVERAGEIFS('Rule results'!$I$4:$I$58,'Rule results'!$B$4:$B$58,$A13,'Rule results'!$C$4:$C$58,B$3),"") -> 0.93548387 | C13: =IFERROR(AVERAGEIFS('Rule results'!$I$4:$I$58,'Rule results'!$B$4:$B$58,$A13,'Rule results'!$C$4:$C$58,C$3),"") | D13: =IFERROR(AVERAGEIFS('Rule results'!$I$4:$I$58,'Rule results'!$B$4:$B$58,$A13,'Rule results'!$C$4:$C$58,D$3),"") | E13: =IFERROR(AVERAGEIFS('Rule results'!$I$4:$I$58,'Rule results'!$B$4:$B$58,$A13,'Rule results'!$C$4:$C$58,E$3),"") | F13: =IFERROR(AVERAGEIFS('Rule results'!$I$4:$I$58,'Rule results'!$B$4:$B$58,$A13,'Rule results'!$C$4:$C$58,F$3),"") | G13: =IF(ISNUMBER(B13),Weights!$C$4,0)+IF(ISNUMBER(C13),Weights!$D$4,0)+IF(ISNUMBER(D13),Weights!$E$4,0)+IF(ISNUMBER(E13),Weights!$F$4,0)+IF(ISNUMBER(F13),Weights!$G$4,0) -> 0.4 | H13: =IF(G13=0,"",(IF(ISNUMBER(B13),Weights!$C$4*B13,0)+IF(ISNUMBER(C13),Weights!$D$4*C13,0)+IF(ISNUMBER(D13),Weights!$E$4*D13,0)+IF(ISNUMBER(E13),Weights!$F$4*E13,0)+IF(ISNUMBER(F13),Weights!$G$4*F13,0))/G13) -> 0.93548387 | I13: =IF(ISNUMBER(B13),Weights!$C$5,0)+IF(ISNUMBER(C13),Weights!$D$5,0)+IF(ISNUMBER(D13),Weights!$E$5,0)+IF(ISNUMBER(E13),Weights!$F$5,0)+IF(ISNUMBER(F13),Weights!$G$5,0) -> 0.25 | J13: =IF(I13=0,"",(IF(ISNUMBER(B13),Weights!$C$5*B13,0)+IF(ISNUMBER(C13),Weights!$D$5*C13,0)+IF(ISNUMBER(D13),Weights!$E$5*D13,0)+IF(ISNUMBER(E13),Weights!$F$5*E13,0)+IF(ISNUMBER(F13),Weights!$G$5*F13,0))/I13) -> 0.93548387 | K13: =IF(AND(ISNUMBER(H13),ISNUMBER(J13)),J13-H13,"") -> 0 | L13: =IF(Controls!$B$3="w1",H13,J13) -> 0.93548387 | M13: =SUMIFS('Rule results'!$G$4:$G$58,'Rule results'!$B$4:$B$58,$A13,'Rule results'!$D$4:$D$58,"critical") -> 0 | N13: =COUNTIFS(Issues!$B$4:$B$577,$A13,Issues!$E$4:$E$577,"critical",Issues!$U$4:$U$577,"<>resolved") -> 0 | O13: =OR(M13>0,N13>0) -> FALSE | P13: =IF(ISNUMBER(K13),IF(ABS(K13)>0.000000000001,1,0),"") -> 0 | Q13: =IF(ISNUMBER(K13),IF(ABS(K13)>=0.005,1,0),"") -> 0 | R13: =IF(ISNUMBER(K13),ABS(K13),"") -> 0 | S13: ='Domain reference'!B13 -> 0.935484 | T13: ='Domain reference'!C13 -> 0.935484 | U13: =AND(IF(ISNUMBER(H13),ISNUMBER(S13),NOT(ISNUMBER(S13))),IF(ISNUMBER(J13),ISNUMBER(T13),NOT(ISNUMBER(T13))),IF(ISNUMBER(H13),ABS(ROUND(H13,6)-S13)<0.0000005,TRUE()),IF(ISNUMBER(J13),ABS(ROUND(J13,6)-T13)<0.0000005,TRUE())) -> TRUE
A14: ds-customers | B14: =IFERROR(AVERAGEIFS('Rule results'!$I$4:$I$58,'Rule results'!$B$4:$B$58,$A14,'Rule results'!$C$4:$C$58,B$3),"") -> 0.99166667 | C14: =IFERROR(AVERAGEIFS('Rule results'!$I$4:$I$58,'Rule results'!$B$4:$B$58,$A14,'Rule results'!$C$4:$C$58,C$3),"") -> 0.99159664 | D14: =IFERROR(AVERAGEIFS('Rule results'!$I$4:$I$58,'Rule results'!$B$4:$B$58,$A14,'Rule results'!$C$4:$C$58,D$3),"") -> 0.98333333 | E14: =IFERROR(AVERAGEIFS('Rule results'!$I$4:$I$58,'Rule results'!$B$4:$B$58,$A14,'Rule results'!$C$4:$C$58,E$3),"") | F14: =IFERROR(AVERAGEIFS('Rule results'!$I$4:$I$58,'Rule results'!$B$4:$B$58,$A14,'Rule results'!$C$4:$C$58,F$3),"") -> 1 | G14: =IF(ISNUMBER(B14),Weights!$C$4,0)+IF(ISNUMBER(C14),Weights!$D$4,0)+IF(ISNUMBER(D14),Weights!$E$4,0)+IF(ISNUMBER(E14),Weights!$F$4,0)+IF(ISNUMBER(F14),Weights!$G$4,0) -> 0.95 | H14: =IF(G14=0,"",(IF(ISNUMBER(B14),Weights!$C$4*B14,0)+IF(ISNUMBER(C14),Weights!$D$4*C14,0)+IF(ISNUMBER(D14),Weights!$E$4*D14,0)+IF(ISNUMBER(E14),Weights!$F$4*E14,0)+IF(ISNUMBER(F14),Weights!$G$4*F14,0))/G14) -> 0.99032876 | I14: =IF(ISNUMBER(B14),Weights!$C$5,0)+IF(ISNUMBER(C14),Weights!$D$5,0)+IF(ISNUMBER(D14),Weights!$E$5,0)+IF(ISNUMBER(E14),Weights!$F$5,0)+IF(ISNUMBER(F14),Weights!$G$5,0) -> 0.85 | J14: =IF(I14=0,"",(IF(ISNUMBER(B14),Weights!$C$5*B14,0)+IF(ISNUMBER(C14),Weights!$D$5*C14,0)+IF(ISNUMBER(D14),Weights!$E$5*D14,0)+IF(ISNUMBER(E14),Weights!$F$5*E14,0)+IF(ISNUMBER(F14),Weights!$G$5*F14,0))/I14) -> 0.99017548 | K14: =IF(AND(ISNUMBER(H14),ISNUMBER(J14)),J14-H14,"") -> -0.00015328113 | L14: =IF(Controls!$B$3="w1",H14,J14) -> 0.99017548 | M14: =SUMIFS('Rule results'!$G$4:$G$58,'Rule results'!$B$4:$B$58,$A14,'Rule results'!$D$4:$D$58,"critical") -> 2 | N14: =COUNTIFS(Issues!$B$4:$B$577,$A14,Issues!$E$4:$E$577,"critical",Issues!$U$4:$U$577,"<>resolved") -> 1 | O14: =OR(M14>0,N14>0) -> TRUE | P14: =IF(ISNUMBER(K14),IF(ABS(K14)>0.000000000001,1,0),"") -> 1 | Q14: =IF(ISNUMBER(K14),IF(ABS(K14)>=0.005,1,0),"") -> 0 | R14: =IF(ISNUMBER(K14),ABS(K14),"") -> 0.00015328113 | S14: ='Domain reference'!B14 -> 0.990329 | T14: ='Domain reference'!C14 -> 0.990175 | U14: =AND(IF(ISNUMBER(H14),ISNUMBER(S14),NOT(ISNUMBER(S14))),IF(ISNUMBER(J14),ISNUMBER(T14),NOT(ISNUMBER(T14))),IF(ISNUMBER(H14),ABS(ROUND(H14,6)-S14)<0.0000005,TRUE()),IF(ISNUMBER(J14),ABS(ROUND(J14,6)-T14)<0.0000005,TRUE())) -> TRUE
A15: ds-delivery-events | B15: =IFERROR(AVERAGEIFS('Rule results'!$I$4:$I$58,'Rule results'!$B$4:$B$58,$A15,'Rule results'!$C$4:$C$58,B$3),"") | C15: =IFERROR(AVERAGEIFS('Rule results'!$I$4:$I$58,'Rule results'!$B$4:$B$58,$A15,'Rule results'!$C$4:$C$58,C$3),"") -> 0.95588235 | D15: =IFERROR(AVERAGEIFS('Rule results'!$I$4:$I$58,'Rule results'!$B$4:$B$58,$A15,'Rule results'!$C$4:$C$58,D$3),"") | E15: =IFERROR(AVERAGEIFS('Rule results'!$I$4:$I$58,'Rule results'!$B$4:$B$58,$A15,'Rule results'!$C$4:$C$58,E$3),"") | F15: =IFERROR(AVERAGEIFS('Rule results'!$I$4:$I$58,'Rule results'!$B$4:$B$58,$A15,'Rule results'!$C$4:$C$58,F$3),"") | G15: =IF(ISNUMBER(B15),Weights!$C$4,0)+IF(ISNUMBER(C15),Weights!$D$4,0)+IF(ISNUMBER(D15),Weights!$E$4,0)+IF(ISNUMBER(E15),Weights!$F$4,0)+IF(ISNUMBER(F15),Weights!$G$4,0) -> 0.3 | H15: =IF(G15=0,"",(IF(ISNUMBER(B15),Weights!$C$4*B15,0)+IF(ISNUMBER(C15),Weights!$D$4*C15,0)+IF(ISNUMBER(D15),Weights!$E$4*D15,0)+IF(ISNUMBER(E15),Weights!$F$4*E15,0)+IF(ISNUMBER(F15),Weights!$G$4*F15,0))/G15) -> 0.95588235 | I15: =IF(ISNUMBER(B15),Weights!$C$5,0)+IF(ISNUMBER(C15),Weights!$D$5,0)+IF(ISNUMBER(D15),Weights!$E$5,0)+IF(ISNUMBER(E15),Weights!$F$5,0)+IF(ISNUMBER(F15),Weights!$G$5,0) -> 0.25 | J15: =IF(I15=0,"",(IF(ISNUMBER(B15),Weights!$C$5*B15,0)+IF(ISNUMBER(C15),Weights!$D$5*C15,0)+IF(ISNUMBER(D15),Weights!$E$5*D15,0)+IF(ISNUMBER(E15),Weights!$F$5*E15,0)+IF(ISNUMBER(F15),Weights!$G$5*F15,0))/I15) -> 0.95588235 | K15: =IF(AND(ISNUMBER(H15),ISNUMBER(J15)),J15-H15,"") -> 0 | L15: =IF(Controls!$B$3="w1",H15,J15) -> 0.95588235 | M15: =SUMIFS('Rule results'!$G$4:$G$58,'Rule results'!$B$4:$B$58,$A15,'Rule results'!$D$4:$D$58,"critical") -> 0 | N15: =COUNTIFS(Issues!$B$4:$B$577,$A15,Issues!$E$4:$E$577,"critical",Issues!$U$4:$U$577,"<>resolved") -> 0 | O15: =OR(M15>0,N15>0) -> FALSE | P15: =IF(ISNUMBER(K15),IF(ABS(K15)>0.000000000001,1,0),"") -> 0 | Q15: =IF(ISNUMBER(K15),IF(ABS(K15)>=0.005,1,0),"") -> 0 | R15: =IF(ISNUMBER(K15),ABS(K15),"") -> 0 | S15: ='Domain reference'!B15 -> 0.955882 | T15: ='Domain reference'!C15 -> 0.955882 | U15: =AND(IF(ISNUMBER(H15),ISNUMBER(S15),NOT(ISNUMBER(S15))),IF(ISNUMBER(J15),ISNUMBER(T15),NOT(ISNUMBER(T15))),IF(ISNUMBER(H15),ABS(ROUND(H15,6)-S15)<0.0000005,TRUE()),IF(ISNUMBER(J15),ABS(ROUND(J15,6)-T15)<0.0000005,TRUE())) -> TRUE
... A43: ds-web-users | B43: =IFERROR(AVERAGEIFS('Rule results'!$I$4:$I$58,'Rule results'!$B$4:$B$58,$A43,'Rule results'!$C$4:$C$58,B$3),"") -> 0.98484848 | C43: =IFERROR(AVERAGEIFS('Rule results'!$I$4:$I$58,'Rule results'!$B$4:$B$58,$A43,'Rule results'!$C$4:$C$58,C$3),"") | D43: =IFERROR(AVERAGEIFS('Rule results'!$I$4:$I$58,'Rule results'!$B$4:$B$58,$A43,'Rule results'!$C$4:$C$58,D$3),"") -> 0.98484848 | E43: =IFERROR(AVERAGEIFS('Rule results'!$I$4:$I$58,'Rule results'!$B$4:$B$58,$A43,'Rule results'!$C$4:$C$58,E$3),"") | F43: =IFERROR(AVERAGEIFS('Rule results'!$I$4:$I$58,'Rule results'!$B$4:$B$58,$A43,'Rule results'!$C$4:$C$58,F$3),"") -> 1 | G43: =IF(ISNUMBER(B43),Weights!$C$4,0)+IF(ISNUMBER(C43),Weights!$D$4,0)+IF(ISNUMBER(D43),Weights!$E$4,0)+IF(ISNUMBER(E43),Weights!$F$4,0)+IF(ISNUMBER(F43),Weights!$G$4,0) -> 0.65 | H43: =IF(G43=0,"",(IF(ISNUMBER(B43),Weights!$C$4*B43,0)+IF(ISNUMBER(C43),Weights!$D$4*C43,0)+IF(ISNUMBER(D43),Weights!$E$4*D43,0)+IF(ISNUMBER(E43),Weights!$F$4*E43,0)+IF(ISNUMBER(F43),Weights!$G$4*F43,0))/G43) -> 0.98601399 | I43: =IF(ISNUMBER(B43),Weights!$C$5,0)+IF(ISNUMBER(C43),Weights!$D$5,0)+IF(ISNUMBER(D43),Weights!$E$5,0)+IF(ISNUMBER(E43),Weights!$F$5,0)+IF(ISNUMBER(F43),Weights!$G$5,0) -> 0.6 | J43: =IF(I43=0,"",(IF(ISNUMBER(B43),Weights!$C$5*B43,0)+IF(ISNUMBER(C43),Weights!$D$5*C43,0)+IF(ISNUMBER(D43),Weights!$E$5*D43,0)+IF(ISNUMBER(E43),Weights!$F$5*E43,0)+IF(ISNUMBER(F43),Weights!$G$5*F43,0))/I43) -> 0.98737374 | K43: =IF(AND(ISNUMBER(H43),ISNUMBER(J43)),J43-H43,"") -> 0.0013597514 | L43: =IF(Controls!$B$3="w1",H43,J43) -> 0.98737374 | M43: =SUMIFS('Rule results'!$G$4:$G$58,'Rule results'!$B$4:$B$58,$A43,'Rule results'!$D$4:$D$58,"critical") -> 0 | N43: =COUNTIFS(Issues!$B$4:$B$577,$A43,Issues!$E$4:$E$577,"critical",Issues!$U$4:$U$577,"<>resolved") -> 0 | O43: =OR(M43>0,N43>0) -> FALSE | P43: =IF(ISNUMBER(K43),IF(ABS(K43)>0.000000000001,1,0),"") -> 1 | Q43: =IF(ISNUMBER(K43),IF(ABS(K43)>=0.005,1,0),"") -> 0 | R43: =IF(ISNUMBER(K43),ABS(K43),"") -> 0.0013597514 | S43: ='Domain reference'!B43 -> 0.986014 | T43: ='Domain reference'!C43 -> 0.987374 | U43: =AND(IF(ISNUMBER(H43),ISNUMBER(S43),NOT(ISNUMBER(S43))),IF(ISNUMBER(J43),ISNUMBER(T43),NOT(ISNUMBER(T43))),IF(ISNUMBER(H43),ABS(ROUND(H43,6)-S43)<0.0000005,TRUE()),IF(ISNUMBER(J43),ABS(ROUND(J43,6)-T43)<0.0000005,TRUE())) -> TRUE
A45: datasets scored (w1) | B45: =COUNT(H4:H43) -> 29
A46: datasets whose score differs between w1 and w2 | B46: =SUM(P4:P43) -> 13
A47: datasets moved by at least 0.005 | B47: =SUM(Q4:Q43) -> 7
A48: mean score under w1 | B48: =AVERAGE(H4:H43) -> 0.95097983
A49: mean score under w2 | B49: =AVERAGE(J4:J43) -> 0.9431178
A50: largest absolute shift | B50: =MAX(R4:R43) -> 0.16747651
A51: largest move (signed) | B51: =INDEX(K4:K43,MATCH(MAX(R4:R43),R4:R43,0)) -> -0.16747651
A52: datasets carrying the critical override | B52: =COUNTIF(O4:O43,TRUE()) -> 1
A53: critical failures (failing rows of active critical rules) | B53: =SUM(M4:M43) -> 2
A54: open critical issues | B54: =SUM(N4:N43) -> 1

Sheet Golden case
A1: The known answer (P07-GOLD-01) by hand, with formulas, against tests/fixtures/golden/expected.json
A2: 100 eligible customer rows, 5 missing e-mails; 90 of the 95 populated pass the format rule; the critical key rule fails on 2 rows. Blue cells are typed from the fixture; every figure in column C is a formula.
A3: input or figure | B3: value (typed or formula) | C3: formula result | D3: expected.json / hand answer | E3: check
A4: eligible customer rows | B4: 100
A5: missing e-mails (null or trimmed-empty) | B5: 5
A6: passing the format rule | B6: 90
A7: completeness = (eligible - missing) / eligible | C7: =(B4-B5)/B4 -> 0.95 | D7: 0.95 | E7: =ABS(C7-D7)<0.0000005 -> TRUE
A8: populated = eligible - missing | C8: =B4-B5 -> 95 | D8: 95 | E8: =C8=D8 -> TRUE
A9: validity, populated-only = passing / populated (labelled) | C9: =B6/C8 -> 0.94736842 | D9: 0.947368 | E9: =ABS(C9-D9)<0.0000005 -> TRUE
A10: validity, all eligible = passing / eligible (labelled) | C10: =B6/B4 -> 0.9 | D10: 0.9 | E10: =ABS(C10-D10)<0.0000005 -> TRUE
A11: key rows duplicated beyond the first | B11: 2
A12: uniqueness score = (eligible - null keys - duplicate rows) / eligible | C12: =(B4-0-B11)/B4 -> 0.98 | D12: 0.98 | E12: =ABS(C12-D12)<0.0000005 -> TRUE
A13: orders: foreign keys in total | B13: 40
A14: null or empty foreign keys (counted apart, outside the denominator) | B14: 3
A15: matched | B15: 35
A16: relationship integrity = matched / (total - null or empty) | C16: =B15/(B13-B14) -> 0.94594595 | D16: 0.945946 | E16: =ABS(C16-D16)<0.0000005 -> TRUE
A17: timeliness score of ds-customers (refreshed in its window) | B17: 1
A18: (weights come from the Weights sheet; relationship is unmeasured on ds-customers)
A19: weighted score under w1 = sum(w x score) / sum(w of the measured dimensions) | C19: =(Weights!$C$4*C7+Weights!$D$4*C9+Weights!$E$4*C12+Weights!$G$4*B17)/(Weights!$C$4+Weights!$D$4+Weights!$E$4+Weights!$G$4) -> 0.95811634 | D19: 0.958116 | E19: =ABS(C19-D19)<0.0000005 -> TRUE
A20: weighted score under w2 | C20: =(Weights!$C$5*C7+Weights!$D$5*C9+Weights!$E$5*C12+Weights!$G$5*B17)/(Weights!$C$5+Weights!$D$5+Weights!$E$5+Weights!$G$5) -> 0.96393189 | D20: 0.963932 | E20: =ABS(C20-D20)<0.0000005 -> TRUE
A21: critical failures of active critical rules (the key rule) | C21: =B11 -> 2 | D21: 2 | E21: =C21=D21 -> TRUE
A22: critical override (a failing critical rule or an open critical issue) | C22: =OR(C21>0,B24>0) -> TRUE | D22: =TRUE() -> TRUE | E22: =C22=D22 -> TRUE
A23: both scores above 0.95 although the override is set | C23: =AND(C19>0.95,C20>0.95,C22) -> TRUE | D23: =TRUE() -> TRUE | E23: =C23=D23 -> TRUE
A24: open critical issues (typed from the fixture) | B24: 1

Sheet Assumptions
A1: Assumptions and limits
A3: id | B3: statement
A4: A-01 | B4: Weights and checklists are append-only versions (D-07 assumption 4): the weighted score is sum(weight x score) / sum(weights of the measured dimensions) under the version named; unmeasured dimensions leave both sums; null if none is measured. Validity enters as populated-only (D-06).
A5: A-02 | B5: A dimension's score on a dataset is the plain mean of its measured rules' scores (D-07 assumption 5). Critical failures are the failing rows of active critical rules; open critical issues (open, reopened or claimed) are counted apart; either sets the override whatever the score is (D-01, D-06).
A6: A-03 | B6: An issue is resolved only after a successful rerun of the same rule version (D-03); claimed issues are listed apart and never counted as resolved; hours = verifying rerun - first detected_at, 4 places.
A7: A-04 | B7: Ownership coverage counts datasets whose owner is active at the as-of (D-02). Lineage coverage counts distinct observed pairs that match a declared pair over declared pairs; the workbook counts edge rows, which equal distinct pairs per kind on this snapshot (80, 70 and 10; asserted by build_workbook.py). Inferred edges never count as observed.
A8: A-05 | B8: Timeliness: the latest daily occurrence started by the as-of, on time in [occurrence, occurrence + grace), pending while open (outside the denominator), else late (D-10 R7-01).
A9: A-06 | B9: Match precision = approved decisions confirmed by the synthetic truth / approved decisions; the review-correct share = reviewed candidates that are the same true entity / reviewed candidates (D-06). The truth is the verification layer's and is typed only for these two formulas.
A10: W-01 | B10: Observed, constructed and hypothetical results are kept apart: every figure is observed in one draw of a generated world; the designed relationships (DR-01..DR-06) and the twelve injected defects are constructed; no benefit to a real organisation is claimed.
A11: W-02 | B11: TYPED from the independent Python side, not replayed by formulas: the per-rule counts (eligible, populated, failing: pattern matching, duplicate keys and parent lookups over 2,554 rows) and the timeliness occurrence and deadline instants (a daily local time in an IANA zone). Every result is compared with the Python domain after recalculation.
A12: W-03 | B12: Recalculation: openpyxl writes formulas only; the delivered file was recalculated by LibreOffice headless and carries its cached values; Excel was NOT run. fullCalcOnLoad is set so Excel recalculates on open. Functions used: AVERAGEIFS, COUNTIFS, SUMIFS, SUMPRODUCT, INDEX, MATCH, IF, IFERROR, ISNUMBER, AND, OR, ROUND, ABS (no _xlfn functions).
A13: W-04 | B13: The switch changes which weight version the Selected column shows; both versions are always computed and checked, so the check cell does not depend on the switch.
A14: W-05 | B14: The workbook has no macros, no external links and no credentials.

Sheet Rule results
A1: The 55 rules active at the as-of: measured counts (typed) and the score each contributes (formula)
A2: eligible, populated and failing are TYPED from the independent Python side (W-02); score_den = populated for validity else eligible; score = (eligible - failing) / score_den, empty when it measures nothing.
A3: rule_id | B3: dataset_id | C3: dimension | D3: severity | E3: eligible | F3: populated | G3: failing | H3: score_den | I3: score
A4: r-accounts-fk-customer_key | B4: ds-accounts | C4: relationship | D4: high | E4: 100 | G4: 5 | H4: =IF(C4="validity",F4,E4) -> 100 | I4: =IF(H4>0,(E4-G4)/H4,"") -> 0.95
A5: r-accounts-unique-account_key | B5: ds-accounts | C5: uniqueness | D5: medium | E5: 101 | G5: 0 | H5: =IF(C5="validity",F5,E5) -> 101 | I5: =IF(H5>0,(E5-G5)/H5,"") -> 1
A6: r-carriers-valid-carrier_code | B6: ds-carriers | C6: validity | D6: medium | E6: 119 | F6: 119 | G6: 4 | H6: =IF(C6="validity",F6,E6) -> 119 | I6: =IF(H6>0,(E6-G6)/H6,"") -> 0.96638655
A7: r-consent-records-complete-consent_flag | B7: ds-consent-records | C7: completeness | D7: high | E7: 85 | F7: 77 | G7: 8 | H7: =IF(C7="validity",F7,E7) -> 85 | I7: =IF(H7>0,(E7-G7)/H7,"") -> 0.90588235
A8: r-consent-records-fresh | B8: ds-consent-records | C8: timeliness | D8: medium | E8: 1 | G8: 0 | H8: =IF(C8="validity",F8,E8) -> 1 | I8: =IF(H8>0,(E8-G8)/H8,"") -> 1
A9: r-contacts-complete-email | B9: ds-contacts | C9: completeness | D9: high | E9: 56 | F9: 55 | G9: 1 | H9: =IF(C9="validity",F9,E9) -> 56 | I9: =IF(H9>0,(E9-G9)/H9,"") -> 0.98214286
A10: r-contacts-fk-customer_key | B10: ds-contacts | C10: relationship | D10: low | E10: 54 | G10: 0 | H10: =IF(C10="validity",F10,E10) -> 54 | I10: =IF(H10>0,(E10-G10)/H10,"") -> 1
A11: r-cost-centres-unique-cost_centre_code | B11: ds-cost-centres | C11: uniqueness | D11: medium | E11: 78 | G11: 2 | H11: =IF(C11="validity",F11,E11) -> 78 | I11: =IF(H11>0,(E11-G11)/H11,"") -> 0.97435897
A12: r-csat-surveys-complete-score | B12: ds-csat-surveys | C12: completeness | D12: low | E12: 124 | F12: 116 | G12: 8 | H12: =IF(C12="validity",F12,E12) -> 124 | I12: =IF(H12>0,(E12-G12)/H12,"") -> 0.93548387
A13: r-customers-complete-email | B13: ds-customers | C13: completeness | D13: high | E13: 120 | F13: 119 | G13: 1 | H13: =IF(C13="validity",F13,E13) -> 120 | I13: =IF(H13>0,(E13-G13)/H13,"") -> 0.99166667
A14: r-customers-fresh | B14: ds-customers | C14: timeliness | D14: medium | E14: 1 | G14: 0 | H14: =IF(C14="validity",F14,E14) -> 1 | I14: =IF(H14>0,(E14-G14)/H14,"") -> 1
A15: r-customers-unique-customer_key | B15: ds-customers | C15: uniqueness | D15: critical | E15: 120 | G15: 2 | H15: =IF(C15="validity",F15,E15) -> 120 | I15: =IF(H15>0,(E15-G15)/H15,"") -> 0.98333333
A16: r-customers-valid-email | B16: ds-customers | C16: validity | D16: medium | E16: 120 | F16: 119 | G16: 2 | H16: =IF(C16="validity",F16,E16) -> 119 | I16: =IF(H16>0,(E16-G16)/H16,"") -> 0.99159664
A17: r-delivery-events-valid-event_ref | B17: ds-delivery-events | C17: validity | D17: high | E17: 68 | F17: 68 | G17: 3 | H17: =IF(C17="validity",F17,E17) -> 68 | I17: =IF(H17>0,(E17-G17)/H17,"") -> 0.95588235
A18: r-employees-valid-work_email | B18: ds-employees | C18: validity | D18: high | E18: 39 | F18: 39 | G18: 0 | H18: =IF(C18="validity",F18,E18) -> 39 | I18: =IF(H18>0,(E18-G18)/H18,"") -> 1
A19: r-inventory-complete-warehouse_code | B19: ds-inventory | C19: completeness | D19: medium | E19: 71 | F19: 71 | G19: 0 | H19: =IF(C19="validity",F19,E19) -> 71 | I19: =IF(H19>0,(E19-G19)/H19,"") -> 1
A20: r-inventory-fresh | B20: ds-inventory | C20: timeliness | D20: high | E20: 1 | G20: 0 | H20: =IF(C20="validity",F20,E20) -> 1 | I20: =IF(H20>0,(E20-G20)/H20,"") -> 1
A21: r-invoices-fk-customer_key | B21: ds-invoices | C21: relationship | D21: low | E21: 81 | G21: 2 | H21: =IF(C21="validity",F21,E21) -> 81 | I21: =IF(H21>0,(E21-G21)/H21,"") -> 0.97530864
A22: r-invoices-fresh | B22: ds-invoices | C22: timeliness | D22: medium | E22: 1 | G22: 0 | H22: =IF(C22="validity",F22,E22) -> 1 | I22: =IF(H22>0,(E22-G22)/H22,"") -> 1
A23: r-invoices-valid-currency | B23: ds-invoices | C23: validity | D23: high | E23: 82 | F23: 82 | G23: 1 | H23: =IF(C23="validity",F23,E23) -> 82 | I23: =IF(H23>0,(E23-G23)/H23,"") -> 0.98780488
A24: r-kb-articles-unique-article_key | B24: ds-kb-articles | C24: uniqueness | D24: medium | E24: 66 | G24: 1 | H24: =IF(C24="validity",F24,E24) -> 66 | I24: =IF(H24>0,(E24-G24)/H24,"") -> 0.98484848
A25: r-ledger-entries-complete-amount | B25: ds-ledger-entries | C25: completeness | D25: high | E25: 54 | F25: 50 | G25: 4 | H25: =IF(C25="validity",F25,E25) -> 54 | I25: =IF(H25>0,(E25-G25)/H25,"") -> 0.92592593
A26: r-ledger-entries-unique-entry_key | B26: ds-ledger-entries | C26: uniqueness | D26: critical | E26: 62 | G26: 0 | H26: =IF(C26="validity",F26,E26) -> 62 | I26: =IF(H26>0,(E26-G26)/H26,"") -> 1
A27: r-ledger-entries-valid-currency | B27: ds-ledger-entries | C27: validity | D27: high | E27: 54 | F27: 54 | G27: 4 | H27: =IF(C27="validity",F27,E27) -> 54 | I27: =IF(H27>0,(E27-G27)/H27,"") -> 0.92592593
A28: r-opportunities-fk-account_key | B28: ds-opportunities | C28: relationship | D28: high | E28: 79 | G28: 9 | H28: =IF(C28="validity",F28,E28) -> 79 | I28: =IF(H28>0,(E28-G28)/H28,"") -> 0.88607595
A29: r-order-lines-fk-order_key | B29: ds-order-lines | C29: relationship | D29: critical | E29: 108 | G29: 0 | H29: =IF(C29="validity",F29,E29) -> 108 | I29: =IF(H29>0,(E29-G29)/H29,"") -> 1
A30: r-order-lines-fk-product_code | B30: ds-order-lines | C30: relationship | D30: low | E30: 106 | G30: 7 | H30: =IF(C30="validity",F30,E30) -> 106 | I30: =IF(H30>0,(E30-G30)/H30,"") -> 0.93396226
A31: r-orders-complete-order_date | B31: ds-orders | C31: completeness | D31: high | E31: 58 | F31: 56 | G31: 2 | H31: =IF(C31="validity",F31,E31) -> 58 | I31: =IF(H31>0,(E31-G31)/H31,"") -> 0.96551724
A32: r-orders-fk-customer_key | B32: ds-orders | C32: relationship | D32: high | E32: 61 | G32: 0 | H32: =IF(C32="validity",F32,E32) -> 61 | I32: =IF(H32>0,(E32-G32)/H32,"") -> 1
A33: r-orders-fresh | B33: ds-orders | C33: timeliness | D33: medium | E33: 1 | G33: 1 | H33: =IF(C33="validity",F33,E33) -> 1 | I33: =IF(H33>0,(E33-G33)/H33,"") -> 0
A34: r-orders-unique-order_key | B34: ds-orders | C34: uniqueness | D34: critical | E34: 66 | G34: 0 | H34: =IF(C34="validity",F34,E34) -> 66 | I34: =IF(H34>0,(E34-G34)/H34,"") -> 1
A35: r-orders-valid-currency | B35: ds-orders | C35: validity | D35: medium | E35: 66 | F35: 66 | G35: 0 | H35: =IF(C35="validity",F35,E35) -> 66 | I35: =IF(H35>0,(E35-G35)/H35,"") -> 1
A36: r-payments-fk-invoice_key | B36: ds-payments | C36: relationship | D36: low | E36: 82 | G36: 1 | H36: =IF(C36="validity",F36,E36) -> 82 | I36: =IF(H36>0,(E36-G36)/H36,"") -> 0.98780488
A37: r-payments-fresh | B37: ds-payments | C37: timeliness | D37: high | E37: 1 | G37: 1 | H37: =IF(C37="validity",F37,E37) -> 1 | I37: =IF(H37>0,(E37-G37)/H37,"") -> 0
A38: r-payments-unique-payment_key | B38: ds-payments | C38: uniqueness | D38: critical | E38: 84 | G38: 0 | H38: =IF(C38="validity",F38,E38) -> 84 | I38: =IF(H38>0,(E38-G38)/H38,"") -> 1
A39: r-products-complete-category | B39: ds-products | C39: completeness | D39: medium | E39: 116 | F39: 114 | G39: 2 | H39: =IF(C39="validity",F39,E39) -> 116 | I39: =IF(H39>0,(E39-G39)/H39,"") -> 0.98275862
A40: r-products-unique-product_code | B40: ds-products | C40: uniqueness | D40: high | E40: 116 | G40: 2 | H40: =IF(C40="validity",F40,E40) -> 116 | I40: =IF(H40>0,(E40-G40)/H40,"") -> 0.98275862
A41: r-purchase-orders-fk-supplier_key | B41: ds-purchase-orders | C41: relationship | D41: high | E41: 45 | G41: 1 | H41: =IF(C41="validity",F41,E41) -> 45 | I41: =IF(H41>0,(E41-G41)/H41,"") -> 0.97777778
A42: r-refunds-fk-payment_key | B42: ds-refunds | C42: relationship | D42: high | E42: 49 | G42: 3 | H42: =IF(C42="validity",F42,E42) -> 49 | I42: =IF(H42>0,(E42-G42)/H42,"") -> 0.93877551
A43: r-returns-complete-reason_code | B43: ds-returns | C43: completeness | D43: medium | E43: 100 | F43: 93 | G43: 7 | H43: =IF(C43="validity",F43,E43) -> 100 | I43: =IF(H43>0,(E43-G43)/H43,"") -> 0.93
A44: r-shipments-fk-order_key | B44: ds-shipments | C44: relationship | D44: medium | E44: 83 | G44: 12 | H44: =IF(C44="validity",F44,E44) -> 83 | I44: =IF(H44>0,(E44-G44)/H44,"") -> 0.85542169
A45: r-shipments-valid-tracking_ref | B45: ds-shipments | C45: validity | D45: medium | E45: 72 | F45: 72 | G45: 11 | H45: =IF(C45="validity",F45,E45) -> 72 | I45: =IF(H45>0,(E45-G45)/H45,"") -> 0.84722222
A46: r-subscriptions-complete-plan_code | B46: ds-subscriptions | C46: completeness | D46: high | E46: 114 | F46: 110 | G46: 4 | H46: =IF(C46="validity",F46,E46) -> 114 | I46: =IF(H46>0,(E46-G46)/H46,"") -> 0.96491228
A47: r-subscriptions-fk-customer_key | B47: ds-subscriptions | C47: relationship | D47: high | E47: 114 | G47: 7 | H47: =IF(C47="validity",F47,E47) -> 114 | I47: =IF(H47>0,(E47-G47)/H47,"") -> 0.93859649
A48: r-suppliers-complete-contact_email | B48: ds-suppliers | C48: completeness | D48: medium | E48: 89 | F48: 84 | G48: 5 | H48: =IF(C48="validity",F48,E48) -> 89 | I48: =IF(H48>0,(E48-G48)/H48,"") -> 0.94382022
A49: r-suppliers-unique-supplier_key | B49: ds-suppliers | C49: uniqueness | D49: high | E49: 89 | G49: 2 | H49: =IF(C49="validity",F49,E49) -> 89 | I49: =IF(H49>0,(E49-G49)/H49,"") -> 0.97752809
A50: r-suppliers-valid-contact_email | B50: ds-suppliers | C50: validity | D50: low | E50: 78 | F50: 75 | G50: 5 | H50: =IF(C50="validity",F50,E50) -> 75 | I50: =IF(H50>0,(E50-G50)/H50,"") -> 0.97333333
A51: r-ticket-events-valid-ticket_key | B51: ds-ticket-events | C51: validity | D51: medium | E51: 70 | F51: 70 | G51: 2 | H51: =IF(C51="validity",F51,E51) -> 70 | I51: =IF(H51>0,(E51-G51)/H51,"") -> 0.97142857
A52: r-tickets-complete-priority | B52: ds-tickets | C52: completeness | D52: medium | E52: 49 | F52: 47 | G52: 2 | H52: =IF(C52="validity",F52,E52) -> 49 | I52: =IF(H52>0,(E52-G52)/H52,"") -> 0.95918367
A53: r-tickets-fresh | B53: ds-tickets | C53: timeliness | D53: high | E53: 1 | G53: 1 | H53: =IF(C53="validity",F53,E53) -> 1 | I53: =IF(H53>0,(E53-G53)/H53,"") -> 0
A54: r-warehouses-valid-postal_code | B54: ds-warehouses | C54: validity | D54: medium | E54: 120 | F54: 120 | G54: 8 | H54: =IF(C54="validity",F54,E54) -> 120 | I54: =IF(H54>0,(E54-G54)/H54,"") -> 0.93333333
A55: r-web-sessions-unique-session_key | B55: ds-web-sessions | C55: uniqueness | D55: high | E55: 70 | G55: 1 | H55: =IF(C55="validity",F55,E55) -> 70 | I55: =IF(H55>0,(E55-G55)/H55,"") -> 0.98571429
A56: r-web-users-complete-email | B56: ds-web-users | C56: completeness | D56: high | E56: 66 | F56: 65 | G56: 1 | H56: =IF(C56="validity",F56,E56) -> 66 | I56: =IF(H56>0,(E56-G56)/H56,"") -> 0.98484848
A57: r-web-users-fresh | B57: ds-web-users | C57: timeliness | D57: high | E57: 1 | G57: 0 | H57: =IF(C57="validity",F57,E57) -> 1 | I57: =IF(H57>0,(E57-G57)/H57,"") -> 1
A58: r-web-users-unique-user_key | B58: ds-web-users | C58: uniqueness | D58: high | E58: 66 | G58: 1 | H58: =IF(C58="validity",F58,E58) -> 66 | I58: =IF(H58>0,(E58-G58)/H58,"") -> 0.98484848

Sheet Issues
A1: 574 issues: the facts of each issue and its verifying run (typed), the class and the hours (formulas)
A2: resolved = closed by the as-of AND the verification run is a rerun, for this issue, of the same rule at the same version, with 0 failures, not before the detection or the latest reopen; claimed = closed otherwise; open = the rest.
A3: issue_id | B3: dataset_id | C3: rule_id | D3: owner_id | E3: severity | F3: status | G3: detected_at | H3: closed_at | I3: verified_at | J3: ver_kind | K3: ver_for_issue | L3: ver_rule_id | M3: ver_rule_version | N3: base_rule_version | O3: ver_failure_count | P3: last_reopen_at | Q3: reopen_cycles | R3: owner_team | S3: closed | T3: verified | U3: class | V3: hours | W3: owner_accountable
A4: iss-0001 | B4: ds-carriers | C4: r-carriers-valid-carrier_code | D4: own-05 | E4: medium | F4: closed | G4: 46216.107 | H4: 46220.114 | I4: 46220.145 | J4: rerun | K4: iss-0001 | L4: r-carriers-valid-carrier_code | M4: 1 | N4: 1 | O4: 0 | Q4: 0 | R4: =INDEX(Owners!$B$4:$B$21,MATCH(D4,Owners!$A$4:$A$21,0)) -> Data Platform | S4: =AND(F4="closed",ISNUMBER(H4),H4<=Controls!$B$4) -> TRUE | T4: =AND(ISNUMBER(I4),I4<=Controls!$B$4,J4="rerun",K4=A4,L4=C4,M4=N4,O4=0,I4>=G4,IF(ISNUMBER(P4),I4>=P4,TRUE())) -> TRUE | U4: =IF(AND(S4,T4),"resolved",IF(S4,"claimed","open")) -> resolved | V4: =ROUND((IF(U4="resolved",I4,IF(U4="claimed",H4,Controls!$B$4))-G4)*24,4) -> 96.9167 | W4: =INDEX(Owners!$E$4:$E$21,MATCH(D4,Owners!$A$4:$A$21,0)) -> TRUE
A5: iss-0002 | B5: ds-contacts | C5: r-contacts-complete-email | D5: own-12 | E5: high | F5: closed | G5: 46216.119 | H5: 46218.958 | I5: 46219.518 | J5: rerun | K5: iss-0002 | L5: r-contacts-complete-email | M5: 1 | N5: 1 | O5: 0 | Q5: 0 | R5: =INDEX(Owners!$B$4:$B$21,MATCH(D5,Owners!$A$4:$A$21,0)) -> Finance Systems | S5: =AND(F5="closed",ISNUMBER(H5),H5<=Controls!$B$4) -> TRUE | T5: =AND(ISNUMBER(I5),I5<=Controls!$B$4,J5="rerun",K5=A5,L5=C5,M5=N5,O5=0,I5>=G5,IF(ISNUMBER(P5),I5>=P5,TRUE())) -> TRUE | U5: =IF(AND(S5,T5),"resolved",IF(S5,"claimed","open")) -> resolved | V5: =ROUND((IF(U5="resolved",I5,IF(U5="claimed",H5,Controls!$B$4))-G5)*24,4) -> 81.5667 | W5: =INDEX(Owners!$E$4:$E$21,MATCH(D5,Owners!$A$4:$A$21,0)) -> FALSE
A6: iss-0003 | B6: ds-products | C6: r-products-complete-category | D6: own-17 | E6: medium | F6: closed | G6: 46216.246 | H6: 46218.61 | I6: 46218.776 | J6: rerun | K6: iss-0003 | L6: r-products-complete-category | M6: 1 | N6: 1 | O6: 0 | Q6: 0 | R6: =INDEX(Owners!$B$4:$B$21,MATCH(D6,Owners!$A$4:$A$21,0)) -> Support Operations | S6: =AND(F6="closed",ISNUMBER(H6),H6<=Controls!$B$4) -> TRUE | T6: =AND(ISNUMBER(I6),I6<=Controls!$B$4,J6="rerun",K6=A6,L6=C6,M6=N6,O6=0,I6>=G6,IF(ISNUMBER(P6),I6>=P6,TRUE())) -> TRUE | U6: =IF(AND(S6,T6),"resolved",IF(S6,"claimed","open")) -> resolved | V6: =ROUND((IF(U6="resolved",I6,IF(U6="claimed",H6,Controls!$B$4))-G6)*24,4) -> 60.7167 | W6: =INDEX(Owners!$E$4:$E$21,MATCH(D6,Owners!$A$4:$A$21,0)) -> TRUE
A7: iss-0004 | B7: ds-customers | C7: r-customers-valid-email | D7: own-07 | E7: medium | F7: closed | G7: 46217.092 | H7: 46217.723 | N7: 1 | Q7: 0 | R7: =INDEX(Owners!$B$4:$B$21,MATCH(D7,Owners!$A$4:$A$21,0)) -> Customer Data | S7: =AND(F7="closed",ISNUMBER(H7),H7<=Controls!$B$4) -> TRUE | T7: =AND(ISNUMBER(I7),I7<=Controls!$B$4,J7="rerun",K7=A7,L7=C7,M7=N7,O7=0,I7>=G7,IF(ISNUMBER(P7),I7>=P7,TRUE())) -> FALSE | U7: =IF(AND(S7,T7),"resolved",IF(S7,"claimed","open")) -> claimed | V7: =ROUND((IF(U7="resolved",I7,IF(U7="claimed",H7,Controls!$B$4))-G7)*24,4) -> 15.1333 | W7: =INDEX(Owners!$E$4:$E$21,MATCH(D7,Owners!$A$4:$A$21,0)) -> TRUE
A8: iss-0005 | B8: ds-refunds | C8: r-refunds-fk-payment_key | D8: own-18 | E8: high | F8: closed | G8: 46217.16 | H8: 46219.298 | I8: 46219.386 | J8: rerun | K8: iss-0005 | L8: r-refunds-fk-payment_key | M8: 1 | N8: 1 | O8: 0 | Q8: 0 | R8: =INDEX(Owners!$B$4:$B$21,MATCH(D8,Owners!$A$4:$A$21,0)) -> Support Operations | S8: =AND(F8="closed",ISNUMBER(H8),H8<=Controls!$B$4) -> TRUE | T8: =AND(ISNUMBER(I8),I8<=Controls!$B$4,J8="rerun",K8=A8,L8=C8,M8=N8,O8=0,I8>=G8,IF(ISNUMBER(P8),I8>=P8,TRUE())) -> TRUE | U8: =IF(AND(S8,T8),"resolved",IF(S8,"claimed","open")) -> resolved | V8: =ROUND((IF(U8="resolved",I8,IF(U8="claimed",H8,Controls!$B$4))-G8)*24,4) -> 53.4167 | W8: =INDEX(Owners!$E$4:$E$21,MATCH(D8,Owners!$A$4:$A$21,0)) -> TRUE
A9: iss-0006 | B9: ds-ledger-entries | C9: r-ledger-entries-valid-currency | D9: own-12 | E9: high | F9: closed | G9: 46217.215 | H9: 46218.948 | I9: 46219.487 | J9: rerun | K9: iss-0006 | L9: r-ledger-entries-valid-currency | M9: 1 | N9: 1 | O9: 0 | Q9: 0 | R9: =INDEX(Owners!$B$4:$B$21,MATCH(D9,Owners!$A$4:$A$21,0)) -> Finance Systems | S9: =AND(F9="closed",ISNUMBER(H9),H9<=Controls!$B$4) -> TRUE | T9: =AND(ISNUMBER(I9),I9<=Controls!$B$4,J9="rerun",K9=A9,L9=C9,M9=N9,O9=0,I9>=G9,IF(ISNUMBER(P9),I9>=P9,TRUE())) -> TRUE | U9: =IF(AND(S9,T9),"resolved",IF(S9,"claimed","open")) -> resolved | V9: =ROUND((IF(U9="resolved",I9,IF(U9="claimed",H9,Controls!$B$4))-G9)*24,4) -> 54.5333 | W9: =INDEX(Owners!$E$4:$E$21,MATCH(D9,Owners!$A$4:$A$21,0)) -> FALSE
A10: iss-0007 | B10: ds-contacts | C10: r-contacts-complete-email | D10: own-12 | E10: high | F10: closed | G10: 46218.119 | H10: 46220.198 | I10: 46220.253 | J10: rerun | K10: iss-0007 | L10: r-contacts-complete-email | M10: 1 | N10: 1 | O10: 0 | Q10: 0 | R10: =INDEX(Owners!$B$4:$B$21,MATCH(D10,Owners!$A$4:$A$21,0)) -> Finance Systems | S10: =AND(F10="closed",ISNUMBER(H10),H10<=Controls!$B$4) -> TRUE | T10: =AND(ISNUMBER(I10),I10<=Controls!$B$4,J10="rerun",K10=A10,L10=C10,M10=N10,O10=0,I10>=G10,IF(ISNUMBER(P10),I10>=P10,TRUE())) -> TRUE | U10: =IF(AND(S10,T10),"resolved",IF(S10,"claimed","open")) -> resolved | V10: =ROUND((IF(U10="resolved",I10,IF(U10="claimed",H10,Controls!$B$4))-G10)*24,4) -> 51.2 | W10: =INDEX(Owners!$E$4:$E$21,MATCH(D10,Owners!$A$4:$A$21,0)) -> FALSE
A11: iss-0008 | B11: ds-opportunities | C11: r-opportunities-fk-account_key | D11: own-04 | E11: high | F11: closed | G11: 46218.165 | H11: 46218.87 | N11: 1 | Q11: 0 | R11: =INDEX(Owners!$B$4:$B$21,MATCH(D11,Owners!$A$4:$A$21,0)) -> Data Platform | S11: =AND(F11="closed",ISNUMBER(H11),H11<=Controls!$B$4) -> TRUE | T11: =AND(ISNUMBER(I11),I11<=Controls!$B$4,J11="rerun",K11=A11,L11=C11,M11=N11,O11=0,I11>=G11,IF(ISNUMBER(P11),I11>=P11,TRUE())) -> FALSE | U11: =IF(AND(S11,T11),"resolved",IF(S11,"claimed","open")) -> claimed | V11: =ROUND((IF(U11="resolved",I11,IF(U11="claimed",H11,Controls!$B$4))-G11)*24,4) -> 16.9333 | W11: =INDEX(Owners!$E$4:$E$21,MATCH(D11,Owners!$A$4:$A$21,0)) -> TRUE
A12: iss-0009 | B12: ds-ledger-entries | C12: r-ledger-entries-unique-entry_key | D12: own-12 | E12: critical | F12: closed | G12: 46218.224 | H12: 46218.56 | I12: 46219.164 | J12: rerun | K12: iss-0009 | L12: r-ledger-entries-unique-entry_key | M12: 1 | N12: 1 | O12: 0 | Q12: 0 | R12: =INDEX(Owners!$B$4:$B$21,MATCH(D12,Owners!$A$4:$A$21,0)) -> Finance Systems | S12: =AND(F12="closed",ISNUMBER(H12),H12<=Controls!$B$4) -> TRUE | T12: =AND(ISNUMBER(I12),I12<=Controls!$B$4,J12="rerun",K12=A12,L12=C12,M12=N12,O12=0,I12>=G12,IF(ISNUMBER(P12),I12>=P12,TRUE())) -> TRUE | U12: =IF(AND(S12,T12),"resolved",IF(S12,"claimed","open")) -> resolved | V12: =ROUND((IF(U12="resolved",I12,IF(U12="claimed",H12,Controls!$B$4))-G12)*24,4) -> 22.5667 | W12: =INDEX(Owners!$E$4:$E$21,MATCH(D12,Owners!$A$4:$A$21,0)) -> FALSE
A13: iss-0010 | B13: ds-ledger-entries | C13: r-ledger-entries-complete-amount | D13: own-12 | E13: high | F13: closed | G13: 46218.233 | H13: 46222.833 | I13: 46223.328 | J13: rerun | K13: iss-0010 | L13: r-ledger-entries-complete-amount | M13: 1 | N13: 1 | O13: 0 | Q13: 0 | R13: =INDEX(Owners!$B$4:$B$21,MATCH(D13,Owners!$A$4:$A$21,0)) -> Finance Systems | S13: =AND(F13="closed",ISNUMBER(H13),H13<=Controls!$B$4) -> TRUE | T13: =AND(ISNUMBER(I13),I13<=Controls!$B$4,J13="rerun",K13=A13,L13=C13,M13=N13,O13=0,I13>=G13,IF(ISNUMBER(P13),I13>=P13,TRUE())) -> TRUE | U13: =IF(AND(S13,T13),"resolved",IF(S13,"claimed","open")) -> resolved | V13: =ROUND((IF(U13="resolved",I13,IF(U13="claimed",H13,Controls!$B$4))-G13)*24,4) -> 122.3 | W13: =INDEX(Owners!$E$4:$E$21,MATCH(D13,Owners!$A$4:$A$21,0)) -> FALSE
A14: iss-0011 | B14: ds-customers | C14: r-customers-valid-email | D14: own-07 | E14: medium | F14: closed | G14: 46219.092 | H14: 46220.781 | I14: 46221.284 | J14: rerun | K14: iss-0011 | L14: r-customers-valid-email | M14: 1 | N14: 1 | O14: 0 | Q14: 0 | R14: =INDEX(Owners!$B$4:$B$21,MATCH(D14,Owners!$A$4:$A$21,0)) -> Customer Data | S14: =AND(F14="closed",ISNUMBER(H14),H14<=Controls!$B$4) -> TRUE | T14: =AND(ISNUMBER(I14),I14<=Controls!$B$4,J14="rerun",K14=A14,L14=C14,M14=N14,O14=0,I14>=G14,IF(ISNUMBER(P14),I14>=P14,TRUE())) -> TRUE | U14: =IF(AND(S14,T14),"resolved",IF(S14,"claimed","open")) -> resolved | V14: =ROUND((IF(U14="resolved",I14,IF(U14="claimed",H14,Controls!$B$4))-G14)*24,4) -> 52.6 | W14: =INDEX(Owners!$E$4:$E$21,MATCH(D14,Owners!$A$4:$A$21,0)) -> TRUE
A15: iss-0012 | B15: ds-subscriptions | C15: r-subscriptions-fk-customer_key | D15: own-06 | E15: high | F15: closed | G15: 46219.142 | H15: 46219.488 | I15: 46219.632 | J15: rerun | K15: iss-0012 | L15: r-subscriptions-fk-customer_key | M15: 1 | N15: 1 | O15: 0 | Q15: 0 | R15: =INDEX(Owners!$B$4:$B$21,MATCH(D15,Owners!$A$4:$A$21,0)) -> Data Platform | S15: =AND(F15="closed",ISNUMBER(H15),H15<=Controls!$B$4) -> TRUE | T15: =AND(ISNUMBER(I15),I15<=Controls!$B$4,J15="rerun",K15=A15,L15=C15,M15=N15,O15=0,I15>=G15,IF(ISNUMBER(P15),I15>=P15,TRUE())) -> TRUE | U15: =IF(AND(S15,T15),"resolved",IF(S15,"claimed","open")) -> resolved | V15: =ROUND((IF(U15="resolved",I15,IF(U15="claimed",H15,Controls!$B$4))-G15)*24,4) -> 11.75 | W15: =INDEX(Owners!$E$4:$E$21,MATCH(D15,Owners!$A$4:$A$21,0)) -> TRUE
A16: iss-0013 | B16: ds-opportunities | C16: r-opportunities-fk-account_key | D16: own-04 | E16: high | F16: closed | G16: 46219.165 | H16: 46219.678 | I16: 46219.783 | J16: rerun | K16: iss-0013 | L16: r-opportunities-fk-account_key | M16: 1 | N16: 1 | O16: 0 | Q16: 0 | R16: =INDEX(Owners!$B$4:$B$21,MATCH(D16,Owners!$A$4:$A$21,0)) -> Data Platform | S16: =AND(F16="closed",ISNUMBER(H16),H16<=Controls!$B$4) -> TRUE | T16: =AND(ISNUMBER(I16),I16<=Controls!$B$4,J16="rerun",K16=A16,L16=C16,M16=N16,O16=0,I16>=G16,IF(ISNUMBER(P16),I16>=P16,TRUE())) -> TRUE | U16: =IF(AND(S16,T16),"resolved",IF(S16,"claimed","open")) -> resolved | V16: =ROUND((IF(U16="resolved",I16,IF(U16="claimed",H16,Controls!$B$4))-G16)*24,4) -> 14.8333 | W16: =INDEX(Owners!$E$4:$E$21,MATCH(D16,Owners!$A$4:$A$21,0)) -> TRUE
A17: iss-0014 | B17: ds-tickets | C17: r-tickets-fk-customer_key | D17: own-05 | E17: medium | F17: closed | G17: 46220.102 | H17: 46221.603 | I17: 46221.624 | J17: rerun | K17: iss-0014 | L17: r-tickets-fk-customer_key | M17: 1 | N17: 1 | O17: 0 | Q17: 0 | R17: =INDEX(Owners!$B$4:$B$21,MATCH(D17,Owners!$A$4:$A$21,0)) -> Data Platform | S17: =AND(F17="closed",ISNUMBER(H17),H17<=Controls!$B$4) -> TRUE | T17: =AND(ISNUMBER(I17),I17<=Controls!$B$4,J17="rerun",K17=A17,L17=C17,M17=N17,O17=0,I17>=G17,IF(ISNUMBER(P17),I17>=P17,TRUE())) -> TRUE | U17: =IF(AND(S17,T17),"resolved",IF(S17,"claimed","open")) -> resolved | V17: =ROUND((IF(U17="resolved",I17,IF(U17="claimed",H17,Controls!$B$4))-G17)*24,4) -> 36.5333 | W17: =INDEX(Owners!$E$4:$E$21,MATCH(D17,Owners!$A$4:$A$21,0)) -> TRUE
A18: iss-0015 | B18: ds-subscriptions | C18: r-subscriptions-fk-customer_key | D18: own-06 | E18: high | F18: closed | G18: 46220.142 | H18: 46220.742 | I18: 46220.832 | J18: rerun | K18: iss-0015 | L18: r-subscriptions-fk-customer_key | M18: 1 | N18: 1 | O18: 0 | Q18: 0 | R18: =INDEX(Owners!$B$4:$B$21,MATCH(D18,Owners!$A$4:$A$21,0)) -> Data Platform | S18: =AND(F18="closed",ISNUMBER(H18),H18<=Controls!$B$4) -> TRUE | T18: =AND(ISNUMBER(I18),I18<=Controls!$B$4,J18="rerun",K18=A18,L18=C18,M18=N18,O18=0,I18>=G18,IF(ISNUMBER(P18),I18>=P18,TRUE())) -> TRUE | U18: =IF(AND(S18,T18),"resolved",IF(S18,"claimed","open")) -> resolved | V18: =ROUND((IF(U18="resolved",I18,IF(U18="claimed",H18,Controls!$B$4))-G18)*24,4) -> 16.55 | W18: =INDEX(Owners!$E$4:$E$21,MATCH(D18,Owners!$A$4:$A$21,0)) -> TRUE
A19: iss-0016 | B19: ds-leads | C19: r-leads-valid-email | D19: own-18 | E19: high | F19: closed | G19: 46220.156 | H19: 46221.186 | N19: 1 | Q19: 0 | R19: =INDEX(Owners!$B$4:$B$21,MATCH(D19,Owners!$A$4:$A$21,0)) -> Support Operations | S19: =AND(F19="closed",ISNUMBER(H19),H19<=Controls!$B$4) -> TRUE | T19: =AND(ISNUMBER(I19),I19<=Controls!$B$4,J19="rerun",K19=A19,L19=C19,M19=N19,O19=0,I19>=G19,IF(ISNUMBER(P19),I19>=P19,TRUE())) -> FALSE | U19: =IF(AND(S19,T19),"resolved",IF(S19,"claimed","open")) -> claimed | V19: =ROUND((IF(U19="resolved",I19,IF(U19="claimed",H19,Controls!$B$4))-G19)*24,4) -> 24.7333 | W19: =INDEX(Owners!$E$4:$E$21,MATCH(D19,Owners!$A$4:$A$21,0)) -> TRUE
A20: iss-0017 | B20: ds-ledger-entries | C20: r-ledger-entries-valid-currency | D20: own-12 | E20: high | F20: closed | G20: 46220.215 | H20: 46226.61 | I20: 46227.175 | J20: rerun | K20: iss-0017 | L20: r-ledger-entries-valid-currency | M20: 1 | N20: 1 | O20: 0 | Q20: 0 | R20: =INDEX(Owners!$B$4:$B$21,MATCH(D20,Owners!$A$4:$A$21,0)) -> Finance Systems | S20: =AND(F20="closed",ISNUMBER(H20),H20<=Controls!$B$4) -> TRUE | T20: =AND(ISNUMBER(I20),I20<=Controls!$B$4,J20="rerun",K20=A20,L20=C20,M20=N20,O20=0,I20>=G20,IF(ISNUMBER(P20),I20>=P20,TRUE())) -> TRUE | U20: =IF(AND(S20,T20),"resolved",IF(S20,"claimed","open")) -> resolved | V20: =ROUND((IF(U20="resolved",I20,IF(U20="claimed",H20,Controls!$B$4))-G20)*24,4) -> 167.05 | W20: =INDEX(Owners!$E$4:$E$21,MATCH(D20,Owners!$A$4:$A$21,0)) -> FALSE
A21: iss-0018 | B21: ds-payments | C21: r-payments-fresh | D21: own-06 | E21: high | F21: closed | G21: 46220.993 | H21: 46221.653 | I21: 46221.698 | J21: rerun | K21: iss-0018 | L21: r-payments-fresh | M21: 1 | N21: 1 | O21: 0 | Q21: 0 | R21: =INDEX(Owners!$B$4:$B$21,MATCH(D21,Owners!$A$4:$A$21,0)) -> Data Platform | S21: =AND(F21="closed",ISNUMBER(H21),H21<=Controls!$B$4) -> TRUE | T21: =AND(ISNUMBER(I21),I21<=Controls!$B$4,J21="rerun",K21=A21,L21=C21,M21=N21,O21=0,I21>=G21,IF(ISNUMBER(P21),I21>=P21,TRUE())) -> TRUE | U21: =IF(AND(S21,T21),"resolved",IF(S21,"claimed","open")) -> resolved | V21: =ROUND((IF(U21="resolved",I21,IF(U21="claimed",H21,Controls!$B$4))-G21)*24,4) -> 16.9167 | W21: =INDEX(Owners!$E$4:$E$21,MATCH(D21,Owners!$A$4:$A$21,0)) -> TRUE
A22: iss-0019 | B22: ds-customers | C22: r-customers-valid-email | D22: own-07 | E22: medium | F22: closed | G22: 46221.092 | H22: 46222.857 | I22: 46223.306 | J22: rerun | K22: iss-0019 | L22: r-customers-valid-email | M22: 1 | N22: 1 | O22: 0 | Q22: 0 | R22: =INDEX(Owners!$B$4:$B$21,MATCH(D22,Owners!$A$4:$A$21,0)) -> Customer Data | S22: =AND(F22="closed",ISNUMBER(H22),H22<=Controls!$B$4) -> TRUE | T22: =AND(ISNUMBER(I22),I22<=Controls!$B$4,J22="rerun",K22=A22,L22=C22,M22=N22,O22=0,I22>=G22,IF(ISNUMBER(P22),I22>=P22,TRUE())) -> TRUE | U22: =IF(AND(S22,T22),"resolved",IF(S22,"claimed","open")) -> resolved | V22: =ROUND((IF(U22="resolved",I22,IF(U22="claimed",H22,Controls!$B$4))-G22)*24,4) -> 53.1333 | W22: =INDEX(Owners!$E$4:$E$21,MATCH(D22,Owners!$A$4:$A$21,0)) -> TRUE
A23: iss-0020 | B23: ds-carriers | C23: r-carriers-valid-carrier_code | D23: own-05 | E23: medium | F23: closed | G23: 46221.107 | H23: 46224.054 | N23: 1 | Q23: 0 | R23: =INDEX(Owners!$B$4:$B$21,MATCH(D23,Owners!$A$4:$A$21,0)) -> Data Platform | S23: =AND(F23="closed",ISNUMBER(H23),H23<=Controls!$B$4) -> TRUE | T23: =AND(ISNUMBER(I23),I23<=Controls!$B$4,J23="rerun",K23=A23,L23=C23,M23=N23,O23=0,I23>=G23,IF(ISNUMBER(P23),I23>=P23,TRUE())) -> FALSE | U23: =IF(AND(S23,T23),"resolved",IF(S23,"claimed","open")) -> claimed | V23: =ROUND((IF(U23="resolved",I23,IF(U23="claimed",H23,Controls!$B$4))-G23)*24,4) -> 70.7333 | W23: =INDEX(Owners!$E$4:$E$21,MATCH(D23,Owners!$A$4:$A$21,0)) -> TRUE
A24: iss-0021 | B24: ds-contacts | C24: r-contacts-complete-email | D24: own-12 | E24: high | F24: closed | G24: 46221.119 | H24: 46223.284 | I24: 46223.326 | J24: rerun | K24: iss-0021 | L24: r-contacts-complete-email | M24: 1 | N24: 1 | O24: 0 | Q24: 0 | R24: =INDEX(Owners!$B$4:$B$21,MATCH(D24,Owners!$A$4:$A$21,0)) -> Finance Systems | S24: =AND(F24="closed",ISNUMBER(H24),H24<=Controls!$B$4) -> TRUE | T24: =AND(ISNUMBER(I24),I24<=Controls!$B$4,J24="rerun",K24=A24,L24=C24,M24=N24,O24=0,I24>=G24,IF(ISNUMBER(P24),I24>=P24,TRUE())) -> TRUE | U24: =IF(AND(S24,T24),"resolved",IF(S24,"claimed","open")) -> resolved | V24: =ROUND((IF(U24="resolved",I24,IF(U24="claimed",H24,Controls!$B$4))-G24)*24,4) -> 52.95 | W24: =INDEX(Owners!$E$4:$E$21,MATCH(D24,Owners!$A$4:$A$21,0)) -> FALSE
A25: iss-0022 | B25: ds-subscriptions | C25: r-subscriptions-complete-plan_code | D25: own-06 | E25: high | F25: closed | G25: 46221.151 | H25: 46222.842 | I25: 46222.929 | J25: rerun | K25: iss-0022 | L25: r-subscriptions-complete-plan_code | M25: 1 | N25: 1 | O25: 0 | Q25: 0 | R25: =INDEX(Owners!$B$4:$B$21,MATCH(D25,Owners!$A$4:$A$21,0)) -> Data Platform | S25: =AND(F25="closed",ISNUMBER(H25),H25<=Controls!$B$4) -> TRUE | T25: =AND(ISNUMBER(I25),I25<=Controls!$B$4,J25="rerun",K25=A25,L25=C25,M25=N25,O25=0,I25>=G25,IF(ISNUMBER(P25),I25>=P25,TRUE())) -> TRUE | U25: =IF(AND(S25,T25),"resolved",IF(S25,"claimed","open")) -> resolved | V25: =ROUND((IF(U25="resolved",I25,IF(U25="claimed",H25,Controls!$B$4))-G25)*24,4) -> 42.6667 | W25: =INDEX(Owners!$E$4:$E$21,MATCH(D25,Owners!$A$4:$A$21,0)) -> TRUE
A26: iss-0023 | B26: ds-opportunities | C26: r-opportunities-fk-account_key | D26: own-04 | E26: high | F26: closed | G26: 46221.165 | H26: 46222.684 | I26: 46222.713 | J26: rerun | K26: iss-0023 | L26: r-opportunities-fk-account_key | M26: 1 | N26: 1 | O26: 0 | Q26: 0 | R26: =INDEX(Owners!$B$4:$B$21,MATCH(D26,Owners!$A$4:$A$21,0)) -> Data Platform | S26: =AND(F26="closed",ISNUMBER(H26),H26<=Controls!$B$4) -> TRUE | T26: =AND(ISNUMBER(I26),I26<=Controls!$B$4,J26="rerun",K26=A26,L26=C26,M26=N26,O26=0,I26>=G26,IF(ISNUMBER(P26),I26>=P26,TRUE())) -> TRUE | U26: =IF(AND(S26,T26),"resolved",IF(S26,"claimed","open")) -> resolved | V26: =ROUND((IF(U26="resolved",I26,IF(U26="claimed",H26,Controls!$B$4))-G26)*24,4) -> 37.15 | W26: =INDEX(Owners!$E$4:$E$21,MATCH(D26,Owners!$A$4:$A$21,0)) -> TRUE
A27: iss-0024 | B27: ds-ledger-entries | C27: r-ledger-entries-valid-currency | D27: own-12 | E27: high | F27: closed | G27: 46221.215 | H27: 46225.809 | I27: 46226.236 | J27: rerun | K27: iss-0024 | L27: r-ledger-entries-valid-currency | M27: 1 | N27: 1 | O27: 0 | Q27: 0 | R27: =INDEX(Owners!$B$4:$B$21,MATCH(D27,Owners!$A$4:$A$21,0)) -> Finance Systems | S27: =AND(F27="closed",ISNUMBER(H27),H27<=Controls!$B$4) -> TRUE | T27: =AND(ISNUMBER(I27),I27<=Controls!$B$4,J27="rerun",K27=A27,L27=C27,M27=N27,O27=0,I27>=G27,IF(ISNUMBER(P27),I27>=P27,TRUE())) -> TRUE | U27: =IF(AND(S27,T27),"resolved",IF(S27,"claimed","open")) -> resolved | V27: =ROUND((IF(U27="resolved",I27,IF(U27="claimed",H27,Controls!$B$4))-G27)*24,4) -> 120.5167 | W27: =INDEX(Owners!$E$4:$E$21,MATCH(D27,Owners!$A$4:$A$21,0)) -> FALSE
A28: iss-0025 | B28: ds-carriers | C28: r-carriers-valid-carrier_code | D28: own-05 | E28: medium | F28: closed | G28: 46222.107 | H28: 46225.354 | I28: 46225.517 | J28: rerun | K28: iss-0025 | L28: r-carriers-valid-carrier_code | M28: 1 | N28: 1 | O28: 0 | Q28: 0 | R28: =INDEX(Owners!$B$4:$B$21,MATCH(D28,Owners!$A$4:$A$21,0)) -> Data Platform | S28: =AND(F28="closed",ISNUMBER(H28),H28<=Controls!$B$4) -> TRUE | T28: =AND(ISNUMBER(I28),I28<=Controls!$B$4,J28="rerun",K28=A28,L28=C28,M28=N28,O28=0,I28>=G28,IF(ISNUMBER(P28),I28>=P28,TRUE())) -> TRUE | U28: =IF(AND(S28,T28),"resolved",IF(S28,"claimed","open")) -> resolved | V28: =ROUND((IF(U28="resolved",I28,IF(U28="claimed",H28,Controls!$B$4))-G28)*24,4) -> 81.8333 | W28: =INDEX(Owners!$E$4:$E$21,MATCH(D28,Owners!$A$4:$A$21,0)) -> TRUE
A29: iss-0026 | B29: ds-subscriptions | C29: r-subscriptions-fk-customer_key | D29: own-06 | E29: high | F29: closed | G29: 46222.142 | H29: 46223.026 | I29: 46223.172 | J29: rerun | K29: iss-0026 | L29: r-subscriptions-fk-customer_key | M29: 1 | N29: 1 | O29: 0 | Q29: 0 | R29: =INDEX(Owners!$B$4:$B$21,MATCH(D29,Owners!$A$4:$A$21,0)) -> Data Platform | S29: =AND(F29="closed",ISNUMBER(H29),H29<=Controls!$B$4) -> TRUE | T29: =AND(ISNUMBER(I29),I29<=Controls!$B$4,J29="rerun",K29=A29,L29=C29,M29=N29,O29=0,I29>=G29,IF(ISNUMBER(P29),I29>=P29,TRUE())) -> TRUE | U29: =IF(AND(S29,T29),"resolved",IF(S29,"claimed","open")) -> resolved | V29: =ROUND((IF(U29="resolved",I29,IF(U29="claimed",H29,Controls!$B$4))-G29)*24,4) -> 24.7 | W29: =INDEX(Owners!$E$4:$E$21,MATCH(D29,Owners!$A$4:$A$21,0)) -> TRUE
A30: iss-0027 | B30: ds-orders | C30: r-orders-complete-order_date | D30: own-04 | E30: high | F30: closed | G30: 46222.183 | H30: 46222.507 | I30: 46222.697 | J30: rerun | K30: iss-0027 | L30: r-orders-complete-order_date | M30: 1 | N30: 1 | O30: 0 | Q30: 0 | R30: =INDEX(Owners!$B$4:$B$21,MATCH(D30,Owners!$A$4:$A$21,0)) -> Data Platform | S30: =AND(F30="closed",ISNUMBER(H30),H30<=Controls!$B$4) -> TRUE | T30: =AND(ISNUMBER(I30),I30<=Controls!$B$4,J30="rerun",K30=A30,L30=C30,M30=N30,O30=0,I30>=G30,IF(ISNUMBER(P30),I30>=P30,TRUE())) -> TRUE | U30: =IF(AND(S30,T30),"resolved",IF(S30,"claimed","open")) -> resolved | V30: =ROUND((IF(U30="resolved",I30,IF(U30="claimed",H30,Controls!$B$4))-G30)*24,4) -> 12.3333 | W30: =INDEX(Owners!$E$4:$E$21,MATCH(D30,Owners!$A$4:$A$21,0)) -> TRUE
A31: iss-0028 | B31: ds-order-lines | C31: r-order-lines-fk-product_code | D31: own-03 | E31: low | F31: closed | G31: 46222.228 | H31: 46224.746 | N31: 1 | Q31: 0 | R31: =INDEX(Owners!$B$4:$B$21,MATCH(D31,Owners!$A$4:$A$21,0)) -> Data Governance | S31: =AND(F31="closed",ISNUMBER(H31),H31<=Controls!$B$4) -> TRUE | T31: =AND(ISNUMBER(I31),I31<=Controls!$B$4,J31="rerun",K31=A31,L31=C31,M31=N31,O31=0,I31>=G31,IF(ISNUMBER(P31),I31>=P31,TRUE())) -> FALSE | U31: =IF(AND(S31,T31),"resolved",IF(S31,"claimed","open")) -> claimed | V31: =ROUND((IF(U31="resolved",I31,IF(U31="claimed",H31,Controls!$B$4))-G31)*24,4) -> 60.4333 | W31: =INDEX(Owners!$E$4:$E$21,MATCH(D31,Owners!$A$4:$A$21,0)) -> TRUE
A32: iss-0029 | B32: ds-ledger-entries | C32: r-ledger-entries-complete-amount | D32: own-12 | E32: high | F32: closed | G32: 46222.233 | H32: 46223.753 | I32: 46223.843 | J32: rerun | K32: iss-0029 | L32: r-ledger-entries-complete-amount | M32: 1 | N32: 1 | O32: 0 | Q32: 0 | R32: =INDEX(Owners!$B$4:$B$21,MATCH(D32,Owners!$A$4:$A$21,0)) -> Finance Systems | S32: =AND(F32="closed",ISNUMBER(H32),H32<=Controls!$B$4) -> TRUE | T32: =AND(ISNUMBER(I32),I32<=Controls!$B$4,J32="rerun",K32=A32,L32=C32,M32=N32,O32=0,I32>=G32,IF(ISNUMBER(P32),I32>=P32,TRUE())) -> TRUE | U32: =IF(AND(S32,T32),"resolved",IF(S32,"claimed","open")) -> resolved | V32: =ROUND((IF(U32="resolved",I32,IF(U32="claimed",H32,Controls!$B$4))-G32)*24,4) -> 38.65 | W32: =INDEX(Owners!$E$4:$E$21,MATCH(D32,Owners!$A$4:$A$21,0)) -> FALSE
A33: iss-0030 | B33: ds-cost-centres | C33: r-cost-centres-complete-owner_ref | D33: own-10 | E33: high | F33: closed | G33: 46223.084 | H33: 46230.142 | I33: 46230.188 | J33: rerun | K33: iss-0030 | L33: r-cost-centres-complete-owner_ref | M33: 1 | N33: 1 | O33: 0 | Q33: 0 | R33: =INDEX(Owners!$B$4:$B$21,MATCH(D33,Owners!$A$4:$A$21,0)) -> Finance Systems | S33: =AND(F33="closed",ISNUMBER(H33),H33<=Controls!$B$4) -> TRUE | T33: =AND(ISNUMBER(I33),I33<=Controls!$B$4,J33="rerun",K33=A33,L33=C33,M33=N33,O33=0,I33>=G33,IF(ISNUMBER(P33),I33>=P33,TRUE())) -> TRUE | U33: =IF(AND(S33,T33),"resolved",IF(S33,"claimed","open")) -> resolved | V33: =ROUND((IF(U33="resolved",I33,IF(U33="claimed",H33,Controls!$B$4))-G33)*24,4) -> 170.5 | W33: =INDEX(Owners!$E$4:$E$21,MATCH(D33,Owners!$A$4:$A$21,0)) -> TRUE
A34: iss-0031 | B34: ds-invoices | C34: r-invoices-valid-currency | D34: own-09 | E34: high | F34: closed | G34: 46223.097 | H34: 46224.556 | N34: 1 | Q34: 0 | R34: =INDEX(Owners!$B$4:$B$21,MATCH(D34,Owners!$A$4:$A$21,0)) -> Customer Data | S34: =AND(F34="closed",ISNUMBER(H34),H34<=Controls!$B$4) -> TRUE | T34: =AND(ISNUMBER(I34),I34<=Controls!$B$4,J34="rerun",K34=A34,L34=C34,M34=N34,O34=0,I34>=G34,IF(ISNUMBER(P34),I34>=P34,TRUE())) -> FALSE | U34: =IF(AND(S34,T34),"resolved",IF(S34,"claimed","open")) -> claimed | V34: =ROUND((IF(U34="resolved",I34,IF(U34="claimed",H34,Controls!$B$4))-G34)*24,4) -> 35.0167 | W34: =INDEX(Owners!$E$4:$E$21,MATCH(D34,Owners!$A$4:$A$21,0)) -> FALSE
A35: iss-0032 | B35: ds-carriers | C35: r-carriers-valid-carrier_code | D35: own-05 | E35: medium | F35: closed | G35: 46223.107 | H35: 46224.064 | I35: 46224.092 | J35: rerun | K35: iss-0032 | L35: r-carriers-valid-carrier_code | M35: 1 | N35: 1 | O35: 0 | Q35: 0 | R35: =INDEX(Owners!$B$4:$B$21,MATCH(D35,Owners!$A$4:$A$21,0)) -> Data Platform | S35: =AND(F35="closed",ISNUMBER(H35),H35<=Controls!$B$4) -> TRUE | T35: =AND(ISNUMBER(I35),I35<=Controls!$B$4,J35="rerun",K35=A35,L35=C35,M35=N35,O35=0,I35>=G35,IF(ISNUMBER(P35),I35>=P35,TRUE())) -> TRUE | U35: =IF(AND(S35,T35),"resolved",IF(S35,"claimed","open")) -> resolved | V35: =ROUND((IF(U35="resolved",I35,IF(U35="claimed",H35,Controls!$B$4))-G35)*24,4) -> 23.6333 | W35: =INDEX(Owners!$E$4:$E$21,MATCH(D35,Owners!$A$4:$A$21,0)) -> TRUE
A36: iss-0033 | B36: ds-tickets | C36: r-tickets-complete-priority | D36: own-05 | E36: medium | F36: closed | G36: 46223.111 | H36: 46224.782 | I36: 46224.973 | J36: rerun | K36: iss-0033 | L36: r-tickets-complete-priority | M36: 1 | N36: 1 | O36: 0 | Q36: 0 | R36: =INDEX(Owners!$B$4:$B$21,MATCH(D36,Owners!$A$4:$A$21,0)) -> Data Platform | S36: =AND(F36="closed",ISNUMBER(H36),H36<=Controls!$B$4) -> TRUE | T36: =AND(ISNUMBER(I36),I36<=Controls!$B$4,J36="rerun",K36=A36,L36=C36,M36=N36,O36=0,I36>=G36,IF(ISNUMBER(P36),I36>=P36,TRUE())) -> TRUE | U36: =IF(AND(S36,T36),"resolved",IF(S36,"claimed","open")) -> resolved | V36: =ROUND((IF(U36="resolved",I36,IF(U36="claimed",H36,Controls!$B$4))-G36)*24,4) -> 44.6833 | W36: =INDEX(Owners!$E$4:$E$21,MATCH(D36,Owners!$A$4:$A$21,0)) -> TRUE
A37: iss-0034 | B37: ds-accounts | C37: r-accounts-fk-customer_key | D37: own-14 | E37: high | F37: closed | G37: 46223.147 | H37: 46225.115 | I37: 46225.506 | J37: rerun | K37: iss-0034 | L37: r-accounts-fk-customer_key | M37: 1 | N37: 1 | O37: 0 | Q37: 0 | R37: =INDEX(Owners!$B$4:$B$21,MATCH(D37,Owners!$A$4:$A$21,0)) -> Supply Chain | S37: =AND(F37="closed",ISNUMBER(H37),H37<=Controls!$B$4) -> TRUE | T37: =AND(ISNUMBER(I37),I37<=Controls!$B$4,J37="rerun",K37=A37,L37=C37,M37=N37,O37=0,I37>=G37,IF(ISNUMBER(P37),I37>=P37,TRUE())) -> TRUE | U37: =IF(AND(S37,T37),"resolved",IF(S37,"claimed","open")) -> resolved | V37: =ROUND((IF(U37="resolved",I37,IF(U37="claimed",H37,Controls!$B$4))-G37)*24,4) -> 56.6333 | W37: =INDEX(Owners!$E$4:$E$21,MATCH(D37,Owners!$A$4:$A$21,0)) -> TRUE
A38: iss-0035 | B38: ds-subscriptions | C38: r-subscriptions-complete-plan_code | D38: own-06 | E38: high | F38: closed | G38: 46223.151 | H38: 46225.724 | N38: 1 | Q38: 0 | R38: =INDEX(Owners!$B$4:$B$21,MATCH(D38,Owners!$A$4:$A$21,0)) -> Data Platform | S38: =AND(F38="closed",ISNUMBER(H38),H38<=Controls!$B$4) -> TRUE | T38: =AND(ISNUMBER(I38),I38<=Controls!$B$4,J38="rerun",K38=A38,L38=C38,M38=N38,O38=0,I38>=G38,IF(ISNUMBER(P38),I38>=P38,TRUE())) -> FALSE | U38: =IF(AND(S38,T38),"resolved",IF(S38,"claimed","open")) -> claimed | V38: =ROUND((IF(U38="resolved",I38,IF(U38="claimed",H38,Controls!$B$4))-G38)*24,4) -> 61.75 | W38: =INDEX(Owners!$E$4:$E$21,MATCH(D38,Owners!$A$4:$A$21,0)) -> TRUE
A39: iss-0036 | B39: ds-refunds | C39: r-refunds-fk-payment_key | D39: own-18 | E39: high | F39: closed | G39: 46223.16 | H39: 46225.956 | I39: 46226.241 | J39: rerun | K39: iss-0036 | L39: r-refunds-fk-payment_key | M39: 1 | N39: 1 | O39: 0 | Q39: 0 | R39: =INDEX(Owners!$B$4:$B$21,MATCH(D39,Owners!$A$4:$A$21,0)) -> Support Operations | S39: =AND(F39="closed",ISNUMBER(H39),H39<=Controls!$B$4) -> TRUE | T39: =AND(ISNUMBER(I39),I39<=Controls!$B$4,J39="rerun",K39=A39,L39=C39,M39=N39,O39=0,I39>=G39,IF(ISNUMBER(P39),I39>=P39,TRUE())) -> TRUE | U39: =IF(AND(S39,T39),"resolved",IF(S39,"claimed","open")) -> resolved | V39: =ROUND((IF(U39="resolved",I39,IF(U39="claimed",H39,Controls!$B$4))-G39)*24,4) -> 73.9333 | W39: =INDEX(Owners!$E$4:$E$21,MATCH(D39,Owners!$A$4:$A$21,0)) -> TRUE
A40: iss-0037 | B40: ds-suppliers | C40: r-suppliers-unique-supplier_key | D40: own-15 | E40: high | F40: closed | G40: 46223.188 | H40: 46232.842 | I40: 46232.951 | J40: rerun | K40: iss-0037 | L40: r-suppliers-unique-supplier_key | M40: 1 | N40: 1 | O40: 0 | Q40: 0 | R40: =INDEX(Owners!$B$4:$B$21,MATCH(D40,Owners!$A$4:$A$21,0)) -> Supply Chain | S40: =AND(F40="closed",ISNUMBER(H40),H40<=Controls!$B$4) -> TRUE | T40: =AND(ISNUMBER(I40),I40<=Controls!$B$4,J40="rerun",K40=A40,L40=C40,M40=N40,O40=0,I40>=G40,IF(ISNUMBER(P40),I40>=P40,TRUE())) -> TRUE | U40: =IF(AND(S40,T40),"resolved",IF(S40,"claimed","open")) -> resolved | V40: =ROUND((IF(U40="resolved",I40,IF(U40="claimed",H40,Controls!$B$4))-G40)*24,4) -> 234.3167 | W40: =INDEX(Owners!$E$4:$E$21,MATCH(D40,Owners!$A$4:$A$21,0)) -> FALSE
A41: iss-0038 | B41: ds-ledger-entries | C41: r-ledger-entries-complete-amount | D41: own-12 | E41: high | F41: closed | G41: 46223.233 | H41: 46225.137 | I41: 46225.46 | J41: rerun | K41: iss-0038 | L41: r-ledger-entries-complete-amount | M41: 1 | N41: 1 | O41: 0 | Q41: 0 | R41: =INDEX(Owners!$B$4:$B$21,MATCH(D41,Owners!$A$4:$A$21,0)) -> Finance Systems | S41: =AND(F41="closed",ISNUMBER(H41),H41<=Controls!$B$4) -> TRUE | T41: =AND(ISNUMBER(I41),I41<=Controls!$B$4,J41="rerun",K41=A41,L41=C41,M41=N41,O41=0,I41>=G41,IF(ISNUMBER(P41),I41>=P41,TRUE())) -> TRUE | U41: =IF(AND(S41,T41),"resolved",IF(S41,"claimed","open")) -> resolved | V41: =ROUND((IF(U41="resolved",I41,IF(U41="claimed",H41,Controls!$B$4))-G41)*24,4) -> 53.4667 | W41: =INDEX(Owners!$E$4:$E$21,MATCH(D41,Owners!$A$4:$A$21,0)) -> FALSE
A42: iss-0039 | B42: ds-products | C42: r-products-complete-category | D42: own-17 | E42: medium | F42: closed | G42: 46223.246 | H42: 46228.863 | I42: 46229.331 | J42: rerun | K42: iss-0039 | L42: r-products-complete-category | M42: 1 | N42: 1 | O42: 0 | Q42: 0 | R42: =INDEX(Owners!$B$4:$B$21,MATCH(D42,Owners!$A$4:$A$21,0)) -> Support Operations | S42: =AND(F42="closed",ISNUMBER(H42),H42<=Controls!$B$4) -> TRUE | T42: =AND(ISNUMBER(I42),I42<=Controls!$B$4,J42="rerun",K42=A42,L42=C42,M42=N42,O42=0,I42>=G42,IF(ISNUMBER(P42),I42>=P42,TRUE())) -> TRUE | U42: =IF(AND(S42,T42),"resolved",IF(S42,"claimed","open")) -> resolved | V42: =ROUND((IF(U42="resolved",I42,IF(U42="claimed",H42,Controls!$B$4))-G42)*24,4) -> 146.0333 | W42: =INDEX(Owners!$E$4:$E$21,MATCH(D42,Owners!$A$4:$A$21,0)) -> TRUE
A43: iss-0040 | B43: ds-orders | C43: r-orders-fresh | D43: own-04 | E43: medium | F43: closed | G43: 46223.993 | H43: 46226.404 | I43: 46226.522 | J43: rerun | K43: iss-0040 | L43: r-orders-fresh | M43: 1 | N43: 1 | O43: 0 | Q43: 0 | R43: =INDEX(Owners!$B$4:$B$21,MATCH(D43,Owners!$A$4:$A$21,0)) -> Data Platform | S43: =AND(F43="closed",ISNUMBER(H43),H43<=Controls!$B$4) -> TRUE | T43: =AND(ISNUMBER(I43),I43<=Controls!$B$4,J43="rerun",K43=A43,L43=C43,M43=N43,O43=0,I43>=G43,IF(ISNUMBER(P43),I43>=P43,TRUE())) -> TRUE | U43: =IF(AND(S43,T43),"resolved",IF(S43,"claimed","open")) -> resolved | V43: =ROUND((IF(U43="resolved",I43,IF(U43="claimed",H43,Controls!$B$4))-G43)*24,4) -> 60.7 | W43: =INDEX(Owners!$E$4:$E$21,MATCH(D43,Owners!$A$4:$A$21,0)) -> TRUE
A44: iss-0041 | B44: ds-contacts | C44: r-contacts-complete-email | D44: own-12 | E44: high | F44: closed | G44: 46224.119 | H44: 46227.482 | I44: 46227.763 | J44: rerun | K44: iss-0041 | L44: r-contacts-complete-email | M44: 1 | N44: 1 | O44: 0 | Q44: 0 | R44: =INDEX(Owners!$B$4:$B$21,MATCH(D44,Owners!$A$4:$A$21,0)) -> Finance Systems | S44: =AND(F44="closed",ISNUMBER(H44),H44<=Controls!$B$4) -> TRUE | T44: =AND(ISNUMBER(I44),I44<=Controls!$B$4,J44="rerun",K44=A44,L44=C44,M44=N44,O44=0,I44>=G44,IF(ISNUMBER(P44),I44>=P44,TRUE())) -> TRUE | U44: =IF(AND(S44,T44),"resolved",IF(S44,"claimed","open")) -> resolved | V44: =ROUND((IF(U44="resolved",I44,IF(U44="claimed",H44,Controls!$B$4))-G44)*24,4) -> 87.45 | W44: =INDEX(Owners!$E$4:$E$21,MATCH(D44,Owners!$A$4:$A$21,0)) -> FALSE
A45: iss-0042 | B45: ds-orders | C45: r-orders-complete-order_date | D45: own-04 | E45: high | F45: closed | G45: 46224.183 | H45: 46225.742 | I45: 46225.835 | J45: rerun | K45: iss-0042 | L45: r-orders-complete-order_date | M45: 1 | N45: 1 | O45: 0 | Q45: 0 | R45: =INDEX(Owners!$B$4:$B$21,MATCH(D45,Owners!$A$4:$A$21,0)) -> Data Platform | S45: =AND(F45="closed",ISNUMBER(H45),H45<=Controls!$B$4) -> TRUE | T45: =AND(ISNUMBER(I45),I45<=Controls!$B$4,J45="rerun",K45=A45,L45=C45,M45=N45,O45=0,I45>=G45,IF(ISNUMBER(P45),I45>=P45,TRUE())) -> TRUE | U45: =IF(AND(S45,T45),"resolved",IF(S45,"claimed","open")) -> resolved | V45: =ROUND((IF(U45="resolved",I45,IF(U45="claimed",H45,Controls!$B$4))-G45)*24,4) -> 39.65 | W45: =INDEX(Owners!$E$4:$E$21,MATCH(D45,Owners!$A$4:$A$21,0)) -> TRUE
A46: iss-0043 | B46: ds-orders | C46: r-orders-fresh | D46: own-04 | E46: medium | F46: closed | G46: 46224.993 | H46: 46225.683 | N46: 1 | Q46: 0 | R46: =INDEX(Owners!$B$4:$B$21,MATCH(D46,Owners!$A$4:$A$21,0)) -> Data Platform | S46: =AND(F46="closed",ISNUMBER(H46),H46<=Controls!$B$4) -> TRUE | T46: =AND(ISNUMBER(I46),I46<=Controls!$B$4,J46="rerun",K46=A46,L46=C46,M46=N46,O46=0,I46>=G46,IF(ISNUMBER(P46),I46>=P46,TRUE())) -> FALSE | U46: =IF(AND(S46,T46),"resolved",IF(S46,"claimed","open")) -> claimed | V46: =ROUND((IF(U46="resolved",I46,IF(U46="claimed",H46,Controls!$B$4))-G46)*24,4) -> 16.55 | W46: =INDEX(Owners!$E$4:$E$21,MATCH(D46,Owners!$A$4:$A$21,0)) -> TRUE
A47: iss-0044 | B47: ds-cost-centres | C47: r-cost-centres-complete-owner_ref | D47: own-10 | E47: high | F47: closed | G47: 46225.084 | H47: 46227.037 | I47: 46227.409 | J47: rerun | K47: iss-0044 | L47: r-cost-centres-complete-owner_ref | M47: 1 | N47: 1 | O47: 0 | Q47: 0 | R47: =INDEX(Owners!$B$4:$B$21,MATCH(D47,Owners!$A$4:$A$21,0)) -> Finance Systems | S47: =AND(F47="closed",ISNUMBER(H47),H47<=Controls!$B$4) -> TRUE | T47: =AND(ISNUMBER(I47),I47<=Controls!$B$4,J47="rerun",K47=A47,L47=C47,M47=N47,O47=0,I47>=G47,IF(ISNUMBER(P47),I47>=P47,TRUE())) -> TRUE | U47: =IF(AND(S47,T47),"resolved",IF(S47,"claimed","open")) -> resolved | V47: =ROUND((IF(U47="resolved",I47,IF(U47="claimed",H47,Controls!$B$4))-G47)*24,4) -> 55.8 | W47: =INDEX(Owners!$E$4:$E$21,MATCH(D47,Owners!$A$4:$A$21,0)) -> TRUE
A48: iss-0045 | B48: ds-tickets | C48: r-tickets-complete-priority | D48: own-05 | E48: medium | F48: closed | G48: 46225.111 | H48: 46226.132 | I48: 46226.265 | J48: rerun | K48: iss-0045 | L48: r-tickets-complete-priority | M48: 1 | N48: 1 | O48: 0 | Q48: 0 | R48: =INDEX(Owners!$B$4:$B$21,MATCH(D48,Owners!$A$4:$A$21,0)) -> Data Platform | S48: =AND(F48="closed",ISNUMBER(H48),H48<=Controls!$B$4) -> TRUE | T48: =AND(ISNUMBER(I48),I48<=Controls!$B$4,J48="rerun",K48=A48,L48=C48,M48=N48,O48=0,I48>=G48,IF(ISNUMBER(P48),I48>=P48,TRUE())) -> TRUE | U48: =IF(AND(S48,T48),"resolved",IF(S48,"claimed","open")) -> resolved | V48: =ROUND((IF(U48="resolved",I48,IF(U48="claimed",H48,Controls!$B$4))-G48)*24,4) -> 27.6833 | W48: =INDEX(Owners!$E$4:$E$21,MATCH(D48,Owners!$A$4:$A$21,0)) -> TRUE
A49: iss-0046 | B49: ds-contacts | C49: r-contacts-complete-email | D49: own-12 | E49: high | F49: closed | G49: 46225.119 | H49: 46226.915 | N49: 1 | Q49: 0 | R49: =INDEX(Owners!$B$4:$B$21,MATCH(D49,Owners!$A$4:$A$21,0)) -> Finance Systems | S49: =AND(F49="closed",ISNUMBER(H49),H49<=Controls!$B$4) -> TRUE | T49: =AND(ISNUMBER(I49),I49<=Controls!$B$4,J49="rerun",K49=A49,L49=C49,M49=N49,O49=0,I49>=G49,IF(ISNUMBER(P49),I49>=P49,TRUE())) -> FALSE | U49: =IF(AND(S49,T49),"resolved",IF(S49,"claimed","open")) -> claimed | V49: =ROUND((IF(U49="resolved",I49,IF(U49="claimed",H49,Controls!$B$4))-G49)*24,4) -> 43.1 | W49: =INDEX(Owners!$E$4:$E$21,MATCH(D49,Owners!$A$4:$A$21,0)) -> FALSE
A50: iss-0047 | B50: ds-accounts | C50: r-accounts-fk-customer_key | D50: own-14 | E50: high | F50: closed | G50: 46225.147 | H50: 46230.785 | I50: 46230.923 | J50: rerun | K50: iss-0047 | L50: r-accounts-fk-customer_key | M50: 1 | N50: 1 | O50: 0 | Q50: 0 | R50: =INDEX(Owners!$B$4:$B$21,MATCH(D50,Owners!$A$4:$A$21,0)) -> Supply Chain | S50: =AND(F50="closed",ISNUMBER(H50),H50<=Controls!$B$4) -> TRUE | T50: =AND(ISNUMBER(I50),I50<=Controls!$B$4,J50="rerun",K50=A50,L50=C50,M50=N50,O50=0,I50>=G50,IF(ISNUMBER(P50),I50>=P50,TRUE())) -> TRUE | U50: =IF(AND(S50,T50),"resolved",IF(S50,"claimed","open")) -> resolved | V50: =ROUND((IF(U50="resolved",I50,IF(U50="claimed",H50,Controls!$B$4))-G50)*24,4) -> 138.6333 | W50: =INDEX(Owners!$E$4:$E$21,MATCH(D50,Owners!$A$4:$A$21,0)) -> TRUE
A51: iss-0048 | B51: ds-contacts | C51: r-contacts-complete-email | D51: own-12 | E51: high | F51: closed | G51: 46226.119 | H51: 46227.603 | I51: 46227.994 | J51: rerun | K51: iss-0048 | L51: r-contacts-complete-email | M51: 1 | N51: 1 | O51: 0 | Q51: 0 | R51: =INDEX(Owners!$B$4:$B$21,MATCH(D51,Owners!$A$4:$A$21,0)) -> Finance Systems | S51: =AND(F51="closed",ISNUMBER(H51),H51<=Controls!$B$4) -> TRUE | T51: =AND(ISNUMBER(I51),I51<=Controls!$B$4,J51="rerun",K51=A51,L51=C51,M51=N51,O51=0,I51>=G51,IF(ISNUMBER(P51),I51>=P51,TRUE())) -> TRUE | U51: =IF(AND(S51,T51),"resolved",IF(S51,"claimed","open")) -> resolved | V51: =ROUND((IF(U51="resolved",I51,IF(U51="claimed",H51,Controls!$B$4))-G51)*24,4) -> 44.9833 | W51: =INDEX(Owners!$E$4:$E$21,MATCH(D51,Owners!$A$4:$A$21,0)) -> FALSE
A52: iss-0049 | B52: ds-subscriptions | C52: r-subscriptions-complete-plan_code | D52: own-06 | E52: high | F52: closed | G52: 46226.151 | H52: 46227.908 | I52: 46228.026 | J52: rerun | K52: iss-0049 | L52: r-subscriptions-complete-plan_code | M52: 1 | N52: 1 | O52: 0 | Q52: 0 | R52: =INDEX(Owners!$B$4:$B$21,MATCH(D52,Owners!$A$4:$A$21,0)) -> Data Platform | S52: =AND(F52="closed",ISNUMBER(H52),H52<=Controls!$B$4) -> TRUE | T52: =AND(ISNUMBER(I52),I52<=Controls!$B$4,J52="rerun",K52=A52,L52=C52,M52=N52,O52=0,I52>=G52,IF(ISNUMBER(P52),I52>=P52,TRUE())) -> TRUE | U52: =IF(AND(S52,T52),"resolved",IF(S52,"claimed","open")) -> resolved | V52: =ROUND((IF(U52="resolved",I52,IF(U52="claimed",H52,Controls!$B$4))-G52)*24,4) -> 45 | W52: =INDEX(Owners!$E$4:$E$21,MATCH(D52,Owners!$A$4:$A$21,0)) -> TRUE
A53: iss-0050 | B53: ds-products | C53: r-products-complete-category | D53: own-17 | E53: medium | F53: closed | G53: 46226.246 | H53: 46227.576 | N53: 1 | Q53: 0 | R53: =INDEX(Owners!$B$4:$B$21,MATCH(D53,Owners!$A$4:$A$21,0)) -> Support Operations | S53: =AND(F53="closed",ISNUMBER(H53),H53<=Controls!$B$4) -> TRUE | T53: =AND(ISNUMBER(I53),I53<=Controls!$B$4,J53="rerun",K53=A53,L53=C53,M53=N53,O53=0,I53>=G53,IF(ISNUMBER(P53),I53>=P53,TRUE())) -> FALSE | U53: =IF(AND(S53,T53),"resolved",IF(S53,"claimed","open")) -> claimed | V53: =ROUND((IF(U53="resolved",I53,IF(U53="claimed",H53,Controls!$B$4))-G53)*24,4) -> 31.9167 | W53: =INDEX(Owners!$E$4:$E$21,MATCH(D53,Owners!$A$4:$A$21,0)) -> TRUE
A54: iss-0051 | B54: ds-contacts | C54: r-contacts-complete-email | D54: own-12 | E54: high | F54: closed | G54: 46227.119 | H54: 46236.345 | I54: 46236.406 | J54: rerun | K54: iss-0051 | L54: r-contacts-complete-email | M54: 1 | N54: 1 | O54: 0 | Q54: 0 | R54: =INDEX(Owners!$B$4:$B$21,MATCH(D54,Owners!$A$4:$A$21,0)) -> Finance Systems | S54: =AND(F54="closed",ISNUMBER(H54),H54<=Controls!$B$4) -> TRUE | T54: =AND(ISNUMBER(I54),I54<=Controls!$B$4,J54="rerun",K54=A54,L54=C54,M54=N54,O54=0,I54>=G54,IF(ISNUMBER(P54),I54>=P54,TRUE())) -> TRUE | U54: =IF(AND(S54,T54),"resolved",IF(S54,"claimed","open")) -> resolved | V54: =ROUND((IF(U54="resolved",I54,IF(U54="claimed",H54,Controls!$B$4))-G54)*24,4) -> 222.8667 | W54: =INDEX(Owners!$E$4:$E$21,MATCH(D54,Owners!$A$4:$A$21,0)) -> FALSE
A55: iss-0052 | B55: ds-shipments | C55: r-shipments-fk-order_key | D55: own-13 | E55: medium | F55: closed | G55: 46227.129 | H55: 46229.46 | I55: 46229.697 | J55: rerun | K55: iss-0052 | L55: r-shipments-fk-order_key | M55: 1 | N55: 1 | O55: 0 | Q55: 0 | R55: =INDEX(Owners!$B$4:$B$21,MATCH(D55,Owners!$A$4:$A$21,0)) -> Supply Chain | S55: =AND(F55="closed",ISNUMBER(H55),H55<=Controls!$B$4) -> TRUE | T55: =AND(ISNUMBER(I55),I55<=Controls!$B$4,J55="rerun",K55=A55,L55=C55,M55=N55,O55=0,I55>=G55,IF(ISNUMBER(P55),I55>=P55,TRUE())) -> TRUE | U55: =IF(AND(S55,T55),"resolved",IF(S55,"claimed","open")) -> resolved | V55: =ROUND((IF(U55="resolved",I55,IF(U55="claimed",H55,Controls!$B$4))-G55)*24,4) -> 61.6167 | W55: =INDEX(Owners!$E$4:$E$21,MATCH(D55,Owners!$A$4:$A$21,0)) -> TRUE
A56: iss-0053 | B56: ds-refunds | C56: r-refunds-fk-payment_key | D56: own-18 | E56: high | F56: closed | G56: 46227.16 | H56: 46235.727 | I56: 46236.047 | J56: rerun | K56: iss-0053 | L56: r-refunds-fk-payment_key | M56: 1 | N56: 1 | O56: 0 | Q56: 0 | R56: =INDEX(Owners!$B$4:$B$21,MATCH(D56,Owners!$A$4:$A$21,0)) -> Support Operations | S56: =AND(F56="closed",ISNUMBER(H56),H56<=Controls!$B$4) -> TRUE | T56: =AND(ISNUMBER(I56),I56<=Controls!$B$4,J56="rerun",K56=A56,L56=C56,M56=N56,O56=0,I56>=G56,IF(ISNUMBER(P56),I56>=P56,TRUE())) -> TRUE | U56: =IF(AND(S56,T56),"resolved",IF(S56,"claimed","open")) -> resolved | V56: =ROUND((IF(U56="resolved",I56,IF(U56="claimed",H56,Controls!$B$4))-G56)*24,4) -> 213.2833 | W56: =INDEX(Owners!$E$4:$E$21,MATCH(D56,Owners!$A$4:$A$21,0)) -> TRUE
A57: iss-0054 | B57: ds-cost-centres | C57: r-cost-centres-unique-cost_centre_code | D57: own-10 | E57: medium | F57: closed | G57: 46227.242 | H57: 46228.331 | I57: 46228.591 | J57: rerun | K57: iss-0054 | L57: r-cost-centres-unique-cost_centre_code | M57: 1 | N57: 1 | O57: 0 | Q57: 0 | R57: =INDEX(Owners!$B$4:$B$21,MATCH(D57,Owners!$A$4:$A$21,0)) -> Finance Systems | S57: =AND(F57="closed",ISNUMBER(H57),H57<=Controls!$B$4) -> TRUE | T57: =AND(ISNUMBER(I57),I57<=Controls!$B$4,J57="rerun",K57=A57,L57=C57,M57=N57,O57=0,I57>=G57,IF(ISNUMBER(P57),I57>=P57,TRUE())) -> TRUE | U57: =IF(AND(S57,T57),"resolved",IF(S57,"claimed","open")) -> resolved | V57: =ROUND((IF(U57="resolved",I57,IF(U57="claimed",H57,Controls!$B$4))-G57)*24,4) -> 32.3833 | W57: =INDEX(Owners!$E$4:$E$21,MATCH(D57,Owners!$A$4:$A$21,0)) -> TRUE
A58: iss-0055 | B58: ds-invoices | C58: r-invoices-valid-currency | D58: own-09 | E58: high | F58: closed | G58: 46228.097 | H58: 46228.831 | N58: 1 | Q58: 0 | R58: =INDEX(Owners!$B$4:$B$21,MATCH(D58,Owners!$A$4:$A$21,0)) -> Customer Data | S58: =AND(F58="closed",ISNUMBER(H58),H58<=Controls!$B$4) -> TRUE | T58: =AND(ISNUMBER(I58),I58<=Controls!$B$4,J58="rerun",K58=A58,L58=C58,M58=N58,O58=0,I58>=G58,IF(ISNUMBER(P58),I58>=P58,TRUE())) -> FALSE | U58: =IF(AND(S58,T58),"resolved",IF(S58,"claimed","open")) -> claimed | V58: =ROUND((IF(U58="resolved",I58,IF(U58="claimed",H58,Controls!$B$4))-G58)*24,4) -> 17.6167 | W58: =INDEX(Owners!$E$4:$E$21,MATCH(D58,Owners!$A$4:$A$21,0)) -> FALSE
A59: iss-0056 | B59: ds-subscriptions | C59: r-subscriptions-complete-plan_code | D59: own-06 | E59: high | F59: closed | G59: 46228.151 | H59: 46228.647 | I59: 46228.77 | J59: rerun | K59: iss-0056 | L59: r-subscriptions-complete-plan_code | M59: 1 | N59: 1 | O59: 0 | Q59: 0 | R59: =INDEX(Owners!$B$4:$B$21,MATCH(D59,Owners!$A$4:$A$21,0)) -> Data Platform | S59: =AND(F59="closed",ISNUMBER(H59),H59<=Controls!$B$4) -> TRUE | T59: =AND(ISNUMBER(I59),I59<=Controls!$B$4,J59="rerun",K59=A59,L59=C59,M59=N59,O59=0,I59>=G59,IF(ISNUMBER(P59),I59>=P59,TRUE())) -> TRUE | U59: =IF(AND(S59,T59),"resolved",IF(S59,"claimed","open")) -> resolved | V59: =ROUND((IF(U59="resolved",I59,IF(U59="claimed",H59,Controls!$B$4))-G59)*24,4) -> 14.85 | W59: =INDEX(Owners!$E$4:$E$21,MATCH(D59,Owners!$A$4:$A$21,0)) -> TRUE
A60: iss-0057 | B60: ds-products | C60: r-products-complete-category | D60: own-17 | E60: medium | F60: closed | G60: 46228.246 | H60: 46228.912 | N60: 1 | Q60: 0 | R60: =INDEX(Owners!$B$4:$B$21,MATCH(D60,Owners!$A$4:$A$21,0)) -> Support Operations | S60: =AND(F60="closed",ISNUMBER(H60),H60<=Controls!$B$4) -> TRUE | T60: =AND(ISNUMBER(I60),I60<=Controls!$B$4,J60="rerun",K60=A60,L60=C60,M60=N60,O60=0,I60>=G60,IF(ISNUMBER(P60),I60>=P60,TRUE())) -> FALSE | U60: =IF(AND(S60,T60),"resolved",IF(S60,"claimed","open")) -> claimed | V60: =ROUND((IF(U60="resolved",I60,IF(U60="claimed",H60,Controls!$B$4))-G60)*24,4) -> 16 | W60: =INDEX(Owners!$E$4:$E$21,MATCH(D60,Owners!$A$4:$A$21,0)) -> TRUE
A61: iss-0058 | B61: ds-orders | C61: r-orders-fresh | D61: own-04 | E61: medium | F61: closed | G61: 46228.993 | H61: 46232.24 | N61: 1 | Q61: 0 | R61: =INDEX(Owners!$B$4:$B$21,MATCH(D61,Owners!$A$4:$A$21,0)) -> Data Platform | S61: =AND(F61="closed",ISNUMBER(H61),H61<=Controls!$B$4) -> TRUE | T61: =AND(ISNUMBER(I61),I61<=Controls!$B$4,J61="rerun",K61=A61,L61=C61,M61=N61,O61=0,I61>=G61,IF(ISNUMBER(P61),I61>=P61,TRUE())) -> FALSE | U61: =IF(AND(S61,T61),"resolved",IF(S61,"claimed","open")) -> claimed | V61: =ROUND((IF(U61="resolved",I61,IF(U61="claimed",H61,Controls!$B$4))-G61)*24,4) -> 77.9167 | W61: =INDEX(Owners!$E$4:$E$21,MATCH(D61,Owners!$A$4:$A$21,0)) -> TRUE
A62: iss-0059 | B62: ds-ticket-events | C62: r-ticket-events-valid-ticket_key | D62: own-11 | E62: medium | F62: closed | G62: 46229.089 | H62: 46231.56 | I62: 46231.747 | J62: rerun | K62: iss-0059 | L62: r-ticket-events-valid-ticket_key | M62: 1 | N62: 1 | O62: 0 | Q62: 0 | R62: =INDEX(Owners!$B$4:$B$21,MATCH(D62,Owners!$A$4:$A$21,0)) -> Finance Systems | S62: =AND(F62="closed",ISNUMBER(H62),H62<=Controls!$B$4) -> TRUE | T62: =AND(ISNUMBER(I62),I62<=Controls!$B$4,J62="rerun",K62=A62,L62=C62,M62=N62,O62=0,I62>=G62,IF(ISNUMBER(P62),I62>=P62,TRUE())) -> TRUE | U62: =IF(AND(S62,T62),"resolved",IF(S62,"claimed","open")) -> resolved | V62: =ROUND((IF(U62="resolved",I62,IF(U62="claimed",H62,Controls!$B$4))-G62)*24,4) -> 63.8 | W62: =INDEX(Owners!$E$4:$E$21,MATCH(D62,Owners!$A$4:$A$21,0)) -> TRUE
A63: iss-0060 | B63: ds-contacts | C63: r-contacts-complete-email | D63: own-12 | E63: high | F63: closed | G63: 46229.119 | H63: 46232.482 | I63: 46232.578 | J63: rerun | K63: iss-0060 | L63: r-contacts-complete-email | M63: 1 | N63: 1 | O63: 0 | Q63: 0 | R63: =INDEX(Owners!$B$4:$B$21,MATCH(D63,Owners!$A$4:$A$21,0)) -> Finance Systems | S63: =AND(F63="closed",ISNUMBER(H63),H63<=Controls!$B$4) -> TRUE | T63: =AND(ISNUMBER(I63),I63<=Controls!$B$4,J63="rerun",K63=A63,L63=C63,M63=N63,O63=0,I63>=G63,IF(ISNUMBER(P63),I63>=P63,TRUE())) -> TRUE | U63: =IF(AND(S63,T63),"resolved",IF(S63,"claimed","open")) -> resolved | V63: =ROUND((IF(U63="resolved",I63,IF(U63="claimed",H63,Controls!$B$4))-G63)*24,4) -> 83.0167 | W63: =INDEX(Owners!$E$4:$E$21,MATCH(D63,Owners!$A$4:$A$21,0)) -> FALSE
A64: iss-0061 | B64: ds-accounts | C64: r-accounts-fk-customer_key | D64: own-14 | E64: high | F64: closed | G64: 46229.147 | H64: 46230.164 | I64: 46230.772 | J64: rerun | K64: iss-0061 | L64: r-accounts-fk-customer_key | M64: 1 | N64: 1 | O64: 0 | Q64: 0 | R64: =INDEX(Owners!$B$4:$B$21,MATCH(D64,Owners!$A$4:$A$21,0)) -> Supply Chain | S64: =AND(F64="closed",ISNUMBER(H64),H64<=Controls!$B$4) -> TRUE | T64: =AND(ISNUMBER(I64),I64<=Controls!$B$4,J64="rerun",K64=A64,L64=C64,M64=N64,O64=0,I64>=G64,IF(ISNUMBER(P64),I64>=P64,TRUE())) -> TRUE | U64: =IF(AND(S64,T64),"resolved",IF(S64,"claimed","open")) -> resolved | V64: =ROUND((IF(U64="resolved",I64,IF(U64="claimed",H64,Controls!$B$4))-G64)*24,4) -> 39.0167 | W64: =INDEX(Owners!$E$4:$E$21,MATCH(D64,Owners!$A$4:$A$21,0)) -> TRUE
A65: iss-0062 | B65: ds-web-users | C65: r-web-users-complete-email | D65: own-05 | E65: high | F65: closed | G65: 46229.192 | H65: 46229.52 | I65: 46229.715 | J65: rerun | K65: iss-0062 | L65: r-web-users-complete-email | M65: 1 | N65: 1 | O65: 0 | Q65: 0 | R65: =INDEX(Owners!$B$4:$B$21,MATCH(D65,Owners!$A$4:$A$21,0)) -> Data Platform | S65: =AND(F65="closed",ISNUMBER(H65),H65<=Controls!$B$4) -> TRUE | T65: =AND(ISNUMBER(I65),I65<=Controls!$B$4,J65="rerun",K65=A65,L65=C65,M65=N65,O65=0,I65>=G65,IF(ISNUMBER(P65),I65>=P65,TRUE())) -> TRUE | U65: =IF(AND(S65,T65),"resolved",IF(S65,"claimed","open")) -> resolved | V65: =ROUND((IF(U65="resolved",I65,IF(U65="claimed",H65,Controls!$B$4))-G65)*24,4) -> 12.5333 | W65: =INDEX(Owners!$E$4:$E$21,MATCH(D65,Owners!$A$4:$A$21,0)) -> TRUE
A66: iss-0063 | B66: ds-cost-centres | C66: r-cost-centres-unique-cost_centre_code | D66: own-10 | E66: medium | F66: closed | G66: 46229.242 | H66: 46236.87 | I66: 46237.055 | J66: rerun | K66: iss-0063 | L66: r-cost-centres-unique-cost_centre_code | M66: 1 | N66: 1 | O66: 0 | Q66: 0 | R66: =INDEX(Owners!$B$4:$B$21,MATCH(D66,Owners!$A$4:$A$21,0)) -> Finance Systems | S66: =AND(F66="closed",ISNUMBER(H66),H66<=Controls!$B$4) -> TRUE | T66: =AND(ISNUMBER(I66),I66<=Controls!$B$4,J66="rerun",K66=A66,L66=C66,M66=N66,O66=0,I66>=G66,IF(ISNUMBER(P66),I66>=P66,TRUE())) -> TRUE | U66: =IF(AND(S66,T66),"resolved",IF(S66,"claimed","open")) -> resolved | V66: =ROUND((IF(U66="resolved",I66,IF(U66="claimed",H66,Controls!$B$4))-G66)*24,4) -> 187.5167 | W66: =INDEX(Owners!$E$4:$E$21,MATCH(D66,Owners!$A$4:$A$21,0)) -> TRUE
A67: iss-0064 | B67: ds-purchase-orders | C67: r-purchase-orders-fresh | D67: own-04 | E67: high | F67: closed | G67: 46229.993 | H67: 46230.814 | I67: 46230.908 | J67: rerun | K67: iss-0064 | L67: r-purchase-orders-fresh | M67: 1 | N67: 1 | O67: 0 | Q67: 0 | R67: =INDEX(Owners!$B$4:$B$21,MATCH(D67,Owners!$A$4:$A$21,0)) -> Data Platform | S67: =AND(F67="closed",ISNUMBER(H67),H67<=Controls!$B$4) -> TRUE | T67: =AND(ISNUMBER(I67),I67<=Controls!$B$4,J67="rerun",K67=A67,L67=C67,M67=N67,O67=0,I67>=G67,IF(ISNUMBER(P67),I67>=P67,TRUE())) -> TRUE | U67: =IF(AND(S67,T67),"resolved",IF(S67,"claimed","open")) -> resolved | V67: =ROUND((IF(U67="resolved",I67,IF(U67="claimed",H67,Controls!$B$4))-G67)*24,4) -> 21.95 | W67: =INDEX(Owners!$E$4:$E$21,MATCH(D67,Owners!$A$4:$A$21,0)) -> TRUE
A68: iss-0065 | B68: ds-cost-centres | C68: r-cost-centres-complete-owner_ref | D68: own-10 | E68: high | F68: closed | G68: 46230.084 | H68: 46230.971 | I68: 46231.474 | J68: rerun | K68: iss-0065 | L68: r-cost-centres-complete-owner_ref | M68: 1 | N68: 1 | O68: 0 | Q68: 0 | R68: =INDEX(Owners!$B$4:$B$21,MATCH(D68,Owners!$A$4:$A$21,0)) -> Finance Systems | S68: =AND(F68="closed",ISNUMBER(H68),H68<=Controls!$B$4) -> TRUE | T68: =AND(ISNUMBER(I68),I68<=Controls!$B$4,J68="rerun",K68=A68,L68=C68,M68=N68,O68=0,I68>=G68,IF(ISNUMBER(P68),I68>=P68,TRUE())) -> TRUE | U68: =IF(AND(S68,T68),"resolved",IF(S68,"claimed","open")) -> resolved | V68: =ROUND((IF(U68="resolved",I68,IF(U68="claimed",H68,Controls!$B$4))-G68)*24,4) -> 33.35 | W68: =INDEX(Owners!$E$4:$E$21,MATCH(D68,Owners!$A$4:$A$21,0)) -> TRUE
A69: iss-0066 | B69: ds-tickets | C69: r-tickets-fk-customer_key | D69: own-05 | E69: medium | F69: closed | G69: 46230.102 | H69: 46239.252 | N69: 1 | Q69: 0 | R69: =INDEX(Owners!$B$4:$B$21,MATCH(D69,Owners!$A$4:$A$21,0)) -> Data Platform | S69: =AND(F69="closed",ISNUMBER(H69),H69<=Controls!$B$4) -> TRUE | T69: =AND(ISNUMBER(I69),I69<=Controls!$B$4,J69="rerun",K69=A69,L69=C69,M69=N69,O69=0,I69>=G69,IF(ISNUMBER(P69),I69>=P69,TRUE())) -> FALSE | U69: =IF(AND(S69,T69),"resolved",IF(S69,"claimed","open")) -> claimed | V69: =ROUND((IF(U69="resolved",I69,IF(U69="claimed",H69,Controls!$B$4))-G69)*24,4) -> 219.6 | W69: =INDEX(Owners!$E$4:$E$21,MATCH(D69,Owners!$A$4:$A$21,0)) -> TRUE
A70: iss-0067 | B70: ds-shipments | C70: r-shipments-fk-order_key | D70: own-13 | E70: medium | F70: closed | G70: 46230.129 | H70: 46237.608 | I70: 46237.788 | J70: rerun | K70: iss-0067 | L70: r-shipments-fk-order_key | M70: 1 | N70: 1 | O70: 0 | Q70: 0 | R70: =INDEX(Owners!$B$4:$B$21,MATCH(D70,Owners!$A$4:$A$21,0)) -> Supply Chain | S70: =AND(F70="closed",ISNUMBER(H70),H70<=Controls!$B$4) -> TRUE | T70: =AND(ISNUMBER(I70),I70<=Controls!$B$4,J70="rerun",K70=A70,L70=C70,M70=N70,O70=0,I70>=G70,IF(ISNUMBER(P70),I70>=P70,TRUE())) -> TRUE | U70: =IF(AND(S70,T70),"resolved",IF(S70,"claimed","open")) -> resolved | V70: =ROUND((IF(U70="resolved",I70,IF(U70="claimed",H70,Controls!$B$4))-G70)*24,4) -> 183.8167 | W70: =INDEX(Owners!$E$4:$E$21,MATCH(D70,Owners!$A$4:$A$21,0)) -> TRUE
A71: iss-0068 | B71: ds-leads | C71: r-leads-valid-email | D71: own-18 | E71: high | F71: closed | G71: 46230.156 | H71: 46235.866 | I71: 46236.081 | J71: rerun | K71: iss-0068 | L71: r-leads-valid-email | M71: 1 | N71: 1 | O71: 0 | Q71: 0 | R71: =INDEX(Owners!$B$4:$B$21,MATCH(D71,Owners!$A$4:$A$21,0)) -> Support Operations | S71: =AND(F71="closed",ISNUMBER(H71),H71<=Controls!$B$4) -> TRUE | T71: =AND(ISNUMBER(I71),I71<=Controls!$B$4,J71="rerun",K71=A71,L71=C71,M71=N71,O71=0,I71>=G71,IF(ISNUMBER(P71),I71>=P71,TRUE())) -> TRUE | U71: =IF(AND(S71,T71),"resolved",IF(S71,"claimed","open")) -> resolved | V71: =ROUND((IF(U71="resolved",I71,IF(U71="claimed",H71,Controls!$B$4))-G71)*24,4) -> 142.2 | W71: =INDEX(Owners!$E$4:$E$21,MATCH(D71,Owners!$A$4:$A$21,0)) -> TRUE
A72: iss-0069 | B72: ds-opportunities | C72: r-opportunities-fk-account_key | D72: own-04 | E72: high | F72: closed | G72: 46230.165 | H72: 46231.163 | N72: 1 | Q72: 0 | R72: =INDEX(Owners!$B$4:$B$21,MATCH(D72,Owners!$A$4:$A$21,0)) -> Data Platform | S72: =AND(F72="closed",ISNUMBER(H72),H72<=Controls!$B$4) -> TRUE | T72: =AND(ISNUMBER(I72),I72<=Controls!$B$4,J72="rerun",K72=A72,L72=C72,M72=N72,O72=0,I72>=G72,IF(ISNUMBER(P72),I72>=P72,TRUE())) -> FALSE | U72: =IF(AND(S72,T72),"resolved",IF(S72,"claimed","open")) -> claimed | V72: =ROUND((IF(U72="resolved",I72,IF(U72="claimed",H72,Controls!$B$4))-G72)*24,4) -> 23.9667 | W72: =INDEX(Owners!$E$4:$E$21,MATCH(D72,Owners!$A$4:$A$21,0)) -> TRUE
A73: iss-0070 | B73: ds-cost-centres | C73: r-cost-centres-complete-owner_ref | D73: own-10 | E73: high | F73: closed | G73: 46231.084 | H73: 46236.63 | I73: 46236.711 | J73: rerun | K73: iss-0070 | L73: r-cost-centres-complete-owner_ref | M73: 1 | N73: 1 | O73: 0 | Q73: 0 | R73: =INDEX(Owners!$B$4:$B$21,MATCH(D73,Owners!$A$4:$A$21,0)) -> Finance Systems | S73: =AND(F73="closed",ISNUMBER(H73),H73<=Controls!$B$4) -> TRUE | T73: =AND(ISNUMBER(I73),I73<=Controls!$B$4,J73="rerun",K73=A73,L73=C73,M73=N73,O73=0,I73>=G73,IF(ISNUMBER(P73),I73>=P73,TRUE())) -> TRUE | U73: =IF(AND(S73,T73),"resolved",IF(S73,"claimed","open")) -> resolved | V73: =ROUND((IF(U73="resolved",I73,IF(U73="claimed",H73,Controls!$B$4))-G73)*24,4) -> 135.05 | W73: =INDEX(Owners!$E$4:$E$21,MATCH(D73,Owners!$A$4:$A$21,0)) -> TRUE
A74: iss-0071 | B74: ds-customers | C74: r-customers-unique-customer_key | D74: own-07 | E74: critical | F74: closed | G74: 46231.101 | H74: 46235.19 | I74: 46235.276 | J74: rerun | K74: iss-0071 | L74: r-customers-unique-customer_key | M74: 1 | N74: 1 | O74: 0 | Q74: 0 | R74: =INDEX(Owners!$B$4:$B$21,MATCH(D74,Owners!$A$4:$A$21,0)) -> Customer Data | S74: =AND(F74="closed",ISNUMBER(H74),H74<=Controls!$B$4) -> TRUE | T74: =AND(ISNUMBER(I74),I74<=Controls!$B$4,J74="rerun",K74=A74,L74=C74,M74=N74,O74=0,I74>=G74,IF(ISNUMBER(P74),I74>=P74,TRUE())) -> TRUE | U74: =IF(AND(S74,T74),"resolved",IF(S74,"claimed","open")) -> resolved | V74: =ROUND((IF(U74="resolved",I74,IF(U74="claimed",H74,Controls!$B$4))-G74)*24,4) -> 100.2 | W74: =INDEX(Owners!$E$4:$E$21,MATCH(D74,Owners!$A$4:$A$21,0)) -> TRUE
A75: iss-0072 | B75: ds-tickets | C75: r-tickets-fk-customer_key | D75: own-05 | E75: medium | F75: closed | G75: 46231.102 | H75: 46233.469 | I75: 46233.641 | J75: rerun | K75: iss-0072 | L75: r-tickets-fk-customer_key | M75: 1 | N75: 1 | O75: 0 | Q75: 0 | R75: =INDEX(Owners!$B$4:$B$21,MATCH(D75,Owners!$A$4:$A$21,0)) -> Data Platform | S75: =AND(F75="closed",ISNUMBER(H75),H75<=Controls!$B$4) -> TRUE | T75: =AND(ISNUMBER(I75),I75<=Controls!$B$4,J75="rerun",K75=A75,L75=C75,M75=N75,O75=0,I75>=G75,IF(ISNUMBER(P75),I75>=P75,TRUE())) -> TRUE | U75: =IF(AND(S75,T75),"resolved",IF(S75,"claimed","open")) -> resolved | V75: =ROUND((IF(U75="resolved",I75,IF(U75="claimed",H75,Controls!$B$4))-G75)*24,4) -> 60.9333 | W75: =INDEX(Owners!$E$4:$E$21,MATCH(D75,Owners!$A$4:$A$21,0)) -> TRUE
A76: iss-0073 | B76: ds-refunds | C76: r-refunds-fk-payment_key | D76: own-18 | E76: high | F76: closed | G76: 46231.16 | H76: 46232.269 | N76: 1 | Q76: 0 | R76: =INDEX(Owners!$B$4:$B$21,MATCH(D76,Owners!$A$4:$A$21,0)) -> Support Operations | S76: =AND(F76="closed",ISNUMBER(H76),H76<=Controls!$B$4) -> TRUE | T76: =AND(ISNUMBER(I76),I76<=Controls!$B$4,J76="rerun",K76=A76,L76=C76,M76=N76,O76=0,I76>=G76,IF(ISNUMBER(P76),I76>=P76,TRUE())) -> FALSE | U76: =IF(AND(S76,T76),"resolved",IF(S76,"claimed","open")) -> claimed | V76: =ROUND((IF(U76="resolved",I76,IF(U76="claimed",H76,Controls!$B$4))-G76)*24,4) -> 26.6 | W76: =INDEX(Owners!$E$4:$E$21,MATCH(D76,Owners!$A$4:$A$21,0)) -> TRUE
A77: iss-0074 | B77: ds-suppliers | C77: r-suppliers-unique-supplier_key | D77: own-15 | E77: high | F77: closed | G77: 46231.188 | H77: 46232.08 | I77: 46232.314 | J77: rerun | K77: iss-0074 | L77: r-suppliers-unique-supplier_key | M77: 1 | N77: 1 | O77: 0 | Q77: 0 | R77: =INDEX(Owners!$B$4:$B$21,MATCH(D77,Owners!$A$4:$A$21,0)) -> Supply Chain | S77: =AND(F77="closed",ISNUMBER(H77),H77<=Controls!$B$4) -> TRUE | T77: =AND(ISNUMBER(I77),I77<=Controls!$B$4,J77="rerun",K77=A77,L77=C77,M77=N77,O77=0,I77>=G77,IF(ISNUMBER(P77),I77>=P77,TRUE())) -> TRUE | U77: =IF(AND(S77,T77),"resolved",IF(S77,"claimed","open")) -> resolved | V77: =ROUND((IF(U77="resolved",I77,IF(U77="claimed",H77,Controls!$B$4))-G77)*24,4) -> 27.0333 | W77: =INDEX(Owners!$E$4:$E$21,MATCH(D77,Owners!$A$4:$A$21,0)) -> FALSE
A78: iss-0075 | B78: ds-ledger-entries | C78: r-ledger-entries-complete-amount | D78: own-12 | E78: high | F78: closed | G78: 46231.233 | H78: 46232.61 | I78: 46232.763 | J78: rerun | K78: iss-0075 | L78: r-ledger-entries-complete-amount | M78: 1 | N78: 1 | O78: 0 | Q78: 0 | R78: =INDEX(Owners!$B$4:$B$21,MATCH(D78,Owners!$A$4:$A$21,0)) -> Finance Systems | S78: =AND(F78="closed",ISNUMBER(H78),H78<=Controls!$B$4) -> TRUE | T78: =AND(ISNUMBER(I78),I78<=Controls!$B$4,J78="rerun",K78=A78,L78=C78,M78=N78,O78=0,I78>=G78,IF(ISNUMBER(P78),I78>=P78,TRUE())) -> TRUE | U78: =IF(AND(S78,T78),"resolved",IF(S78,"claimed","open")) -> resolved | V78: =ROUND((IF(U78="resolved",I78,IF(U78="claimed",H78,Controls!$B$4))-G78)*24,4) -> 36.7333 | W78: =INDEX(Owners!$E$4:$E$21,MATCH(D78,Owners!$A$4:$A$21,0)) -> FALSE
A79: iss-0076 | B79: ds-ticket-events | C79: r-ticket-events-valid-ticket_key | D79: own-11 | E79: medium | F79: closed | G79: 46232.089 | H79: 46233.086 | N79: 1 | Q79: 0 | R79: =INDEX(Owners!$B$4:$B$21,MATCH(D79,Owners!$A$4:$A$21,0)) -> Finance Systems | S79: =AND(F79="closed",ISNUMBER(H79),H79<=Controls!$B$4) -> TRUE | T79: =AND(ISNUMBER(I79),I79<=Controls!$B$4,J79="rerun",K79=A79,L79=C79,M79=N79,O79=0,I79>=G79,IF(ISNUMBER(P79),I79>=P79,TRUE())) -> FALSE | U79: =IF(AND(S79,T79),"resolved",IF(S79,"claimed","open")) -> claimed | V79: =ROUND((IF(U79="resolved",I79,IF(U79="claimed",H79,Controls!$B$4))-G79)*24,4) -> 23.9333 | W79: =INDEX(Owners!$E$4:$E$21,MATCH(D79,Owners!$A$4:$A$21,0)) -> TRUE
A80: iss-0077 | B80: ds-tickets | C80: r-tickets-fk-customer_key | D80: own-05 | E80: medium | F80: closed | G80: 46232.102 | H80: 46232.965 | I80: 46233.134 | J80: rerun | K80: iss-0077 | L80: r-tickets-fk-customer_key | M80: 1 | N80: 1 | O80: 0 | Q80: 0 | R80: =INDEX(Owners!$B$4:$B$21,MATCH(D80,Owners!$A$4:$A$21,0)) -> Data Platform | S80: =AND(F80="closed",ISNUMBER(H80),H80<=Controls!$B$4) -> TRUE | T80: =AND(ISNUMBER(I80),I80<=Controls!$B$4,J80="rerun",K80=A80,L80=C80,M80=N80,O80=0,I80>=G80,IF(ISNUMBER(P80),I80>=P80,TRUE())) -> TRUE | U80: =IF(AND(S80,T80),"resolved",IF(S80,"claimed","open")) -> resolved | V80: =ROUND((IF(U80="resolved",I80,IF(U80="claimed",H80,Controls!$B$4))-G80)*24,4) -> 24.7667 | W80: =INDEX(Owners!$E$4:$E$21,MATCH(D80,Owners!$A$4:$A$21,0)) -> TRUE
A81: iss-0078 | B81: ds-carriers | C81: r-carriers-valid-carrier_code | D81: own-05 | E81: medium | F81: closed | G81: 46232.107 | H81: 46234.128 | I81: 46234.183 | J81: rerun | K81: iss-0078 | L81: r-carriers-valid-carrier_code | M81: 1 | N81: 1 | O81: 0 | Q81: 0 | R81: =INDEX(Owners!$B$4:$B$21,MATCH(D81,Owners!$A$4:$A$21,0)) -> Data Platform | S81: =AND(F81="closed",ISNUMBER(H81),H81<=Controls!$B$4) -> TRUE | T81: =AND(ISNUMBER(I81),I81<=Controls!$B$4,J81="rerun",K81=A81,L81=C81,M81=N81,O81=0,I81>=G81,IF(ISNUMBER(P81),I81>=P81,TRUE())) -> TRUE | U81: =IF(AND(S81,T81),"resolved",IF(S81,"claimed","open")) -> resolved | V81: =ROUND((IF(U81="resolved",I81,IF(U81="claimed",H81,Controls!$B$4))-G81)*24,4) -> 49.8333 | W81: =INDEX(Owners!$E$4:$E$21,MATCH(D81,Owners!$A$4:$A$21,0)) -> TRUE
A82: iss-0079 | B82: ds-subscriptions | C82: r-subscriptions-fk-customer_key | D82: own-06 | E82: high | F82: closed | G82: 46232.142 | H82: 46232.952 | I82: 46233.147 | J82: rerun | K82: iss-0079 | L82: r-subscriptions-fk-customer_key | M82: 1 | N82: 1 | O82: 0 | Q82: 0 | R82: =INDEX(Owners!$B$4:$B$21,MATCH(D82,Owners!$A$4:$A$21,0)) -> Data Platform | S82: =AND(F82="closed",ISNUMBER(H82),H82<=Controls!$B$4) -> TRUE | T82: =AND(ISNUMBER(I82),I82<=Controls!$B$4,J82="rerun",K82=A82,L82=C82,M82=N82,O82=0,I82>=G82,IF(ISNUMBER(P82),I82>=P82,TRUE())) -> TRUE | U82: =IF(AND(S82,T82),"resolved",IF(S82,"claimed","open")) -> resolved | V82: =ROUND((IF(U82="resolved",I82,IF(U82="claimed",H82,Controls!$B$4))-G82)*24,4) -> 24.1 | W82: =INDEX(Owners!$E$4:$E$21,MATCH(D82,Owners!$A$4:$A$21,0)) -> TRUE
A83: iss-0080 | B83: ds-subscriptions | C83: r-subscriptions-complete-plan_code | D83: own-06 | E83: high | F83: closed | G83: 46232.151 | H83: 46235.174 | N83: 1 | Q83: 0 | R83: =INDEX(Owners!$B$4:$B$21,MATCH(D83,Owners!$A$4:$A$21,0)) -> Data Platform | S83: =AND(F83="closed",ISNUMBER(H83),H83<=Controls!$B$4) -> TRUE | T83: =AND(ISNUMBER(I83),I83<=Controls!$B$4,J83="rerun",K83=A83,L83=C83,M83=N83,O83=0,I83>=G83,IF(ISNUMBER(P83),I83>=P83,TRUE())) -> FALSE | U83: =IF(AND(S83,T83),"resolved",IF(S83,"claimed","open")) -> claimed | V83: =ROUND((IF(U83="resolved",I83,IF(U83="claimed",H83,Controls!$B$4))-G83)*24,4) -> 72.5333 | W83: =INDEX(Owners!$E$4:$E$21,MATCH(D83,Owners!$A$4:$A$21,0)) -> TRUE
A84: iss-0081 | B84: ds-suppliers | C84: r-suppliers-valid-contact_email | D84: own-15 | E84: low | F84: closed | G84: 46232.178 | H84: 46234.389 | I84: 46234.694 | J84: rerun | K84: iss-0081 | L84: r-suppliers-valid-contact_email | M84: 1 | N84: 1 | O84: 0 | Q84: 0 | R84: =INDEX(Owners!$B$4:$B$21,MATCH(D84,Owners!$A$4:$A$21,0)) -> Supply Chain | S84: =AND(F84="closed",ISNUMBER(H84),H84<=Controls!$B$4) -> TRUE | T84: =AND(ISNUMBER(I84),I84<=Controls!$B$4,J84="rerun",K84=A84,L84=C84,M84=N84,O84=0,I84>=G84,IF(ISNUMBER(P84),I84>=P84,TRUE())) -> TRUE | U84: =IF(AND(S84,T84),"resolved",IF(S84,"claimed","open")) -> resolved | V84: =ROUND((IF(U84="resolved",I84,IF(U84="claimed",H84,Controls!$B$4))-G84)*24,4) -> 60.3833 | W84: =INDEX(Owners!$E$4:$E$21,MATCH(D84,Owners!$A$4:$A$21,0)) -> FALSE
A85: iss-0082 | B85: ds-suppliers | C85: r-suppliers-unique-supplier_key | D85: own-15 | E85: high | F85: closed | G85: 46232.188 | H85: 46233.485 | N85: 1 | Q85: 0 | R85: =INDEX(Owners!$B$4:$B$21,MATCH(D85,Owners!$A$4:$A$21,0)) -> Supply Chain | S85: =AND(F85="closed",ISNUMBER(H85),H85<=Controls!$B$4) -> TRUE | T85: =AND(ISNUMBER(I85),I85<=Controls!$B$4,J85="rerun",K85=A85,L85=C85,M85=N85,O85=0,I85>=G85,IF(ISNUMBER(P85),I85>=P85,TRUE())) -> FALSE | U85: =IF(AND(S85,T85),"resolved",IF(S85,"claimed","open")) -> claimed | V85: =ROUND((IF(U85="resolved",I85,IF(U85="claimed",H85,Controls!$B$4))-G85)*24,4) -> 31.15 | W85: =INDEX(Owners!$E$4:$E$21,MATCH(D85,Owners!$A$4:$A$21,0)) -> FALSE
A86: iss-0083 | B86: ds-invoices | C86: r-invoices-valid-currency | D86: own-09 | E86: high | F86: closed | G86: 46233.097 | H86: 46237.606 | I86: 46238.112 | J86: rerun | K86: iss-0083 | L86: r-invoices-valid-currency | M86: 1 | N86: 1 | O86: 0 | Q86: 0 | R86: =INDEX(Owners!$B$4:$B$21,MATCH(D86,Owners!$A$4:$A$21,0)) -> Customer Data | S86: =AND(F86="closed",ISNUMBER(H86),H86<=Controls!$B$4) -> TRUE | T86: =AND(ISNUMBER(I86),I86<=Controls!$B$4,J86="rerun",K86=A86,L86=C86,M86=N86,O86=0,I86>=G86,IF(ISNUMBER(P86),I86>=P86,TRUE())) -> TRUE | U86: =IF(AND(S86,T86),"resolved",IF(S86,"claimed","open")) -> resolved | V86: =ROUND((IF(U86="resolved",I86,IF(U86="claimed",H86,Controls!$B$4))-G86)*24,4) -> 120.35 | W86: =INDEX(Owners!$E$4:$E$21,MATCH(D86,Owners!$A$4:$A$21,0)) -> FALSE
A87: iss-0084 | B87: ds-opportunities | C87: r-opportunities-fk-account_key | D87: own-04 | E87: high | F87: closed | G87: 46233.165 | H87: 46234.569 | I87: 46234.747 | J87: rerun | K87: iss-0084 | L87: r-opportunities-fk-account_key | M87: 1 | N87: 1 | O87: 0 | Q87: 0 | R87: =INDEX(Owners!$B$4:$B$21,MATCH(D87,Owners!$A$4:$A$21,0)) -> Data Platform | S87: =AND(F87="closed",ISNUMBER(H87),H87<=Controls!$B$4) -> TRUE | T87: =AND(ISNUMBER(I87),I87<=Controls!$B$4,J87="rerun",K87=A87,L87=C87,M87=N87,O87=0,I87>=G87,IF(ISNUMBER(P87),I87>=P87,TRUE())) -> TRUE | U87: =IF(AND(S87,T87),"resolved",IF(S87,"claimed","open")) -> resolved | V87: =ROUND((IF(U87="resolved",I87,IF(U87="claimed",H87,Controls!$B$4))-G87)*24,4) -> 37.9667 | W87: =INDEX(Owners!$E$4:$E$21,MATCH(D87,Owners!$A$4:$A$21,0)) -> TRUE
A88: iss-0085 | B88: ds-web-users | C88: r-web-users-complete-email | D88: own-05 | E88: high | F88: closed | G88: 46233.192 | H88: 46234.199 | N88: 1 | Q88: 0 | R88: =INDEX(Owners!$B$4:$B$21,MATCH(D88,Owners!$A$4:$A$21,0)) -> Data Platform | S88: =AND(F88="closed",ISNUMBER(H88),H88<=Controls!$B$4) -> TRUE | T88: =AND(ISNUMBER(I88),I88<=Controls!$B$4,J88="rerun",K88=A88,L88=C88,M88=N88,O88=0,I88>=G88,IF(ISNUMBER(P88),I88>=P88,TRUE())) -> FALSE | U88: =IF(AND(S88,T88),"resolved",IF(S88,"claimed","open")) -> claimed | V88: =ROUND((IF(U88="resolved",I88,IF(U88="claimed",H88,Controls!$B$4))-G88)*24,4) -> 24.1667 | W88: =INDEX(Owners!$E$4:$E$21,MATCH(D88,Owners!$A$4:$A$21,0)) -> TRUE
A89: iss-0086 | B89: ds-cost-centres | C89: r-cost-centres-complete-owner_ref | D89: own-10 | E89: high | F89: closed | G89: 46234.084 | H89: 46237.511 | I89: 46237.623 | J89: rerun | K89: iss-0086 | L89: r-cost-centres-complete-owner_ref | M89: 1 | N89: 1 | O89: 0 | Q89: 0 | R89: =INDEX(Owners!$B$4:$B$21,MATCH(D89,Owners!$A$4:$A$21,0)) -> Finance Systems | S89: =AND(F89="closed",ISNUMBER(H89),H89<=Controls!$B$4) -> TRUE | T89: =AND(ISNUMBER(I89),I89<=Controls!$B$4,J89="rerun",K89=A89,L89=C89,M89=N89,O89=0,I89>=G89,IF(ISNUMBER(P89),I89>=P89,TRUE())) -> TRUE | U89: =IF(AND(S89,T89),"resolved",IF(S89,"claimed","open")) -> resolved | V89: =ROUND((IF(U89="resolved",I89,IF(U89="claimed",H89,Controls!$B$4))-G89)*24,4) -> 84.9333 | W89: =INDEX(Owners!$E$4:$E$21,MATCH(D89,Owners!$A$4:$A$21,0)) -> TRUE
A90: iss-0087 | B90: ds-invoices | C90: r-invoices-valid-currency | D90: own-09 | E90: high | F90: closed | G90: 46234.097 | H90: 46239.808 | I90: 46240.012 | J90: rerun | K90: iss-0087 | L90: r-invoices-valid-currency | M90: 1 | N90: 1 | O90: 0 | Q90: 0 | R90: =INDEX(Owners!$B$4:$B$21,MATCH(D90,Owners!$A$4:$A$21,0)) -> Customer Data | S90: =AND(F90="closed",ISNUMBER(H90),H90<=Controls!$B$4) -> TRUE | T90: =AND(ISNUMBER(I90),I90<=Controls!$B$4,J90="rerun",K90=A90,L90=C90,M90=N90,O90=0,I90>=G90,IF(ISNUMBER(P90),I90>=P90,TRUE())) -> TRUE | U90: =IF(AND(S90,T90),"resolved",IF(S90,"claimed","open")) -> resolved | V90: =ROUND((IF(U90="resolved",I90,IF(U90="claimed",H90,Controls!$B$4))-G90)*24,4) -> 141.95 | W90: =INDEX(Owners!$E$4:$E$21,MATCH(D90,Owners!$A$4:$A$21,0)) -> FALSE
A91: iss-0088 | B91: ds-contacts | C91: r-contacts-complete-email | D91: own-12 | E91: high | F91: closed | G91: 46234.119 | H91: 46236.515 | I91: 46237.092 | J91: rerun | K91: iss-0088 | L91: r-contacts-complete-email | M91: 1 | N91: 1 | O91: 0 | Q91: 0 | R91: =INDEX(Owners!$B$4:$B$21,MATCH(D91,Owners!$A$4:$A$21,0)) -> Finance Systems | S91: =AND(F91="closed",ISNUMBER(H91),H91<=Controls!$B$4) -> TRUE | T91: =AND(ISNUMBER(I91),I91<=Controls!$B$4,J91="rerun",K91=A91,L91=C91,M91=N91,O91=0,I91>=G91,IF(ISNUMBER(P91),I91>=P91,TRUE())) -> TRUE | U91: =IF(AND(S91,T91),"resolved",IF(S91,"claimed","open")) -> resolved | V91: =ROUND((IF(U91="resolved",I91,IF(U91="claimed",H91,Controls!$B$4))-G91)*24,4) -> 71.35 | W91: =INDEX(Owners!$E$4:$E$21,MATCH(D91,Owners!$A$4:$A$21,0)) -> FALSE
A92: iss-0089 | B92: ds-refunds | C92: r-refunds-fk-payment_key | D92: own-18 | E92: high | F92: closed | G92: 46234.16 | H92: 46235.492 | I92: 46236.091 | J92: rerun | K92: iss-0089 | L92: r-refunds-fk-payment_key | M92: 1 | N92: 1 | O92: 0 | Q92: 0 | R92: =INDEX(Owners!$B$4:$B$21,MATCH(D92,Owners!$A$4:$A$21,0)) -> Support Operations | S92: =AND(F92="closed",ISNUMBER(H92),H92<=Controls!$B$4) -> TRUE | T92: =AND(ISNUMBER(I92),I92<=Controls!$B$4,J92="rerun",K92=A92,L92=C92,M92=N92,O92=0,I92>=G92,IF(ISNUMBER(P92),I92>=P92,TRUE())) -> TRUE | U92: =IF(AND(S92,T92),"resolved",IF(S92,"claimed","open")) -> resolved | V92: =ROUND((IF(U92="resolved",I92,IF(U92="claimed",H92,Controls!$B$4))-G92)*24,4) -> 46.3333 | W92: =INDEX(Owners!$E$4:$E$21,MATCH(D92,Owners!$A$4:$A$21,0)) -> TRUE
A93: iss-0090 | B93: ds-suppliers | C93: r-suppliers-unique-supplier_key | D93: own-15 | E93: high | F93: closed | G93: 46234.188 | H93: 46236.772 | I93: 46237.284 | J93: rerun | K93: iss-0090 | L93: r-suppliers-unique-supplier_key | M93: 1 | N93: 1 | O93: 0 | Q93: 0 | R93: =INDEX(Owners!$B$4:$B$21,MATCH(D93,Owners!$A$4:$A$21,0)) -> Supply Chain | S93: =AND(F93="closed",ISNUMBER(H93),H93<=Controls!$B$4) -> TRUE | T93: =AND(ISNUMBER(I93),I93<=Controls!$B$4,J93="rerun",K93=A93,L93=C93,M93=N93,O93=0,I93>=G93,IF(ISNUMBER(P93),I93>=P93,TRUE())) -> TRUE | U93: =IF(AND(S93,T93),"resolved",IF(S93,"claimed","open")) -> resolved | V93: =ROUND((IF(U93="resolved",I93,IF(U93="claimed",H93,Controls!$B$4))-G93)*24,4) -> 74.3167 | W93: =INDEX(Owners!$E$4:$E$21,MATCH(D93,Owners!$A$4:$A$21,0)) -> FALSE
A94: iss-0091 | B94: ds-ledger-entries | C94: r-ledger-entries-valid-currency | D94: own-12 | E94: high | F94: closed | G94: 46234.215 | H94: 46234.849 | N94: 1 | Q94: 0 | R94: =INDEX(Owners!$B$4:$B$21,MATCH(D94,Owners!$A$4:$A$21,0)) -> Finance Systems | S94: =AND(F94="closed",ISNUMBER(H94),H94<=Controls!$B$4) -> TRUE | T94: =AND(ISNUMBER(I94),I94<=Controls!$B$4,J94="rerun",K94=A94,L94=C94,M94=N94,O94=0,I94>=G94,IF(ISNUMBER(P94),I94>=P94,TRUE())) -> FALSE | U94: =IF(AND(S94,T94),"resolved",IF(S94,"claimed","open")) -> claimed | V94: =ROUND((IF(U94="resolved",I94,IF(U94="claimed",H94,Controls!$B$4))-G94)*24,4) -> 15.2333 | W94: =INDEX(Owners!$E$4:$E$21,MATCH(D94,Owners!$A$4:$A$21,0)) -> FALSE
A95: iss-0092 | B95: ds-cost-centres | C95: r-cost-centres-unique-cost_centre_code | D95: own-10 | E95: medium | F95: closed | G95: 46234.242 | H95: 46236.269 | I95: 46236.442 | J95: rerun | K95: iss-0092 | L95: r-cost-centres-unique-cost_centre_code | M95: 1 | N95: 1 | O95: 0 | Q95: 0 | R95: =INDEX(Owners!$B$4:$B$21,MATCH(D95,Owners!$A$4:$A$21,0)) -> Finance Systems | S95: =AND(F95="closed",ISNUMBER(H95),H95<=Controls!$B$4) -> TRUE | T95: =AND(ISNUMBER(I95),I95<=Controls!$B$4,J95="rerun",K95=A95,L95=C95,M95=N95,O95=0,I95>=G95,IF(ISNUMBER(P95),I95>=P95,TRUE())) -> TRUE | U95: =IF(AND(S95,T95),"resolved",IF(S95,"claimed","open")) -> resolved | V95: =ROUND((IF(U95="resolved",I95,IF(U95="claimed",H95,Controls!$B$4))-G95)*24,4) -> 52.8167 | W95: =INDEX(Owners!$E$4:$E$21,MATCH(D95,Owners!$A$4:$A$21,0)) -> TRUE
A96: iss-0093 | B96: ds-web-users | C96: r-web-users-fresh | D96: own-05 | E96: high | F96: closed | G96: 46234.993 | H96: 46235.44 | I96: 46235.632 | J96: rerun | K96: iss-0093 | L96: r-web-users-fresh | M96: 1 | N96: 1 | O96: 0 | Q96: 0 | R96: =INDEX(Owners!$B$4:$B$21,MATCH(D96,Owners!$A$4:$A$21,0)) -> Data Platform | S96: =AND(F96="closed",ISNUMBER(H96),H96<=Controls!$B$4) -> TRUE | T96: =AND(ISNUMBER(I96),I96<=Controls!$B$4,J96="rerun",K96=A96,L96=C96,M96=N96,O96=0,I96>=G96,IF(ISNUMBER(P96),I96>=P96,TRUE())) -> TRUE | U96: =IF(AND(S96,T96),"resolved",IF(S96,"claimed","open")) -> resolved | V96: =ROUND((IF(U96="resolved",I96,IF(U96="claimed",H96,Controls!$B$4))-G96)*24,4) -> 15.3333 | W96: =INDEX(Owners!$E$4:$E$21,MATCH(D96,Owners!$A$4:$A$21,0)) -> TRUE
A97: iss-0094 | B97: ds-customers | C97: r-customers-complete-email | D97: own-07 | E97: high | F97: closed | G97: 46235.083 | H97: 46236.986 | I97: 46237.34 | J97: rerun | K97: iss-0094 | L97: r-customers-complete-email | M97: 1 | N97: 1 | O97: 0 | Q97: 0 | R97: =INDEX(Owners!$B$4:$B$21,MATCH(D97,Owners!$A$4:$A$21,0)) -> Customer Data | S97: =AND(F97="closed",ISNUMBER(H97),H97<=Controls!$B$4) -> TRUE | T97: =AND(ISNUMBER(I97),I97<=Controls!$B$4,J97="rerun",K97=A97,L97=C97,M97=N97,O97=0,I97>=G97,IF(ISNUMBER(P97),I97>=P97,TRUE())) -> TRUE | U97: =IF(AND(S97,T97),"resolved",IF(S97,"claimed","open")) -> resolved | V97: =ROUND((IF(U97="resolved",I97,IF(U97="claimed",H97,Controls!$B$4))-G97)*24,4) -> 54.1667 | W97: =INDEX(Owners!$E$4:$E$21,MATCH(D97,Owners!$A$4:$A$21,0)) -> TRUE
A98: iss-0095 | B98: ds-cost-centres | C98: r-cost-centres-complete-owner_ref | D98: own-10 | E98: high | F98: closed | G98: 46235.084 | H98: 46237.033 | I98: 46237.604 | J98: rerun | K98: iss-0095 | L98: r-cost-centres-complete-owner_ref | M98: 1 | N98: 1 | O98: 0 | Q98: 0 | R98: =INDEX(Owners!$B$4:$B$21,MATCH(D98,Owners!$A$4:$A$21,0)) -> Finance Systems | S98: =AND(F98="closed",ISNUMBER(H98),H98<=Controls!$B$4) -> TRUE | T98: =AND(ISNUMBER(I98),I98<=Controls!$B$4,J98="rerun",K98=A98,L98=C98,M98=N98,O98=0,I98>=G98,IF(ISNUMBER(P98),I98>=P98,TRUE())) -> TRUE | U98: =IF(AND(S98,T98),"resolved",IF(S98,"claimed","open")) -> resolved | V98: =ROUND((IF(U98="resolved",I98,IF(U98="claimed",H98,Controls!$B$4))-G98)*24,4) -> 60.4833 | W98: =INDEX(Owners!$E$4:$E$21,MATCH(D98,Owners!$A$4:$A$21,0)) -> TRUE
A99: iss-0096 | B99: ds-customers | C99: r-customers-valid-email | D99: own-07 | E99: medium | F99: closed | G99: 46235.092 | H99: 46236.774 | I99: 46237.268 | J99: rerun | K99: iss-0096 | L99: r-customers-valid-email | M99: 1 | N99: 1 | O99: 0 | Q99: 0 | R99: =INDEX(Owners!$B$4:$B$21,MATCH(D99,Owners!$A$4:$A$21,0)) -> Customer Data | S99: =AND(F99="closed",ISNUMBER(H99),H99<=Controls!$B$4) -> TRUE | T99: =AND(ISNUMBER(I99),I99<=Controls!$B$4,J99="rerun",K99=A99,L99=C99,M99=N99,O99=0,I99>=G99,IF(ISNUMBER(P99),I99>=P99,TRUE())) -> TRUE | U99: =IF(AND(S99,T99),"resolved",IF(S99,"claimed","open")) -> resolved | V99: =ROUND((IF(U99="resolved",I99,IF(U99="claimed",H99,Controls!$B$4))-G99)*24,4) -> 52.2167 | W99: =INDEX(Owners!$E$4:$E$21,MATCH(D99,Owners!$A$4:$A$21,0)) -> TRUE
A100: iss-0097 | B100: ds-tickets | C100: r-tickets-complete-priority | D100: own-05 | E100: medium | F100: closed | G100: 46235.111 | H100: 46235.724 | I100: 46235.776 | J100: rerun | K100: iss-0097 | L100: r-tickets-complete-priority | M100: 1 | N100: 1 | O100: 0 | Q100: 0 | R100: =INDEX(Owners!$B$4:$B$21,MATCH(D100,Owners!$A$4:$A$21,0)) -> Data Platform | S100: =AND(F100="closed",ISNUMBER(H100),H100<=Controls!$B$4) -> TRUE | T100: =AND(ISNUMBER(I100),I100<=Controls!$B$4,J100="rerun",K100=A100,L100=C100,M100=N100,O100=0,I100>=G100,IF(ISNUMBER(P100),I100>=P100,TRUE())) -> TRUE | U100: =IF(AND(S100,T100),"resolved",IF(S100,"claimed","open")) -> resolved | V100: =ROUND((IF(U100="resolved",I100,IF(U100="claimed",H100,Controls!$B$4))-G100)*24,4) -> 15.95 | W100: =INDEX(Owners!$E$4:$E$21,MATCH(D100,Owners!$A$4:$A$21,0)) -> TRUE
...

Sheet Owners
A1: Owners register (18; three inactive)
A2: accountable_at_as_of = the owner is active at the as-of (a deactivation after the as-of still counts as active).
A3: owner_id | B3: team | C3: active | D3: deactivated_at (serial) | E3: accountable_at_as_of
A4: own-01 | B4: Data Governance | C4: =TRUE() -> TRUE | E4: =IF(ISNUMBER(D4),Controls!$B$4<D4,C4) -> TRUE
A5: own-02 | B5: Data Governance | C5: =TRUE() -> TRUE | E5: =IF(ISNUMBER(D5),Controls!$B$4<D5,C5) -> TRUE
A6: own-03 | B6: Data Governance | C6: =TRUE() -> TRUE | E6: =IF(ISNUMBER(D6),Controls!$B$4<D6,C6) -> TRUE
A7: own-04 | B7: Data Platform | C7: =TRUE() -> TRUE | E7: =IF(ISNUMBER(D7),Controls!$B$4<D7,C7) -> TRUE
A8: own-05 | B8: Data Platform | C8: =TRUE() -> TRUE | E8: =IF(ISNUMBER(D8),Controls!$B$4<D8,C8) -> TRUE
A9: own-06 | B9: Data Platform | C9: =TRUE() -> TRUE | E9: =IF(ISNUMBER(D9),Controls!$B$4<D9,C9) -> TRUE
A10: own-07 | B10: Customer Data | C10: =TRUE() -> TRUE | E10: =IF(ISNUMBER(D10),Controls!$B$4<D10,C10) -> TRUE
A11: own-08 | B11: Customer Data | C11: =TRUE() -> TRUE | E11: =IF(ISNUMBER(D11),Controls!$B$4<D11,C11) -> TRUE
A12: own-09 | B12: Customer Data | C12: =FALSE() -> FALSE | D12: 46252.375 | E12: =IF(ISNUMBER(D12),Controls!$B$4<D12,C12) -> FALSE
A13: own-10 | B13: Finance Systems | C13: =TRUE() -> TRUE | E13: =IF(ISNUMBER(D13),Controls!$B$4<D13,C13) -> TRUE
A14: own-11 | B14: Finance Systems | C14: =TRUE() -> TRUE | E14: =IF(ISNUMBER(D14),Controls!$B$4<D14,C14) -> TRUE
A15: own-12 | B15: Finance Systems | C15: =FALSE() -> FALSE | D15: 46269.375 | E15: =IF(ISNUMBER(D15),Controls!$B$4<D15,C15) -> FALSE
A16: own-13 | B16: Supply Chain | C16: =TRUE() -> TRUE | E16: =IF(ISNUMBER(D16),Controls!$B$4<D16,C16) -> TRUE
A17: own-14 | B17: Supply Chain | C17: =TRUE() -> TRUE | E17: =IF(ISNUMBER(D17),Controls!$B$4<D17,C17) -> TRUE
A18: own-15 | B18: Supply Chain | C18: =FALSE() -> FALSE | D18: 46287.375 | E18: =IF(ISNUMBER(D18),Controls!$B$4<D18,C18) -> FALSE
A19: own-16 | B19: Support Operations | C19: =TRUE() -> TRUE | E19: =IF(ISNUMBER(D19),Controls!$B$4<D19,C19) -> TRUE
A20: own-17 | B20: Support Operations | C20: =TRUE() -> TRUE | E20: =IF(ISNUMBER(D20),Controls!$B$4<D20,C20) -> TRUE
A21: own-18 | B21: Support Operations | C21: =TRUE() -> TRUE | E21: =IF(ISNUMBER(D21),Controls!$B$4<D21,C21) -> TRUE

Sheet Datasets
A1: Datasets registered by the as-of (40)
A2: owner_covered = the owner is accountable at the as-of (Owners!E).
A3: dataset_id | B3: owner_id | C3: monitored | D3: owner_covered | E3: owner_team
A4: ds-accounts | B4: own-14 | C4: =FALSE() -> FALSE | D4: =INDEX(Owners!$E$4:$E$21,MATCH(B4,Owners!$A$4:$A$21,0)) -> TRUE | E4: =INDEX(Owners!$B$4:$B$21,MATCH(B4,Owners!$A$4:$A$21,0)) -> Supply Chain
A5: ds-billing-accounts | B5: own-13 | C5: =FALSE() -> FALSE | D5: =INDEX(Owners!$E$4:$E$21,MATCH(B5,Owners!$A$4:$A$21,0)) -> TRUE | E5: =INDEX(Owners!$B$4:$B$21,MATCH(B5,Owners!$A$4:$A$21,0)) -> Supply Chain
A6: ds-campaigns | B6: own-07 | C6: =TRUE() -> TRUE | D6: =INDEX(Owners!$E$4:$E$21,MATCH(B6,Owners!$A$4:$A$21,0)) -> TRUE | E6: =INDEX(Owners!$B$4:$B$21,MATCH(B6,Owners!$A$4:$A$21,0)) -> Customer Data
A7: ds-carriers | B7: own-05 | C7: =FALSE() -> FALSE | D7: =INDEX(Owners!$E$4:$E$21,MATCH(B7,Owners!$A$4:$A$21,0)) -> TRUE | E7: =INDEX(Owners!$B$4:$B$21,MATCH(B7,Owners!$A$4:$A$21,0)) -> Data Platform
A8: ds-consent-records | B8: own-14 | C8: =TRUE() -> TRUE | D8: =INDEX(Owners!$E$4:$E$21,MATCH(B8,Owners!$A$4:$A$21,0)) -> TRUE | E8: =INDEX(Owners!$B$4:$B$21,MATCH(B8,Owners!$A$4:$A$21,0)) -> Supply Chain
A9: ds-contacts | B9: own-12 | C9: =TRUE() -> TRUE | D9: =INDEX(Owners!$E$4:$E$21,MATCH(B9,Owners!$A$4:$A$21,0)) -> FALSE | E9: =INDEX(Owners!$B$4:$B$21,MATCH(B9,Owners!$A$4:$A$21,0)) -> Finance Systems
A10: ds-cost-centres | B10: own-10 | C10: =FALSE() -> FALSE | D10: =INDEX(Owners!$E$4:$E$21,MATCH(B10,Owners!$A$4:$A$21,0)) -> TRUE | E10: =INDEX(Owners!$B$4:$B$21,MATCH(B10,Owners!$A$4:$A$21,0)) -> Finance Systems
A11: ds-credit-notes | B11: own-08 | C11: =FALSE() -> FALSE | D11: =INDEX(Owners!$E$4:$E$21,MATCH(B11,Owners!$A$4:$A$21,0)) -> TRUE | E11: =INDEX(Owners!$B$4:$B$21,MATCH(B11,Owners!$A$4:$A$21,0)) -> Customer Data
A12: ds-crm-activities | B12: own-08 | C12: =FALSE() -> FALSE | D12: =INDEX(Owners!$E$4:$E$21,MATCH(B12,Owners!$A$4:$A$21,0)) -> TRUE | E12: =INDEX(Owners!$B$4:$B$21,MATCH(B12,Owners!$A$4:$A$21,0)) -> Customer Data
A13: ds-csat-surveys | B13: own-08 | C13: =FALSE() -> FALSE | D13: =INDEX(Owners!$E$4:$E$21,MATCH(B13,Owners!$A$4:$A$21,0)) -> TRUE | E13: =INDEX(Owners!$B$4:$B$21,MATCH(B13,Owners!$A$4:$A$21,0)) -> Customer Data
A14: ds-customers | B14: own-07 | C14: =TRUE() -> TRUE | D14: =INDEX(Owners!$E$4:$E$21,MATCH(B14,Owners!$A$4:$A$21,0)) -> TRUE | E14: =INDEX(Owners!$B$4:$B$21,MATCH(B14,Owners!$A$4:$A$21,0)) -> Customer Data
A15: ds-delivery-events | B15: own-13 | C15: =FALSE() -> FALSE | D15: =INDEX(Owners!$E$4:$E$21,MATCH(B15,Owners!$A$4:$A$21,0)) -> TRUE | E15: =INDEX(Owners!$B$4:$B$21,MATCH(B15,Owners!$A$4:$A$21,0)) -> Supply Chain
A16: ds-employees | B16: own-16 | C16: =FALSE() -> FALSE | D16: =INDEX(Owners!$E$4:$E$21,MATCH(B16,Owners!$A$4:$A$21,0)) -> TRUE | E16: =INDEX(Owners!$B$4:$B$21,MATCH(B16,Owners!$A$4:$A$21,0)) -> Support Operations
A17: ds-experiments | B17: own-02 | C17: =FALSE() -> FALSE | D17: =INDEX(Owners!$E$4:$E$21,MATCH(B17,Owners!$A$4:$A$21,0)) -> TRUE | E17: =INDEX(Owners!$B$4:$B$21,MATCH(B17,Owners!$A$4:$A$21,0)) -> Data Governance
A18: ds-inventory | B18: own-06 | C18: =TRUE() -> TRUE | D18: =INDEX(Owners!$E$4:$E$21,MATCH(B18,Owners!$A$4:$A$21,0)) -> TRUE | E18: =INDEX(Owners!$B$4:$B$21,MATCH(B18,Owners!$A$4:$A$21,0)) -> Data Platform
A19: ds-invoices | B19: own-09 | C19: =TRUE() -> TRUE | D19: =INDEX(Owners!$E$4:$E$21,MATCH(B19,Owners!$A$4:$A$21,0)) -> FALSE | E19: =INDEX(Owners!$B$4:$B$21,MATCH(B19,Owners!$A$4:$A$21,0)) -> Customer Data
A20: ds-kb-articles | B20: own-14 | C20: =FALSE() -> FALSE | D20: =INDEX(Owners!$E$4:$E$21,MATCH(B20,Owners!$A$4:$A$21,0)) -> TRUE | E20: =INDEX(Owners!$B$4:$B$21,MATCH(B20,Owners!$A$4:$A$21,0)) -> Supply Chain
A21: ds-leads | B21: own-18 | C21: =FALSE() -> FALSE | D21: =INDEX(Owners!$E$4:$E$21,MATCH(B21,Owners!$A$4:$A$21,0)) -> TRUE | E21: =INDEX(Owners!$B$4:$B$21,MATCH(B21,Owners!$A$4:$A$21,0)) -> Support Operations
A22: ds-ledger-entries | B22: own-12 | C22: =FALSE() -> FALSE | D22: =INDEX(Owners!$E$4:$E$21,MATCH(B22,Owners!$A$4:$A$21,0)) -> FALSE | E22: =INDEX(Owners!$B$4:$B$21,MATCH(B22,Owners!$A$4:$A$21,0)) -> Finance Systems
A23: ds-opportunities | B23: own-04 | C23: =FALSE() -> FALSE | D23: =INDEX(Owners!$E$4:$E$21,MATCH(B23,Owners!$A$4:$A$21,0)) -> TRUE | E23: =INDEX(Owners!$B$4:$B$21,MATCH(B23,Owners!$A$4:$A$21,0)) -> Data Platform
A24: ds-order-lines | B24: own-03 | C24: =FALSE() -> FALSE | D24: =INDEX(Owners!$E$4:$E$21,MATCH(B24,Owners!$A$4:$A$21,0)) -> TRUE | E24: =INDEX(Owners!$B$4:$B$21,MATCH(B24,Owners!$A$4:$A$21,0)) -> Data Governance
A25: ds-orders | B25: own-04 | C25: =TRUE() -> TRUE | D25: =INDEX(Owners!$E$4:$E$21,MATCH(B25,Owners!$A$4:$A$21,0)) -> TRUE | E25: =INDEX(Owners!$B$4:$B$21,MATCH(B25,Owners!$A$4:$A$21,0)) -> Data Platform
A26: ds-page-events | B26: own-03 | C26: =FALSE() -> FALSE | D26: =INDEX(Owners!$E$4:$E$21,MATCH(B26,Owners!$A$4:$A$21,0)) -> TRUE | E26: =INDEX(Owners!$B$4:$B$21,MATCH(B26,Owners!$A$4:$A$21,0)) -> Data Governance
A27: ds-payments | B27: own-06 | C27: =TRUE() -> TRUE | D27: =INDEX(Owners!$E$4:$E$21,MATCH(B27,Owners!$A$4:$A$21,0)) -> TRUE | E27: =INDEX(Owners!$B$4:$B$21,MATCH(B27,Owners!$A$4:$A$21,0)) -> Data Platform
A28: ds-price-books | B28: own-14 | C28: =TRUE() -> TRUE | D28: =INDEX(Owners!$E$4:$E$21,MATCH(B28,Owners!$A$4:$A$21,0)) -> TRUE | E28: =INDEX(Owners!$B$4:$B$21,MATCH(B28,Owners!$A$4:$A$21,0)) -> Supply Chain
A29: ds-products | B29: own-17 | C29: =FALSE() -> FALSE | D29: =INDEX(Owners!$E$4:$E$21,MATCH(B29,Owners!$A$4:$A$21,0)) -> TRUE | E29: =INDEX(Owners!$B$4:$B$21,MATCH(B29,Owners!$A$4:$A$21,0)) -> Support Operations
A30: ds-purchase-orders | B30: own-04 | C30: =TRUE() -> TRUE | D30: =INDEX(Owners!$E$4:$E$21,MATCH(B30,Owners!$A$4:$A$21,0)) -> TRUE | E30: =INDEX(Owners!$B$4:$B$21,MATCH(B30,Owners!$A$4:$A$21,0)) -> Data Platform
A31: ds-refunds | B31: own-18 | C31: =FALSE() -> FALSE | D31: =INDEX(Owners!$E$4:$E$21,MATCH(B31,Owners!$A$4:$A$21,0)) -> TRUE | E31: =INDEX(Owners!$B$4:$B$21,MATCH(B31,Owners!$A$4:$A$21,0)) -> Support Operations
A32: ds-returns | B32: own-09 | C32: =FALSE() -> FALSE | D32: =INDEX(Owners!$E$4:$E$21,MATCH(B32,Owners!$A$4:$A$21,0)) -> FALSE | E32: =INDEX(Owners!$B$4:$B$21,MATCH(B32,Owners!$A$4:$A$21,0)) -> Customer Data
A33: ds-segments | B33: own-14 | C33: =FALSE() -> FALSE | D33: =INDEX(Owners!$E$4:$E$21,MATCH(B33,Owners!$A$4:$A$21,0)) -> TRUE | E33: =INDEX(Owners!$B$4:$B$21,MATCH(B33,Owners!$A$4:$A$21,0)) -> Supply Chain
A34: ds-shipments | B34: own-13 | C34: =TRUE() -> TRUE | D34: =INDEX(Owners!$E$4:$E$21,MATCH(B34,Owners!$A$4:$A$21,0)) -> TRUE | E34: =INDEX(Owners!$B$4:$B$21,MATCH(B34,Owners!$A$4:$A$21,0)) -> Supply Chain
A35: ds-sla-policies | B35: own-11 | C35: =TRUE() -> TRUE | D35: =INDEX(Owners!$E$4:$E$21,MATCH(B35,Owners!$A$4:$A$21,0)) -> TRUE | E35: =INDEX(Owners!$B$4:$B$21,MATCH(B35,Owners!$A$4:$A$21,0)) -> Finance Systems
A36: ds-subscriptions | B36: own-06 | C36: =TRUE() -> TRUE | D36: =INDEX(Owners!$E$4:$E$21,MATCH(B36,Owners!$A$4:$A$21,0)) -> TRUE | E36: =INDEX(Owners!$B$4:$B$21,MATCH(B36,Owners!$A$4:$A$21,0)) -> Data Platform
A37: ds-suppliers | B37: own-15 | C37: =FALSE() -> FALSE | D37: =INDEX(Owners!$E$4:$E$21,MATCH(B37,Owners!$A$4:$A$21,0)) -> FALSE | E37: =INDEX(Owners!$B$4:$B$21,MATCH(B37,Owners!$A$4:$A$21,0)) -> Supply Chain
A38: ds-support-agents | B38: own-02 | C38: =FALSE() -> FALSE | D38: =INDEX(Owners!$E$4:$E$21,MATCH(B38,Owners!$A$4:$A$21,0)) -> TRUE | E38: =INDEX(Owners!$B$4:$B$21,MATCH(B38,Owners!$A$4:$A$21,0)) -> Data Governance
A39: ds-ticket-events | B39: own-11 | C39: =FALSE() -> FALSE | D39: =INDEX(Owners!$E$4:$E$21,MATCH(B39,Owners!$A$4:$A$21,0)) -> TRUE | E39: =INDEX(Owners!$B$4:$B$21,MATCH(B39,Owners!$A$4:$A$21,0)) -> Finance Systems
A40: ds-tickets | B40: own-05 | C40: =TRUE() -> TRUE | D40: =INDEX(Owners!$E$4:$E$21,MATCH(B40,Owners!$A$4:$A$21,0)) -> TRUE | E40: =INDEX(Owners!$B$4:$B$21,MATCH(B40,Owners!$A$4:$A$21,0)) -> Data Platform
A41: ds-warehouses | B41: own-16 | C41: =FALSE() -> FALSE | D41: =INDEX(Owners!$E$4:$E$21,MATCH(B41,Owners!$A$4:$A$21,0)) -> TRUE | E41: =INDEX(Owners!$B$4:$B$21,MATCH(B41,Owners!$A$4:$A$21,0)) -> Support Operations
A42: ds-web-sessions | B42: own-02 | C42: =FALSE() -> FALSE | D42: =INDEX(Owners!$E$4:$E$21,MATCH(B42,Owners!$A$4:$A$21,0)) -> TRUE | E42: =INDEX(Owners!$B$4:$B$21,MATCH(B42,Owners!$A$4:$A$21,0)) -> Data Governance
A43: ds-web-users | B43: own-05 | C43: =TRUE() -> TRUE | D43: =INDEX(Owners!$E$4:$E$21,MATCH(B43,Owners!$A$4:$A$21,0)) -> TRUE | E43: =INDEX(Owners!$B$4:$B$21,MATCH(B43,Owners!$A$4:$A$21,0)) -> Data Platform

Sheet Lineage
A1: 160 lineage edges: declared 80, observed 70, inferred 10
A2: An observed edge has an observation instant and a declared one does not (D-08). pair_declared / pair_observed look the (source, target) pair up across the edges; an inferred edge is never observed.
A3: edge_id | B3: source_dataset_id | C3: target_dataset_id | D3: evidence_type | E3: observed_at | F3: pair | G3: pair_declared | H3: pair_observed | I3: counts_as_observed_match
A4: ed-001 | B4: ds-customers | C4: ds-contacts | D4: declared | F4: =B4&">"&C4 -> ds-customers>ds-contacts | G4: =COUNTIFS($F$4:$F$163,F4,$D$4:$D$163,"declared")>0 -> TRUE | H4: =COUNTIFS($F$4:$F$163,F4,$D$4:$D$163,"observed")>0 -> TRUE | I4: =AND(D4="observed",G4) -> FALSE
A5: ed-002 | B5: ds-customers | C5: ds-accounts | D5: declared | F5: =B5&">"&C5 -> ds-customers>ds-accounts | G5: =COUNTIFS($F$4:$F$163,F5,$D$4:$D$163,"declared")>0 -> TRUE | H5: =COUNTIFS($F$4:$F$163,F5,$D$4:$D$163,"observed")>0 -> TRUE | I5: =AND(D5="observed",G5) -> FALSE
A6: ed-003 | B6: ds-accounts | C6: ds-opportunities | D6: declared | F6: =B6&">"&C6 -> ds-accounts>ds-opportunities | G6: =COUNTIFS($F$4:$F$163,F6,$D$4:$D$163,"declared")>0 -> TRUE | H6: =COUNTIFS($F$4:$F$163,F6,$D$4:$D$163,"observed")>0 -> TRUE | I6: =AND(D6="observed",G6) -> FALSE
A7: ed-004 | B7: ds-customers | C7: ds-orders | D7: declared | F7: =B7&">"&C7 -> ds-customers>ds-orders | G7: =COUNTIFS($F$4:$F$163,F7,$D$4:$D$163,"declared")>0 -> TRUE | H7: =COUNTIFS($F$4:$F$163,F7,$D$4:$D$163,"observed")>0 -> TRUE | I7: =AND(D7="observed",G7) -> FALSE
A8: ed-005 | B8: ds-orders | C8: ds-order-lines | D8: declared | F8: =B8&">"&C8 -> ds-orders>ds-order-lines | G8: =COUNTIFS($F$4:$F$163,F8,$D$4:$D$163,"declared")>0 -> TRUE | H8: =COUNTIFS($F$4:$F$163,F8,$D$4:$D$163,"observed")>0 -> TRUE | I8: =AND(D8="observed",G8) -> FALSE
A9: ed-006 | B9: ds-products | C9: ds-order-lines | D9: declared | F9: =B9&">"&C9 -> ds-products>ds-order-lines | G9: =COUNTIFS($F$4:$F$163,F9,$D$4:$D$163,"declared")>0 -> TRUE | H9: =COUNTIFS($F$4:$F$163,F9,$D$4:$D$163,"observed")>0 -> TRUE | I9: =AND(D9="observed",G9) -> FALSE
A10: ed-007 | B10: ds-customers | C10: ds-invoices | D10: declared | F10: =B10&">"&C10 -> ds-customers>ds-invoices | G10: =COUNTIFS($F$4:$F$163,F10,$D$4:$D$163,"declared")>0 -> TRUE | H10: =COUNTIFS($F$4:$F$163,F10,$D$4:$D$163,"observed")>0 -> TRUE | I10: =AND(D10="observed",G10) -> FALSE
A11: ed-008 | B11: ds-invoices | C11: ds-payments | D11: declared | F11: =B11&">"&C11 -> ds-invoices>ds-payments | G11: =COUNTIFS($F$4:$F$163,F11,$D$4:$D$163,"declared")>0 -> TRUE | H11: =COUNTIFS($F$4:$F$163,F11,$D$4:$D$163,"observed")>0 -> TRUE | I11: =AND(D11="observed",G11) -> FALSE
A12: ed-009 | B12: ds-customers | C12: ds-subscriptions | D12: declared | F12: =B12&">"&C12 -> ds-customers>ds-subscriptions | G12: =COUNTIFS($F$4:$F$163,F12,$D$4:$D$163,"declared")>0 -> TRUE | H12: =COUNTIFS($F$4:$F$163,F12,$D$4:$D$163,"observed")>0 -> TRUE | I12: =AND(D12="observed",G12) -> FALSE
A13: ed-010 | B13: ds-payments | C13: ds-refunds | D13: declared | F13: =B13&">"&C13 -> ds-payments>ds-refunds | G13: =COUNTIFS($F$4:$F$163,F13,$D$4:$D$163,"declared")>0 -> TRUE | H13: =COUNTIFS($F$4:$F$163,F13,$D$4:$D$163,"observed")>0 -> FALSE | I13: =AND(D13="observed",G13) -> FALSE
A14: ed-011 | B14: ds-suppliers | C14: ds-purchase-orders | D14: declared | F14: =B14&">"&C14 -> ds-suppliers>ds-purchase-orders | G14: =COUNTIFS($F$4:$F$163,F14,$D$4:$D$163,"declared")>0 -> TRUE | H14: =COUNTIFS($F$4:$F$163,F14,$D$4:$D$163,"observed")>0 -> TRUE | I14: =AND(D14="observed",G14) -> FALSE
A15: ed-012 | B15: ds-customers | C15: ds-tickets | D15: declared | F15: =B15&">"&C15 -> ds-customers>ds-tickets | G15: =COUNTIFS($F$4:$F$163,F15,$D$4:$D$163,"declared")>0 -> TRUE | H15: =COUNTIFS($F$4:$F$163,F15,$D$4:$D$163,"observed")>0 -> TRUE | I15: =AND(D15="observed",G15) -> FALSE
... A93: ei-010 | B93: ds-csat-surveys | C93: ds-shipments | D93: inferred | F93: =B93&">"&C93 -> ds-csat-surveys>ds-shipments | G93: =COUNTIFS($F$4:$F$163,F93,$D$4:$D$163,"declared")>0 -> FALSE | H93: =COUNTIFS($F$4:$F$163,F93,$D$4:$D$163,"observed")>0 -> FALSE | I93: =AND(D93="observed",G93) -> FALSE
A94: eo-001 | B94: ds-crm-activities | C94: ds-refunds | D94: observed | E94: 46285.883 | F94: =B94&">"&C94 -> ds-crm-activities>ds-refunds | G94: =COUNTIFS($F$4:$F$163,F94,$D$4:$D$163,"declared")>0 -> TRUE | H94: =COUNTIFS($F$4:$F$163,F94,$D$4:$D$163,"observed")>0 -> TRUE | I94: =AND(D94="observed",G94) -> TRUE
A95: eo-002 | B95: ds-credit-notes | C95: ds-products | D95: observed | E95: 46278.59 | F95: =B95&">"&C95 -> ds-credit-notes>ds-products | G95: =COUNTIFS($F$4:$F$163,F95,$D$4:$D$163,"declared")>0 -> TRUE | H95: =COUNTIFS($F$4:$F$163,F95,$D$4:$D$163,"observed")>0 -> TRUE | I95: =AND(D95="observed",G95) -> TRUE
A96: eo-003 | B96: ds-payments | C96: ds-suppliers | D96: observed | E96: 46253.001 | F96: =B96&">"&C96 -> ds-payments>ds-suppliers | G96: =COUNTIFS($F$4:$F$163,F96,$D$4:$D$163,"declared")>0 -> TRUE | H96: =COUNTIFS($F$4:$F$163,F96,$D$4:$D$163,"observed")>0 -> TRUE | I96: =AND(D96="observed",G96) -> TRUE
A97: eo-004 | B97: ds-invoices | C97: ds-payments | D97: observed | E97: 46238.995 | F97: =B97&">"&C97 -> ds-invoices>ds-payments | G97: =COUNTIFS($F$4:$F$163,F97,$D$4:$D$163,"declared")>0 -> TRUE | H97: =COUNTIFS($F$4:$F$163,F97,$D$4:$D$163,"observed")>0 -> TRUE | I97: =AND(D97="observed",G97) -> TRUE
A98: eo-005 | B98: ds-products | C98: ds-tickets | D98: observed | E98: 46233.256 | F98: =B98&">"&C98 -> ds-products>ds-tickets | G98: =COUNTIFS($F$4:$F$163,F98,$D$4:$D$163,"declared")>0 -> TRUE | H98: =COUNTIFS($F$4:$F$163,F98,$D$4:$D$163,"observed")>0 -> TRUE | I98: =AND(D98="observed",G98) -> TRUE
A99: eo-006 | B99: ds-support-agents | C99: ds-sla-policies | D99: observed | E99: 46222.163 | F99: =B99&">"&C99 -> ds-support-agents>ds-sla-policies | G99: =COUNTIFS($F$4:$F$163,F99,$D$4:$D$163,"declared")>0 -> TRUE | H99: =COUNTIFS($F$4:$F$163,F99,$D$4:$D$163,"observed")>0 -> TRUE | I99: =AND(D99="observed",G99) -> TRUE
A100: eo-007 | B100: ds-csat-surveys | C100: ds-sla-policies | D100: observed | E100: 46247.148 | F100: =B100&">"&C100 -> ds-csat-surveys>ds-sla-policies | G100: =COUNTIFS($F$4:$F$163,F100,$D$4:$D$163,"declared")>0 -> TRUE | H100: =COUNTIFS($F$4:$F$163,F100,$D$4:$D$163,"observed")>0 -> TRUE | I100: =AND(D100="observed",G100) -> TRUE
A101: eo-008 | B101: ds-orders | C101: ds-web-users | D101: observed | E101: 46228.488 | F101: =B101&">"&C101 -> ds-orders>ds-web-users | G101: =COUNTIFS($F$4:$F$163,F101,$D$4:$D$163,"declared")>0 -> TRUE | H101: =COUNTIFS($F$4:$F$163,F101,$D$4:$D$163,"observed")>0 -> TRUE | I101: =AND(D101="observed",G101) -> TRUE
A102: eo-009 | B102: ds-csat-surveys | C102: ds-cost-centres | D102: observed | E102: 46264.881 | F102: =B102&">"&C102 -> ds-csat-surveys>ds-cost-centres | G102: =COUNTIFS($F$4:$F$163,F102,$D$4:$D$163,"declared")>0 -> FALSE | H102: =COUNTIFS($F$4:$F$163,F102,$D$4:$D$163,"observed")>0 -> TRUE | I102: =AND(D102="observed",G102) -> FALSE
A103: eo-010 | B103: ds-price-books | C103: ds-kb-articles | D103: observed | E103: 46292.812 | F103: =B103&">"&C103 -> ds-price-books>ds-kb-articles | G103: =COUNTIFS($F$4:$F$163,F103,$D$4:$D$163,"declared")>0 -> TRUE | H103: =COUNTIFS($F$4:$F$163,F103,$D$4:$D$163,"observed")>0 -> TRUE | I103: =AND(D103="observed",G103) -> TRUE
A104: eo-011 | B104: ds-cost-centres | C104: ds-returns | D104: observed | E104: 46294.209 | F104: =B104&">"&C104 -> ds-cost-centres>ds-returns | G104: =COUNTIFS($F$4:$F$163,F104,$D$4:$D$163,"declared")>0 -> TRUE | H104: =COUNTIFS($F$4:$F$163,F104,$D$4:$D$163,"observed")>0 -> TRUE | I104: =AND(D104="observed",G104) -> TRUE
A105: eo-012 | B105: ds-leads | C105: ds-csat-surveys | D105: observed | E105: 46252.86 | F105: =B105&">"&C105 -> ds-leads>ds-csat-surveys | G105: =COUNTIFS($F$4:$F$163,F105,$D$4:$D$163,"declared")>0 -> FALSE | H105: =COUNTIFS($F$4:$F$163,F105,$D$4:$D$163,"observed")>0 -> TRUE | I105: =AND(D105="observed",G105) -> FALSE
... A163: eo-070 | B163: ds-refunds | C163: ds-support-agents | D163: observed | E163: 46247.849 | F163: =B163&">"&C163 -> ds-refunds>ds-support-agents | G163: =COUNTIFS($F$4:$F$163,F163,$D$4:$D$163,"declared")>0 -> FALSE | H163: =COUNTIFS($F$4:$F$163,F163,$D$4:$D$163,"observed")>0 -> TRUE | I163: =AND(D163="observed",G163) -> FALSE

Sheet Definitions
A1: The effective published version of each of the 30 metrics at the as-of, and the checklist cl-1
A2: Complete when definition, grain and refresh are non-blank, the source-field list is non-empty with no blank entry and the owner exists in the register. The texts are TYPED; the checks are formulas.
A3: metric_id | B3: version | C3: owner_id | D3: definition | E3: grain | F3: refresh | G3: source_fields | H3: blank_source_field | I3: has_definition | J3: has_grain | K3: has_refresh | L3: has_source_fields | M3: has_owner | N3: complete
A4: m-active-customers | B4: 1 | C4: own-14 | D4: Active customers as defined in the governance glossary, computed from delivery-events.shipment_key, accounts.status, customers.email | E4: shipment | F4: daily | G4: 3 | H4: =FALSE() -> FALSE | I4: =LEN(TRIM(D4))>0 -> TRUE | J4: =LEN(TRIM(E4))>0 -> TRUE | K4: =LEN(TRIM(F4))>0 -> TRUE | L4: =AND(G4>0,NOT(H4)) -> TRUE | M4: =COUNTIF(Owners!$A$4:$A$21,C4)>0 -> TRUE | N4: =AND(I4,J4,K4,L4,M4) -> TRUE
A5: m-average-order-value | B5: 1 | C5: own-16 | D5: Average order value as defined in the governance glossary, computed from consent-records.consent_key, customers.customer_key, warehouses.warehouse_code | F5: monthly | G5: 3 | H5: =FALSE() -> FALSE | I5: =LEN(TRIM(D5))>0 -> TRUE | J5: =LEN(TRIM(E5))>0 -> FALSE | K5: =LEN(TRIM(F5))>0 -> TRUE | L5: =AND(G5>0,NOT(H5)) -> TRUE | M5: =COUNTIF(Owners!$A$4:$A$21,C5)>0 -> TRUE | N5: =AND(I5,J5,K5,L5,M5) -> FALSE
A6: m-consent-coverage | B6: 2 | C6: own-11 | D6: Consent coverage as defined in the governance glossary, computed from web-sessions.status, warehouses.status; revised: source moved to the curated layer | E6: shipment | F6: daily | G6: 2 | H6: =FALSE() -> FALSE | I6: =LEN(TRIM(D6))>0 -> TRUE | J6: =LEN(TRIM(E6))>0 -> TRUE | K6: =LEN(TRIM(F6))>0 -> TRUE | L6: =AND(G6>0,NOT(H6)) -> TRUE | M6: =COUNTIF(Owners!$A$4:$A$21,C6)>0 -> TRUE | N6: =AND(I6,J6,K6,L6,M6) -> TRUE
A7: m-csat-score | B7: 2 | C7: own-03 | D7: CSAT score as defined in the governance glossary, computed from delivery-events.shipment_key, order-lines.status, payments.paid_at; revised: refunds are netted from the figure | E7: customer | F7: weekly | G7: 0 | H7: =FALSE() -> FALSE | I7: =LEN(TRIM(D7))>0 -> TRUE | J7: =LEN(TRIM(E7))>0 -> TRUE | K7: =LEN(TRIM(F7))>0 -> TRUE | L7: =AND(G7>0,NOT(H7)) -> FALSE | M7: =COUNTIF(Owners!$A$4:$A$21,C7)>0 -> TRUE | N7: =AND(I7,J7,K7,L7,M7) -> FALSE
A8: m-customer-churn-rate | B8: 2 | C8: own-16 | D8: Customer churn rate as defined in the governance glossary, computed from subscriptions.subscription_key, payments.amount, inventory.inventory_key; revised: excludes internal test accounts | E8: ticket | F8: monthly | G8: 3 | H8: =FALSE() -> FALSE | I8: =LEN(TRIM(D8))>0 -> TRUE | J8: =LEN(TRIM(E8))>0 -> TRUE | K8: =LEN(TRIM(F8))>0 -> TRUE | L8: =AND(G8>0,NOT(H8)) -> TRUE | M8: =COUNTIF(Owners!$A$4:$A$21,C8)>0 -> TRUE | N8: =AND(I8,J8,K8,L8,M8) -> TRUE
A9: m-customer-lifetime-value | B9: 2 | C9: own-06 | E9: shipment | F9: daily | G9: 3 | H9: =FALSE() -> FALSE | I9: =LEN(TRIM(D9))>0 -> FALSE | J9: =LEN(TRIM(E9))>0 -> TRUE | K9: =LEN(TRIM(F9))>0 -> TRUE | L9: =AND(G9>0,NOT(H9)) -> TRUE | M9: =COUNTIF(Owners!$A$4:$A$21,C9)>0 -> TRUE | N9: =AND(I9,J9,K9,L9,M9) -> FALSE
A10: m-days-sales-outstanding | B10: 1 | C10: own-02 | D10: Days sales outstanding as defined in the governance glossary, computed from opportunities.stage | E10: order | F10: daily | G10: 1 | H10: =FALSE() -> FALSE | I10: =LEN(TRIM(D10))>0 -> TRUE | J10: =LEN(TRIM(E10))>0 -> TRUE | K10: =LEN(TRIM(F10))>0 -> TRUE | L10: =AND(G10>0,NOT(H10)) -> TRUE | M10: =COUNTIF(Owners!$A$4:$A$21,C10)>0 -> TRUE | N10: =AND(I10,J10,K10,L10,M10) -> TRUE
A11: m-gross-margin | B11: 2 | C11: own-18 | D11: Gross margin as defined in the governance glossary, computed from suppliers.supplier_name, order-lines.order_key; revised: excludes internal test accounts | E11: shipment | G11: 2 | H11: =FALSE() -> FALSE | I11: =LEN(TRIM(D11))>0 -> TRUE | J11: =LEN(TRIM(E11))>0 -> TRUE | K11: =LEN(TRIM(F11))>0 -> FALSE | L11: =AND(G11>0,NOT(H11)) -> TRUE | M11: =COUNTIF(Owners!$A$4:$A$21,C11)>0 -> TRUE | N11: =AND(I11,J11,K11,L11,M11) -> FALSE
A12: m-inventory-turnover | B12: 1 | C12: own-09 | D12: Inventory turnover as defined in the governance glossary, computed from carriers.carrier_code, accounts.tier, ledger-entries.currency | E12: ticket | F12: weekly | G12: 3 | H12: =FALSE() -> FALSE | I12: =LEN(TRIM(D12))>0 -> TRUE | J12: =LEN(TRIM(E12))>0 -> TRUE | K12: =LEN(TRIM(F12))>0 -> TRUE | L12: =AND(G12>0,NOT(H12)) -> TRUE | M12: =COUNTIF(Owners!$A$4:$A$21,C12)>0 -> TRUE | N12: =AND(I12,J12,K12,L12,M12) -> TRUE
A13: m-invoice-accuracy-rate | B13: 1 | C13: own-05 | D13: Invoice accuracy rate as defined in the governance glossary, computed from ticket-events.ticket_key, inventory.warehouse_code | E13: customer | F13: daily | G13: 2 | H13: =FALSE() -> FALSE | I13: =LEN(TRIM(D13))>0 -> TRUE | J13: =LEN(TRIM(E13))>0 -> TRUE | K13: =LEN(TRIM(F13))>0 -> TRUE | L13: =AND(G13>0,NOT(H13)) -> TRUE | M13: =COUNTIF(Owners!$A$4:$A$21,C13)>0 -> TRUE | N13: =AND(I13,J13,K13,L13,M13) -> TRUE
A14: m-lead-conversion-rate | B14: 1 | C14: own-11 | D14: Lead conversion rate as defined in the governance glossary, computed from web-sessions.user_key, employees.status, csat-surveys.score | E14: day | F14: daily | G14: 3 | H14: =FALSE() -> FALSE | I14: =LEN(TRIM(D14))>0 -> TRUE | J14: =LEN(TRIM(E14))>0 -> TRUE | K14: =LEN(TRIM(F14))>0 -> TRUE | L14: =AND(G14>0,NOT(H14)) -> TRUE | M14: =COUNTIF(Owners!$A$4:$A$21,C14)>0 -> TRUE | N14: =AND(I14,J14,K14,L14,M14) -> TRUE
A15: m-net-promoter-score | B15: 1 | C15: own-17 | D15: Net promoter score as defined in the governance glossary, computed from web-sessions.user_key, subscriptions.started_on | E15: customer-month | F15: daily | G15: 2 | H15: =FALSE() -> FALSE | I15: =LEN(TRIM(D15))>0 -> TRUE | J15: =LEN(TRIM(E15))>0 -> TRUE | K15: =LEN(TRIM(F15))>0 -> TRUE | L15: =AND(G15>0,NOT(H15)) -> TRUE | M15: =COUNTIF(Owners!$A$4:$A$21,C15)>0 -> TRUE | N15: =AND(I15,J15,K15,L15,M15) -> TRUE
A16: m-net-revenue | B16: 2 | C16: own-02 | D16: Net revenue as defined in the governance glossary, computed from opportunities.status, web-users.email, ticket-events.status; revised: refunds are netted from the figure | F16: daily | G16: 3 | H16: =FALSE() -> FALSE | I16: =LEN(TRIM(D16))>0 -> TRUE | J16: =LEN(TRIM(E16))>0 -> FALSE | K16: =LEN(TRIM(F16))>0 -> TRUE | L16: =AND(G16>0,NOT(H16)) -> TRUE | M16: =COUNTIF(Owners!$A$4:$A$21,C16)>0 -> TRUE | N16: =AND(I16,J16,K16,L16,M16) -> FALSE
A17: m-new-customers | B17: 2 | C17: own-07 | D17: New customers as defined in the governance glossary, computed from purchase-orders.supplier_key; revised: window aligned to the fiscal calendar | E17: ticket | F17: daily | G17: 1 | H17: =FALSE() -> FALSE | I17: =LEN(TRIM(D17))>0 -> TRUE | J17: =LEN(TRIM(E17))>0 -> TRUE | K17: =LEN(TRIM(F17))>0 -> TRUE | L17: =AND(G17>0,NOT(H17)) -> TRUE | M17: =COUNTIF(Owners!$A$4:$A$21,C17)>0 -> TRUE | N17: =AND(I17,J17,K17,L17,M17) -> TRUE
A18: m-on-time-delivery-rate | B18: 1 | C18: own-06 | D18: On-time delivery rate as defined in the governance glossary, computed from consent-records.user_key, returns.status | E18: customer | F18: monthly | G18: 2 | H18: =FALSE() -> FALSE | I18: =LEN(TRIM(D18))>0 -> TRUE | J18: =LEN(TRIM(E18))>0 -> TRUE | K18: =LEN(TRIM(F18))>0 -> TRUE | L18: =AND(G18>0,NOT(H18)) -> TRUE | M18: =COUNTIF(Owners!$A$4:$A$21,C18)>0 -> TRUE | N18: =AND(I18,J18,K18,L18,M18) -> TRUE
A19: m-opportunity-win-rate | B19: 1 | C19: own-06 | D19: Opportunity win rate as defined in the governance glossary, computed from refunds.status | E19: day | F19: daily | G19: 1 | H19: =FALSE() -> FALSE | I19: =LEN(TRIM(D19))>0 -> TRUE | J19: =LEN(TRIM(E19))>0 -> TRUE | K19: =LEN(TRIM(F19))>0 -> TRUE | L19: =AND(G19>0,NOT(H19)) -> TRUE | M19: =COUNTIF(Owners!$A$4:$A$21,C19)>0 -> TRUE | N19: =AND(I19,J19,K19,L19,M19) -> TRUE
A20: m-order-fill-rate | B20: 2 | C20: own-14 | D20: Order fill rate as defined in the governance glossary, computed from delivery-events.status, contacts.full_name; revised: source moved to the curated layer | E20: shipment | F20: daily | G20: 2 | H20: =FALSE() -> FALSE | I20: =LEN(TRIM(D20))>0 -> TRUE | J20: =LEN(TRIM(E20))>0 -> TRUE | K20: =LEN(TRIM(F20))>0 -> TRUE | L20: =AND(G20>0,NOT(H20)) -> TRUE | M20: =COUNTIF(Owners!$A$4:$A$21,C20)>0 -> TRUE | N20: =AND(I20,J20,K20,L20,M20) -> TRUE
A21: m-pipeline-coverage | B21: 1 | C21: own-13 | D21: Pipeline coverage as defined in the governance glossary, computed from subscriptions.plan_code, tickets.opened_at | E21: day | F21: weekly | G21: 2 | H21: =FALSE() -> FALSE | I21: =LEN(TRIM(D21))>0 -> TRUE | J21: =LEN(TRIM(E21))>0 -> TRUE | K21: =LEN(TRIM(F21))>0 -> TRUE | L21: =AND(G21>0,NOT(H21)) -> TRUE | M21: =COUNTIF(Owners!$A$4:$A$21,C21)>0 -> TRUE | N21: =AND(I21,J21,K21,L21,M21) -> TRUE
A22: m-purchase-price-variance | B22: 1 | C22: own-02 | D22: Purchase price variance as defined in the governance glossary, computed from ledger-entries.cost_centre_code, warehouses.status, payments.invoice_key | E22: customer | F22: daily | G22: 3 | H22: =FALSE() -> FALSE | I22: =LEN(TRIM(D22))>0 -> TRUE | J22: =LEN(TRIM(E22))>0 -> TRUE | K22: =LEN(TRIM(F22))>0 -> TRUE | L22: =AND(G22>0,NOT(H22)) -> TRUE | M22: =COUNTIF(Owners!$A$4:$A$21,C22)>0 -> TRUE | N22: =AND(I22,J22,K22,L22,M22) -> TRUE
A23: m-refund-rate | B23: 1 | C23: own-02 | D23: Refund rate as defined in the governance glossary, computed from consent-records.status, cost-centres.created_date | E23: day | F23: weekly | G23: 2 | H23: =FALSE() -> FALSE | I23: =LEN(TRIM(D23))>0 -> TRUE | J23: =LEN(TRIM(E23))>0 -> TRUE | K23: =LEN(TRIM(F23))>0 -> TRUE | L23: =AND(G23>0,NOT(H23)) -> TRUE | M23: =COUNTIF(Owners!$A$4:$A$21,C23)>0 -> TRUE | N23: =AND(I23,J23,K23,L23,M23) -> TRUE
A24: m-repeat-purchase-rate | B24: 2 | C24: own-05 | D24: Repeat purchase rate as defined in the governance glossary, computed from consent-records.consent_key; revised: refunds are netted from the figure | E24: ticket | F24: daily | G24: 1 | H24: =FALSE() -> FALSE | I24: =LEN(TRIM(D24))>0 -> TRUE | J24: =LEN(TRIM(E24))>0 -> TRUE | K24: =LEN(TRIM(F24))>0 -> TRUE | L24: =AND(G24>0,NOT(H24)) -> TRUE | M24: =COUNTIF(Owners!$A$4:$A$21,C24)>0 -> TRUE | N24: =AND(I24,J24,K24,L24,M24) -> TRUE
A25: m-session-conversion-rate | B25: 2 | D25: Session conversion rate as defined in the governance glossary, computed from payments.invoice_key; revised: excludes internal test accounts | E25: order | F25: weekly | G25: 1 | H25: =FALSE() -> FALSE | I25: =LEN(TRIM(D25))>0 -> TRUE | J25: =LEN(TRIM(E25))>0 -> TRUE | K25: =LEN(TRIM(F25))>0 -> TRUE | L25: =AND(G25>0,NOT(H25)) -> TRUE | M25: =COUNTIF(Owners!$A$4:$A$21,C25)>0 -> FALSE | N25: =AND(I25,J25,K25,L25,M25) -> FALSE
A26: m-stock-out-rate | B26: 1 | C26: own-04 | D26: Stock-out rate as defined in the governance glossary, computed from shipments.shipment_key | E26: day | F26: daily | G26: 1 | H26: =FALSE() -> FALSE | I26: =LEN(TRIM(D26))>0 -> TRUE | J26: =LEN(TRIM(E26))>0 -> TRUE | K26: =LEN(TRIM(F26))>0 -> TRUE | L26: =AND(G26>0,NOT(H26)) -> TRUE | M26: =COUNTIF(Owners!$A$4:$A$21,C26)>0 -> TRUE | N26: =AND(I26,J26,K26,L26,M26) -> TRUE
A27: m-subscription-churn | B27: 2 | C27: own-02 | D27: Subscription churn as defined in the governance glossary, computed from delivery-events.status, opportunities.stage; revised: excludes internal test accounts | E27: shipment | F27: weekly | G27: 2 | H27: =FALSE() -> FALSE | I27: =LEN(TRIM(D27))>0 -> TRUE | J27: =LEN(TRIM(E27))>0 -> TRUE | K27: =LEN(TRIM(F27))>0 -> TRUE | L27: =AND(G27>0,NOT(H27)) -> TRUE | M27: =COUNTIF(Owners!$A$4:$A$21,C27)>0 -> TRUE | N27: =AND(I27,J27,K27,L27,M27) -> TRUE
A28: m-subscription-mrr | B28: 2 | C28: own-13 | D28: Subscription MRR as defined in the governance glossary, computed from delivery-events.occurred_at; revised: grain changed from order to customer-month | E28: customer-month | F28: monthly | G28: 1 | H28: =FALSE() -> FALSE | I28: =LEN(TRIM(D28))>0 -> TRUE | J28: =LEN(TRIM(E28))>0 -> TRUE | K28: =LEN(TRIM(F28))>0 -> TRUE | L28: =AND(G28>0,NOT(H28)) -> TRUE | M28: =COUNTIF(Owners!$A$4:$A$21,C28)>0 -> TRUE | N28: =AND(I28,J28,K28,L28,M28) -> TRUE
A29: m-supplier-lead-time | B29: 2 | C29: own-08 | D29: Supplier lead time as defined in the governance glossary, computed from orders.order_date, ticket-events.ticket_key; revised: source moved to the curated layer | E29: customer-month | F29: monthly | G29: 2 | H29: =FALSE() -> FALSE | I29: =LEN(TRIM(D29))>0 -> TRUE | J29: =LEN(TRIM(E29))>0 -> TRUE | K29: =LEN(TRIM(F29))>0 -> TRUE | L29: =AND(G29>0,NOT(H29)) -> TRUE | M29: =COUNTIF(Owners!$A$4:$A$21,C29)>0 -> TRUE | N29: =AND(I29,J29,K29,L29,M29) -> TRUE
A30: m-support-backlog | B30: 2 | C30: own-08 | D30: Support backlog as defined in the governance glossary, computed from inventory.warehouse_code, shipments.shipped_on, opportunities.opportunity_key; revised: refunds are netted from the figure | E30: customer-month | F30: daily | G30: 3 | H30: =FALSE() -> FALSE | I30: =LEN(TRIM(D30))>0 -> TRUE | J30: =LEN(TRIM(E30))>0 -> TRUE | K30: =LEN(TRIM(F30))>0 -> TRUE | L30: =AND(G30>0,NOT(H30)) -> TRUE | M30: =COUNTIF(Owners!$A$4:$A$21,C30)>0 -> TRUE | N30: =AND(I30,J30,K30,L30,M30) -> TRUE
A31: m-ticket-first-response-time | B31: 2 | C31: own-10 | D31: Ticket first-response time as defined in the governance glossary, computed from employees.department_code; revised: window aligned to the fiscal calendar | E31: customer | F31: weekly | G31: 1 | H31: =FALSE() -> FALSE | I31: =LEN(TRIM(D31))>0 -> TRUE | J31: =LEN(TRIM(E31))>0 -> TRUE | K31: =LEN(TRIM(F31))>0 -> TRUE | L31: =AND(G31>0,NOT(H31)) -> TRUE | M31: =COUNTIF(Owners!$A$4:$A$21,C31)>0 -> TRUE | N31: =AND(I31,J31,K31,L31,M31) -> TRUE
A32: m-ticket-resolution-time | B32: 1 | C32: own-12 | D32: Ticket resolution time as defined in the governance glossary, computed from consent-records.consent_flag, invoices.invoice_key, purchase-orders.status | E32: customer-month | G32: 3 | H32: =FALSE() -> FALSE | I32: =LEN(TRIM(D32))>0 -> TRUE | J32: =LEN(TRIM(E32))>0 -> TRUE | K32: =LEN(TRIM(F32))>0 -> FALSE | L32: =AND(G32>0,NOT(H32)) -> TRUE | M32: =COUNTIF(Owners!$A$4:$A$21,C32)>0 -> TRUE | N32: =AND(I32,J32,K32,L32,M32) -> FALSE
A33: m-trial-conversion-rate | B33: 1 | C33: own-04 | D33: Trial conversion rate as defined in the governance glossary, computed from inventory.status | E33: customer-month | F33: weekly | G33: 1 | H33: =FALSE() -> FALSE | I33: =LEN(TRIM(D33))>0 -> TRUE | J33: =LEN(TRIM(E33))>0 -> TRUE | K33: =LEN(TRIM(F33))>0 -> TRUE | L33: =AND(G33>0,NOT(H33)) -> TRUE | M33: =COUNTIF(Owners!$A$4:$A$21,C33)>0 -> TRUE | N33: =AND(I33,J33,K33,L33,M33) -> TRUE

Sheet Matching
A1: 400 match candidates: the human decision and the verification layer's truth flag
A2: truth_same_entity comes from the synthetic truth held only in the manifest (verification layer): TYPED here for the precision formulas, never used to propose or decide.
A3: candidate_id | B3: decision | C3: reversed | D3: flagged_possible_household | E3: truth_same_entity | F3: decision_agrees_with_truth
A4: cand-0001 | B4: approve | C4: =FALSE() -> FALSE | D4: =TRUE() -> TRUE | E4: =TRUE() -> TRUE | F4: =IF(B4="none","",(B4="approve")=E4) -> TRUE
A5: cand-0002 | B5: approve | C5: =FALSE() -> FALSE | D5: =TRUE() -> TRUE | E5: =TRUE() -> TRUE | F5: =IF(B5="none","",(B5="approve")=E5) -> TRUE
A6: cand-0003 | B6: approve | C6: =FALSE() -> FALSE | D6: =TRUE() -> TRUE | E6: =TRUE() -> TRUE | F6: =IF(B6="none","",(B6="approve")=E6) -> TRUE
A7: cand-0004 | B7: approve | C7: =FALSE() -> FALSE | D7: =TRUE() -> TRUE | E7: =TRUE() -> TRUE | F7: =IF(B7="none","",(B7="approve")=E7) -> TRUE
A8: cand-0005 | B8: none | C8: =FALSE() -> FALSE | D8: =TRUE() -> TRUE | E8: =TRUE() -> TRUE | F8: =IF(B8="none","",(B8="approve")=E8)
A9: cand-0006 | B9: approve | C9: =FALSE() -> FALSE | D9: =TRUE() -> TRUE | E9: =TRUE() -> TRUE | F9: =IF(B9="none","",(B9="approve")=E9) -> TRUE
A10: cand-0007 | B10: approve | C10: =FALSE() -> FALSE | D10: =FALSE() -> FALSE | E10: =TRUE() -> TRUE | F10: =IF(B10="none","",(B10="approve")=E10) -> TRUE
A11: cand-0008 | B11: approve | C11: =FALSE() -> FALSE | D11: =TRUE() -> TRUE | E11: =TRUE() -> TRUE | F11: =IF(B11="none","",(B11="approve")=E11) -> TRUE
A12: cand-0009 | B12: approve | C12: =FALSE() -> FALSE | D12: =FALSE() -> FALSE | E12: =TRUE() -> TRUE | F12: =IF(B12="none","",(B12="approve")=E12) -> TRUE
A13: cand-0010 | B13: none | C13: =FALSE() -> FALSE | D13: =FALSE() -> FALSE | E13: =TRUE() -> TRUE | F13: =IF(B13="none","",(B13="approve")=E13)
A14: cand-0011 | B14: approve | C14: =FALSE() -> FALSE | D14: =FALSE() -> FALSE | E14: =TRUE() -> TRUE | F14: =IF(B14="none","",(B14="approve")=E14) -> TRUE
A15: cand-0012 | B15: approve | C15: =FALSE() -> FALSE | D15: =FALSE() -> FALSE | E15: =TRUE() -> TRUE | F15: =IF(B15="none","",(B15="approve")=E15) -> TRUE
A16: cand-0013 | B16: reject | C16: =FALSE() -> FALSE | D16: =TRUE() -> TRUE | E16: =TRUE() -> TRUE | F16: =IF(B16="none","",(B16="approve")=E16) -> FALSE
A17: cand-0014 | B17: none | C17: =FALSE() -> FALSE | D17: =TRUE() -> TRUE | E17: =TRUE() -> TRUE | F17: =IF(B17="none","",(B17="approve")=E17)
A18: cand-0015 | B18: reject | C18: =FALSE() -> FALSE | D18: =FALSE() -> FALSE | E18: =TRUE() -> TRUE | F18: =IF(B18="none","",(B18="approve")=E18) -> FALSE
A19: cand-0016 | B19: approve | C19: =FALSE() -> FALSE | D19: =TRUE() -> TRUE | E19: =TRUE() -> TRUE | F19: =IF(B19="none","",(B19="approve")=E19) -> TRUE
A20: cand-0017 | B20: none | C20: =FALSE() -> FALSE | D20: =TRUE() -> TRUE | E20: =TRUE() -> TRUE | F20: =IF(B20="none","",(B20="approve")=E20)
A21: cand-0018 | B21: approve | C21: =FALSE() -> FALSE | D21: =TRUE() -> TRUE | E21: =TRUE() -> TRUE | F21: =IF(B21="none","",(B21="approve")=E21) -> TRUE
A22: cand-0019 | B22: reject | C22: =FALSE() -> FALSE | D22: =FALSE() -> FALSE | E22: =FALSE() -> FALSE | F22: =IF(B22="none","",(B22="approve")=E22) -> TRUE
A23: cand-0020 | B23: reject | C23: =FALSE() -> FALSE | D23: =TRUE() -> TRUE | E23: =FALSE() -> FALSE | F23: =IF(B23="none","",(B23="approve")=E23) -> TRUE
A24: cand-0021 | B24: approve | C24: =FALSE() -> FALSE | D24: =TRUE() -> TRUE | E24: =TRUE() -> TRUE | F24: =IF(B24="none","",(B24="approve")=E24) -> TRUE
A25: cand-0022 | B25: none | C25: =FALSE() -> FALSE | D25: =TRUE() -> TRUE | E25: =TRUE() -> TRUE | F25: =IF(B25="none","",(B25="approve")=E25)
A26: cand-0023 | B26: none | C26: =FALSE() -> FALSE | D26: =FALSE() -> FALSE | E26: =TRUE() -> TRUE | F26: =IF(B26="none","",(B26="approve")=E26)
A27: cand-0024 | B27: none | C27: =FALSE() -> FALSE | D27: =TRUE() -> TRUE | E27: =TRUE() -> TRUE | F27: =IF(B27="none","",(B27="approve")=E27)
A28: cand-0025 | B28: approve | C28: =FALSE() -> FALSE | D28: =TRUE() -> TRUE | E28: =TRUE() -> TRUE | F28: =IF(B28="none","",(B28="approve")=E28) -> TRUE
A29: cand-0026 | B29: approve | C29: =FALSE() -> FALSE | D29: =FALSE() -> FALSE | E29: =TRUE() -> TRUE | F29: =IF(B29="none","",(B29="approve")=E29) -> TRUE
A30: cand-0027 | B30: reject | C30: =FALSE() -> FALSE | D30: =FALSE() -> FALSE | E30: =TRUE() -> TRUE | F30: =IF(B30="none","",(B30="approve")=E30) -> FALSE
A31: cand-0028 | B31: approve | C31: =FALSE() -> FALSE | D31: =FALSE() -> FALSE | E31: =TRUE() -> TRUE | F31: =IF(B31="none","",(B31="approve")=E31) -> TRUE
A32: cand-0029 | B32: none | C32: =FALSE() -> FALSE | D32: =TRUE() -> TRUE | E32: =FALSE() -> FALSE | F32: =IF(B32="none","",(B32="approve")=E32)
A33: cand-0030 | B33: approve | C33: =FALSE() -> FALSE | D33: =FALSE() -> FALSE | E33: =TRUE() -> TRUE | F33: =IF(B33="none","",(B33="approve")=E33) -> TRUE
A34: cand-0031 | B34: approve | C34: =FALSE() -> FALSE | D34: =TRUE() -> TRUE | E34: =TRUE() -> TRUE | F34: =IF(B34="none","",(B34="approve")=E34) -> TRUE
A35: cand-0032 | B35: none | C35: =FALSE() -> FALSE | D35: =FALSE() -> FALSE | E35: =TRUE() -> TRUE | F35: =IF(B35="none","",(B35="approve")=E35)
A36: cand-0033 | B36: reject | C36: =FALSE() -> FALSE | D36: =FALSE() -> FALSE | E36: =FALSE() -> FALSE | F36: =IF(B36="none","",(B36="approve")=E36) -> TRUE
A37: cand-0034 | B37: approve | C37: =FALSE() -> FALSE | D37: =TRUE() -> TRUE | E37: =TRUE() -> TRUE | F37: =IF(B37="none","",(B37="approve")=E37) -> TRUE
A38: cand-0035 | B38: approve | C38: =FALSE() -> FALSE | D38: =FALSE() -> FALSE | E38: =TRUE() -> TRUE | F38: =IF(B38="none","",(B38="approve")=E38) -> TRUE
A39: cand-0036 | B39: none | C39: =FALSE() -> FALSE | D39: =FALSE() -> FALSE | E39: =FALSE() -> FALSE | F39: =IF(B39="none","",(B39="approve")=E39)
A40: cand-0037 | B40: approve | C40: =FALSE() -> FALSE | D40: =FALSE() -> FALSE | E40: =TRUE() -> TRUE | F40: =IF(B40="none","",(B40="approve")=E40) -> TRUE
A41: cand-0038 | B41: reject | C41: =FALSE() -> FALSE | D41: =TRUE() -> TRUE | E41: =TRUE() -> TRUE | F41: =IF(B41="none","",(B41="approve")=E41) -> FALSE
A42: cand-0039 | B42: approve | C42: =FALSE() -> FALSE | D42: =TRUE() -> TRUE | E42: =TRUE() -> TRUE | F42: =IF(B42="none","",(B42="approve")=E42) -> TRUE
A43: cand-0040 | B43: reject | C43: =FALSE() -> FALSE | D43: =TRUE() -> TRUE | E43: =FALSE() -> FALSE | F43: =IF(B43="none","",(B43="approve")=E43) -> TRUE
A44: cand-0041 | B44: approve | C44: =FALSE() -> FALSE | D44: =FALSE() -> FALSE | E44: =TRUE() -> TRUE | F44: =IF(B44="none","",(B44="approve")=E44) -> TRUE
A45: cand-0042 | B45: reject | C45: =FALSE() -> FALSE | D45: =TRUE() -> TRUE | E45: =FALSE() -> FALSE | F45: =IF(B45="none","",(B45="approve")=E45) -> TRUE
A46: cand-0043 | B46: reject | C46: =FALSE() -> FALSE | D46: =TRUE() -> TRUE | E46: =FALSE() -> FALSE | F46: =IF(B46="none","",(B46="approve")=E46) -> TRUE
A47: cand-0044 | B47: none | C47: =FALSE() -> FALSE | D47: =FALSE() -> FALSE | E47: =TRUE() -> TRUE | F47: =IF(B47="none","",(B47="approve")=E47)
A48: cand-0045 | B48: approve | C48: =FALSE() -> FALSE | D48: =FALSE() -> FALSE | E48: =TRUE() -> TRUE | F48: =IF(B48="none","",(B48="approve")=E48) -> TRUE
A49: cand-0046 | B49: reject | C49: =FALSE() -> FALSE | D49: =TRUE() -> TRUE | E49: =FALSE() -> FALSE | F49: =IF(B49="none","",(B49="approve")=E49) -> TRUE
A50: cand-0047 | B50: approve | C50: =FALSE() -> FALSE | D50: =FALSE() -> FALSE | E50: =TRUE() -> TRUE | F50: =IF(B50="none","",(B50="approve")=E50) -> TRUE
A51: cand-0048 | B51: approve | C51: =FALSE() -> FALSE | D51: =FALSE() -> FALSE | E51: =TRUE() -> TRUE | F51: =IF(B51="none","",(B51="approve")=E51) -> TRUE
A52: cand-0049 | B52: approve | C52: =FALSE() -> FALSE | D52: =TRUE() -> TRUE | E52: =TRUE() -> TRUE | F52: =IF(B52="none","",(B52="approve")=E52) -> TRUE
A53: cand-0050 | B53: approve | C53: =TRUE() -> TRUE | D53: =FALSE() -> FALSE | E53: =TRUE() -> TRUE | F53: =IF(B53="none","",(B53="approve")=E53) -> TRUE
A54: cand-0051 | B54: reject | C54: =FALSE() -> FALSE | D54: =TRUE() -> TRUE | E54: =FALSE() -> FALSE | F54: =IF(B54="none","",(B54="approve")=E54) -> TRUE
A55: cand-0052 | B55: none | C55: =FALSE() -> FALSE | D55: =FALSE() -> FALSE | E55: =TRUE() -> TRUE | F55: =IF(B55="none","",(B55="approve")=E55)
A56: cand-0053 | B56: none | C56: =FALSE() -> FALSE | D56: =TRUE() -> TRUE | E56: =TRUE() -> TRUE | F56: =IF(B56="none","",(B56="approve")=E56)
A57: cand-0054 | B57: none | C57: =FALSE() -> FALSE | D57: =FALSE() -> FALSE | E57: =TRUE() -> TRUE | F57: =IF(B57="none","",(B57="approve")=E57)
A58: cand-0055 | B58: approve | C58: =FALSE() -> FALSE | D58: =TRUE() -> TRUE | E58: =TRUE() -> TRUE | F58: =IF(B58="none","",(B58="approve")=E58) -> TRUE
A59: cand-0056 | B59: approve | C59: =FALSE() -> FALSE | D59: =TRUE() -> TRUE | E59: =TRUE() -> TRUE | F59: =IF(B59="none","",(B59="approve")=E59) -> TRUE
A60: cand-0057 | B60: approve | C60: =FALSE() -> FALSE | D60: =TRUE() -> TRUE | E60: =TRUE() -> TRUE | F60: =IF(B60="none","",(B60="approve")=E60) -> TRUE
A61: cand-0058 | B61: approve | C61: =FALSE() -> FALSE | D61: =FALSE() -> FALSE | E61: =TRUE() -> TRUE | F61: =IF(B61="none","",(B61="approve")=E61) -> TRUE
A62: cand-0059 | B62: reject | C62: =FALSE() -> FALSE | D62: =TRUE() -> TRUE | E62: =FALSE() -> FALSE | F62: =IF(B62="none","",(B62="approve")=E62) -> TRUE
A63: cand-0060 | B63: approve | C63: =FALSE() -> FALSE | D63: =FALSE() -> FALSE | E63: =TRUE() -> TRUE | F63: =IF(B63="none","",(B63="approve")=E63) -> TRUE
A64: cand-0061 | B64: approve | C64: =FALSE() -> FALSE | D64: =TRUE() -> TRUE | E64: =TRUE() -> TRUE | F64: =IF(B64="none","",(B64="approve")=E64) -> TRUE
A65: cand-0062 | B65: approve | C65: =FALSE() -> FALSE | D65: =FALSE() -> FALSE | E65: =TRUE() -> TRUE | F65: =IF(B65="none","",(B65="approve")=E65) -> TRUE
A66: cand-0063 | B66: reject | C66: =FALSE() -> FALSE | D66: =TRUE() -> TRUE | E66: =FALSE() -> FALSE | F66: =IF(B66="none","",(B66="approve")=E66) -> TRUE
A67: cand-0064 | B67: approve | C67: =FALSE() -> FALSE | D67: =TRUE() -> TRUE | E67: =TRUE() -> TRUE | F67: =IF(B67="none","",(B67="approve")=E67) -> TRUE
A68: cand-0065 | B68: none | C68: =FALSE() -> FALSE | D68: =FALSE() -> FALSE | E68: =TRUE() -> TRUE | F68: =IF(B68="none","",(B68="approve")=E68)
A69: cand-0066 | B69: approve | C69: =FALSE() -> FALSE | D69: =FALSE() -> FALSE | E69: =TRUE() -> TRUE | F69: =IF(B69="none","",(B69="approve")=E69) -> TRUE
A70: cand-0067 | B70: none | C70: =FALSE() -> FALSE | D70: =TRUE() -> TRUE | E70: =TRUE() -> TRUE | F70: =IF(B70="none","",(B70="approve")=E70)
A71: cand-0068 | B71: approve | C71: =TRUE() -> TRUE | D71: =TRUE() -> TRUE | E71: =TRUE() -> TRUE | F71: =IF(B71="none","",(B71="approve")=E71) -> TRUE
A72: cand-0069 | B72: approve | C72: =FALSE() -> FALSE | D72: =FALSE() -> FALSE | E72: =TRUE() -> TRUE | F72: =IF(B72="none","",(B72="approve")=E72) -> TRUE
A73: cand-0070 | B73: none | C73: =FALSE() -> FALSE | D73: =TRUE() -> TRUE | E73: =TRUE() -> TRUE | F73: =IF(B73="none","",(B73="approve")=E73)
A74: cand-0071 | B74: approve | C74: =FALSE() -> FALSE | D74: =TRUE() -> TRUE | E74: =TRUE() -> TRUE | F74: =IF(B74="none","",(B74="approve")=E74) -> TRUE
A75: cand-0072 | B75: approve | C75: =FALSE() -> FALSE | D75: =FALSE() -> FALSE | E75: =TRUE() -> TRUE | F75: =IF(B75="none","",(B75="approve")=E75) -> TRUE
A76: cand-0073 | B76: none | C76: =FALSE() -> FALSE | D76: =TRUE() -> TRUE | E76: =FALSE() -> FALSE | F76: =IF(B76="none","",(B76="approve")=E76)
A77: cand-0074 | B77: reject | C77: =FALSE() -> FALSE | D77: =TRUE() -> TRUE | E77: =TRUE() -> TRUE | F77: =IF(B77="none","",(B77="approve")=E77) -> FALSE
A78: cand-0075 | B78: approve | C78: =FALSE() -> FALSE | D78: =TRUE() -> TRUE | E78: =TRUE() -> TRUE | F78: =IF(B78="none","",(B78="approve")=E78) -> TRUE
A79: cand-0076 | B79: approve | C79: =TRUE() -> TRUE | D79: =TRUE() -> TRUE | E79: =TRUE() -> TRUE | F79: =IF(B79="none","",(B79="approve")=E79) -> TRUE
A80: cand-0077 | B80: approve | C80: =FALSE() -> FALSE | D80: =TRUE() -> TRUE | E80: =TRUE() -> TRUE | F80: =IF(B80="none","",(B80="approve")=E80) -> TRUE
A81: cand-0078 | B81: approve | C81: =FALSE() -> FALSE | D81: =TRUE() -> TRUE | E81: =TRUE() -> TRUE | F81: =IF(B81="none","",(B81="approve")=E81) -> TRUE
A82: cand-0079 | B82: reject | C82: =FALSE() -> FALSE | D82: =FALSE() -> FALSE | E82: =FALSE() -> FALSE | F82: =IF(B82="none","",(B82="approve")=E82) -> TRUE
A83: cand-0080 | B83: none | C83: =FALSE() -> FALSE | D83: =TRUE() -> TRUE | E83: =TRUE() -> TRUE | F83: =IF(B83="none","",(B83="approve")=E83)
A84: cand-0081 | B84: approve | C84: =FALSE() -> FALSE | D84: =TRUE() -> TRUE | E84: =TRUE() -> TRUE | F84: =IF(B84="none","",(B84="approve")=E84) -> TRUE
A85: cand-0082 | B85: reject | C85: =FALSE() -> FALSE | D85: =FALSE() -> FALSE | E85: =FALSE() -> FALSE | F85: =IF(B85="none","",(B85="approve")=E85) -> TRUE
A86: cand-0083 | B86: reject | C86: =FALSE() -> FALSE | D86: =TRUE() -> TRUE | E86: =TRUE() -> TRUE | F86: =IF(B86="none","",(B86="approve")=E86) -> FALSE
A87: cand-0084 | B87: reject | C87: =FALSE() -> FALSE | D87: =FALSE() -> FALSE | E87: =FALSE() -> FALSE | F87: =IF(B87="none","",(B87="approve")=E87) -> TRUE
A88: cand-0085 | B88: none | C88: =FALSE() -> FALSE | D88: =FALSE() -> FALSE | E88: =TRUE() -> TRUE | F88: =IF(B88="none","",(B88="approve")=E88)
A89: cand-0086 | B89: none | C89: =FALSE() -> FALSE | D89: =FALSE() -> FALSE | E89: =TRUE() -> TRUE | F89: =IF(B89="none","",(B89="approve")=E89)
A90: cand-0087 | B90: approve | C90: =FALSE() -> FALSE | D90: =TRUE() -> TRUE | E90: =TRUE() -> TRUE | F90: =IF(B90="none","",(B90="approve")=E90) -> TRUE
A91: cand-0088 | B91: none | C91: =FALSE() -> FALSE | D91: =TRUE() -> TRUE | E91: =TRUE() -> TRUE | F91: =IF(B91="none","",(B91="approve")=E91)
A92: cand-0089 | B92: none | C92: =FALSE() -> FALSE | D92: =FALSE() -> FALSE | E92: =TRUE() -> TRUE | F92: =IF(B92="none","",(B92="approve")=E92)
A93: cand-0090 | B93: approve | C93: =FALSE() -> FALSE | D93: =TRUE() -> TRUE | E93: =TRUE() -> TRUE | F93: =IF(B93="none","",(B93="approve")=E93) -> TRUE
A94: cand-0091 | B94: none | C94: =FALSE() -> FALSE | D94: =FALSE() -> FALSE | E94: =TRUE() -> TRUE | F94: =IF(B94="none","",(B94="approve")=E94)
A95: cand-0092 | B95: approve | C95: =FALSE() -> FALSE | D95: =TRUE() -> TRUE | E95: =TRUE() -> TRUE | F95: =IF(B95="none","",(B95="approve")=E95) -> TRUE
A96: cand-0093 | B96: none | C96: =FALSE() -> FALSE | D96: =FALSE() -> FALSE | E96: =TRUE() -> TRUE | F96: =IF(B96="none","",(B96="approve")=E96)
A97: cand-0094 | B97: none | C97: =FALSE() -> FALSE | D97: =FALSE() -> FALSE | E97: =TRUE() -> TRUE | F97: =IF(B97="none","",(B97="approve")=E97)
A98: cand-0095 | B98: approve | C98: =FALSE() -> FALSE | D98: =TRUE() -> TRUE | E98: =TRUE() -> TRUE | F98: =IF(B98="none","",(B98="approve")=E98) -> TRUE
A99: cand-0096 | B99: none | C99: =FALSE() -> FALSE | D99: =FALSE() -> FALSE | E99: =TRUE() -> TRUE | F99: =IF(B99="none","",(B99="approve")=E99)
A100: cand-0097 | B100: approve | C100: =FALSE() -> FALSE | D100: =TRUE() -> TRUE | E100: =TRUE() -> TRUE | F100: =IF(B100="none","",(B100="approve")=E100) -> TRUE
...

Sheet Timeliness
A1: The 15 monitored datasets at the as-of: the judged occurrence and deadline (typed from the Python side) and the state (formula)
A2: state = on_time when a refresh lies in [occurrence, deadline); otherwise pending while the deadline is after the as-of; otherwise late. A pending dataset is outside the denominator.
A3: dataset_id | B3: timezone | C3: scheduled_local | D3: grace_minutes | E3: occurrence_utc | F3: deadline_utc | G3: last_refreshed_at | H3: state
A4: ds-campaigns | B4: Asia/Singapore | C4: 01:00 | D4: 60 | E4: 46299.708 | F4: 46299.75 | G4: 46299.836 | H4: =IF(AND(ISNUMBER(G4),G4>=E4,G4<F4),"on_time",IF(F4>Controls!$B$4,"pending","late")) -> late
A5: ds-consent-records | B5: America/Chicago | C5: 15:00 | D5: 60 | E5: 46299.833 | F5: 46299.875 | G5: 46299.837 | H5: =IF(AND(ISNUMBER(G5),G5>=E5,G5<F5),"on_time",IF(F5>Controls!$B$4,"pending","late")) -> on_time
A6: ds-contacts | B6: America/New_York | C6: 11:30 | D6: 30 | E6: 46299.646 | F6: 46299.667 | G6: 46299.655 | H6: =IF(AND(ISNUMBER(G6),G6>=E6,G6<F6),"on_time",IF(F6>Controls!$B$4,"pending","late")) -> on_time
A7: ds-customers | B7: America/New_York | C7: 06:00 | D7: 60 | E7: 46299.417 | F7: 46299.458 | G7: 46299.457 | H7: =IF(AND(ISNUMBER(G7),G7>=E7,G7<F7),"on_time",IF(F7>Controls!$B$4,"pending","late")) -> on_time
A8: ds-inventory | B8: Asia/Kolkata | C8: 18:45 | D8: 30 | E8: 46299.552 | F8: 46299.573 | G8: 46299.555 | H8: =IF(AND(ISNUMBER(G8),G8>=E8,G8<F8),"on_time",IF(F8>Controls!$B$4,"pending","late")) -> on_time
A9: ds-invoices | B9: Asia/Singapore | C9: 12:45 | D9: 60 | E9: 46299.198 | F9: 46299.24 | G9: 46299.212 | H9: =IF(AND(ISNUMBER(G9),G9>=E9,G9<F9),"on_time",IF(F9>Controls!$B$4,"pending","late")) -> on_time
A10: ds-orders | B10: Europe/London | C10: 15:45 | D10: 30 | E10: 46299.615 | F10: 46299.635 | G10: 46299.708 | H10: =IF(AND(ISNUMBER(G10),G10>=E10,G10<F10),"on_time",IF(F10>Controls!$B$4,"pending","late")) -> late
A11: ds-payments | B11: UTC | C11: 06:00 | D11: 120 | E11: 46299.25 | F11: 46299.333 | G11: 46299.496 | H11: =IF(AND(ISNUMBER(G11),G11>=E11,G11<F11),"on_time",IF(F11>Controls!$B$4,"pending","late")) -> late
A12: ds-price-books | B12: Europe/Berlin | C12: 19:15 | D12: 120 | E12: 46299.719 | F12: 46299.802 | G12: 46299.728 | H12: =IF(AND(ISNUMBER(G12),G12>=E12,G12<F12),"on_time",IF(F12>Controls!$B$4,"pending","late")) -> on_time
A13: ds-purchase-orders | B13: America/New_York | C13: 18:30 | D13: 30 | E13: 46299.938 | F13: 46299.958 | G13: 46299.943 | H13: =IF(AND(ISNUMBER(G13),G13>=E13,G13<F13),"on_time",IF(F13>Controls!$B$4,"pending","late")) -> on_time
A14: ds-shipments | B14: America/New_York | C14: 03:45 | D14: 30 | E14: 46299.323 | F14: 46299.344 | G14: 46299.343 | H14: =IF(AND(ISNUMBER(G14),G14>=E14,G14<F14),"on_time",IF(F14>Controls!$B$4,"pending","late")) -> on_time
A15: ds-sla-policies | B15: Asia/Kolkata | C15: 14:30 | D15: 120 | E15: 46299.375 | F15: 46299.458 | G15: 46299.425 | H15: =IF(AND(ISNUMBER(G15),G15>=E15,G15<F15),"on_time",IF(F15>Controls!$B$4,"pending","late")) -> on_time
... A18: ds-web-users | B18: Europe/Berlin | C18: 12:30 | D18: 30 | E18: 46299.438 | F18: 46299.458 | G18: 46299.451 | H18: =IF(AND(ISNUMBER(G18),G18>=E18,G18<F18),"on_time",IF(F18>Controls!$B$4,"pending","late")) -> on_time

Sheet Weights
A1: Rule-weight versions (append-only: a change is a new version, D-07 assumption 4)
A3: weight_version | B3: valid_from (UTC) | C3: completeness | D3: validity | E3: uniqueness | F3: relationship | G3: timeliness
A4: w1 | B4: 2026-01-01T00:00:00Z | C4: 0.4 | D4: 0.3 | E4: 0.2 | F4: 0.05 | G4: 0.05
A5: w2 | B5: 2026-09-01T00:00:00Z | C5: 0.25 | D5: 0.25 | E5: 0.25 | F5: 0.15 | G5: 0.1

Sheet Domain reference
A1: PASTED VALUES from the Python domain (run_pipeline over the snapshot with the verification truth for precision), read only by the check columns
A2: Dataset weighted scores under both weight versions ("not measured" = the domain measures no dimension: never 0).
A3: dataset_id | B3: w1 | C3: w2
A4: ds-accounts | B4: 0.99 | C4: 0.98125
A5: ds-billing-accounts | B5: not measured | C5: not measured
A6: ds-campaigns | B6: not measured | C6: not measured
A7: ds-carriers | B7: 0.966387 | C7: 0.966387
A8: ds-consent-records | B8: 0.91634 | C8: 0.932773
A9: ds-contacts | B9: 0.984127 | C9: 0.988839
A10: ds-cost-centres | B10: 0.974359 | C10: 0.974359
A11: ds-credit-notes | B11: not measured | C11: not measured
A12: ds-crm-activities | B12: not measured | C12: not measured
A13: ds-csat-surveys | B13: 0.935484 | C13: 0.935484
A14: ds-customers | B14: 0.990329 | C14: 0.990175
A15: ds-delivery-events | B15: 0.955882 | C15: 0.955882
A16: ds-employees | B16: 1 | C16: 1
A17: ds-experiments | B17: not measured | C17: not measured
A18: ds-inventory | B18: 1 | C18: 1
A19: ds-invoices | B19: 0.987767 | C19: 0.986495
A20: ds-kb-articles | B20: 0.984848 | C20: 0.984848
A21: ds-leads | B21: not measured | C21: not measured
A22: ds-ledger-entries | B22: 0.942387 | C22: 0.950617
A23: ds-opportunities | B23: 0.886076 | C23: 0.886076
A24: ds-order-lines | B24: 0.966981 | C24: 0.966981
A25: ds-orders | B25: 0.936207 | C25: 0.891379
A26: ds-page-events | B26: not measured | C26: not measured
A27: ds-payments | B27: 0.831301 | C27: 0.796341
A28: ds-price-books | B28: not measured | C28: not measured
A29: ds-products | B29: 0.982759 | C29: 0.982759
A30: ds-purchase-orders | B30: 0.977778 | C30: 0.977778
A31: ds-refunds | B31: 0.938776 | C31: 0.938776
A32: ds-returns | B32: 0.93 | C32: 0.93
A33: ds-segments | B33: not measured | C33: not measured
A34: ds-shipments | B34: 0.848394 | C34: 0.850297
A35: ds-sla-policies | B35: not measured | C35: not measured
A36: ds-subscriptions | B36: 0.961988 | C36: 0.955044
A37: ds-suppliers | B37: 0.961149 | C37: 0.964894
A38: ds-support-agents | B38: not measured | C38: not measured
A39: ds-ticket-events | B39: 0.971429 | C39: 0.971429
A40: ds-tickets | B40: 0.852608 | C40: 0.685131
A41: ds-warehouses | B41: 0.933333 | C41: 0.933333
A42: ds-web-sessions | B42: 0.985714 | C42: 0.985714
A43: ds-web-users | B43: 0.986014 | C43: 0.987374

Sheet SQL results (pasted)
A1: PASTED VALUES from data/sql/analysis/run_all.py (artifacts/analysis-results.json)
A2: The headline result sets; reconciliation: every row equal across the SQL, the reference SQL, the Python domain, the manifests and the independent Python side.
A4: reconciliation rows 175, equal 175; result sets 51, rows 233; dataset tl-20261026-20261026 / a9f7a3321b102752dd7aa95b76df14c1d9372103e685e10222959fd6438f27ff; code 0b5d686
A6: 01_ds_customers_override_both_weights__weighted
A7: weight_version | B7: valid_from | C7: measured_dimensions | D7: weight_sum | E7: weighted_score | F7: above_0_95
A8: w1 | B8: 2026-01-01 | C8: completeness,validity,uniqueness,timeliness | D8: 0.95 | E8: 0.990329 | F8: true
A9: w2 | B9: 2026-09-01 | C9: completeness,validity,uniqueness,timeliness | D9: 0.85 | E9: 0.990175 | F9: true
A11: 02_ownership_coverage__summary
A12: datasets | B12: covered | C12: uncovered | D12: coverage
A13: 40 | B13: 35 | C13: 5 | D13: 0.875
A15: 03_weight_shift_dr03__summary
A16: datasets_scored | B16: datasets_with_different_score | C16: datasets_moved_at_least_0_005 | D16: mean_score_w1 | E16: mean_score_w2 | F16: largest_move | G16: largest_move_dataset
A17: 29 | B17: 13 | C17: 7 | D17: 0.95098 | E17: 0.943118 | F17: -0.167477 | G17: ds-tickets
A19: 04_issue_classes_and_resolution__classes
A20: class | B20: issues | C20: share_of_issues | D20: reopened
A21: resolved | B21: 315 | C21: 0.54878 | D21: 1
A22: claimed | B22: 99 | C22: 0.172474 | D22: 0
A23: open | B23: 160 | C23: 0.278746 | D23: 8
A25: 04_issue_classes_and_resolution__resolution_overall
A26: resolved | B26: mean_hours | C26: fast_team_ratio | D26: open_count | E26: reopened_issues | F26: reopen_cycles
A27: 315 | B27: 68.2716 | C27: 0.399384 | D27: 160 | E27: 9 | F27: 9
A29: 04_issue_classes_and_resolution__fast_team_vs_others
A30: group_name | B30: resolved | C30: mean_hours
A31: Data Platform | B31: 109 | C31: 34.4202
A32: all other teams | B32: 206 | C32: 86.1833
A34: 05_lineage_coverage_evidence__coverage
A35: declared_pairs | B35: observed_pairs | C35: observed_matching_declared | D35: coverage | E35: undeclared_observed | F35: declared_not_observed | G35: inferred_pairs | H35: inferred_on_declared_unobserved | I35: inferred_also_observed
A36: 80 | B36: 70 | C36: 58 | D36: 0.725 | E36: 12 | F36: 22 | G36: 10 | H36: 4 | I36: 0
A38: 06_definition_coverage__summary
A39: checklist_version | B39: published_metrics | C39: complete_metrics | D39: incomplete_metrics | E39: coverage
A40: cl-1 | B40: 30 | C40: 23 | D40: 7 | E40: 0.766667
A42: 07_match_precision__precision
A43: approved | B43: approved_correct | C43: precision | D43: reviewed | E43: rejected | F43: reviewed_correct | G43: reviewed_correct_share | H43: decisions_agreeing_with_truth | I43: decision_agreement_share
A44: 174 | B44: 172 | C44: 0.988506 | D44: 220 | E44: 46 | F44: 185 | G44: 0.840909 | H44: 205 | I44: 0.931818
A46: 08_timeliness_states__by_read_instant
A47: read_no | B47: label | C47: read_at | D47: monitored_datasets | E47: on_time | F47: pending | G47: late | H47: evaluated | I47: timeliness
A48: 0 | B48: as-of | C48: 2026-10-05T00:00:00Z | D48: 15 | E48: 10 | F48: 0 | G48: 5 | H48: 15 | I48: 0.666667
A49: 1 | B49: as-of + 10h30m | C49: 2026-10-05T10:30:00Z | D49: 15 | E49: 5 | F49: 3 | G49: 7 | H49: 12 | I49: 0.416667
A50: 2 | B50: as-of + 13h | C50: 2026-10-05T13:00:00Z | D50: 15 | E50: 5 | F50: 0 | G50: 10 | H50: 15 | I50: 0.333333
A51: 3 | B51: as-of + 25h | C51: 2026-10-06T01:00:00Z | D51: 15 | E51: 0 | F51: 0 | G51: 15 | H51: 15 | I51: 0
A53: 09_golden_known_answer__weighted_scores
A54: weight_version | B54: measured_dimensions | C54: weight_sum | D54: weighted_score | E54: critical_failures | F54: critical_open_issues | G54: critical_override
A55: w1 | B55: completeness,validity,uniqueness,timeliness | C55: 0.95 | D55: 0.958116 | E55: 2 | F55: 1 | G55: true
A56: w2 | B56: completeness,validity,uniqueness,timeliness | C56: 0.85 | D56: 0.963932 | E56: 2 | F56: 1 | G56: true
