Workbook

Sheet Inputs
A1: Inputs: the golden fixture rows (tests/fixtures/golden/inputs.json, fixture revenue-atlas-golden-v1)
A2: SYNTHETIC. Every cell below is a typed input copied from the fixture (blue). Contract v1 / v1.1, docs/contracts.md.
A4: customers
A5: customer_id | B5: customer_name | C5: region_id | D5: segment | E5: effective_from
A6: cust-001 | B6: Golden Customer | C6: reg-001 | D6: SMB | E6: 2025-01-01
A8: products
A9: product_id | B9: sku | C9: category_id | D9: unit_of_measure | E9: active
A10: prod-001 | B10: SKU-A | C10: cat-001 | D10: each | E10: true
A11: prod-002 | B11: SKU-B | C11: cat-001 | D11: each | E11: true
A13: orders
A14: order_id | B14: customer_id | C14: order_date | D14: currency | E14: status
A15: ord-001 | B15: cust-001 | C15: 2026-03-08 | D15: USD | E15: shipped
A17: order_lines
A18: line_id | B18: order_id | C18: product_id | D18: quantity | E18: unit_price
A19: line-001 | B19: ord-001 | C19: prod-001 | D19: 2 | E19: 100
A20: line-002 | B20: ord-001 | C20: prod-002 | D20: 1 | E20: 50
A22: discounts
A23: discount_id | B23: line_id | C23: discount_amount | D23: reason_code | E23: approved_by
A24: disc-001 | B24: line-001 | C24: 20 | D24: VOLUME | E24: mgr-001
A25: disc-002 | B25: line-002 | C25: 5 | D25: PROMO | E25: mgr-001
A27: shipments
A28: shipment_id | B28: order_id | C28: shipped_at | D28: shipping_cost | E28: currency
A29: shp-001 | B29: ord-001 | C29: 2026-03-10T14:30:00Z | D29: 15 | E29: USD
A31: shipment_lines
A32: shipment_line_id | B32: shipment_id | C32: line_id | D32: shipped_quantity | E32: cost_version_id
A33: sl-001 | B33: shp-001 | C33: line-001 | D33: 2 | E33: cv-001
A34: sl-002 | B34: shp-001 | C34: line-002 | D34: 1 | E34: cv-002
A36: returns
A37: return_id | B37: shipment_line_id | C37: returned_quantity | D37: credit_amount | E37: credit_date
A38: ret-001 | B38: sl-001 | C38: 1 | D38: 90 | E38: 2026-03-20
A40: cost_versions
A41: cost_version_id | B41: product_id | C41: unit_cost | D41: valid_from | E41: valid_to
A42: cv-001 | B42: prod-001 | C42: 60 | D42: 2026-01-01
A43: cv-002 | B43: prod-002 | C43: 20 | D43: 2026-01-01
A45: exchange_rates
A46: rate_id | B46: currency | C46: reporting_currency | D46: rate_date | E46: rate
A47: fx-001 | B47: USD | C47: USD | D47: 2026-01-01 | E47: 1

Sheet Allocation
A1: Allocation: freight and discounts by shipment line, largest remainder as live formulas (D-04)
A2: Cents are integers: floor(T x w / W), remainder mod(T x w, W); leftover cents go to the largest remainders, ties to the lowest shipment_line_id. Zero-gross fallback (weight = quantity) is in the weight formula.
A4: 1. Freight: shipping_cost over the shipment's lines by gross-sales weight
A5: shipment_line_id | B5: shipment_id | C5: line_id | D5: shipped_quantity | E5: unit_price | F5: gross_sales | G5: total_cents | H5: weight | I5: weight_sum | J5: floor_cents | K5: remainder | L5: leftover_cents | M5: rank | N5: extra_cent | O5: allocated_amount
A6: =Inputs!A33 -> sl-001 | B6: =Inputs!B33 -> shp-001 | C6: =Inputs!C33 -> line-001 | D6: =Inputs!D33 -> 2 | E6: =INDEX(Inputs!$E$19:$E$20,MATCH(C6,Inputs!$A$19:$A$20,0)) -> 100 | F6: =D6*E6 -> 200 | G6: =ROUND(INDEX(Inputs!$D$29:$D$29,MATCH(B6,Inputs!$A$29:$A$29,0)),2)*100 -> 1500 | H6: =IF(SUMIF($B$6:$B$7,B6,$F$6:$F$7)>0,ROUND(F6*100,0),D6) -> 20000 | I6: =SUMIF($B$6:$B$7,B6,$H$6:$H$7) -> 25000 | J6: =IF(I6=0,0,QUOTIENT(G6*H6,I6)) -> 1200 | K6: =IF(I6=0,0,MOD(G6*H6,I6)) -> 0 | L6: =G6-SUMIF($B$6:$B$7,B6,$J$6:$J$7) -> 0 | M6: =1+SUMPRODUCT(($B$6:$B$7=B6)*($K$6:$K$7>K6))+SUMPRODUCT(($B$6:$B$7=B6)*($K$6:$K$7=K6)*($A$6:$A$7<A6)) -> 1 | N6: =IF(AND(I6>0,M6<=L6),1,0) -> 0 | O6: =(J6+N6)/100 -> 12
A7: =Inputs!A34 -> sl-002 | B7: =Inputs!B34 -> shp-001 | C7: =Inputs!C34 -> line-002 | D7: =Inputs!D34 -> 1 | E7: =INDEX(Inputs!$E$19:$E$20,MATCH(C7,Inputs!$A$19:$A$20,0)) -> 50 | F7: =D7*E7 -> 50 | G7: =ROUND(INDEX(Inputs!$D$29:$D$29,MATCH(B7,Inputs!$A$29:$A$29,0)),2)*100 -> 1500 | H7: =IF(SUMIF($B$6:$B$7,B7,$F$6:$F$7)>0,ROUND(F7*100,0),D7) -> 5000 | I7: =SUMIF($B$6:$B$7,B7,$H$6:$H$7) -> 25000 | J7: =IF(I7=0,0,QUOTIENT(G7*H7,I7)) -> 300 | K7: =IF(I7=0,0,MOD(G7*H7,I7)) -> 0 | L7: =G7-SUMIF($B$6:$B$7,B7,$J$6:$J$7) -> 0 | M7: =1+SUMPRODUCT(($B$6:$B$7=B7)*($K$6:$K$7>K7))+SUMPRODUCT(($B$6:$B$7=B7)*($K$6:$K$7=K7)*($A$6:$A$7<A7)) -> 2 | N7: =IF(AND(I7>0,M7<=L7),1,0) -> 0 | O7: =(J7+N7)/100 -> 3
A10: 2. Discounts: round(discount x shipped/ordered, 2) per order line, split by shipped quantity
A11: shipment_line_id | B11: line_id | C11: shipment_id | D11: shipped_quantity | E11: ordered_quantity | F11: line_discount | G11: total_cents | H11: weight | I11: weight_sum | J11: floor_cents | K11: remainder | L11: leftover_cents | M11: rank | N11: extra_cent | O11: allocated_amount
A12: =Inputs!A33 -> sl-001 | B12: =Inputs!C33 -> line-001 | C12: =Inputs!B33 -> shp-001 | D12: =Inputs!D33 -> 2 | E12: =INDEX(Inputs!$D$19:$D$20,MATCH(B12,Inputs!$A$19:$A$20,0)) -> 2 | F12: =SUMIF(Inputs!$B$24:$B$25,B12,Inputs!$C$24:$C$25) -> 20 | G12: =ROUND(F12*SUMIF(Inputs!$C$33:$C$34,B12,Inputs!$D$33:$D$34)/E12,2)*100 -> 2000 | H12: =D12 -> 2 | I12: =SUMIF($B$12:$B$13,B12,$H$12:$H$13) -> 2 | J12: =IF(I12=0,0,QUOTIENT(G12*H12,I12)) -> 2000 | K12: =IF(I12=0,0,MOD(G12*H12,I12)) -> 0 | L12: =G12-SUMIF($B$12:$B$13,B12,$J$12:$J$13) -> 0 | M12: =1+SUMPRODUCT(($B$12:$B$13=B12)*($K$12:$K$13>K12))+SUMPRODUCT(($B$12:$B$13=B12)*($K$12:$K$13=K12)*($A$12:$A$13<A12)) -> 1 | N12: =IF(AND(I12>0,M12<=L12),1,0) -> 0 | O12: =(J12+N12)/100 -> 20
A13: =Inputs!A34 -> sl-002 | B13: =Inputs!C34 -> line-002 | C13: =Inputs!B34 -> shp-001 | D13: =Inputs!D34 -> 1 | E13: =INDEX(Inputs!$D$19:$D$20,MATCH(B13,Inputs!$A$19:$A$20,0)) -> 1 | F13: =SUMIF(Inputs!$B$24:$B$25,B13,Inputs!$C$24:$C$25) -> 5 | G13: =ROUND(F13*SUMIF(Inputs!$C$33:$C$34,B13,Inputs!$D$33:$D$34)/E13,2)*100 -> 500 | H13: =D13 -> 1 | I13: =SUMIF($B$12:$B$13,B13,$H$12:$H$13) -> 1 | J13: =IF(I13=0,0,QUOTIENT(G13*H13,I13)) -> 500 | K13: =IF(I13=0,0,MOD(G13*H13,I13)) -> 0 | L13: =G13-SUMIF($B$12:$B$13,B13,$J$12:$J$13) -> 0 | M13: =1+SUMPRODUCT(($B$12:$B$13=B13)*($K$12:$K$13>K13))+SUMPRODUCT(($B$12:$B$13=B13)*($K$12:$K$13=K13)*($A$12:$A$13<A13)) -> 1 | N13: =IF(AND(I13>0,M13<=L13),1,0) -> 0 | O13: =(J13+N13)/100 -> 5
A16: 3. Formula self-test (author-typed illustrative inputs, NOT fixture or snapshot data): 10.00 split over three equal weights; expected 3.34 / 3.33 / 3.33 (one leftover cent to the lowest id)
A17: id | B17: group | C17: amount_to_split | D17: n/a | E17: n/a | F17: n/a | G17: total_cents | H17: weight | I17: weight_sum | J17: floor_cents | K17: remainder | L17: leftover_cents | M17: rank | N17: extra_cent | O17: allocated_amount
A18: t-1 | B18: g | C18: 10 | G18: =ROUND(C18,2)*100 -> 1000 | H18: 1 | I18: =SUMIF($B$18:$B$20,B18,$H$18:$H$20) -> 3 | J18: =IF(I18=0,0,QUOTIENT(G18*H18,I18)) -> 333 | K18: =IF(I18=0,0,MOD(G18*H18,I18)) -> 1 | L18: =G18-SUMIF($B$18:$B$20,B18,$J$18:$J$20) -> 1 | M18: =1+SUMPRODUCT(($B$18:$B$20=B18)*($K$18:$K$20>K18))+SUMPRODUCT(($B$18:$B$20=B18)*($K$18:$K$20=K18)*($A$18:$A$20<A18)) -> 1 | N18: =IF(AND(I18>0,M18<=L18),1,0) -> 1 | O18: =(J18+N18)/100 -> 3.34
A19: t-2 | B19: g | C19: 10 | G19: =ROUND(C19,2)*100 -> 1000 | H19: 1 | I19: =SUMIF($B$18:$B$20,B19,$H$18:$H$20) -> 3 | J19: =IF(I19=0,0,QUOTIENT(G19*H19,I19)) -> 333 | K19: =IF(I19=0,0,MOD(G19*H19,I19)) -> 1 | L19: =G19-SUMIF($B$18:$B$20,B19,$J$18:$J$20) -> 1 | M19: =1+SUMPRODUCT(($B$18:$B$20=B19)*($K$18:$K$20>K19))+SUMPRODUCT(($B$18:$B$20=B19)*($K$18:$K$20=K19)*($A$18:$A$20<A19)) -> 2 | N19: =IF(AND(I19>0,M19<=L19),1,0) -> 0 | O19: =(J19+N19)/100 -> 3.33
A20: t-3 | B20: g | C20: 10 | G20: =ROUND(C20,2)*100 -> 1000 | H20: 1 | I20: =SUMIF($B$18:$B$20,B20,$H$18:$H$20) -> 3 | J20: =IF(I20=0,0,QUOTIENT(G20*H20,I20)) -> 333 | K20: =IF(I20=0,0,MOD(G20*H20,I20)) -> 1 | L20: =G20-SUMIF($B$18:$B$20,B20,$J$18:$J$20) -> 1 | M20: =1+SUMPRODUCT(($B$18:$B$20=B20)*($K$18:$K$20>K20))+SUMPRODUCT(($B$18:$B$20=B20)*($K$18:$K$20=K20)*($A$18:$A$20<A20)) -> 3 | N20: =IF(AND(I20>0,M20<=L20),1,0) -> 0 | O20: =(J20+N20)/100 -> 3.33

Sheet Bridge
A1: Bridge: gross sales to contribution margin (D-05), baseline and after the return
A2: All cells are formulas over Inputs and Allocation. Blue cells are typed switches/inputs. USD only (fixture FX 1.0).
A3: Returns included (1 = yes) | B3: 0 | C3: 1
A4: Step | B4: Baseline (before return) | C4: After return | D4: Contract rule
A5: Gross sales | B5: =SUM(Allocation!$F$6:$F$7) -> 250 | C5: =SUM(Allocation!$F$6:$F$7) -> 250 | D5: sum(shipped qty x unit price)
A6: Allocated discounts | B6: =SUM(Allocation!$O$12:$O$13) -> 25 | C6: =SUM(Allocation!$O$12:$O$13) -> 25 | D6: line discount x shipped/ordered, largest remainder
A7: Merchandise credits | B7: =B$3*SUM($F$27:$F$28) -> 0 | C7: =C$3*SUM($F$27:$F$28) -> 90 | D7: posted credits, recognised on credit_date (D-01a)
A8: Net merchandise sales | B8: =B5-B6-B7 -> 225 | C8: =C5-C6-C7 -> 135 | D8: gross - discounts - credits
A9: COGS before returns | B9: =SUM($E$27:$E$28) -> 140 | C9: =SUM($E$27:$E$28) -> 140 | D9: shipped qty x unit cost of the line's cost version
A10: Recoverable return cost | B10: =B$3*SUM($H$27:$H$28) -> 0 | C10: =C$3*SUM($H$27:$H$28) -> 60 | D10: returned qty x that same unit cost
A11: COGS | B11: =B9-B10 -> 140 | C11: =C9-C10 -> 80 | D11: COGS before returns - recoverable return cost
A12: Gross profit | B12: =B8-B11 -> 85 | C12: =C8-C11 -> 55 | D12: net - COGS
A13: Shipping revenue | B13: 0 | C13: 0 | D13: none in the fixture (typed input)
A14: Shipping cost (allocated freight) | B14: =SUM(Allocation!$O$6:$O$7) -> 15 | C14: =SUM(Allocation!$O$6:$O$7) -> 15 | D14: sum of allocated freight
A15: Other variable costs | B15: 0 | C15: 0 | D15: none in the fixture (typed input)
A16: Contribution margin | B16: =B12+B13-B14-B15 -> 70 | C16: =C12+C13-C14-C15 -> 40 | D16: GP + shipping revenue - shipping cost - other
A17: Allocation residual | B17: =SUM(Inputs!$D$29:$D$29)-SUM(Allocation!$O$6:$O$7) -> 0 | C17: =SUM(Inputs!$D$29:$D$29)-SUM(Allocation!$O$6:$O$7) -> 0 | D17: shipping_cost - sum(allocated), must be 0.00
A18: Eligible net revenue | B18: =B8+B13 -> 225 | C18: =C8+C13 -> 135 | D18: net + shipping revenue
A19: Contribution margin rate | B19: =IF(B18=0,"",B16/B18) -> 0.31111111 | C19: =IF(C18=0,"",C16/C18) -> 0.2962963 | D19: contribution / eligible net revenue; blank when 0
A20: Discount rate | B20: =IF(B5=0,"",B6/B5) -> 0.1 | C20: =IF(C5=0,"",C6/C5) -> 0.1 | D20: discounts / gross sales; blank when 0
A21: Return rate | B21: =IF(SUM($D$27:$D$28)=0,"",B$3*SUM($G$27:$G$28)/SUM($D$27:$D$28)) -> 0 | C21: =IF(SUM($D$27:$D$28)=0,"",C$3*SUM($G$27:$G$28)/SUM($D$27:$D$28)) -> 0.33333333 | D21: returned units / shipped units; blank when 0
A25: Helper: cost and returns per shipment line
A26: shipment_line_id | B26: cost_version_id | C26: unit_cost | D26: shipped_quantity | E26: cogs_before_returns | F26: credit_amount | G26: returned_quantity | H26: recoverable_cost
A27: =Inputs!A33 -> sl-001 | B27: =Inputs!E33 -> cv-001 | C27: =INDEX(Inputs!$C$42:$C$43,MATCH(B27,Inputs!$A$42:$A$43,0)) -> 60 | D27: =Inputs!D33 -> 2 | E27: =C27*D27 -> 120 | F27: =SUMIF(Inputs!$B$38:$B$38,A27,Inputs!$D$38:$D$38) -> 90 | G27: =SUMIF(Inputs!$B$38:$B$38,A27,Inputs!$C$38:$C$38) -> 1 | H27: =G27*C27 -> 60
A28: =Inputs!A34 -> sl-002 | B28: =Inputs!E34 -> cv-002 | C28: =INDEX(Inputs!$C$42:$C$43,MATCH(B28,Inputs!$A$42:$A$43,0)) -> 20 | D28: =Inputs!D34 -> 1 | E28: =C28*D28 -> 20 | F28: =SUMIF(Inputs!$B$38:$B$38,A28,Inputs!$D$38:$D$38) -> 0 | G28: =SUMIF(Inputs!$B$38:$B$38,A28,Inputs!$C$38:$C$38) -> 0 | H28: =G28*C28 -> 0

Sheet Assumptions
A1: Assumptions: contract decisions D-01..D-07 (docs/contracts.md, contract v1.1)
A3: ID | B3: Decision | C3: Rule as applied in this workbook
A4: D-01 | B4: Grain, population, time basis | C4: Fact grain is the shipment line. Population: lines whose shipment shipped_at is in the half-open UTC window [from, to), order status shipped or partially_returned, not quarantined. Cancelled orders never enter. Returns are recognised on credit_date (D-01a, contract v1.1): lines by shipped_at, credits and recoverable cost by credit_date, a closed window stays closed.
A5: D-02 | B5: Money, currency, rounding | C5: Decimal money; NUMERIC(20,6) in the database. Convert with the exchange_rates row whose rate_date equals the shipment's UTC date (returns: the credit date). A missing rate quarantines the line (FX_RATE_MISSING), never 1.0 or 0. Rounding to cents only at allocation and presentation. This workbook is USD only.
A6: D-03 | B6: Historical cost | C6: cost_versions are half-open [valid_from, valid_to); the cost of a line is the single version containing shipped_at; zero or several quarantine the line (COST_VERSION_MISSING / COST_VERSION_AMBIGUOUS). A return reverses cost at the same version.
A7: D-04 | B7: Allocation of discounts and freight | C7: Discount: round(discount x shipped/ordered, 2) per order line, split by shipped quantity. Freight: shipping_cost split by gross-sales weight (quantity if gross is 0). Both use largest remainder, lowest shipment_line_id breaks ties; allocation_residual must be 0.00; keyed by shipment_line_id.
A8: D-05 | B8: Metric formulas | C8: Net = gross - discounts - credits. COGS = shipped qty x historical cost - recoverable return cost. Contribution = GP + shipping revenue - shipping cost - other variable costs. Rates are ratios of sums, null on a zero denominator; rates carried to six decimals.
A9: D-06 | B9: Workflow invariants | C9: Malformed currency rejects the order and dependents (raw rows kept); same idempotency key + different payload is 409; return quantity <= remaining and credit >= 0 (RETURN_EXCEEDS_REMAINING, CREDIT_SIGN_REVERSED); region = customers version effective at shipped_at else UNASSIGNED; quotas join at (rep, period) only.
A10: D-07 | B10: Scenario deltas | C10: Signed fractions discount_delta and shipping_delta apply to a copy: allocated_discount x (1 + discount_delta), freight x (1 + shipping_delta); credits and costs not rescaled; results are labelled estimates. Not implemented in this workbook.
A12: Workbook-specific
A13: W-1 | C13: Everything in Inputs, Allocation and Bridge is synthetic (golden fixture revenue-atlas-golden-v1); nothing here describes a real company.
A14: W-2 | C14: Zero-gross shipments allocate freight by shipped quantity (weight formula); the explicit unallocated_freight row of D-04 is not modelled.
A15: W-3 | C15: A single FX rate of 1.0 (USD to USD) applies; non-USD conversion at shipped or credit-date rates is not modelled in the formula chain.
A16: W-4 | C16: Cached values: see docs/workbook.md. Formulas are the deliverable; Excel recalculates on open (fullCalcOnLoad is set).

Sheet Snapshot summary
A1: Snapshot summary: PASTED VALUES (not formulas) from the SQL analysis
A2: Source: data/sql/analysis/run_all.py on the seeded synthetic snapshot, dataset_hash 40f541fcd8681eb0..., dataset_version ra-20261026-20261026. Re-run the query to refresh; nothing on this sheet recalculates.
A4: 01_margin_bridge_by_month.sql: Margin bridge by month (USD)
A5: period | B5: gross_sales | C5: discounts | D5: credits | E5: net_sales | F5: cogs | G5: gross_profit | H5: freight | I5: contribution | J5: cm_rate
A6: 2024-10 | B6: 261575.89 | C6: 5067.7 | D6: 2357.53 | E6: 254150.66 | F6: 148894.49 | G6: 105256.17 | H6: 1427.36 | I6: 103828.82 | J6: 0.4085
A7: 2024-11 | B7: 374858.99 | C7: 10581.16 | D7: 6096.4 | E7: 358181.43 | F7: 211585.17 | G7: 146596.26 | H7: 1827.94 | I7: 144768.32 | J7: 0.4042
A8: 2024-12 | B8: 384823.58 | C8: 9789.3 | D8: 19839.68 | E8: 355194.6 | F8: 207231.56 | G8: 147963.04 | H8: 2121.75 | I8: 145841.29 | J8: 0.4106
A9: 2025-01 | B9: 396984.2 | C9: 7677.47 | D9: 17532.58 | E9: 371774.15 | F9: 219372.09 | G9: 152402.06 | H9: 2171.32 | I9: 150230.74 | J9: 0.4041
A10: 2025-02 | B10: 389210.7 | C10: 7668.08 | D10: 8450.23 | E10: 373092.39 | F10: 218408.4 | G10: 154683.99 | H10: 2124.24 | I10: 152559.75 | J10: 0.4089
A11: 2025-03 | B11: 300740.38 | C11: 6688.56 | D11: 29852.07 | E11: 264199.75 | F11: 156247.93 | G11: 107951.82 | H11: 1858.88 | I11: 106092.94 | J11: 0.4016
A12: 2025-04 | B12: 282971.47 | C12: 6530.65 | D12: 2931.66 | E12: 273509.16 | F12: 165882.39 | G12: 107626.77 | H12: 1623.55 | I12: 106003.23 | J12: 0.3876
A13: 2025-05 | B13: 333697.12 | C13: 7226.17 | D13: 10452.4 | E13: 316018.55 | F13: 188269.22 | G13: 127749.33 | H13: 1800.37 | I13: 125948.96 | J13: 0.3985
A14: 2025-06 | B14: 393338.19 | C14: 10178.44 | D14: 19882.59 | E14: 363277.15 | F14: 221056.57 | G14: 142220.58 | H14: 2142.34 | I14: 140078.24 | J14: 0.3856
A15: 2025-07 | B15: 374168.86 | C15: 9957.94 | D15: 4511.86 | E15: 359699.05 | F15: 216820.02 | G15: 142879.03 | H15: 1770.39 | I15: 141108.64 | J15: 0.3923
A16: 2025-08 | B16: 391070.6 | C16: 11675.87 | D16: 11265.66 | E16: 368129.07 | F16: 224610.17 | G16: 143518.9 | H16: 2120.16 | I16: 141398.74 | J16: 0.3841
A17: 2025-09 | B17: 453982.64 | C17: 10901.4 | D17: 5922.1 | E17: 437159.14 | F17: 263721.83 | G17: 173437.31 | H17: 2355.34 | I17: 171081.97 | J17: 0.3913
... A32: SUBTOTAL 2026-01..2026-09 | B32: 3935867.8 | C32: 108422.3 | D32: 165664.08 | E32: 3661781.4 | F32: 2445495.4 | G32: 1216286 | H32: 19979.42 | I32: 1196306.6 | J32: 0.3267
A34: 02_contribution_by_region.sql: Contribution by region, UNASSIGNED shown
A35: region_id | B35: shipment_lines | C35: gross_sales | D35: net_sales | E35: contribution | F35: cm_rate
A36: UNASSIGNED | B36: 8 | C36: 2503.37 | D36: 2411.97 | E36: 961.43 | F36: 0.3986
A37: reg-east | B37: 1192 | C37: 1232751.9 | D37: 1159426.9 | E37: 423813.87 | F37: 0.3655
A38: reg-north | B38: 2287 | C38: 4415286.6 | D38: 4112856.7 | E38: 1496108.2 | F38: 0.3638
A39: reg-south | B39: 2014 | C39: 3259116.5 | D39: 3079326.9 | E39: 1141427.2 | F39: 0.3707
A40: reg-west | B40: 1087 | C40: 741548.51 | D40: 686997.89 | E40: 247515.56 | F40: 0.3603
A41: TOTAL | B41: 6588 | C41: 9651206.9 | D41: 9041020.4 | E41: 3309826.2 | F41: 0.3661
A43: 03_discount_rate_by_region_before_after_2026_03.sql: Discount rate by region, before / after 2026-03
A44: region | B44: rate_before | C44: rate_after | D44: delta_pp | E44: gross_before | F44: gross_after | G44: extra_discount_usd
A45: UNASSIGNED | B45: 0.0092 | E45: 2503.37
A46: reg-east | B46: 0.0263 | C46: 0.0251 | D46: -0.11 | E46: 862711.54 | F46: 370040.4 | G46: -416.37
A47: reg-north | B47: 0.0252 | C47: 0.026 | D47: 0.08 | E47: 2860569 | F47: 1554717.6 | G47: 1288.97
A48: reg-south | B48: 0.0242 | C48: 0.0238 | D48: -0.04 | E48: 2335322.9 | F48: 923793.56 | G48: -383.5
A49: reg-west | B49: 0.0263 | C49: 0.0574 | D49: 3.11 | E49: 529620.56 | F49: 211927.95 | G49: 6592.14
A50: ALL REGIONS | B50: 0.025 | C50: 0.0274 | D50: 0.23 | E50: 6590727.4 | F50: 3060479.5 | G50: 7181.47
A52: 04_fixtures_cost_vs_price_by_month.sql: cat-fixtures unit cost vs price by month
A53: month | B53: fixtures_units | C53: fixtures_unit_price | D53: fixtures_unit_cost | E53: cost_to_price | F53: other_cost_to_price | G53: extra_cost_usd
A54: 2024-10 | B54: 712 | C54: 127.69 | D54: 74.22 | E54: 0.5813 | F54: 0.5711
A55: 2024-11 | B55: 728 | C55: 143.18 | D55: 82.33 | E55: 0.575 | F55: 0.5742
A56: 2024-12 | B56: 624 | C56: 189.94 | D56: 107.55 | E56: 0.5662 | F56: 0.5704
A57: 2025-01 | B57: 830 | C57: 157.64 | D57: 92.27 | E57: 0.5853 | F57: 0.5741
A58: 2025-02 | B58: 833 | C58: 142.66 | D58: 83.74 | E58: 0.587 | F58: 0.5679
A59: 2025-03 | B59: 696 | C59: 128.94 | D59: 75.9 | E59: 0.5886 | F59: 0.5727
A60: 2025-04 | B60: 542 | C60: 115.42 | D60: 69.17 | E60: 0.5993 | F60: 0.5906
A61: 2025-05 | B61: 595 | C61: 144.19 | D61: 86.6 | E61: 0.6006 | F61: 0.5767
A62: 2025-06 | B62: 1118 | C62: 126.51 | D62: 75.43 | E62: 0.5963 | F62: 0.5877
A63: 2025-07 | B63: 742 | C63: 143.15 | D63: 84.56 | E63: 0.5908 | F63: 0.5857
A64: 2025-08 | B64: 1101 | C64: 136.98 | D64: 82.6 | E64: 0.603 | F64: 0.5834
A65: 2025-09 | B65: 866 | C65: 135.67 | D65: 81.27 | E65: 0.599 | F65: 0.5852
... A68: 2025-12 | B68: 1208 | C68: 162.1 | D68: 98.41 | E68: 0.6071 | F68: 0.5906
A69: 2026-01 | B69: 935 | C69: 152.05 | D69: 109.65 | E69: 0.7212 | F69: 0.5991 | G69: 18033.81
A70: 2026-02 | B70: 981 | C70: 161.73 | D70: 116.01 | E70: 0.7173 | F70: 0.598 | G70: 19517.57
A71: 2026-03 | B71: 1026 | C71: 153.18 | D71: 108.45 | E71: 0.708 | F71: 0.5862 | G71: 17864.73
A72: 2026-04 | B72: 586 | C72: 169.67 | D72: 124.62 | E72: 0.7345 | F72: 0.6156 | G72: 13940.1
A73: 2026-05 | B73: 1349 | C73: 147.1 | D73: 108.89 | E73: 0.7403 | F73: 0.6066 | G73: 28966.97
A74: 2026-06 | B74: 989 | C74: 161.98 | D74: 118.75 | E74: 0.7331 | F74: 0.6126 | G74: 22239.93
A75: 2026-07 | B75: 1116 | C75: 141.45 | D75: 104.54 | E75: 0.7391 | F75: 0.6176 | G75: 22853.05
A76: 2026-08 | B76: 1093 | C76: 146.72 | D76: 107.85 | E76: 0.7351 | F76: 0.6051 | G76: 22573.03
A77: 2026-09 | B77: 1182 | C77: 138.46 | D77: 100.42 | E77: 0.7252 | F77: 0.6065 | G77: 21427.21
A78: SUM 2026-01..2026-09 | B78: 9257 | E78: 0.7284 | F78: 0.6048 | G78: 187416.4
A79: SUM 2024-10..2025-12 | B79: 12976 | E79: 0.5943 | F79: 0.5826
A81: 05_return_rate_by_segment_category.sql: Return rate by segment x category (top 12 by mature_rate)
A82: segment | B82: category_id | C82: shipped_units | D82: returned_units | E82: return_rate | F82: mature_units | G82: mature_rate
A83: enterprise | B83: cat-apparel | C83: 13904 | D83: 1197 | E83: 0.0861 | F83: 12449 | G83: 0.0866
A84: smb | B84: cat-office | C84: 1256 | D84: 90 | E84: 0.0717 | F84: 1173 | G84: 0.0665
A85: smb | B85: cat-safety | C85: 1219 | D85: 76 | E85: 0.0623 | F85: 1121 | G85: 0.0633
A86: mid_market | B86: cat-safety | C86: 3673 | D86: 181 | E86: 0.0493 | F86: 3355 | G86: 0.0539
A87: enterprise | B87: cat-office | C87: 15810 | D87: 825 | E87: 0.0522 | F87: 14539 | G87: 0.0508
A88: mid_market | B88: cat-fixtures | C88: 4528 | D88: 193 | E88: 0.0426 | F88: 4158 | G88: 0.0464
A89: smb | B89: cat-packaging | C89: 4669 | D89: 204 | E89: 0.0437 | F89: 4338 | G89: 0.0415
A90: mid_market | B90: cat-packaging | C90: 16004 | D90: 614 | E90: 0.0384 | F90: 14825 | G90: 0.0414
A91: enterprise | B91: cat-packaging | C91: 54467 | D91: 1897 | E91: 0.0348 | F91: 51010 | G91: 0.0372
A92: mid_market | B92: cat-apparel | C92: 3725 | D92: 126 | E92: 0.0338 | F92: 3419 | G92: 0.0369
A93: enterprise | B93: cat-tools | C93: 13448 | D93: 488 | E93: 0.0363 | F93: 12680 | G93: 0.0356
A94: smb | B94: cat-fixtures | C94: 1320 | D94: 45 | E94: 0.0341 | F94: 1242 | G94: 0.0354
... A96: ALL | B96: all cells | C96: 172801 | D96: 6888 | E96: 0.0399 | F96: 160009 | G96: 0.0407
A98: 06_top10_customers_contribution_decline.sql: Top 10 customers by contribution decline, A=2025-10..2026-03 vs B=2026-04..2026-09
A99: rank | B99: customer_id | C99: customer_name | D99: latest_region | E99: contribution_a | F99: contribution_b | G99: decline | H99: pct_of_total_decline | I99: all_customers_a | J99: all_customers_b
A100: 1 | B100: cust-0017 | C100: Umberfield Foundry Trading Company | D100: reg-south | E100: 105429.6 | F100: 62073.12 | G100: 43356.48 | H100: 33.3 | I100: 905548.02 | J100: 775336.56
A101: 2 | B101: cust-0009 | C101: Fenwick Meadow Fabrication Ltd | D101: reg-south | E101: 85987.98 | F101: 48497.24 | G101: 37490.74 | H101: 28.8 | I101: 905548.02 | J101: 775336.56
A102: 3 | B102: cust-0007 | C102: Northern Territories Mining, Forestry and Heavy Equipment Contractors Purchasing Consortium Limited | D102: reg-north | E102: 92749.95 | F102: 63191.3 | G102: 29558.65 | H102: 22.7 | I102: 905548.02 | J102: 775336.56
A103: 4 | B103: cust-0032 | C103: International Association of Municipal Facilities Maintenance and Public Works Procurement Cooperatives | D103: reg-south | E103: 20779.38 | F103: 10012.57 | G103: 10766.8 | H103: 8.3 | I103: 905548.02 | J103: 775336.56
A104: 5 | B104: cust-0039 | C104: Moorfield Lakeside Works Partners | D104: reg-north | E104: 24448.14 | F104: 15388.62 | G104: 9059.52 | H104: 7 | I104: 905548.02 | J104: 775336.56
A105: 6 | B105: cust-0048 | C105: Fenwick Lakeside Fabrication Ltd | D105: reg-south | E105: 22939.22 | F105: 15619.74 | G105: 7319.48 | H105: 5.6 | I105: 905548.02 | J105: 775336.56
A106: 7 | B106: cust-0024 | C106: Consolidated Regional Wholesale Distribution and Industrial Supply Partnership of the Great Lakes | D106: reg-west | E106: 12190.51 | F106: 5448.58 | G106: 6741.93 | H106: 5.2 | I106: 905548.02 | J106: 775336.56
A107: 8 | B107: cust-0036 | C107: Thornley Foundry Trading Company | D107: reg-east | E107: 76856.45 | F107: 70325 | G107: 6531.45 | H107: 5 | I107: 905548.02 | J107: 775336.56
A108: 9 | B108: cust-0005 | C108: Valewood Harbor Works Partners | D108: reg-west | E108: 5551.27 | F108: 443.61 | G108: 5107.66 | H108: 3.9 | I108: 905548.02 | J108: 775336.56
A109: 10 | B109: cust-0040 | C109: Umberfield Foundry Logistics Corp | D109: reg-east | E109: 3913.92 | F109: -88.11 | G109: 4002.03 | H109: 3.1 | I109: 905548.02 | J109: 775336.56
A111: 07_quarantine_reasons.sql: Quarantine and rejection reasons
A112: kind | B112: entity | C112: reason_code | D112: records | E112: shipments | F112: gross_usd_at_stake
A113: rejected | B113: order_lines | C113: CURRENCY_NOT_ISO4217 | D113: 5
A114: rejected | B114: orders | C114: CURRENCY_NOT_ISO4217 | D114: 3
A115: rejected | B115: returns | C115: CURRENCY_NOT_ISO4217 | D115: 1
A116: rejected | B116: shipment_lines | C116: CURRENCY_NOT_ISO4217 | D116: 5
A117: rejected | B117: shipments | C117: CURRENCY_NOT_ISO4217 | D117: 3
A118: quarantined | B118: shipment_lines | C118: COST_VERSION_AMBIGUOUS | D118: 31 | E118: 30 | F118: 42742.55
A119: quarantined | B119: shipment_lines | C119: COST_VERSION_MISSING | D119: 15 | E119: 15 | F119: 5205.01
A120: quarantined | B120: shipment_lines | C120: FX_RATE_MISSING | D120: 10 | E120: 5
A122: 08_allocation_residual_check.sql: Allocation residual check
A123: shipments_checked | B123: shipments_nonzero_residual | C123: freight_abs_residual | D123: shipments_without_allocation | E123: order_lines_checked | F123: order_lines_nonzero_residual | G123: discount_abs_residual | H123: failures
A124: 2724 | B124: 0 | C124: 0 | D124: 0 | E124: 6152 | F124: 0 | G124: 0 | H124: 0
A126: 09_stored_vs_contract_freight.sql: Stored C04 freight vs contract freight (diagnostic)
...

Sheet Checks
A1: Checks: workbook results against tests/fixtures/golden/expected.json
A2: Expected values are typed from expected.json (blue); results are live formulas from Bridge. Rates compared at 6 dp, money at 2 dp.
A4: state | B4: metric | C4: expected (expected.json) | D4: workbook | E4: match
A5: baseline | B5: gross_sales | C5: 250 | D5: =Bridge!B5 -> 250 | E5: =ROUND(D5,2)=ROUND(C5,2) -> TRUE
A6: baseline | B6: allocated_discounts | C6: 25 | D6: =Bridge!B6 -> 25 | E6: =ROUND(D6,2)=ROUND(C6,2) -> TRUE
A7: baseline | B7: merchandise_credits | C7: 0 | D7: =Bridge!B7 -> 0 | E7: =ROUND(D7,2)=ROUND(C7,2) -> TRUE
A8: baseline | B8: net_merchandise_sales | C8: 225 | D8: =Bridge!B8 -> 225 | E8: =ROUND(D8,2)=ROUND(C8,2) -> TRUE
A9: baseline | B9: cogs | C9: 140 | D9: =Bridge!B11 -> 140 | E9: =ROUND(D9,2)=ROUND(C9,2) -> TRUE
A10: baseline | B10: gross_profit | C10: 85 | D10: =Bridge!B12 -> 85 | E10: =ROUND(D10,2)=ROUND(C10,2) -> TRUE
A11: baseline | B11: shipping_cost | C11: 15 | D11: =Bridge!B14 -> 15 | E11: =ROUND(D11,2)=ROUND(C11,2) -> TRUE
A12: baseline | B12: contribution_margin | C12: 70 | D12: =Bridge!B16 -> 70 | E12: =ROUND(D12,2)=ROUND(C12,2) -> TRUE
A13: baseline | B13: allocation_residual | C13: 0 | D13: =Bridge!B17 -> 0 | E13: =ROUND(D13,2)=ROUND(C13,2) -> TRUE
A14: baseline | B14: contribution_margin_rate | C14: 0.311111 | D14: =Bridge!B19 -> 0.31111111 | E14: =ROUND(D14,6)=ROUND(C14,6) -> TRUE
A15: baseline | B15: discount_rate | C15: 0.1 | D15: =Bridge!B20 -> 0.1 | E15: =ROUND(D15,6)=ROUND(C15,6) -> TRUE
A16: baseline | B16: return_rate | C16: 0 | D16: =Bridge!B21 -> 0 | E16: =ROUND(D16,6)=ROUND(C16,6) -> TRUE
A17: after_return | B17: gross_sales | C17: 250 | D17: =Bridge!C5 -> 250 | E17: =ROUND(D17,2)=ROUND(C17,2) -> TRUE
A18: after_return | B18: allocated_discounts | C18: 25 | D18: =Bridge!C6 -> 25 | E18: =ROUND(D18,2)=ROUND(C18,2) -> TRUE
A19: after_return | B19: merchandise_credits | C19: 90 | D19: =Bridge!C7 -> 90 | E19: =ROUND(D19,2)=ROUND(C19,2) -> TRUE
A20: after_return | B20: net_merchandise_sales | C20: 135 | D20: =Bridge!C8 -> 135 | E20: =ROUND(D20,2)=ROUND(C20,2) -> TRUE
A21: after_return | B21: cogs | C21: 80 | D21: =Bridge!C11 -> 80 | E21: =ROUND(D21,2)=ROUND(C21,2) -> TRUE
A22: after_return | B22: gross_profit | C22: 55 | D22: =Bridge!C12 -> 55 | E22: =ROUND(D22,2)=ROUND(C22,2) -> TRUE
A23: after_return | B23: shipping_cost | C23: 15 | D23: =Bridge!C14 -> 15 | E23: =ROUND(D23,2)=ROUND(C23,2) -> TRUE
A24: after_return | B24: contribution_margin | C24: 40 | D24: =Bridge!C16 -> 40 | E24: =ROUND(D24,2)=ROUND(C24,2) -> TRUE
A25: after_return | B25: allocation_residual | C25: 0 | D25: =Bridge!C17 -> 0 | E25: =ROUND(D25,2)=ROUND(C25,2) -> TRUE
A26: after_return | B26: contribution_margin_rate | C26: 0.296296 | D26: =Bridge!C19 -> 0.2962963 | E26: =ROUND(D26,6)=ROUND(C26,6) -> TRUE
A27: after_return | B27: discount_rate | C27: 0.1 | D27: =Bridge!C20 -> 0.1 | E27: =ROUND(D27,6)=ROUND(C27,6) -> TRUE
A28: after_return | B28: return_rate | C28: 0.333333 | D28: =Bridge!C21 -> 0.33333333 | E28: =ROUND(D28,6)=ROUND(C28,6) -> TRUE
A30: all checks | E30: =AND(E5:E28) -> TRUE
A32: Allocation self-test (block 3): 3.34 / 3.33 / 3.33, sum 10.00 | E32: =AND(ROUND(Allocation!O18,2)=3.34,ROUND(Allocation!O19,2)=3.33,ROUND(Allocation!O20,2)=3.33,ROUND(SUM(Allocation!O18:O20),2)=10) -> TRUE
