Workbook

Sheet Read me
A1: ChangeWorks analyst workbook (P09-ART-05)
A3: What it is | B3: A formula-driven recomputation of the ChangeWorks scenario model over the published synthetic snapshot cw-20261026-20261026 (dataset hash 6bf7ebaad6bf75084c82c41de1031d6d585af730c8a22979ed7c77df2a38e3a9, code revision 29948f9, as-of 2026-10-05T00:00:00Z): 24 initiatives, 30 scenarios, 900 cost rows, 700 benefit rows, 36 monthly periods from 2026-01.
A4: The decision | B4: Which transformation initiative should be funded and how will success be established? The workbook shows each initiative's dated cash flow, NPV and both paybacks in the selected scenario, the four benefit classes kept apart and the attributable portfolio NPV beside the plain sum. Nothing here funds anything: a selected scenario is a proposal.
A5: Synthetic data | B5: Everything is synthetic (a seeded generator). Observed = what this one draw shows; constructed = what the generator built in on purpose (its designed relationships DR-01..DR-07 and injected defects INJ-01..INJ-12); every NPV is a plan estimate; no benefit to a real organisation is claimed.
A6: How to use it | B6: Open the .xlsx in any spreadsheet application; nothing needs installing to read the cached values. Controls!B3 switches the scenario; Controls!B4 overrides the period rate; Checks!B2 is TRUE when every figure agrees with the Python domain, the SQL ledger and the golden hand answer.
A7: Recalculation status | B7: openpyxl wrote formulas only; LibreOffice (headless) recalculated the delivered file. Microsoft Excel was NOT run: nothing here was opened or recalculated by Excel (docs/workbook.md).
A8: Sheets | B8: Controls, Checks, Portfolio, Initiatives, Cash flow, Golden case, Assumptions (read-this-first limits), data sheets (Benefits, Costs, Scenario inputs, Scenarios, Periods), Domain reference (pasted values), SQL results (pasted).
A9: Colour | B9: Blue = typed input or pasted value; black = formula.

Sheet Controls
A1: Controls
A2: Change B3 to any stored scenario: every sheet follows it. B4 overrides the period rate (blank = the scenario's own rate; the checks against the domain stand down while it is set). Blue cells are inputs.
A3: Scenario (switch) | B3: scn-025
A4: Period-rate override (blank = the scenario's rate)
A5: Period basis of the dataset | B5: monthly
A6: As-of (UTC) | B6: 46300
A7: First period starts | B7: 46023
A9: Selected scenario's declared rate and basis | B9: =INDEX(Scenarios!$D$4:$D$33,MATCH($B$3,Scenarios!$A$4:$A$33,0))&" "&INDEX(Scenarios!$C$4:$C$33,MATCH($B$3,Scenarios!$A$4:$A$33,0)) -> 0.08 annual
A10: Rate source | B10: =INDEX(Scenarios!$J$4:$J$33,MATCH($B$3,Scenarios!$A$4:$A$33,0)) -> conversion
A11: Effective period rate used | B11: =IF(LEN(B4)>0,B4,INDEX(Scenarios!$I$4:$I$33,MATCH($B$3,Scenarios!$A$4:$A$33,0))) -> 0.006434
A12: Horizon (periods) | B12: =INDEX(Scenarios!$F$4:$F$33,MATCH($B$3,Scenarios!$A$4:$A$33,0)) -> 36
A13: Matured periods at the as-of | B13: =SUM(Periods!D4:D39) -> 9
A15: All checks pass (Checks!B2) | B15: =Checks!B2 -> TRUE
A16: Attributable NPV of the selected scenario (Portfolio!B19) | B16: =Portfolio!B19 -> 1243149.1

Sheet Checks
A1: Checks: TRUE when every comparison with the Python domain, the SQL ledger and the golden hand answer holds
A2: All checks pass | B2: =AND(Portfolio!E4:E19,Initiatives!U4:U27,'Golden case'!E8,'Golden case'!E9,'Golden case'!E10,'Golden case'!E11,'Golden case'!E12,'Golden case'!E13,'Golden case'!E15,'Golden case'!E16,'Golden case'!E17,'Golden case'!E18,'Golden case'!E19,'Golden case'!E20,B5,B6,B7) -> TRUE
A4: check | B4: result
A5: Every benefit row has a class when its initiative is in the scenario and the row is inside the horizon, and none otherwise | B5: =SUMPRODUCT((Benefits!N4:N703=TRUE())*(Benefits!R4:R703=""))+SUMPRODUCT((Benefits!N4:N703=FALSE())*(Benefits!R4:R703<>""))=0 -> TRUE
A6: Every recurring cost row expands to end - start periods and every one-time row to exactly one (Costs!L) | B6: =SUMPRODUCT((Costs!C4:C903="one_time")*(Costs!L4:L903<>1))=0 -> TRUE
A7: The scenario switch names a stored scenario | B7: =COUNTIF(Scenarios!A4:A33,Controls!B3)=1 -> TRUE

Sheet Portfolio
A1: The portfolio ledger of the selected scenario: four benefit classes apart, the attributable totals beside the plain sums, checked against the domain and the SQL ledger
A2: Column B is a formula over the data sheets; C is the reference (pasted, `Domain reference`); D is the tolerance; E is TRUE when they agree (or when the rate override is in use: see Controls!B4).
A3: measure (USD unless hours) | B3: workbook (formula) | C3: reference (pasted) | D3: tolerance | E3: check
A4: initiatives in the scenario | B4: =SUM(Initiatives!B4:B27) -> 24 | C4: =INDEX(Scenarios!$H$4:$H$33,MATCH(Controls!$B$3,Scenarios!$A$4:$A$33,0)) -> 24 | D4: 0 | E4: =IF(LEN(Controls!$B$4)>0,TRUE(),ABS(B4-C4)<=D4) -> TRUE
A5: planned costs (inside the horizon, recurring rows expanded) | B5: =SUM('Cash flow'!E4:E867) -> 25914200 | C5: =INDEX('Domain reference'!$I$4:$I$33,MATCH(Controls!$B$3,'Domain reference'!$A$4:$A$33,0)) -> 25914200 | D5: 0.005 | E5: =IF(LEN(Controls!$B$4)>0,TRUE(),ABS(B5-C5)<=D5) -> TRUE
A6: cash benefits (enter the flow) | B6: =SUM('Cash flow'!F4:F867) -> 15288067 | C6: =INDEX('Domain reference'!$J$4:$J$33,MATCH(Controls!$B$3,'Domain reference'!$A$4:$A$33,0)) -> 15288067 | D6: 0.005 | E6: =IF(LEN(Controls!$B$4)>0,TRUE(),ABS(B6-C6)<=D6) -> TRUE
A7: revenue (enters the flow) | B7: =SUM('Cash flow'!G4:G867) -> 6074000.1 | C7: =INDEX('Domain reference'!$K$4:$K$33,MATCH(Controls!$B$3,'Domain reference'!$A$4:$A$33,0)) -> 6074000.1 | D7: 0.005 | E7: =IF(LEN(Controls!$B$4)>0,TRUE(),ABS(B7-C7)<=D7) -> TRUE
A8: avoided cost realised (cash_realisation and evidence) | B8: =SUM('Cash flow'!H4:H867) -> 5516433.3 | C8: =INDEX('Domain reference'!$L$4:$L$33,MATCH(Controls!$B$3,'Domain reference'!$A$4:$A$33,0)) -> 5516433.3 | D8: 0.005 | E8: =IF(LEN(Controls!$B$4)>0,TRUE(),ABS(B8-C8)<=D8) -> TRUE
A9: capacity converted to money (a conversion rate with staffing evidence) | B9: =SUM('Cash flow'!I4:I867) -> 1774010.6 | C9: =INDEX('Domain reference'!$M$4:$M$33,MATCH(Controls!$B$3,'Domain reference'!$A$4:$A$33,0)) -> 1774010.6 | D9: 0.005 | E9: =IF(LEN(Controls!$B$4)>0,TRUE(),ABS(B9-C9)<=D9) -> TRUE
A10: avoided cost beside the cash flow (never in it) | B10: =SUMIFS(Benefits!S4:S703,Benefits!R4:R703,"avoided_cost_beside") -> 4025383.5 | C10: =INDEX('Domain reference'!$N$4:$N$33,MATCH(Controls!$B$3,'Domain reference'!$A$4:$A$33,0)) -> 4025383.5 | D10: 0.005 | E10: =IF(LEN(Controls!$B$4)>0,TRUE(),ABS(B10-C10)<=D10) -> TRUE
A11: capacity hours not converted (hours, never added to dollars) | B11: =SUMIFS(Benefits!P4:P703,Benefits!R4:R703,"capacity_hours") -> 145045.62 | C11: =INDEX('Domain reference'!$O$4:$O$33,MATCH(Controls!$B$3,'Domain reference'!$A$4:$A$33,0)) -> 145045.62 | D11: 0.005 | E11: =IF(LEN(Controls!$B$4)>0,TRUE(),ABS(B11-C11)<=D11) -> TRUE
A12: planned benefits: the plain sum of the money claims | B12: =SUM(B6:B9)+B10 -> 32677895 | C12: =INDEX('Domain reference'!$E$4:$E$33,MATCH(Controls!$B$3,'Domain reference'!$A$4:$A$33,0)) -> 32677895 | D12: 0.005 | E12: =IF(LEN(Controls!$B$4)>0,TRUE(),ABS(B12-C12)<=D12) -> TRUE
A13: double-counted amount (the residual): claims beyond the largest of a shared key | B13: =SUM(Benefits!X4:X703) -> 207146.32 | C13: =INDEX('Domain reference'!$F$4:$F$33,MATCH(Controls!$B$3,'Domain reference'!$A$4:$A$33,0)) -> 207146.32 | D13: 0.005 | E13: =IF(LEN(Controls!$B$4)>0,TRUE(),ABS(B13-C13)<=D13) -> TRUE
A14: attributable benefits | B14: =B12-B13 -> 32470748 | C14: =INDEX('Domain reference'!$P$4:$P$33,MATCH(Controls!$B$3,'Domain reference'!$A$4:$A$33,0)) -> 32470748 | D14: 0.005 | E14: =IF(LEN(Controls!$B$4)>0,TRUE(),ABS(B14-C14)<=D14) -> TRUE
A15: capacity hours planned (every capacity row, converted or not) | B15: =SUMIFS(Benefits!P4:P703,Benefits!E4:E703,"capacity",Benefits!N4:N703,TRUE()) -> 194875.92 | C15: =INDEX('Domain reference'!$G$4:$G$33,MATCH(Controls!$B$3,'Domain reference'!$A$4:$A$33,0)) -> 194875.92 | D15: 0.005 | E15: =IF(LEN(Controls!$B$4)>0,TRUE(),ABS(B15-C15)<=D15) -> TRUE
A16: hours residual (shared capacity counted twice) | B16: =SUM(Benefits!AC4:AC703) -> 5974.8 | C16: =INDEX('Domain reference'!$H$4:$H$33,MATCH(Controls!$B$3,'Domain reference'!$A$4:$A$33,0)) -> 5974.8 | D16: 0.005 | E16: =IF(LEN(Controls!$B$4)>0,TRUE(),ABS(B16-C16)<=D16) -> TRUE
A17: NPV, plain sum of the initiative NPVs | B17: =SUM(Initiatives!G4:G27) -> 1438382.3 | C17: =INDEX('Domain reference'!$B$4:$B$33,MATCH(Controls!$B$3,'Domain reference'!$A$4:$A$33,0)) -> 1438382.2 | D17: 0.005 | E17: =IF(LEN(Controls!$B$4)>0,TRUE(),ABS(B17-C17)<=D17) -> TRUE
A18: present value of the claims counted twice (double_counted_pv) | B18: =SUM(Benefits!Y4:Y703) -> 195233.2 | C18: =INDEX('Domain reference'!$C$4:$C$33,MATCH(Controls!$B$3,'Domain reference'!$A$4:$A$33,0)) -> 195233.2 | D18: 0.005 | E18: =IF(LEN(Controls!$B$4)>0,TRUE(),ABS(B18-C18)<=D18) -> TRUE
A19: NPV, attributable (the headline) | B19: =B17-B18 -> 1243149.1 | C19: =INDEX('Domain reference'!$D$4:$D$33,MATCH(Controls!$B$3,'Domain reference'!$A$4:$A$33,0)) -> 1243149.1 | D19: 0.005 | E19: =IF(LEN(Controls!$B$4)>0,TRUE(),ABS(B19-C19)<=D19) -> TRUE
A20: initiatives that never pay back (simple) | B20: =SUMPRODUCT((Initiatives!B4:B27=1)*(Initiatives!K4:K27<>"")) -> 6

Sheet Initiatives
A1: Each initiative in the selected scenario: costs, benefits entering, NPV, both paybacks by the last crossing, checked against the domain
A2: A payback is the first period after the last negative cumulative; never negative = NO_INVESTMENT; ending negative = NOT_RECOVERED; no rows at all = NO_FLOWS (R9-12). Checks compare with `Domain reference` for the same scenario.
A3: initiative_id | B3: member | C3: has_flows | D3: planned_costs | E3: benefits_entering | F3: net_total | G3: npv | H3: negatives | I3: last_negative_plus_1 | J3: simple_payback | K3: simple_reason | L3: simple_interpolated | M3: negatives_discounted | N3: last_negative_discounted_plus_1 | O3: discounted_payback | P3: discounted_reason | Q3: discounted_interpolated | R3: domain npv | S3: domain simple | T3: domain discounted | U3: check
A4: init-001 | B4: =IF(COUNTIF('Scenario inputs'!$A$4:$A$213,Controls!$B$3&"|"&A4)>0,1,0) -> 1 | C4: =IF(B4=1,OR(SUMPRODUCT((Costs!$B$4:$B$903=A4)*(Costs!$D$4:$D$903="planned")*(Costs!$J$4:$J$903<Controls!$B$12)*(Costs!$K$4:$K$903>Costs!$J$4:$J$903))>0,SUMPRODUCT((Benefits!$B$4:$B$703=A4)*(Benefits!$T$4:$T$703=1))>0),FALSE()) -> TRUE | D4: =SUMIFS('Cash flow'!$E$4:$E$867,'Cash flow'!$A$4:$A$867,A4) -> 1163100 | E4: =SUMIFS('Cash flow'!$J$4:$J$867,'Cash flow'!$A$4:$A$867,A4) -> 1830605.5 | F4: =SUMIFS('Cash flow'!$K$4:$K$867,'Cash flow'!$A$4:$A$867,A4) -> 667505.47 | G4: =IF(C4,SUMIFS('Cash flow'!$N$4:$N$867,'Cash flow'!$A$4:$A$867,A4),"") -> 578533.26 | H4: =COUNTIFS('Cash flow'!$A$4:$A$867,A4,'Cash flow'!$P$4:$P$867,1) -> 10 | I4: =SUMPRODUCT(MAX(('Cash flow'!$A$4:$A$867=A4)*('Cash flow'!$P$4:$P$867=1)*('Cash flow'!$B$4:$B$867+1))) -> 10 | J4: =IF(OR(NOT(C4),H4=0,I4=Controls!$B$12),"",I4) -> 10 | K4: =IF(NOT(C4),"NO_FLOWS",IF(H4=0,"NO_INVESTMENT",IF(I4=Controls!$B$12,"NOT_RECOVERED",""))) | L4: =IF(J4="","",(J4-1)+(-SUMIFS('Cash flow'!$L$4:$L$867,'Cash flow'!$A$4:$A$867,A4,'Cash flow'!$B$4:$B$867,J4-1))/(SUMIFS('Cash flow'!$L$4:$L$867,'Cash flow'!$A$4:$A$867,A4,'Cash flow'!$B$4:$B$867,J4)-SUMIFS('Cash flow'!$L$4:$L$867,'Cash flow'!$A$4:$A$867,A4,'Cash flow'!$B$4:$B$867,J4-1))) -> 9.2751283 | M4: =COUNTIFS('Cash flow'!$A$4:$A$867,A4,'Cash flow'!$Q$4:$Q$867,1) -> 10 | N4: =SUMPRODUCT(MAX(('Cash flow'!$A$4:$A$867=A4)*('Cash flow'!$Q$4:$Q$867=1)*('Cash flow'!$B$4:$B$867+1))) -> 10 | O4: =IF(OR(NOT(C4),M4=0,N4=Controls!$B$12),"",N4) -> 10 | P4: =IF(NOT(C4),"NO_FLOWS",IF(M4=0,"NO_INVESTMENT",IF(N4=Controls!$B$12,"NOT_RECOVERED",""))) | Q4: =IF(O4="","",(O4-1)+(-SUMIFS('Cash flow'!$O$4:$O$867,'Cash flow'!$A$4:$A$867,A4,'Cash flow'!$B$4:$B$867,O4-1))/(SUMIFS('Cash flow'!$O$4:$O$867,'Cash flow'!$A$4:$A$867,A4,'Cash flow'!$B$4:$B$867,O4)-SUMIFS('Cash flow'!$O$4:$O$867,'Cash flow'!$A$4:$A$867,A4,'Cash flow'!$B$4:$B$867,O4-1))) -> 9.4880978 | R4: =IFERROR(INDEX('Domain reference'!$C$40:$C$249,MATCH(Controls!$B$3&"|"&A4,'Domain reference'!$A$40:$A$249,0)),"") -> 578533.26 | S4: =IFERROR(INDEX('Domain reference'!$D$40:$D$249,MATCH(Controls!$B$3&"|"&A4,'Domain reference'!$A$40:$A$249,0)),"") -> 10 | T4: =IFERROR(INDEX('Domain reference'!$E$40:$E$249,MATCH(Controls!$B$3&"|"&A4,'Domain reference'!$A$40:$A$249,0)),"") -> 10 | U4: =IF(LEN(Controls!$B$4)>0,TRUE(),IF(B4=0,AND(R4="",E4=0),AND(ABS(N(G4)-N(R4))<0.005,ISNUMBER(G4)=ISNUMBER(R4),IF(S4=-1,J4="",J4=S4),IF(T4=-1,O4="",O4=T4)))) -> TRUE
A5: init-002 | B5: =IF(COUNTIF('Scenario inputs'!$A$4:$A$213,Controls!$B$3&"|"&A5)>0,1,0) -> 1 | C5: =IF(B5=1,OR(SUMPRODUCT((Costs!$B$4:$B$903=A5)*(Costs!$D$4:$D$903="planned")*(Costs!$J$4:$J$903<Controls!$B$12)*(Costs!$K$4:$K$903>Costs!$J$4:$J$903))>0,SUMPRODUCT((Benefits!$B$4:$B$703=A5)*(Benefits!$T$4:$T$703=1))>0),FALSE()) -> TRUE | D5: =SUMIFS('Cash flow'!$E$4:$E$867,'Cash flow'!$A$4:$A$867,A5) -> 830750 | E5: =SUMIFS('Cash flow'!$J$4:$J$867,'Cash flow'!$A$4:$A$867,A5) -> 1308595.1 | F5: =SUMIFS('Cash flow'!$K$4:$K$867,'Cash flow'!$A$4:$A$867,A5) -> 477845.09 | G5: =IF(C5,SUMIFS('Cash flow'!$N$4:$N$867,'Cash flow'!$A$4:$A$867,A5),"") -> 413388.43 | H5: =COUNTIFS('Cash flow'!$A$4:$A$867,A5,'Cash flow'!$P$4:$P$867,1) -> 10 | I5: =SUMPRODUCT(MAX(('Cash flow'!$A$4:$A$867=A5)*('Cash flow'!$P$4:$P$867=1)*('Cash flow'!$B$4:$B$867+1))) -> 10 | J5: =IF(OR(NOT(C5),H5=0,I5=Controls!$B$12),"",I5) -> 10 | K5: =IF(NOT(C5),"NO_FLOWS",IF(H5=0,"NO_INVESTMENT",IF(I5=Controls!$B$12,"NOT_RECOVERED",""))) | L5: =IF(J5="","",(J5-1)+(-SUMIFS('Cash flow'!$L$4:$L$867,'Cash flow'!$A$4:$A$867,A5,'Cash flow'!$B$4:$B$867,J5-1))/(SUMIFS('Cash flow'!$L$4:$L$867,'Cash flow'!$A$4:$A$867,A5,'Cash flow'!$B$4:$B$867,J5)-SUMIFS('Cash flow'!$L$4:$L$867,'Cash flow'!$A$4:$A$867,A5,'Cash flow'!$B$4:$B$867,J5-1))) -> 9.9761475 | M5: =COUNTIFS('Cash flow'!$A$4:$A$867,A5,'Cash flow'!$Q$4:$Q$867,1) -> 11 | N5: =SUMPRODUCT(MAX(('Cash flow'!$A$4:$A$867=A5)*('Cash flow'!$Q$4:$Q$867=1)*('Cash flow'!$B$4:$B$867+1))) -> 11 | O5: =IF(OR(NOT(C5),M5=0,N5=Controls!$B$12),"",N5) -> 11 | P5: =IF(NOT(C5),"NO_FLOWS",IF(M5=0,"NO_INVESTMENT",IF(N5=Controls!$B$12,"NOT_RECOVERED",""))) | Q5: =IF(O5="","",(O5-1)+(-SUMIFS('Cash flow'!$O$4:$O$867,'Cash flow'!$A$4:$A$867,A5,'Cash flow'!$B$4:$B$867,O5-1))/(SUMIFS('Cash flow'!$O$4:$O$867,'Cash flow'!$A$4:$A$867,A5,'Cash flow'!$B$4:$B$867,O5)-SUMIFS('Cash flow'!$O$4:$O$867,'Cash flow'!$A$4:$A$867,A5,'Cash flow'!$B$4:$B$867,O5-1))) -> 10.181277 | R5: =IFERROR(INDEX('Domain reference'!$C$40:$C$249,MATCH(Controls!$B$3&"|"&A5,'Domain reference'!$A$40:$A$249,0)),"") -> 413388.43 | S5: =IFERROR(INDEX('Domain reference'!$D$40:$D$249,MATCH(Controls!$B$3&"|"&A5,'Domain reference'!$A$40:$A$249,0)),"") -> 10 | T5: =IFERROR(INDEX('Domain reference'!$E$40:$E$249,MATCH(Controls!$B$3&"|"&A5,'Domain reference'!$A$40:$A$249,0)),"") -> 11 | U5: =IF(LEN(Controls!$B$4)>0,TRUE(),IF(B5=0,AND(R5="",E5=0),AND(ABS(N(G5)-N(R5))<0.005,ISNUMBER(G5)=ISNUMBER(R5),IF(S5=-1,J5="",J5=S5),IF(T5=-1,O5="",O5=T5)))) -> TRUE
A6: init-003 | B6: =IF(COUNTIF('Scenario inputs'!$A$4:$A$213,Controls!$B$3&"|"&A6)>0,1,0) -> 1 | C6: =IF(B6=1,OR(SUMPRODUCT((Costs!$B$4:$B$903=A6)*(Costs!$D$4:$D$903="planned")*(Costs!$J$4:$J$903<Controls!$B$12)*(Costs!$K$4:$K$903>Costs!$J$4:$J$903))>0,SUMPRODUCT((Benefits!$B$4:$B$703=A6)*(Benefits!$T$4:$T$703=1))>0),FALSE()) -> TRUE | D6: =SUMIFS('Cash flow'!$E$4:$E$867,'Cash flow'!$A$4:$A$867,A6) -> 652800 | E6: =SUMIFS('Cash flow'!$J$4:$J$867,'Cash flow'!$A$4:$A$867,A6) -> 1075421.3 | F6: =SUMIFS('Cash flow'!$K$4:$K$867,'Cash flow'!$A$4:$A$867,A6) -> 422621.27 | G6: =IF(C6,SUMIFS('Cash flow'!$N$4:$N$867,'Cash flow'!$A$4:$A$867,A6),"") -> 363049.68 | H6: =COUNTIFS('Cash flow'!$A$4:$A$867,A6,'Cash flow'!$P$4:$P$867,1) -> 12 | I6: =SUMPRODUCT(MAX(('Cash flow'!$A$4:$A$867=A6)*('Cash flow'!$P$4:$P$867=1)*('Cash flow'!$B$4:$B$867+1))) -> 12 | J6: =IF(OR(NOT(C6),H6=0,I6=Controls!$B$12),"",I6) -> 12 | K6: =IF(NOT(C6),"NO_FLOWS",IF(H6=0,"NO_INVESTMENT",IF(I6=Controls!$B$12,"NOT_RECOVERED",""))) | L6: =IF(J6="","",(J6-1)+(-SUMIFS('Cash flow'!$L$4:$L$867,'Cash flow'!$A$4:$A$867,A6,'Cash flow'!$B$4:$B$867,J6-1))/(SUMIFS('Cash flow'!$L$4:$L$867,'Cash flow'!$A$4:$A$867,A6,'Cash flow'!$B$4:$B$867,J6)-SUMIFS('Cash flow'!$L$4:$L$867,'Cash flow'!$A$4:$A$867,A6,'Cash flow'!$B$4:$B$867,J6-1))) -> 11.151724 | M6: =COUNTIFS('Cash flow'!$A$4:$A$867,A6,'Cash flow'!$Q$4:$Q$867,1) -> 12 | N6: =SUMPRODUCT(MAX(('Cash flow'!$A$4:$A$867=A6)*('Cash flow'!$Q$4:$Q$867=1)*('Cash flow'!$B$4:$B$867+1))) -> 12 | O6: =IF(OR(NOT(C6),M6=0,N6=Controls!$B$12),"",N6) -> 12 | P6: =IF(NOT(C6),"NO_FLOWS",IF(M6=0,"NO_INVESTMENT",IF(N6=Controls!$B$12,"NOT_RECOVERED",""))) | Q6: =IF(O6="","",(O6-1)+(-SUMIFS('Cash flow'!$O$4:$O$867,'Cash flow'!$A$4:$A$867,A6,'Cash flow'!$B$4:$B$867,O6-1))/(SUMIFS('Cash flow'!$O$4:$O$867,'Cash flow'!$A$4:$A$867,A6,'Cash flow'!$B$4:$B$867,O6)-SUMIFS('Cash flow'!$O$4:$O$867,'Cash flow'!$A$4:$A$867,A6,'Cash flow'!$B$4:$B$867,O6-1))) -> 11.351814 | R6: =IFERROR(INDEX('Domain reference'!$C$40:$C$249,MATCH(Controls!$B$3&"|"&A6,'Domain reference'!$A$40:$A$249,0)),"") -> 363049.68 | S6: =IFERROR(INDEX('Domain reference'!$D$40:$D$249,MATCH(Controls!$B$3&"|"&A6,'Domain reference'!$A$40:$A$249,0)),"") -> 12 | T6: =IFERROR(INDEX('Domain reference'!$E$40:$E$249,MATCH(Controls!$B$3&"|"&A6,'Domain reference'!$A$40:$A$249,0)),"") -> 12 | U6: =IF(LEN(Controls!$B$4)>0,TRUE(),IF(B6=0,AND(R6="",E6=0),AND(ABS(N(G6)-N(R6))<0.005,ISNUMBER(G6)=ISNUMBER(R6),IF(S6=-1,J6="",J6=S6),IF(T6=-1,O6="",O6=T6)))) -> TRUE
A7: init-004 | B7: =IF(COUNTIF('Scenario inputs'!$A$4:$A$213,Controls!$B$3&"|"&A7)>0,1,0) -> 1 | C7: =IF(B7=1,OR(SUMPRODUCT((Costs!$B$4:$B$903=A7)*(Costs!$D$4:$D$903="planned")*(Costs!$J$4:$J$903<Controls!$B$12)*(Costs!$K$4:$K$903>Costs!$J$4:$J$903))>0,SUMPRODUCT((Benefits!$B$4:$B$703=A7)*(Benefits!$T$4:$T$703=1))>0),FALSE()) -> TRUE | D7: =SUMIFS('Cash flow'!$E$4:$E$867,'Cash flow'!$A$4:$A$867,A7) -> 1422150 | E7: =SUMIFS('Cash flow'!$J$4:$J$867,'Cash flow'!$A$4:$A$867,A7) -> 2058532.4 | F7: =SUMIFS('Cash flow'!$K$4:$K$867,'Cash flow'!$A$4:$A$867,A7) -> 636382.4 | G7: =IF(C7,SUMIFS('Cash flow'!$N$4:$N$867,'Cash flow'!$A$4:$A$867,A7),"") -> 523302.08 | H7: =COUNTIFS('Cash flow'!$A$4:$A$867,A7,'Cash flow'!$P$4:$P$867,1) -> 14 | I7: =SUMPRODUCT(MAX(('Cash flow'!$A$4:$A$867=A7)*('Cash flow'!$P$4:$P$867=1)*('Cash flow'!$B$4:$B$867+1))) -> 14 | J7: =IF(OR(NOT(C7),H7=0,I7=Controls!$B$12),"",I7) -> 14 | K7: =IF(NOT(C7),"NO_FLOWS",IF(H7=0,"NO_INVESTMENT",IF(I7=Controls!$B$12,"NOT_RECOVERED",""))) | L7: =IF(J7="","",(J7-1)+(-SUMIFS('Cash flow'!$L$4:$L$867,'Cash flow'!$A$4:$A$867,A7,'Cash flow'!$B$4:$B$867,J7-1))/(SUMIFS('Cash flow'!$L$4:$L$867,'Cash flow'!$A$4:$A$867,A7,'Cash flow'!$B$4:$B$867,J7)-SUMIFS('Cash flow'!$L$4:$L$867,'Cash flow'!$A$4:$A$867,A7,'Cash flow'!$B$4:$B$867,J7-1))) -> 13.099104 | M7: =COUNTIFS('Cash flow'!$A$4:$A$867,A7,'Cash flow'!$Q$4:$Q$867,1) -> 14 | N7: =SUMPRODUCT(MAX(('Cash flow'!$A$4:$A$867=A7)*('Cash flow'!$Q$4:$Q$867=1)*('Cash flow'!$B$4:$B$867+1))) -> 14 | O7: =IF(OR(NOT(C7),M7=0,N7=Controls!$B$12),"",N7) -> 14 | P7: =IF(NOT(C7),"NO_FLOWS",IF(M7=0,"NO_INVESTMENT",IF(N7=Controls!$B$12,"NOT_RECOVERED",""))) | Q7: =IF(O7="","",(O7-1)+(-SUMIFS('Cash flow'!$O$4:$O$867,'Cash flow'!$A$4:$A$867,A7,'Cash flow'!$B$4:$B$867,O7-1))/(SUMIFS('Cash flow'!$O$4:$O$867,'Cash flow'!$A$4:$A$867,A7,'Cash flow'!$B$4:$B$867,O7)-SUMIFS('Cash flow'!$O$4:$O$867,'Cash flow'!$A$4:$A$867,A7,'Cash flow'!$B$4:$B$867,O7-1))) -> 13.333038 | R7: =IFERROR(INDEX('Domain reference'!$C$40:$C$249,MATCH(Controls!$B$3&"|"&A7,'Domain reference'!$A$40:$A$249,0)),"") -> 523302.08 | S7: =IFERROR(INDEX('Domain reference'!$D$40:$D$249,MATCH(Controls!$B$3&"|"&A7,'Domain reference'!$A$40:$A$249,0)),"") -> 14 | T7: =IFERROR(INDEX('Domain reference'!$E$40:$E$249,MATCH(Controls!$B$3&"|"&A7,'Domain reference'!$A$40:$A$249,0)),"") -> 14 | U7: =IF(LEN(Controls!$B$4)>0,TRUE(),IF(B7=0,AND(R7="",E7=0),AND(ABS(N(G7)-N(R7))<0.005,ISNUMBER(G7)=ISNUMBER(R7),IF(S7=-1,J7="",J7=S7),IF(T7=-1,O7="",O7=T7)))) -> TRUE
A8: init-005 | B8: =IF(COUNTIF('Scenario inputs'!$A$4:$A$213,Controls!$B$3&"|"&A8)>0,1,0) -> 1 | C8: =IF(B8=1,OR(SUMPRODUCT((Costs!$B$4:$B$903=A8)*(Costs!$D$4:$D$903="planned")*(Costs!$J$4:$J$903<Controls!$B$12)*(Costs!$K$4:$K$903>Costs!$J$4:$J$903))>0,SUMPRODUCT((Benefits!$B$4:$B$703=A8)*(Benefits!$T$4:$T$703=1))>0),FALSE()) -> TRUE | D8: =SUMIFS('Cash flow'!$E$4:$E$867,'Cash flow'!$A$4:$A$867,A8) -> 907200 | E8: =SUMIFS('Cash flow'!$J$4:$J$867,'Cash flow'!$A$4:$A$867,A8) -> 1179266.8 | F8: =SUMIFS('Cash flow'!$K$4:$K$867,'Cash flow'!$A$4:$A$867,A8) -> 272066.75 | G8: =IF(C8,SUMIFS('Cash flow'!$N$4:$N$867,'Cash flow'!$A$4:$A$867,A8),"") -> 209002.21 | H8: =COUNTIFS('Cash flow'!$A$4:$A$867,A8,'Cash flow'!$P$4:$P$867,1) -> 19 | I8: =SUMPRODUCT(MAX(('Cash flow'!$A$4:$A$867=A8)*('Cash flow'!$P$4:$P$867=1)*('Cash flow'!$B$4:$B$867+1))) -> 19 | J8: =IF(OR(NOT(C8),H8=0,I8=Controls!$B$12),"",I8) -> 19 | K8: =IF(NOT(C8),"NO_FLOWS",IF(H8=0,"NO_INVESTMENT",IF(I8=Controls!$B$12,"NOT_RECOVERED",""))) | L8: =IF(J8="","",(J8-1)+(-SUMIFS('Cash flow'!$L$4:$L$867,'Cash flow'!$A$4:$A$867,A8,'Cash flow'!$B$4:$B$867,J8-1))/(SUMIFS('Cash flow'!$L$4:$L$867,'Cash flow'!$A$4:$A$867,A8,'Cash flow'!$B$4:$B$867,J8)-SUMIFS('Cash flow'!$L$4:$L$867,'Cash flow'!$A$4:$A$867,A8,'Cash flow'!$B$4:$B$867,J8-1))) -> 18.434749 | M8: =COUNTIFS('Cash flow'!$A$4:$A$867,A8,'Cash flow'!$Q$4:$Q$867,1) -> 19 | N8: =SUMPRODUCT(MAX(('Cash flow'!$A$4:$A$867=A8)*('Cash flow'!$Q$4:$Q$867=1)*('Cash flow'!$B$4:$B$867+1))) -> 19 | O8: =IF(OR(NOT(C8),M8=0,N8=Controls!$B$12),"",N8) -> 19 | P8: =IF(NOT(C8),"NO_FLOWS",IF(M8=0,"NO_INVESTMENT",IF(N8=Controls!$B$12,"NOT_RECOVERED",""))) | Q8: =IF(O8="","",(O8-1)+(-SUMIFS('Cash flow'!$O$4:$O$867,'Cash flow'!$A$4:$A$867,A8,'Cash flow'!$B$4:$B$867,O8-1))/(SUMIFS('Cash flow'!$O$4:$O$867,'Cash flow'!$A$4:$A$867,A8,'Cash flow'!$B$4:$B$867,O8)-SUMIFS('Cash flow'!$O$4:$O$867,'Cash flow'!$A$4:$A$867,A8,'Cash flow'!$B$4:$B$867,O8-1))) -> 18.74007 | R8: =IFERROR(INDEX('Domain reference'!$C$40:$C$249,MATCH(Controls!$B$3&"|"&A8,'Domain reference'!$A$40:$A$249,0)),"") -> 209002.21 | S8: =IFERROR(INDEX('Domain reference'!$D$40:$D$249,MATCH(Controls!$B$3&"|"&A8,'Domain reference'!$A$40:$A$249,0)),"") -> 19 | T8: =IFERROR(INDEX('Domain reference'!$E$40:$E$249,MATCH(Controls!$B$3&"|"&A8,'Domain reference'!$A$40:$A$249,0)),"") -> 19 | U8: =IF(LEN(Controls!$B$4)>0,TRUE(),IF(B8=0,AND(R8="",E8=0),AND(ABS(N(G8)-N(R8))<0.005,ISNUMBER(G8)=ISNUMBER(R8),IF(S8=-1,J8="",J8=S8),IF(T8=-1,O8="",O8=T8)))) -> TRUE
A9: init-006 | B9: =IF(COUNTIF('Scenario inputs'!$A$4:$A$213,Controls!$B$3&"|"&A9)>0,1,0) -> 1 | C9: =IF(B9=1,OR(SUMPRODUCT((Costs!$B$4:$B$903=A9)*(Costs!$D$4:$D$903="planned")*(Costs!$J$4:$J$903<Controls!$B$12)*(Costs!$K$4:$K$903>Costs!$J$4:$J$903))>0,SUMPRODUCT((Benefits!$B$4:$B$703=A9)*(Benefits!$T$4:$T$703=1))>0),FALSE()) -> TRUE | D9: =SUMIFS('Cash flow'!$E$4:$E$867,'Cash flow'!$A$4:$A$867,A9) -> 588850 | E9: =SUMIFS('Cash flow'!$J$4:$J$867,'Cash flow'!$A$4:$A$867,A9) -> 0 | F9: =SUMIFS('Cash flow'!$K$4:$K$867,'Cash flow'!$A$4:$A$867,A9) -> -588850 | G9: =IF(C9,SUMIFS('Cash flow'!$N$4:$N$867,'Cash flow'!$A$4:$A$867,A9),"") -> -535631.92 | H9: =COUNTIFS('Cash flow'!$A$4:$A$867,A9,'Cash flow'!$P$4:$P$867,1) -> 36 | I9: =SUMPRODUCT(MAX(('Cash flow'!$A$4:$A$867=A9)*('Cash flow'!$P$4:$P$867=1)*('Cash flow'!$B$4:$B$867+1))) -> 36 | J9: =IF(OR(NOT(C9),H9=0,I9=Controls!$B$12),"",I9) | K9: =IF(NOT(C9),"NO_FLOWS",IF(H9=0,"NO_INVESTMENT",IF(I9=Controls!$B$12,"NOT_RECOVERED",""))) -> NOT_RECOVERED | L9: =IF(J9="","",(J9-1)+(-SUMIFS('Cash flow'!$L$4:$L$867,'Cash flow'!$A$4:$A$867,A9,'Cash flow'!$B$4:$B$867,J9-1))/(SUMIFS('Cash flow'!$L$4:$L$867,'Cash flow'!$A$4:$A$867,A9,'Cash flow'!$B$4:$B$867,J9)-SUMIFS('Cash flow'!$L$4:$L$867,'Cash flow'!$A$4:$A$867,A9,'Cash flow'!$B$4:$B$867,J9-1))) | M9: =COUNTIFS('Cash flow'!$A$4:$A$867,A9,'Cash flow'!$Q$4:$Q$867,1) -> 36 | N9: =SUMPRODUCT(MAX(('Cash flow'!$A$4:$A$867=A9)*('Cash flow'!$Q$4:$Q$867=1)*('Cash flow'!$B$4:$B$867+1))) -> 36 | O9: =IF(OR(NOT(C9),M9=0,N9=Controls!$B$12),"",N9) | P9: =IF(NOT(C9),"NO_FLOWS",IF(M9=0,"NO_INVESTMENT",IF(N9=Controls!$B$12,"NOT_RECOVERED",""))) -> NOT_RECOVERED | Q9: =IF(O9="","",(O9-1)+(-SUMIFS('Cash flow'!$O$4:$O$867,'Cash flow'!$A$4:$A$867,A9,'Cash flow'!$B$4:$B$867,O9-1))/(SUMIFS('Cash flow'!$O$4:$O$867,'Cash flow'!$A$4:$A$867,A9,'Cash flow'!$B$4:$B$867,O9)-SUMIFS('Cash flow'!$O$4:$O$867,'Cash flow'!$A$4:$A$867,A9,'Cash flow'!$B$4:$B$867,O9-1))) | R9: =IFERROR(INDEX('Domain reference'!$C$40:$C$249,MATCH(Controls!$B$3&"|"&A9,'Domain reference'!$A$40:$A$249,0)),"") -> -535631.92 | S9: =IFERROR(INDEX('Domain reference'!$D$40:$D$249,MATCH(Controls!$B$3&"|"&A9,'Domain reference'!$A$40:$A$249,0)),"") -> -1 | T9: =IFERROR(INDEX('Domain reference'!$E$40:$E$249,MATCH(Controls!$B$3&"|"&A9,'Domain reference'!$A$40:$A$249,0)),"") -> -1 | U9: =IF(LEN(Controls!$B$4)>0,TRUE(),IF(B9=0,AND(R9="",E9=0),AND(ABS(N(G9)-N(R9))<0.005,ISNUMBER(G9)=ISNUMBER(R9),IF(S9=-1,J9="",J9=S9),IF(T9=-1,O9="",O9=T9)))) -> TRUE
A10: init-007 | B10: =IF(COUNTIF('Scenario inputs'!$A$4:$A$213,Controls!$B$3&"|"&A10)>0,1,0) -> 1 | C10: =IF(B10=1,OR(SUMPRODUCT((Costs!$B$4:$B$903=A10)*(Costs!$D$4:$D$903="planned")*(Costs!$J$4:$J$903<Controls!$B$12)*(Costs!$K$4:$K$903>Costs!$J$4:$J$903))>0,SUMPRODUCT((Benefits!$B$4:$B$703=A10)*(Benefits!$T$4:$T$703=1))>0),FALSE()) -> TRUE | D10: =SUMIFS('Cash flow'!$E$4:$E$867,'Cash flow'!$A$4:$A$867,A10) -> 1961550 | E10: =SUMIFS('Cash flow'!$J$4:$J$867,'Cash flow'!$A$4:$A$867,A10) -> 2489519.3 | F10: =SUMIFS('Cash flow'!$K$4:$K$867,'Cash flow'!$A$4:$A$867,A10) -> 527969.27 | G10: =IF(C10,SUMIFS('Cash flow'!$N$4:$N$867,'Cash flow'!$A$4:$A$867,A10),"") -> 415366 | H10: =COUNTIFS('Cash flow'!$A$4:$A$867,A10,'Cash flow'!$P$4:$P$867,1) -> 11 | I10: =SUMPRODUCT(MAX(('Cash flow'!$A$4:$A$867=A10)*('Cash flow'!$P$4:$P$867=1)*('Cash flow'!$B$4:$B$867+1))) -> 11 | J10: =IF(OR(NOT(C10),H10=0,I10=Controls!$B$12),"",I10) -> 11 | K10: =IF(NOT(C10),"NO_FLOWS",IF(H10=0,"NO_INVESTMENT",IF(I10=Controls!$B$12,"NOT_RECOVERED",""))) | L10: =IF(J10="","",(J10-1)+(-SUMIFS('Cash flow'!$L$4:$L$867,'Cash flow'!$A$4:$A$867,A10,'Cash flow'!$B$4:$B$867,J10-1))/(SUMIFS('Cash flow'!$L$4:$L$867,'Cash flow'!$A$4:$A$867,A10,'Cash flow'!$B$4:$B$867,J10)-SUMIFS('Cash flow'!$L$4:$L$867,'Cash flow'!$A$4:$A$867,A10,'Cash flow'!$B$4:$B$867,J10-1))) -> 10.255564 | M10: =COUNTIFS('Cash flow'!$A$4:$A$867,A10,'Cash flow'!$Q$4:$Q$867,1) -> 11 | N10: =SUMPRODUCT(MAX(('Cash flow'!$A$4:$A$867=A10)*('Cash flow'!$Q$4:$Q$867=1)*('Cash flow'!$B$4:$B$867+1))) -> 11 | O10: =IF(OR(NOT(C10),M10=0,N10=Controls!$B$12),"",N10) -> 11 | P10: =IF(NOT(C10),"NO_FLOWS",IF(M10=0,"NO_INVESTMENT",IF(N10=Controls!$B$12,"NOT_RECOVERED",""))) | Q10: =IF(O10="","",(O10-1)+(-SUMIFS('Cash flow'!$O$4:$O$867,'Cash flow'!$A$4:$A$867,A10,'Cash flow'!$B$4:$B$867,O10-1))/(SUMIFS('Cash flow'!$O$4:$O$867,'Cash flow'!$A$4:$A$867,A10,'Cash flow'!$B$4:$B$867,O10)-SUMIFS('Cash flow'!$O$4:$O$867,'Cash flow'!$A$4:$A$867,A10,'Cash flow'!$B$4:$B$867,O10-1))) -> 10.516712 | R10: =IFERROR(INDEX('Domain reference'!$C$40:$C$249,MATCH(Controls!$B$3&"|"&A10,'Domain reference'!$A$40:$A$249,0)),"") -> 415366 | S10: =IFERROR(INDEX('Domain reference'!$D$40:$D$249,MATCH(Controls!$B$3&"|"&A10,'Domain reference'!$A$40:$A$249,0)),"") -> 11 | T10: =IFERROR(INDEX('Domain reference'!$E$40:$E$249,MATCH(Controls!$B$3&"|"&A10,'Domain reference'!$A$40:$A$249,0)),"") -> 11 | U10: =IF(LEN(Controls!$B$4)>0,TRUE(),IF(B10=0,AND(R10="",E10=0),AND(ABS(N(G10)-N(R10))<0.005,ISNUMBER(G10)=ISNUMBER(R10),IF(S10=-1,J10="",J10=S10),IF(T10=-1,O10="",O10=T10)))) -> TRUE
A11: init-008 | B11: =IF(COUNTIF('Scenario inputs'!$A$4:$A$213,Controls!$B$3&"|"&A11)>0,1,0) -> 1 | C11: =IF(B11=1,OR(SUMPRODUCT((Costs!$B$4:$B$903=A11)*(Costs!$D$4:$D$903="planned")*(Costs!$J$4:$J$903<Controls!$B$12)*(Costs!$K$4:$K$903>Costs!$J$4:$J$903))>0,SUMPRODUCT((Benefits!$B$4:$B$703=A11)*(Benefits!$T$4:$T$703=1))>0),FALSE()) -> TRUE | D11: =SUMIFS('Cash flow'!$E$4:$E$867,'Cash flow'!$A$4:$A$867,A11) -> 1039700 | E11: =SUMIFS('Cash flow'!$J$4:$J$867,'Cash flow'!$A$4:$A$867,A11) -> 1158800 | F11: =SUMIFS('Cash flow'!$K$4:$K$867,'Cash flow'!$A$4:$A$867,A11) -> 119100 | G11: =IF(C11,SUMIFS('Cash flow'!$N$4:$N$867,'Cash flow'!$A$4:$A$867,A11),"") -> 65253.906 | H11: =COUNTIFS('Cash flow'!$A$4:$A$867,A11,'Cash flow'!$P$4:$P$867,1) -> 13 | I11: =SUMPRODUCT(MAX(('Cash flow'!$A$4:$A$867=A11)*('Cash flow'!$P$4:$P$867=1)*('Cash flow'!$B$4:$B$867+1))) -> 13 | J11: =IF(OR(NOT(C11),H11=0,I11=Controls!$B$12),"",I11) -> 13 | K11: =IF(NOT(C11),"NO_FLOWS",IF(H11=0,"NO_INVESTMENT",IF(I11=Controls!$B$12,"NOT_RECOVERED",""))) | L11: =IF(J11="","",(J11-1)+(-SUMIFS('Cash flow'!$L$4:$L$867,'Cash flow'!$A$4:$A$867,A11,'Cash flow'!$B$4:$B$867,J11-1))/(SUMIFS('Cash flow'!$L$4:$L$867,'Cash flow'!$A$4:$A$867,A11,'Cash flow'!$B$4:$B$867,J11)-SUMIFS('Cash flow'!$L$4:$L$867,'Cash flow'!$A$4:$A$867,A11,'Cash flow'!$B$4:$B$867,J11-1))) -> 12.387476 | M11: =COUNTIFS('Cash flow'!$A$4:$A$867,A11,'Cash flow'!$Q$4:$Q$867,1) -> 13 | N11: =SUMPRODUCT(MAX(('Cash flow'!$A$4:$A$867=A11)*('Cash flow'!$Q$4:$Q$867=1)*('Cash flow'!$B$4:$B$867+1))) -> 13 | O11: =IF(OR(NOT(C11),M11=0,N11=Controls!$B$12),"",N11) -> 13 | P11: =IF(NOT(C11),"NO_FLOWS",IF(M11=0,"NO_INVESTMENT",IF(N11=Controls!$B$12,"NOT_RECOVERED",""))) | Q11: =IF(O11="","",(O11-1)+(-SUMIFS('Cash flow'!$O$4:$O$867,'Cash flow'!$A$4:$A$867,A11,'Cash flow'!$B$4:$B$867,O11-1))/(SUMIFS('Cash flow'!$O$4:$O$867,'Cash flow'!$A$4:$A$867,A11,'Cash flow'!$B$4:$B$867,O11)-SUMIFS('Cash flow'!$O$4:$O$867,'Cash flow'!$A$4:$A$867,A11,'Cash flow'!$B$4:$B$867,O11-1))) -> 12.762514 | R11: =IFERROR(INDEX('Domain reference'!$C$40:$C$249,MATCH(Controls!$B$3&"|"&A11,'Domain reference'!$A$40:$A$249,0)),"") -> 65253.91 | S11: =IFERROR(INDEX('Domain reference'!$D$40:$D$249,MATCH(Controls!$B$3&"|"&A11,'Domain reference'!$A$40:$A$249,0)),"") -> 13 | T11: =IFERROR(INDEX('Domain reference'!$E$40:$E$249,MATCH(Controls!$B$3&"|"&A11,'Domain reference'!$A$40:$A$249,0)),"") -> 13 | U11: =IF(LEN(Controls!$B$4)>0,TRUE(),IF(B11=0,AND(R11="",E11=0),AND(ABS(N(G11)-N(R11))<0.005,ISNUMBER(G11)=ISNUMBER(R11),IF(S11=-1,J11="",J11=S11),IF(T11=-1,O11="",O11=T11)))) -> TRUE
A12: init-009 | B12: =IF(COUNTIF('Scenario inputs'!$A$4:$A$213,Controls!$B$3&"|"&A12)>0,1,0) -> 1 | C12: =IF(B12=1,OR(SUMPRODUCT((Costs!$B$4:$B$903=A12)*(Costs!$D$4:$D$903="planned")*(Costs!$J$4:$J$903<Controls!$B$12)*(Costs!$K$4:$K$903>Costs!$J$4:$J$903))>0,SUMPRODUCT((Benefits!$B$4:$B$703=A12)*(Benefits!$T$4:$T$703=1))>0),FALSE()) -> TRUE | D12: =SUMIFS('Cash flow'!$E$4:$E$867,'Cash flow'!$A$4:$A$867,A12) -> 775800 | E12: =SUMIFS('Cash flow'!$J$4:$J$867,'Cash flow'!$A$4:$A$867,A12) -> 0 | F12: =SUMIFS('Cash flow'!$K$4:$K$867,'Cash flow'!$A$4:$A$867,A12) -> -775800 | G12: =IF(C12,SUMIFS('Cash flow'!$N$4:$N$867,'Cash flow'!$A$4:$A$867,A12),"") -> -761535.73 | H12: =COUNTIFS('Cash flow'!$A$4:$A$867,A12,'Cash flow'!$P$4:$P$867,1) -> 36 | I12: =SUMPRODUCT(MAX(('Cash flow'!$A$4:$A$867=A12)*('Cash flow'!$P$4:$P$867=1)*('Cash flow'!$B$4:$B$867+1))) -> 36 | J12: =IF(OR(NOT(C12),H12=0,I12=Controls!$B$12),"",I12) | K12: =IF(NOT(C12),"NO_FLOWS",IF(H12=0,"NO_INVESTMENT",IF(I12=Controls!$B$12,"NOT_RECOVERED",""))) -> NOT_RECOVERED | L12: =IF(J12="","",(J12-1)+(-SUMIFS('Cash flow'!$L$4:$L$867,'Cash flow'!$A$4:$A$867,A12,'Cash flow'!$B$4:$B$867,J12-1))/(SUMIFS('Cash flow'!$L$4:$L$867,'Cash flow'!$A$4:$A$867,A12,'Cash flow'!$B$4:$B$867,J12)-SUMIFS('Cash flow'!$L$4:$L$867,'Cash flow'!$A$4:$A$867,A12,'Cash flow'!$B$4:$B$867,J12-1))) | M12: =COUNTIFS('Cash flow'!$A$4:$A$867,A12,'Cash flow'!$Q$4:$Q$867,1) -> 36 | N12: =SUMPRODUCT(MAX(('Cash flow'!$A$4:$A$867=A12)*('Cash flow'!$Q$4:$Q$867=1)*('Cash flow'!$B$4:$B$867+1))) -> 36 | O12: =IF(OR(NOT(C12),M12=0,N12=Controls!$B$12),"",N12) | P12: =IF(NOT(C12),"NO_FLOWS",IF(M12=0,"NO_INVESTMENT",IF(N12=Controls!$B$12,"NOT_RECOVERED",""))) -> NOT_RECOVERED | Q12: =IF(O12="","",(O12-1)+(-SUMIFS('Cash flow'!$O$4:$O$867,'Cash flow'!$A$4:$A$867,A12,'Cash flow'!$B$4:$B$867,O12-1))/(SUMIFS('Cash flow'!$O$4:$O$867,'Cash flow'!$A$4:$A$867,A12,'Cash flow'!$B$4:$B$867,O12)-SUMIFS('Cash flow'!$O$4:$O$867,'Cash flow'!$A$4:$A$867,A12,'Cash flow'!$B$4:$B$867,O12-1))) | R12: =IFERROR(INDEX('Domain reference'!$C$40:$C$249,MATCH(Controls!$B$3&"|"&A12,'Domain reference'!$A$40:$A$249,0)),"") -> -761535.73 | S12: =IFERROR(INDEX('Domain reference'!$D$40:$D$249,MATCH(Controls!$B$3&"|"&A12,'Domain reference'!$A$40:$A$249,0)),"") -> -1 | T12: =IFERROR(INDEX('Domain reference'!$E$40:$E$249,MATCH(Controls!$B$3&"|"&A12,'Domain reference'!$A$40:$A$249,0)),"") -> -1 | U12: =IF(LEN(Controls!$B$4)>0,TRUE(),IF(B12=0,AND(R12="",E12=0),AND(ABS(N(G12)-N(R12))<0.005,ISNUMBER(G12)=ISNUMBER(R12),IF(S12=-1,J12="",J12=S12),IF(T12=-1,O12="",O12=T12)))) -> TRUE
A13: init-010 | B13: =IF(COUNTIF('Scenario inputs'!$A$4:$A$213,Controls!$B$3&"|"&A13)>0,1,0) -> 1 | C13: =IF(B13=1,OR(SUMPRODUCT((Costs!$B$4:$B$903=A13)*(Costs!$D$4:$D$903="planned")*(Costs!$J$4:$J$903<Controls!$B$12)*(Costs!$K$4:$K$903>Costs!$J$4:$J$903))>0,SUMPRODUCT((Benefits!$B$4:$B$703=A13)*(Benefits!$T$4:$T$703=1))>0),FALSE()) -> TRUE | D13: =SUMIFS('Cash flow'!$E$4:$E$867,'Cash flow'!$A$4:$A$867,A13) -> 1571900 | E13: =SUMIFS('Cash flow'!$J$4:$J$867,'Cash flow'!$A$4:$A$867,A13) -> 2122033.2 | F13: =SUMIFS('Cash flow'!$K$4:$K$867,'Cash flow'!$A$4:$A$867,A13) -> 550133.17 | G13: =IF(C13,SUMIFS('Cash flow'!$N$4:$N$867,'Cash flow'!$A$4:$A$867,A13),"") -> 423409.74 | H13: =COUNTIFS('Cash flow'!$A$4:$A$867,A13,'Cash flow'!$P$4:$P$867,1) -> 18 | I13: =SUMPRODUCT(MAX(('Cash flow'!$A$4:$A$867=A13)*('Cash flow'!$P$4:$P$867=1)*('Cash flow'!$B$4:$B$867+1))) -> 18 | J13: =IF(OR(NOT(C13),H13=0,I13=Controls!$B$12),"",I13) -> 18 | K13: =IF(NOT(C13),"NO_FLOWS",IF(H13=0,"NO_INVESTMENT",IF(I13=Controls!$B$12,"NOT_RECOVERED",""))) | L13: =IF(J13="","",(J13-1)+(-SUMIFS('Cash flow'!$L$4:$L$867,'Cash flow'!$A$4:$A$867,A13,'Cash flow'!$B$4:$B$867,J13-1))/(SUMIFS('Cash flow'!$L$4:$L$867,'Cash flow'!$A$4:$A$867,A13,'Cash flow'!$B$4:$B$867,J13)-SUMIFS('Cash flow'!$L$4:$L$867,'Cash flow'!$A$4:$A$867,A13,'Cash flow'!$B$4:$B$867,J13-1))) -> 17.372425 | M13: =COUNTIFS('Cash flow'!$A$4:$A$867,A13,'Cash flow'!$Q$4:$Q$867,1) -> 18 | N13: =SUMPRODUCT(MAX(('Cash flow'!$A$4:$A$867=A13)*('Cash flow'!$Q$4:$Q$867=1)*('Cash flow'!$B$4:$B$867+1))) -> 18 | O13: =IF(OR(NOT(C13),M13=0,N13=Controls!$B$12),"",N13) -> 18 | P13: =IF(NOT(C13),"NO_FLOWS",IF(M13=0,"NO_INVESTMENT",IF(N13=Controls!$B$12,"NOT_RECOVERED",""))) | Q13: =IF(O13="","",(O13-1)+(-SUMIFS('Cash flow'!$O$4:$O$867,'Cash flow'!$A$4:$A$867,A13,'Cash flow'!$B$4:$B$867,O13-1))/(SUMIFS('Cash flow'!$O$4:$O$867,'Cash flow'!$A$4:$A$867,A13,'Cash flow'!$B$4:$B$867,O13)-SUMIFS('Cash flow'!$O$4:$O$867,'Cash flow'!$A$4:$A$867,A13,'Cash flow'!$B$4:$B$867,O13-1))) -> 17.697349 | R13: =IFERROR(INDEX('Domain reference'!$C$40:$C$249,MATCH(Controls!$B$3&"|"&A13,'Domain reference'!$A$40:$A$249,0)),"") -> 423409.74 | S13: =IFERROR(INDEX('Domain reference'!$D$40:$D$249,MATCH(Controls!$B$3&"|"&A13,'Domain reference'!$A$40:$A$249,0)),"") -> 18 | T13: =IFERROR(INDEX('Domain reference'!$E$40:$E$249,MATCH(Controls!$B$3&"|"&A13,'Domain reference'!$A$40:$A$249,0)),"") -> 18 | U13: =IF(LEN(Controls!$B$4)>0,TRUE(),IF(B13=0,AND(R13="",E13=0),AND(ABS(N(G13)-N(R13))<0.005,ISNUMBER(G13)=ISNUMBER(R13),IF(S13=-1,J13="",J13=S13),IF(T13=-1,O13="",O13=T13)))) -> TRUE
A14: init-011 | B14: =IF(COUNTIF('Scenario inputs'!$A$4:$A$213,Controls!$B$3&"|"&A14)>0,1,0) -> 1 | C14: =IF(B14=1,OR(SUMPRODUCT((Costs!$B$4:$B$903=A14)*(Costs!$D$4:$D$903="planned")*(Costs!$J$4:$J$903<Controls!$B$12)*(Costs!$K$4:$K$903>Costs!$J$4:$J$903))>0,SUMPRODUCT((Benefits!$B$4:$B$703=A14)*(Benefits!$T$4:$T$703=1))>0),FALSE()) -> TRUE | D14: =SUMIFS('Cash flow'!$E$4:$E$867,'Cash flow'!$A$4:$A$867,A14) -> 452900 | E14: =SUMIFS('Cash flow'!$J$4:$J$867,'Cash flow'!$A$4:$A$867,A14) -> 566000 | F14: =SUMIFS('Cash flow'!$K$4:$K$867,'Cash flow'!$A$4:$A$867,A14) -> 113100 | G14: =IF(C14,SUMIFS('Cash flow'!$N$4:$N$867,'Cash flow'!$A$4:$A$867,A14),"") -> 84012.759 | H14: =COUNTIFS('Cash flow'!$A$4:$A$867,A14,'Cash flow'!$P$4:$P$867,1) -> 21 | I14: =SUMPRODUCT(MAX(('Cash flow'!$A$4:$A$867=A14)*('Cash flow'!$P$4:$P$867=1)*('Cash flow'!$B$4:$B$867+1))) -> 21 | J14: =IF(OR(NOT(C14),H14=0,I14=Controls!$B$12),"",I14) -> 21 | K14: =IF(NOT(C14),"NO_FLOWS",IF(H14=0,"NO_INVESTMENT",IF(I14=Controls!$B$12,"NOT_RECOVERED",""))) | L14: =IF(J14="","",(J14-1)+(-SUMIFS('Cash flow'!$L$4:$L$867,'Cash flow'!$A$4:$A$867,A14,'Cash flow'!$B$4:$B$867,J14-1))/(SUMIFS('Cash flow'!$L$4:$L$867,'Cash flow'!$A$4:$A$867,A14,'Cash flow'!$B$4:$B$867,J14)-SUMIFS('Cash flow'!$L$4:$L$867,'Cash flow'!$A$4:$A$867,A14,'Cash flow'!$B$4:$B$867,J14-1))) -> 20.564777 | M14: =COUNTIFS('Cash flow'!$A$4:$A$867,A14,'Cash flow'!$Q$4:$Q$867,1) -> 21 | N14: =SUMPRODUCT(MAX(('Cash flow'!$A$4:$A$867=A14)*('Cash flow'!$Q$4:$Q$867=1)*('Cash flow'!$B$4:$B$867+1))) -> 21 | O14: =IF(OR(NOT(C14),M14=0,N14=Controls!$B$12),"",N14) -> 21 | P14: =IF(NOT(C14),"NO_FLOWS",IF(M14=0,"NO_INVESTMENT",IF(N14=Controls!$B$12,"NOT_RECOVERED",""))) | Q14: =IF(O14="","",(O14-1)+(-SUMIFS('Cash flow'!$O$4:$O$867,'Cash flow'!$A$4:$A$867,A14,'Cash flow'!$B$4:$B$867,O14-1))/(SUMIFS('Cash flow'!$O$4:$O$867,'Cash flow'!$A$4:$A$867,A14,'Cash flow'!$B$4:$B$867,O14)-SUMIFS('Cash flow'!$O$4:$O$867,'Cash flow'!$A$4:$A$867,A14,'Cash flow'!$B$4:$B$867,O14-1))) -> 20.89204 | R14: =IFERROR(INDEX('Domain reference'!$C$40:$C$249,MATCH(Controls!$B$3&"|"&A14,'Domain reference'!$A$40:$A$249,0)),"") -> 84012.76 | S14: =IFERROR(INDEX('Domain reference'!$D$40:$D$249,MATCH(Controls!$B$3&"|"&A14,'Domain reference'!$A$40:$A$249,0)),"") -> 21 | T14: =IFERROR(INDEX('Domain reference'!$E$40:$E$249,MATCH(Controls!$B$3&"|"&A14,'Domain reference'!$A$40:$A$249,0)),"") -> 21 | U14: =IF(LEN(Controls!$B$4)>0,TRUE(),IF(B14=0,AND(R14="",E14=0),AND(ABS(N(G14)-N(R14))<0.005,ISNUMBER(G14)=ISNUMBER(R14),IF(S14=-1,J14="",J14=S14),IF(T14=-1,O14="",O14=T14)))) -> TRUE
A15: init-012 | B15: =IF(COUNTIF('Scenario inputs'!$A$4:$A$213,Controls!$B$3&"|"&A15)>0,1,0) -> 1 | C15: =IF(B15=1,OR(SUMPRODUCT((Costs!$B$4:$B$903=A15)*(Costs!$D$4:$D$903="planned")*(Costs!$J$4:$J$903<Controls!$B$12)*(Costs!$K$4:$K$903>Costs!$J$4:$J$903))>0,SUMPRODUCT((Benefits!$B$4:$B$703=A15)*(Benefits!$T$4:$T$703=1))>0),FALSE()) -> TRUE | D15: =SUMIFS('Cash flow'!$E$4:$E$867,'Cash flow'!$A$4:$A$867,A15) -> 970800 | E15: =SUMIFS('Cash flow'!$J$4:$J$867,'Cash flow'!$A$4:$A$867,A15) -> 1164800.1 | F15: =SUMIFS('Cash flow'!$K$4:$K$867,'Cash flow'!$A$4:$A$867,A15) -> 194000.08 | G15: =IF(C15,SUMIFS('Cash flow'!$N$4:$N$867,'Cash flow'!$A$4:$A$867,A15),"") -> 126524.02 | H15: =COUNTIFS('Cash flow'!$A$4:$A$867,A15,'Cash flow'!$P$4:$P$867,1) -> 27 | I15: =SUMPRODUCT(MAX(('Cash flow'!$A$4:$A$867=A15)*('Cash flow'!$P$4:$P$867=1)*('Cash flow'!$B$4:$B$867+1))) -> 27 | J15: =IF(OR(NOT(C15),H15=0,I15=Controls!$B$12),"",I15) -> 27 | K15: =IF(NOT(C15),"NO_FLOWS",IF(H15=0,"NO_INVESTMENT",IF(I15=Controls!$B$12,"NOT_RECOVERED",""))) | L15: =IF(J15="","",(J15-1)+(-SUMIFS('Cash flow'!$L$4:$L$867,'Cash flow'!$A$4:$A$867,A15,'Cash flow'!$B$4:$B$867,J15-1))/(SUMIFS('Cash flow'!$L$4:$L$867,'Cash flow'!$A$4:$A$867,A15,'Cash flow'!$B$4:$B$867,J15)-SUMIFS('Cash flow'!$L$4:$L$867,'Cash flow'!$A$4:$A$867,A15,'Cash flow'!$B$4:$B$867,J15-1))) -> 26.224256 | M15: =COUNTIFS('Cash flow'!$A$4:$A$867,A15,'Cash flow'!$Q$4:$Q$867,1) -> 27 | N15: =SUMPRODUCT(MAX(('Cash flow'!$A$4:$A$867=A15)*('Cash flow'!$Q$4:$Q$867=1)*('Cash flow'!$B$4:$B$867+1))) -> 27 | O15: =IF(OR(NOT(C15),M15=0,N15=Controls!$B$12),"",N15) -> 27 | P15: =IF(NOT(C15),"NO_FLOWS",IF(M15=0,"NO_INVESTMENT",IF(N15=Controls!$B$12,"NOT_RECOVERED",""))) | Q15: =IF(O15="","",(O15-1)+(-SUMIFS('Cash flow'!$O$4:$O$867,'Cash flow'!$A$4:$A$867,A15,'Cash flow'!$B$4:$B$867,O15-1))/(SUMIFS('Cash flow'!$O$4:$O$867,'Cash flow'!$A$4:$A$867,A15,'Cash flow'!$B$4:$B$867,O15)-SUMIFS('Cash flow'!$O$4:$O$867,'Cash flow'!$A$4:$A$867,A15,'Cash flow'!$B$4:$B$867,O15-1))) -> 26.616542 | R15: =IFERROR(INDEX('Domain reference'!$C$40:$C$249,MATCH(Controls!$B$3&"|"&A15,'Domain reference'!$A$40:$A$249,0)),"") -> 126524.02 | S15: =IFERROR(INDEX('Domain reference'!$D$40:$D$249,MATCH(Controls!$B$3&"|"&A15,'Domain reference'!$A$40:$A$249,0)),"") -> 27 | T15: =IFERROR(INDEX('Domain reference'!$E$40:$E$249,MATCH(Controls!$B$3&"|"&A15,'Domain reference'!$A$40:$A$249,0)),"") -> 27 | U15: =IF(LEN(Controls!$B$4)>0,TRUE(),IF(B15=0,AND(R15="",E15=0),AND(ABS(N(G15)-N(R15))<0.005,ISNUMBER(G15)=ISNUMBER(R15),IF(S15=-1,J15="",J15=S15),IF(T15=-1,O15="",O15=T15)))) -> TRUE
... A27: init-024 | B27: =IF(COUNTIF('Scenario inputs'!$A$4:$A$213,Controls!$B$3&"|"&A27)>0,1,0) -> 1 | C27: =IF(B27=1,OR(SUMPRODUCT((Costs!$B$4:$B$903=A27)*(Costs!$D$4:$D$903="planned")*(Costs!$J$4:$J$903<Controls!$B$12)*(Costs!$K$4:$K$903>Costs!$J$4:$J$903))>0,SUMPRODUCT((Benefits!$B$4:$B$703=A27)*(Benefits!$T$4:$T$703=1))>0),FALSE()) -> TRUE | D27: =SUMIFS('Cash flow'!$E$4:$E$867,'Cash flow'!$A$4:$A$867,A27) -> 1284900 | E27: =SUMIFS('Cash flow'!$J$4:$J$867,'Cash flow'!$A$4:$A$867,A27) -> 1606266.8 | F27: =SUMIFS('Cash flow'!$K$4:$K$867,'Cash flow'!$A$4:$A$867,A27) -> 321366.78 | G27: =IF(C27,SUMIFS('Cash flow'!$N$4:$N$867,'Cash flow'!$A$4:$A$867,A27),"") -> 230132.79 | H27: =COUNTIFS('Cash flow'!$A$4:$A$867,A27,'Cash flow'!$P$4:$P$867,1) -> 20 | I27: =SUMPRODUCT(MAX(('Cash flow'!$A$4:$A$867=A27)*('Cash flow'!$P$4:$P$867=1)*('Cash flow'!$B$4:$B$867+1))) -> 20 | J27: =IF(OR(NOT(C27),H27=0,I27=Controls!$B$12),"",I27) -> 20 | K27: =IF(NOT(C27),"NO_FLOWS",IF(H27=0,"NO_INVESTMENT",IF(I27=Controls!$B$12,"NOT_RECOVERED",""))) | L27: =IF(J27="","",(J27-1)+(-SUMIFS('Cash flow'!$L$4:$L$867,'Cash flow'!$A$4:$A$867,A27,'Cash flow'!$B$4:$B$867,J27-1))/(SUMIFS('Cash flow'!$L$4:$L$867,'Cash flow'!$A$4:$A$867,A27,'Cash flow'!$B$4:$B$867,J27)-SUMIFS('Cash flow'!$L$4:$L$867,'Cash flow'!$A$4:$A$867,A27,'Cash flow'!$B$4:$B$867,J27-1))) -> 19.740642 | M27: =COUNTIFS('Cash flow'!$A$4:$A$867,A27,'Cash flow'!$Q$4:$Q$867,1) -> 21 | N27: =SUMPRODUCT(MAX(('Cash flow'!$A$4:$A$867=A27)*('Cash flow'!$Q$4:$Q$867=1)*('Cash flow'!$B$4:$B$867+1))) -> 21 | O27: =IF(OR(NOT(C27),M27=0,N27=Controls!$B$12),"",N27) -> 21 | P27: =IF(NOT(C27),"NO_FLOWS",IF(M27=0,"NO_INVESTMENT",IF(N27=Controls!$B$12,"NOT_RECOVERED",""))) | Q27: =IF(O27="","",(O27-1)+(-SUMIFS('Cash flow'!$O$4:$O$867,'Cash flow'!$A$4:$A$867,A27,'Cash flow'!$B$4:$B$867,O27-1))/(SUMIFS('Cash flow'!$O$4:$O$867,'Cash flow'!$A$4:$A$867,A27,'Cash flow'!$B$4:$B$867,O27)-SUMIFS('Cash flow'!$O$4:$O$867,'Cash flow'!$A$4:$A$867,A27,'Cash flow'!$B$4:$B$867,O27-1))) -> 20.119448 | R27: =IFERROR(INDEX('Domain reference'!$C$40:$C$249,MATCH(Controls!$B$3&"|"&A27,'Domain reference'!$A$40:$A$249,0)),"") -> 230132.79 | S27: =IFERROR(INDEX('Domain reference'!$D$40:$D$249,MATCH(Controls!$B$3&"|"&A27,'Domain reference'!$A$40:$A$249,0)),"") -> 20 | T27: =IFERROR(INDEX('Domain reference'!$E$40:$E$249,MATCH(Controls!$B$3&"|"&A27,'Domain reference'!$A$40:$A$249,0)),"") -> 21 | U27: =IF(LEN(Controls!$B$4)>0,TRUE(),IF(B27=0,AND(R27="",E27=0),AND(ABS(N(G27)-N(R27))<0.005,ISNUMBER(G27)=ISNUMBER(R27),IF(S27=-1,J27="",J27=S27),IF(T27=-1,O27="",O27=T27)))) -> TRUE

Sheet Cash flow
A1: The dated cash flow of every initiative in the selected scenario (formulas only)
A2: Rows past the horizon or for initiatives outside the scenario are 0. costs = planned rows whose half-open range holds the period; the four classes enter the flow; capacity hours and the avoided cost beside never do.
A3: initiative_id | B3: period_index | C3: member | D3: active | E3: costs | F3: cash | G3: revenue | H3: avoided_cost_realised | I3: capacity_converted | J3: benefits | K3: net_cash_flow | L3: cumulative | M3: discount_factor | N3: discounted | O3: cumulative_discounted | P3: negative | Q3: negative_discounted
A4: init-001 | B4: 0 | C4: =IF(COUNTIF('Scenario inputs'!$A$4:$A$213,Controls!$B$3&"|"&A4)>0,1,0) -> 1 | D4: =IF(AND(C4=1,B4<Controls!$B$12),1,0) -> 1 | E4: =IF(D4=1,SUMPRODUCT((Costs!$B$4:$B$903=A4)*(Costs!$D$4:$D$903="planned")*(Costs!$J$4:$J$903<=B4)*(Costs!$K$4:$K$903>B4)*Costs!$E$4:$E$903),0) -> 783200 | F4: =IF(D4=1,SUMIFS(Benefits!$S$4:$S$703,Benefits!$B$4:$B$703,A4,Benefits!$F$4:$F$703,B4,Benefits!$R$4:$R$703,"cash"),0) -> 0 | G4: =IF(D4=1,SUMIFS(Benefits!$S$4:$S$703,Benefits!$B$4:$B$703,A4,Benefits!$F$4:$F$703,B4,Benefits!$R$4:$R$703,"revenue"),0) -> 0 | H4: =IF(D4=1,SUMIFS(Benefits!$S$4:$S$703,Benefits!$B$4:$B$703,A4,Benefits!$F$4:$F$703,B4,Benefits!$R$4:$R$703,"avoided_cost_realised"),0) -> 0 | I4: =IF(D4=1,SUMIFS(Benefits!$S$4:$S$703,Benefits!$B$4:$B$703,A4,Benefits!$F$4:$F$703,B4,Benefits!$R$4:$R$703,"capacity_converted"),0) -> 0 | J4: =SUM(F4:I4) -> 0 | K4: =J4-E4 -> -783200 | L4: =IF(D4=1,K4,0) -> -783200 | M4: =IF(D4=1,1/(1+Controls!$B$11)^B4,0) -> 1 | N4: =K4*M4 -> -783200 | O4: =IF(D4=1,N4,0) -> -783200 | P4: =IF(AND(D4=1,L4<0),1,0) -> 1 | Q4: =IF(AND(D4=1,O4<0),1,0) -> 1
A5: init-001 | B5: 1 | C5: =IF(COUNTIF('Scenario inputs'!$A$4:$A$213,Controls!$B$3&"|"&A5)>0,1,0) -> 1 | D5: =IF(AND(C5=1,B5<Controls!$B$12),1,0) -> 1 | E5: =IF(D5=1,SUMPRODUCT((Costs!$B$4:$B$903=A5)*(Costs!$D$4:$D$903="planned")*(Costs!$J$4:$J$903<=B5)*(Costs!$K$4:$K$903>B5)*Costs!$E$4:$E$903),0) -> 161800 | F5: =IF(D5=1,SUMIFS(Benefits!$S$4:$S$703,Benefits!$B$4:$B$703,A5,Benefits!$F$4:$F$703,B5,Benefits!$R$4:$R$703,"cash"),0) -> 0 | G5: =IF(D5=1,SUMIFS(Benefits!$S$4:$S$703,Benefits!$B$4:$B$703,A5,Benefits!$F$4:$F$703,B5,Benefits!$R$4:$R$703,"revenue"),0) -> 0 | H5: =IF(D5=1,SUMIFS(Benefits!$S$4:$S$703,Benefits!$B$4:$B$703,A5,Benefits!$F$4:$F$703,B5,Benefits!$R$4:$R$703,"avoided_cost_realised"),0) -> 2669.6215 | I5: =IF(D5=1,SUMIFS(Benefits!$S$4:$S$703,Benefits!$B$4:$B$703,A5,Benefits!$F$4:$F$703,B5,Benefits!$R$4:$R$703,"capacity_converted"),0) -> 1497.3339 | J5: =SUM(F5:I5) -> 4166.9554 | K5: =J5-E5 -> -157633.04 | L5: =IF(D5=1,L4+K5,0) -> -940833.04 | M5: =IF(D5=1,1/(1+Controls!$B$11)^B5,0) -> 0.99360713 | N5: =K5*M5 -> -156625.32 | O5: =IF(D5=1,O4+N5,0) -> -939825.32 | P5: =IF(AND(D5=1,L5<0),1,0) -> 1 | Q5: =IF(AND(D5=1,O5<0),1,0) -> 1
A6: init-001 | B6: 2 | C6: =IF(COUNTIF('Scenario inputs'!$A$4:$A$213,Controls!$B$3&"|"&A6)>0,1,0) -> 1 | D6: =IF(AND(C6=1,B6<Controls!$B$12),1,0) -> 1 | E6: =IF(D6=1,SUMPRODUCT((Costs!$B$4:$B$903=A6)*(Costs!$D$4:$D$903="planned")*(Costs!$J$4:$J$903<=B6)*(Costs!$K$4:$K$903>B6)*Costs!$E$4:$E$903),0) -> 18000 | F6: =IF(D6=1,SUMIFS(Benefits!$S$4:$S$703,Benefits!$B$4:$B$703,A6,Benefits!$F$4:$F$703,B6,Benefits!$R$4:$R$703,"cash"),0) -> 4005.3251 | G6: =IF(D6=1,SUMIFS(Benefits!$S$4:$S$703,Benefits!$B$4:$B$703,A6,Benefits!$F$4:$F$703,B6,Benefits!$R$4:$R$703,"revenue"),0) -> 0 | H6: =IF(D6=1,SUMIFS(Benefits!$S$4:$S$703,Benefits!$B$4:$B$703,A6,Benefits!$F$4:$F$703,B6,Benefits!$R$4:$R$703,"avoided_cost_realised"),0) -> 8008.9393 | I6: =IF(D6=1,SUMIFS(Benefits!$S$4:$S$703,Benefits!$B$4:$B$703,A6,Benefits!$F$4:$F$703,B6,Benefits!$R$4:$R$703,"capacity_converted"),0) -> 4492.0435 | J6: =SUM(F6:I6) -> 16506.308 | K6: =J6-E6 -> -1493.6922 | L6: =IF(D6=1,L5+K6,0) -> -942326.74 | M6: =IF(D6=1,1/(1+Controls!$B$11)^B6,0) -> 0.98725513 | N6: =K6*M6 -> -1474.6552 | O6: =IF(D6=1,O5+N6,0) -> -941299.97 | P6: =IF(AND(D6=1,L6<0),1,0) -> 1 | Q6: =IF(AND(D6=1,O6<0),1,0) -> 1
A7: init-001 | B7: 3 | C7: =IF(COUNTIF('Scenario inputs'!$A$4:$A$213,Controls!$B$3&"|"&A7)>0,1,0) -> 1 | D7: =IF(AND(C7=1,B7<Controls!$B$12),1,0) -> 1 | E7: =IF(D7=1,SUMPRODUCT((Costs!$B$4:$B$903=A7)*(Costs!$D$4:$D$903="planned")*(Costs!$J$4:$J$903<=B7)*(Costs!$K$4:$K$903>B7)*Costs!$E$4:$E$903),0) -> 18000 | F7: =IF(D7=1,SUMIFS(Benefits!$S$4:$S$703,Benefits!$B$4:$B$703,A7,Benefits!$F$4:$F$703,B7,Benefits!$R$4:$R$703,"cash"),0) -> 12016.087 | G7: =IF(D7=1,SUMIFS(Benefits!$S$4:$S$703,Benefits!$B$4:$B$703,A7,Benefits!$F$4:$F$703,B7,Benefits!$R$4:$R$703,"revenue"),0) -> 0 | H7: =IF(D7=1,SUMIFS(Benefits!$S$4:$S$703,Benefits!$B$4:$B$703,A7,Benefits!$F$4:$F$703,B7,Benefits!$R$4:$R$703,"avoided_cost_realised"),0) -> 16017.879 | I7: =IF(D7=1,SUMIFS(Benefits!$S$4:$S$703,Benefits!$B$4:$B$703,A7,Benefits!$F$4:$F$703,B7,Benefits!$R$4:$R$703,"capacity_converted"),0) -> 8984.087 | J7: =SUM(F7:I7) -> 37018.053 | K7: =J7-E7 -> 19018.053 | L7: =IF(D7=1,L6+K7,0) -> -923308.68 | M7: =IF(D7=1,1/(1+Controls!$B$11)^B7,0) -> 0.98094374 | N7: =K7*M7 -> 18655.64 | O7: =IF(D7=1,O6+N7,0) -> -922644.33 | P7: =IF(AND(D7=1,L7<0),1,0) -> 1 | Q7: =IF(AND(D7=1,O7<0),1,0) -> 1
A8: init-001 | B8: 4 | C8: =IF(COUNTIF('Scenario inputs'!$A$4:$A$213,Controls!$B$3&"|"&A8)>0,1,0) -> 1 | D8: =IF(AND(C8=1,B8<Controls!$B$12),1,0) -> 1 | E8: =IF(D8=1,SUMPRODUCT((Costs!$B$4:$B$903=A8)*(Costs!$D$4:$D$903="planned")*(Costs!$J$4:$J$903<=B8)*(Costs!$K$4:$K$903>B8)*Costs!$E$4:$E$903),0) -> 18000 | F8: =IF(D8=1,SUMIFS(Benefits!$S$4:$S$703,Benefits!$B$4:$B$703,A8,Benefits!$F$4:$F$703,B8,Benefits!$R$4:$R$703,"cash"),0) -> 24032.175 | G8: =IF(D8=1,SUMIFS(Benefits!$S$4:$S$703,Benefits!$B$4:$B$703,A8,Benefits!$F$4:$F$703,B8,Benefits!$R$4:$R$703,"revenue"),0) -> 0 | H8: =IF(D8=1,SUMIFS(Benefits!$S$4:$S$703,Benefits!$B$4:$B$703,A8,Benefits!$F$4:$F$703,B8,Benefits!$R$4:$R$703,"avoided_cost_realised"),0) -> 26696.439 | I8: =IF(D8=1,SUMIFS(Benefits!$S$4:$S$703,Benefits!$B$4:$B$703,A8,Benefits!$F$4:$F$703,B8,Benefits!$R$4:$R$703,"capacity_converted"),0) -> 14973.464 | J8: =SUM(F8:I8) -> 65702.078 | K8: =J8-E8 -> 47702.078 | L8: =IF(D8=1,L7+K8,0) -> -875606.61 | M8: =IF(D8=1,1/(1+Controls!$B$11)^B8,0) -> 0.9746727 | N8: =K8*M8 -> 46493.913 | O8: =IF(D8=1,O7+N8,0) -> -876150.42 | P8: =IF(AND(D8=1,L8<0),1,0) -> 1 | Q8: =IF(AND(D8=1,O8<0),1,0) -> 1
A9: init-001 | B9: 5 | C9: =IF(COUNTIF('Scenario inputs'!$A$4:$A$213,Controls!$B$3&"|"&A9)>0,1,0) -> 1 | D9: =IF(AND(C9=1,B9<Controls!$B$12),1,0) -> 1 | E9: =IF(D9=1,SUMPRODUCT((Costs!$B$4:$B$903=A9)*(Costs!$D$4:$D$903="planned")*(Costs!$J$4:$J$903<=B9)*(Costs!$K$4:$K$903>B9)*Costs!$E$4:$E$903),0) -> 18000 | F9: =IF(D9=1,SUMIFS(Benefits!$S$4:$S$703,Benefits!$B$4:$B$703,A9,Benefits!$F$4:$F$703,B9,Benefits!$R$4:$R$703,"cash"),0) -> 40053.587 | G9: =IF(D9=1,SUMIFS(Benefits!$S$4:$S$703,Benefits!$B$4:$B$703,A9,Benefits!$F$4:$F$703,B9,Benefits!$R$4:$R$703,"revenue"),0) -> 0 | H9: =IF(D9=1,SUMIFS(Benefits!$S$4:$S$703,Benefits!$B$4:$B$703,A9,Benefits!$F$4:$F$703,B9,Benefits!$R$4:$R$703,"avoided_cost_realised"),0) -> 40044.622 | I9: =IF(D9=1,SUMIFS(Benefits!$S$4:$S$703,Benefits!$B$4:$B$703,A9,Benefits!$F$4:$F$703,B9,Benefits!$R$4:$R$703,"capacity_converted"),0) -> 22460.176 | J9: =SUM(F9:I9) -> 102558.38 | K9: =J9-E9 -> 84558.385 | L9: =IF(D9=1,L8+K9,0) -> -791048.22 | M9: =IF(D9=1,1/(1+Controls!$B$11)^B9,0) -> 0.96844174 | N9: =K9*M9 -> 81889.869 | O9: =IF(D9=1,O8+N9,0) -> -794260.55 | P9: =IF(AND(D9=1,L9<0),1,0) -> 1 | Q9: =IF(AND(D9=1,O9<0),1,0) -> 1
A10: init-001 | B10: 6 | C10: =IF(COUNTIF('Scenario inputs'!$A$4:$A$213,Controls!$B$3&"|"&A10)>0,1,0) -> 1 | D10: =IF(AND(C10=1,B10<Controls!$B$12),1,0) -> 1 | E10: =IF(D10=1,SUMPRODUCT((Costs!$B$4:$B$903=A10)*(Costs!$D$4:$D$903="planned")*(Costs!$J$4:$J$903<=B10)*(Costs!$K$4:$K$903>B10)*Costs!$E$4:$E$903),0) -> 18000 | F10: =IF(D10=1,SUMIFS(Benefits!$S$4:$S$703,Benefits!$B$4:$B$703,A10,Benefits!$F$4:$F$703,B10,Benefits!$R$4:$R$703,"cash"),0) -> 60080.325 | G10: =IF(D10=1,SUMIFS(Benefits!$S$4:$S$703,Benefits!$B$4:$B$703,A10,Benefits!$F$4:$F$703,B10,Benefits!$R$4:$R$703,"revenue"),0) -> 0 | H10: =IF(D10=1,SUMIFS(Benefits!$S$4:$S$703,Benefits!$B$4:$B$703,A10,Benefits!$F$4:$F$703,B10,Benefits!$R$4:$R$703,"avoided_cost_realised"),0) -> 56062.5 | I10: =IF(D10=1,SUMIFS(Benefits!$S$4:$S$703,Benefits!$B$4:$B$703,A10,Benefits!$F$4:$F$703,B10,Benefits!$R$4:$R$703,"capacity_converted"),0) -> 31444.263 | J10: =SUM(F10:I10) -> 147587.09 | K10: =J10-E10 -> 129587.09 | L10: =IF(D10=1,L9+K10,0) -> -661461.13 | M10: =IF(D10=1,1/(1+Controls!$B$11)^B10,0) -> 0.96225062 | N10: =K10*M10 -> 124695.26 | O10: =IF(D10=1,O9+N10,0) -> -669565.29 | P10: =IF(AND(D10=1,L10<0),1,0) -> 1 | Q10: =IF(AND(D10=1,O10<0),1,0) -> 1
A11: init-001 | B11: 7 | C11: =IF(COUNTIF('Scenario inputs'!$A$4:$A$213,Controls!$B$3&"|"&A11)>0,1,0) -> 1 | D11: =IF(AND(C11=1,B11<Controls!$B$12),1,0) -> 1 | E11: =IF(D11=1,SUMPRODUCT((Costs!$B$4:$B$903=A11)*(Costs!$D$4:$D$903="planned")*(Costs!$J$4:$J$903<=B11)*(Costs!$K$4:$K$903>B11)*Costs!$E$4:$E$903),0) -> 18300 | F11: =IF(D11=1,SUMIFS(Benefits!$S$4:$S$703,Benefits!$B$4:$B$703,A11,Benefits!$F$4:$F$703,B11,Benefits!$R$4:$R$703,"cash"),0) -> 84112.5 | G11: =IF(D11=1,SUMIFS(Benefits!$S$4:$S$703,Benefits!$B$4:$B$703,A11,Benefits!$F$4:$F$703,B11,Benefits!$R$4:$R$703,"revenue"),0) -> 0 | H11: =IF(D11=1,SUMIFS(Benefits!$S$4:$S$703,Benefits!$B$4:$B$703,A11,Benefits!$F$4:$F$703,B11,Benefits!$R$4:$R$703,"avoided_cost_realised"),0) -> 74750 | I11: =IF(D11=1,SUMIFS(Benefits!$S$4:$S$703,Benefits!$B$4:$B$703,A11,Benefits!$F$4:$F$703,B11,Benefits!$R$4:$R$703,"capacity_converted"),0) -> 41925.683 | J11: =SUM(F11:I11) -> 200788.18 | K11: =J11-E11 -> 182488.18 | L11: =IF(D11=1,L10+K11,0) -> -478972.95 | M11: =IF(D11=1,1/(1+Controls!$B$11)^B11,0) -> 0.95609908 | N11: =K11*M11 -> 174476.78 | O11: =IF(D11=1,O10+N11,0) -> -495088.51 | P11: =IF(AND(D11=1,L11<0),1,0) -> 1 | Q11: =IF(AND(D11=1,O11<0),1,0) -> 1
A12: init-001 | B12: 8 | C12: =IF(COUNTIF('Scenario inputs'!$A$4:$A$213,Controls!$B$3&"|"&A12)>0,1,0) -> 1 | D12: =IF(AND(C12=1,B12<Controls!$B$12),1,0) -> 1 | E12: =IF(D12=1,SUMPRODUCT((Costs!$B$4:$B$903=A12)*(Costs!$D$4:$D$903="planned")*(Costs!$J$4:$J$903<=B12)*(Costs!$K$4:$K$903>B12)*Costs!$E$4:$E$903),0) -> 18300 | F12: =IF(D12=1,SUMIFS(Benefits!$S$4:$S$703,Benefits!$B$4:$B$703,A12,Benefits!$F$4:$F$703,B12,Benefits!$R$4:$R$703,"cash"),0) -> 112150 | G12: =IF(D12=1,SUMIFS(Benefits!$S$4:$S$703,Benefits!$B$4:$B$703,A12,Benefits!$F$4:$F$703,B12,Benefits!$R$4:$R$703,"revenue"),0) -> 0 | H12: =IF(D12=1,SUMIFS(Benefits!$S$4:$S$703,Benefits!$B$4:$B$703,A12,Benefits!$F$4:$F$703,B12,Benefits!$R$4:$R$703,"avoided_cost_realised"),0) -> 74750 | I12: =IF(D12=1,SUMIFS(Benefits!$S$4:$S$703,Benefits!$B$4:$B$703,A12,Benefits!$F$4:$F$703,B12,Benefits!$R$4:$R$703,"capacity_converted"),0) -> 41925.683 | J12: =SUM(F12:I12) -> 228825.68 | K12: =J12-E12 -> 210525.68 | L12: =IF(D12=1,L11+K12,0) -> -268447.27 | M12: =IF(D12=1,1/(1+Controls!$B$11)^B12,0) -> 0.94998686 | N12: =K12*M12 -> 199996.63 | O12: =IF(D12=1,O11+N12,0) -> -295091.88 | P12: =IF(AND(D12=1,L12<0),1,0) -> 1 | Q12: =IF(AND(D12=1,O12<0),1,0) -> 1
A13: init-001 | B13: 9 | C13: =IF(COUNTIF('Scenario inputs'!$A$4:$A$213,Controls!$B$3&"|"&A13)>0,1,0) -> 1 | D13: =IF(AND(C13=1,B13<Controls!$B$12),1,0) -> 1 | E13: =IF(D13=1,SUMPRODUCT((Costs!$B$4:$B$903=A13)*(Costs!$D$4:$D$903="planned")*(Costs!$J$4:$J$903<=B13)*(Costs!$K$4:$K$903>B13)*Costs!$E$4:$E$903),0) -> 18300 | F13: =IF(D13=1,SUMIFS(Benefits!$S$4:$S$703,Benefits!$B$4:$B$703,A13,Benefits!$F$4:$F$703,B13,Benefits!$R$4:$R$703,"cash"),0) -> 112150 | G13: =IF(D13=1,SUMIFS(Benefits!$S$4:$S$703,Benefits!$B$4:$B$703,A13,Benefits!$F$4:$F$703,B13,Benefits!$R$4:$R$703,"revenue"),0) -> 0 | H13: =IF(D13=1,SUMIFS(Benefits!$S$4:$S$703,Benefits!$B$4:$B$703,A13,Benefits!$F$4:$F$703,B13,Benefits!$R$4:$R$703,"avoided_cost_realised"),0) -> 74750 | I13: =IF(D13=1,SUMIFS(Benefits!$S$4:$S$703,Benefits!$B$4:$B$703,A13,Benefits!$F$4:$F$703,B13,Benefits!$R$4:$R$703,"capacity_converted"),0) -> 41925.683 | J13: =SUM(F13:I13) -> 228825.68 | K13: =J13-E13 -> 210525.68 | L13: =IF(D13=1,L12+K13,0) -> -57921.583 | M13: =IF(D13=1,1/(1+Controls!$B$11)^B13,0) -> 0.94391372 | N13: =K13*M13 -> 198718.08 | O13: =IF(D13=1,O12+N13,0) -> -96373.795 | P13: =IF(AND(D13=1,L13<0),1,0) -> 1 | Q13: =IF(AND(D13=1,O13<0),1,0) -> 1
A14: init-001 | B14: 10 | C14: =IF(COUNTIF('Scenario inputs'!$A$4:$A$213,Controls!$B$3&"|"&A14)>0,1,0) -> 1 | D14: =IF(AND(C14=1,B14<Controls!$B$12),1,0) -> 1 | E14: =IF(D14=1,SUMPRODUCT((Costs!$B$4:$B$903=A14)*(Costs!$D$4:$D$903="planned")*(Costs!$J$4:$J$903<=B14)*(Costs!$K$4:$K$903>B14)*Costs!$E$4:$E$903),0) -> 18300 | F14: =IF(D14=1,SUMIFS(Benefits!$S$4:$S$703,Benefits!$B$4:$B$703,A14,Benefits!$F$4:$F$703,B14,Benefits!$R$4:$R$703,"cash"),0) -> 112150 | G14: =IF(D14=1,SUMIFS(Benefits!$S$4:$S$703,Benefits!$B$4:$B$703,A14,Benefits!$F$4:$F$703,B14,Benefits!$R$4:$R$703,"revenue"),0) -> 0 | H14: =IF(D14=1,SUMIFS(Benefits!$S$4:$S$703,Benefits!$B$4:$B$703,A14,Benefits!$F$4:$F$703,B14,Benefits!$R$4:$R$703,"avoided_cost_realised"),0) -> 74750 | I14: =IF(D14=1,SUMIFS(Benefits!$S$4:$S$703,Benefits!$B$4:$B$703,A14,Benefits!$F$4:$F$703,B14,Benefits!$R$4:$R$703,"capacity_converted"),0) -> 41925.683 | J14: =SUM(F14:I14) -> 228825.68 | K14: =J14-E14 -> 210525.68 | L14: =IF(D14=1,L13+K14,0) -> 152604.1 | M14: =IF(D14=1,1/(1+Controls!$B$11)^B14,0) -> 0.93787941 | N14: =K14*M14 -> 197447.7 | O14: =IF(D14=1,O13+N14,0) -> 101073.91 | P14: =IF(AND(D14=1,L14<0),1,0) -> 0 | Q14: =IF(AND(D14=1,O14<0),1,0) -> 0
A15: init-001 | B15: 11 | C15: =IF(COUNTIF('Scenario inputs'!$A$4:$A$213,Controls!$B$3&"|"&A15)>0,1,0) -> 1 | D15: =IF(AND(C15=1,B15<Controls!$B$12),1,0) -> 1 | E15: =IF(D15=1,SUMPRODUCT((Costs!$B$4:$B$903=A15)*(Costs!$D$4:$D$903="planned")*(Costs!$J$4:$J$903<=B15)*(Costs!$K$4:$K$903>B15)*Costs!$E$4:$E$903),0) -> 18300 | F15: =IF(D15=1,SUMIFS(Benefits!$S$4:$S$703,Benefits!$B$4:$B$703,A15,Benefits!$F$4:$F$703,B15,Benefits!$R$4:$R$703,"cash"),0) -> 112150 | G15: =IF(D15=1,SUMIFS(Benefits!$S$4:$S$703,Benefits!$B$4:$B$703,A15,Benefits!$F$4:$F$703,B15,Benefits!$R$4:$R$703,"revenue"),0) -> 0 | H15: =IF(D15=1,SUMIFS(Benefits!$S$4:$S$703,Benefits!$B$4:$B$703,A15,Benefits!$F$4:$F$703,B15,Benefits!$R$4:$R$703,"avoided_cost_realised"),0) -> 74750 | I15: =IF(D15=1,SUMIFS(Benefits!$S$4:$S$703,Benefits!$B$4:$B$703,A15,Benefits!$F$4:$F$703,B15,Benefits!$R$4:$R$703,"capacity_converted"),0) -> 41925.683 | J15: =SUM(F15:I15) -> 228825.68 | K15: =J15-E15 -> 210525.68 | L15: =IF(D15=1,L14+K15,0) -> 363129.78 | M15: =IF(D15=1,1/(1+Controls!$B$11)^B15,0) -> 0.93188367 | N15: =K15*M15 -> 196185.45 | O15: =IF(D15=1,O14+N15,0) -> 297259.35 | P15: =IF(AND(D15=1,L15<0),1,0) -> 0 | Q15: =IF(AND(D15=1,O15<0),1,0) -> 0
A16: init-001 | B16: 12 | C16: =IF(COUNTIF('Scenario inputs'!$A$4:$A$213,Controls!$B$3&"|"&A16)>0,1,0) -> 1 | D16: =IF(AND(C16=1,B16<Controls!$B$12),1,0) -> 1 | E16: =IF(D16=1,SUMPRODUCT((Costs!$B$4:$B$903=A16)*(Costs!$D$4:$D$903="planned")*(Costs!$J$4:$J$903<=B16)*(Costs!$K$4:$K$903>B16)*Costs!$E$4:$E$903),0) -> 18300 | F16: =IF(D16=1,SUMIFS(Benefits!$S$4:$S$703,Benefits!$B$4:$B$703,A16,Benefits!$F$4:$F$703,B16,Benefits!$R$4:$R$703,"cash"),0) -> 112150 | G16: =IF(D16=1,SUMIFS(Benefits!$S$4:$S$703,Benefits!$B$4:$B$703,A16,Benefits!$F$4:$F$703,B16,Benefits!$R$4:$R$703,"revenue"),0) -> 0 | H16: =IF(D16=1,SUMIFS(Benefits!$S$4:$S$703,Benefits!$B$4:$B$703,A16,Benefits!$F$4:$F$703,B16,Benefits!$R$4:$R$703,"avoided_cost_realised"),0) -> 74750 | I16: =IF(D16=1,SUMIFS(Benefits!$S$4:$S$703,Benefits!$B$4:$B$703,A16,Benefits!$F$4:$F$703,B16,Benefits!$R$4:$R$703,"capacity_converted"),0) -> 41925.683 | J16: =SUM(F16:I16) -> 228825.68 | K16: =J16-E16 -> 210525.68 | L16: =IF(D16=1,L15+K16,0) -> 573655.47 | M16: =IF(D16=1,1/(1+Controls!$B$11)^B16,0) -> 0.92592626 | N16: =K16*M16 -> 194931.26 | O16: =IF(D16=1,O15+N16,0) -> 492190.61 | P16: =IF(AND(D16=1,L16<0),1,0) -> 0 | Q16: =IF(AND(D16=1,O16<0),1,0) -> 0
... A39: init-001 | B39: 35 | C39: =IF(COUNTIF('Scenario inputs'!$A$4:$A$213,Controls!$B$3&"|"&A39)>0,1,0) -> 1 | D39: =IF(AND(C39=1,B39<Controls!$B$12),1,0) -> 1 | E39: =IF(D39=1,SUMPRODUCT((Costs!$B$4:$B$903=A39)*(Costs!$D$4:$D$903="planned")*(Costs!$J$4:$J$903<=B39)*(Costs!$K$4:$K$903>B39)*Costs!$E$4:$E$903),0) -> 0 | F39: =IF(D39=1,SUMIFS(Benefits!$S$4:$S$703,Benefits!$B$4:$B$703,A39,Benefits!$F$4:$F$703,B39,Benefits!$R$4:$R$703,"cash"),0) -> 0 | G39: =IF(D39=1,SUMIFS(Benefits!$S$4:$S$703,Benefits!$B$4:$B$703,A39,Benefits!$F$4:$F$703,B39,Benefits!$R$4:$R$703,"revenue"),0) -> 0 | H39: =IF(D39=1,SUMIFS(Benefits!$S$4:$S$703,Benefits!$B$4:$B$703,A39,Benefits!$F$4:$F$703,B39,Benefits!$R$4:$R$703,"avoided_cost_realised"),0) -> 0 | I39: =IF(D39=1,SUMIFS(Benefits!$S$4:$S$703,Benefits!$B$4:$B$703,A39,Benefits!$F$4:$F$703,B39,Benefits!$R$4:$R$703,"capacity_converted"),0) -> 0 | J39: =SUM(F39:I39) -> 0 | K39: =J39-E39 -> 0 | L39: =IF(D39=1,L38+K39,0) -> 667505.47 | M39: =IF(D39=1,1/(1+Controls!$B$11)^B39,0) -> 0.79894062 | N39: =K39*M39 -> 0 | O39: =IF(D39=1,O38+N39,0) -> 578533.26 | P39: =IF(AND(D39=1,L39<0),1,0) -> 0 | Q39: =IF(AND(D39=1,O39<0),1,0) -> 0
A40: init-002 | B40: 0 | C40: =IF(COUNTIF('Scenario inputs'!$A$4:$A$213,Controls!$B$3&"|"&A40)>0,1,0) -> 1 | D40: =IF(AND(C40=1,B40<Controls!$B$12),1,0) -> 1 | E40: =IF(D40=1,SUMPRODUCT((Costs!$B$4:$B$903=A40)*(Costs!$D$4:$D$903="planned")*(Costs!$J$4:$J$903<=B40)*(Costs!$K$4:$K$903>B40)*Costs!$E$4:$E$903),0) -> 223650 | F40: =IF(D40=1,SUMIFS(Benefits!$S$4:$S$703,Benefits!$B$4:$B$703,A40,Benefits!$F$4:$F$703,B40,Benefits!$R$4:$R$703,"cash"),0) -> 0 | G40: =IF(D40=1,SUMIFS(Benefits!$S$4:$S$703,Benefits!$B$4:$B$703,A40,Benefits!$F$4:$F$703,B40,Benefits!$R$4:$R$703,"revenue"),0) -> 0 | H40: =IF(D40=1,SUMIFS(Benefits!$S$4:$S$703,Benefits!$B$4:$B$703,A40,Benefits!$F$4:$F$703,B40,Benefits!$R$4:$R$703,"avoided_cost_realised"),0) -> 0 | I40: =IF(D40=1,SUMIFS(Benefits!$S$4:$S$703,Benefits!$B$4:$B$703,A40,Benefits!$F$4:$F$703,B40,Benefits!$R$4:$R$703,"capacity_converted"),0) -> 0 | J40: =SUM(F40:I40) -> 0 | K40: =J40-E40 -> -223650 | L40: =IF(D40=1,K40,0) -> -223650 | M40: =IF(D40=1,1/(1+Controls!$B$11)^B40,0) -> 1 | N40: =K40*M40 -> -223650 | O40: =IF(D40=1,N40,0) -> -223650 | P40: =IF(AND(D40=1,L40<0),1,0) -> 1 | Q40: =IF(AND(D40=1,O40<0),1,0) -> 1
A41: init-002 | B41: 1 | C41: =IF(COUNTIF('Scenario inputs'!$A$4:$A$213,Controls!$B$3&"|"&A41)>0,1,0) -> 1 | D41: =IF(AND(C41=1,B41<Controls!$B$12),1,0) -> 1 | E41: =IF(D41=1,SUMPRODUCT((Costs!$B$4:$B$903=A41)*(Costs!$D$4:$D$903="planned")*(Costs!$J$4:$J$903<=B41)*(Costs!$K$4:$K$903>B41)*Costs!$E$4:$E$903),0) -> 141450 | F41: =IF(D41=1,SUMIFS(Benefits!$S$4:$S$703,Benefits!$B$4:$B$703,A41,Benefits!$F$4:$F$703,B41,Benefits!$R$4:$R$703,"cash"),0) -> 0 | G41: =IF(D41=1,SUMIFS(Benefits!$S$4:$S$703,Benefits!$B$4:$B$703,A41,Benefits!$F$4:$F$703,B41,Benefits!$R$4:$R$703,"revenue"),0) -> 0 | H41: =IF(D41=1,SUMIFS(Benefits!$S$4:$S$703,Benefits!$B$4:$B$703,A41,Benefits!$F$4:$F$703,B41,Benefits!$R$4:$R$703,"avoided_cost_realised"),0) -> 0 | I41: =IF(D41=1,SUMIFS(Benefits!$S$4:$S$703,Benefits!$B$4:$B$703,A41,Benefits!$F$4:$F$703,B41,Benefits!$R$4:$R$703,"capacity_converted"),0) -> 0 | J41: =SUM(F41:I41) -> 0 | K41: =J41-E41 -> -141450 | L41: =IF(D41=1,L40+K41,0) -> -365100 | M41: =IF(D41=1,1/(1+Controls!$B$11)^B41,0) -> 0.99360713 | N41: =K41*M41 -> -140545.73 | O41: =IF(D41=1,O40+N41,0) -> -364195.73 | P41: =IF(AND(D41=1,L41<0),1,0) -> 1 | Q41: =IF(AND(D41=1,O41<0),1,0) -> 1
A42: init-002 | B42: 2 | C42: =IF(COUNTIF('Scenario inputs'!$A$4:$A$213,Controls!$B$3&"|"&A42)>0,1,0) -> 1 | D42: =IF(AND(C42=1,B42<Controls!$B$12),1,0) -> 1 | E42: =IF(D42=1,SUMPRODUCT((Costs!$B$4:$B$903=A42)*(Costs!$D$4:$D$903="planned")*(Costs!$J$4:$J$903<=B42)*(Costs!$K$4:$K$903>B42)*Costs!$E$4:$E$903),0) -> 316400 | F42: =IF(D42=1,SUMIFS(Benefits!$S$4:$S$703,Benefits!$B$4:$B$703,A42,Benefits!$F$4:$F$703,B42,Benefits!$R$4:$R$703,"cash"),0) -> 4608.8917 | G42: =IF(D42=1,SUMIFS(Benefits!$S$4:$S$703,Benefits!$B$4:$B$703,A42,Benefits!$F$4:$F$703,B42,Benefits!$R$4:$R$703,"revenue"),0) -> 0 | H42: =IF(D42=1,SUMIFS(Benefits!$S$4:$S$703,Benefits!$B$4:$B$703,A42,Benefits!$F$4:$F$703,B42,Benefits!$R$4:$R$703,"avoided_cost_realised"),0) -> 0 | I42: =IF(D42=1,SUMIFS(Benefits!$S$4:$S$703,Benefits!$B$4:$B$703,A42,Benefits!$F$4:$F$703,B42,Benefits!$R$4:$R$703,"capacity_converted"),0) -> 0 | J42: =SUM(F42:I42) -> 4608.8917 | K42: =J42-E42 -> -311791.11 | L42: =IF(D42=1,L41+K42,0) -> -676891.11 | M42: =IF(D42=1,1/(1+Controls!$B$11)^B42,0) -> 0.98725513 | N42: =K42*M42 -> -307817.37 | O42: =IF(D42=1,O41+N42,0) -> -672013.1 | P42: =IF(AND(D42=1,L42<0),1,0) -> 1 | Q42: =IF(AND(D42=1,O42<0),1,0) -> 1
A43: init-002 | B43: 3 | C43: =IF(COUNTIF('Scenario inputs'!$A$4:$A$213,Controls!$B$3&"|"&A43)>0,1,0) -> 1 | D43: =IF(AND(C43=1,B43<Controls!$B$12),1,0) -> 1 | E43: =IF(D43=1,SUMPRODUCT((Costs!$B$4:$B$903=A43)*(Costs!$D$4:$D$903="planned")*(Costs!$J$4:$J$903<=B43)*(Costs!$K$4:$K$903>B43)*Costs!$E$4:$E$903),0) -> 12000 | F43: =IF(D43=1,SUMIFS(Benefits!$S$4:$S$703,Benefits!$B$4:$B$703,A43,Benefits!$F$4:$F$703,B43,Benefits!$R$4:$R$703,"cash"),0) -> 13826.804 | G43: =IF(D43=1,SUMIFS(Benefits!$S$4:$S$703,Benefits!$B$4:$B$703,A43,Benefits!$F$4:$F$703,B43,Benefits!$R$4:$R$703,"revenue"),0) -> 0 | H43: =IF(D43=1,SUMIFS(Benefits!$S$4:$S$703,Benefits!$B$4:$B$703,A43,Benefits!$F$4:$F$703,B43,Benefits!$R$4:$R$703,"avoided_cost_realised"),0) -> 0 | I43: =IF(D43=1,SUMIFS(Benefits!$S$4:$S$703,Benefits!$B$4:$B$703,A43,Benefits!$F$4:$F$703,B43,Benefits!$R$4:$R$703,"capacity_converted"),0) -> 1233.0039 | J43: =SUM(F43:I43) -> 15059.808 | K43: =J43-E43 -> 3059.8081 | L43: =IF(D43=1,L42+K43,0) -> -673831.3 | M43: =IF(D43=1,1/(1+Controls!$B$11)^B43,0) -> 0.98094374 | N43: =K43*M43 -> 3001.4996 | O43: =IF(D43=1,O42+N43,0) -> -669011.6 | P43: =IF(AND(D43=1,L43<0),1,0) -> 1 | Q43: =IF(AND(D43=1,O43<0),1,0) -> 1
A44: init-002 | B44: 4 | C44: =IF(COUNTIF('Scenario inputs'!$A$4:$A$213,Controls!$B$3&"|"&A44)>0,1,0) -> 1 | D44: =IF(AND(C44=1,B44<Controls!$B$12),1,0) -> 1 | E44: =IF(D44=1,SUMPRODUCT((Costs!$B$4:$B$903=A44)*(Costs!$D$4:$D$903="planned")*(Costs!$J$4:$J$903<=B44)*(Costs!$K$4:$K$903>B44)*Costs!$E$4:$E$903),0) -> 12000 | F44: =IF(D44=1,SUMIFS(Benefits!$S$4:$S$703,Benefits!$B$4:$B$703,A44,Benefits!$F$4:$F$703,B44,Benefits!$R$4:$R$703,"cash"),0) -> 27653.608 | G44: =IF(D44=1,SUMIFS(Benefits!$S$4:$S$703,Benefits!$B$4:$B$703,A44,Benefits!$F$4:$F$703,B44,Benefits!$R$4:$R$703,"revenue"),0) -> 0 | H44: =IF(D44=1,SUMIFS(Benefits!$S$4:$S$703,Benefits!$B$4:$B$703,A44,Benefits!$F$4:$F$703,B44,Benefits!$R$4:$R$703,"avoided_cost_realised"),0) -> 0 | I44: =IF(D44=1,SUMIFS(Benefits!$S$4:$S$703,Benefits!$B$4:$B$703,A44,Benefits!$F$4:$F$703,B44,Benefits!$R$4:$R$703,"capacity_converted"),0) -> 3699.0463 | J44: =SUM(F44:I44) -> 31352.655 | K44: =J44-E44 -> 19352.655 | L44: =IF(D44=1,L43+K44,0) -> -654478.65 | M44: =IF(D44=1,1/(1+Controls!$B$11)^B44,0) -> 0.9746727 | N44: =K44*M44 -> 18862.504 | O44: =IF(D44=1,O43+N44,0) -> -650149.1 | P44: =IF(AND(D44=1,L44<0),1,0) -> 1 | Q44: =IF(AND(D44=1,O44<0),1,0) -> 1
A45: init-002 | B45: 5 | C45: =IF(COUNTIF('Scenario inputs'!$A$4:$A$213,Controls!$B$3&"|"&A45)>0,1,0) -> 1 | D45: =IF(AND(C45=1,B45<Controls!$B$12),1,0) -> 1 | E45: =IF(D45=1,SUMPRODUCT((Costs!$B$4:$B$903=A45)*(Costs!$D$4:$D$903="planned")*(Costs!$J$4:$J$903<=B45)*(Costs!$K$4:$K$903>B45)*Costs!$E$4:$E$903),0) -> 12000 | F45: =IF(D45=1,SUMIFS(Benefits!$S$4:$S$703,Benefits!$B$4:$B$703,A45,Benefits!$F$4:$F$703,B45,Benefits!$R$4:$R$703,"cash"),0) -> 46089.304 | G45: =IF(D45=1,SUMIFS(Benefits!$S$4:$S$703,Benefits!$B$4:$B$703,A45,Benefits!$F$4:$F$703,B45,Benefits!$R$4:$R$703,"revenue"),0) -> 0 | H45: =IF(D45=1,SUMIFS(Benefits!$S$4:$S$703,Benefits!$B$4:$B$703,A45,Benefits!$F$4:$F$703,B45,Benefits!$R$4:$R$703,"avoided_cost_realised"),0) -> 0 | I45: =IF(D45=1,SUMIFS(Benefits!$S$4:$S$703,Benefits!$B$4:$B$703,A45,Benefits!$F$4:$F$703,B45,Benefits!$R$4:$R$703,"capacity_converted"),0) -> 7398.0926 | J45: =SUM(F45:I45) -> 53487.397 | K45: =J45-E45 -> 41487.397 | L45: =IF(D45=1,L44+K45,0) -> -612991.25 | M45: =IF(D45=1,1/(1+Controls!$B$11)^B45,0) -> 0.96844174 | N45: =K45*M45 -> 40178.127 | O45: =IF(D45=1,O44+N45,0) -> -609970.97 | P45: =IF(AND(D45=1,L45<0),1,0) -> 1 | Q45: =IF(AND(D45=1,O45<0),1,0) -> 1
A46: init-002 | B46: 6 | C46: =IF(COUNTIF('Scenario inputs'!$A$4:$A$213,Controls!$B$3&"|"&A46)>0,1,0) -> 1 | D46: =IF(AND(C46=1,B46<Controls!$B$12),1,0) -> 1 | E46: =IF(D46=1,SUMPRODUCT((Costs!$B$4:$B$903=A46)*(Costs!$D$4:$D$903="planned")*(Costs!$J$4:$J$903<=B46)*(Costs!$K$4:$K$903>B46)*Costs!$E$4:$E$903),0) -> 12000 | F46: =IF(D46=1,SUMIFS(Benefits!$S$4:$S$703,Benefits!$B$4:$B$703,A46,Benefits!$F$4:$F$703,B46,Benefits!$R$4:$R$703,"cash"),0) -> 69133.892 | G46: =IF(D46=1,SUMIFS(Benefits!$S$4:$S$703,Benefits!$B$4:$B$703,A46,Benefits!$F$4:$F$703,B46,Benefits!$R$4:$R$703,"revenue"),0) -> 0 | H46: =IF(D46=1,SUMIFS(Benefits!$S$4:$S$703,Benefits!$B$4:$B$703,A46,Benefits!$F$4:$F$703,B46,Benefits!$R$4:$R$703,"avoided_cost_realised"),0) -> 0 | I46: =IF(D46=1,SUMIFS(Benefits!$S$4:$S$703,Benefits!$B$4:$B$703,A46,Benefits!$F$4:$F$703,B46,Benefits!$R$4:$R$703,"capacity_converted"),0) -> 12330.143 | J46: =SUM(F46:I46) -> 81464.034 | K46: =J46-E46 -> 69464.034 | L46: =IF(D46=1,L45+K46,0) -> -543527.21 | M46: =IF(D46=1,1/(1+Controls!$B$11)^B46,0) -> 0.96225062 | N46: =K46*M46 -> 66841.81 | O46: =IF(D46=1,O45+N46,0) -> -543129.16 | P46: =IF(AND(D46=1,L46<0),1,0) -> 1 | Q46: =IF(AND(D46=1,O46<0),1,0) -> 1
A47: init-002 | B47: 7 | C47: =IF(COUNTIF('Scenario inputs'!$A$4:$A$213,Controls!$B$3&"|"&A47)>0,1,0) -> 1 | D47: =IF(AND(C47=1,B47<Controls!$B$12),1,0) -> 1 | E47: =IF(D47=1,SUMPRODUCT((Costs!$B$4:$B$903=A47)*(Costs!$D$4:$D$903="planned")*(Costs!$J$4:$J$903<=B47)*(Costs!$K$4:$K$903>B47)*Costs!$E$4:$E$903),0) -> 12000 | F47: =IF(D47=1,SUMIFS(Benefits!$S$4:$S$703,Benefits!$B$4:$B$703,A47,Benefits!$F$4:$F$703,B47,Benefits!$R$4:$R$703,"cash"),0) -> 96787.5 | G47: =IF(D47=1,SUMIFS(Benefits!$S$4:$S$703,Benefits!$B$4:$B$703,A47,Benefits!$F$4:$F$703,B47,Benefits!$R$4:$R$703,"revenue"),0) -> 0 | H47: =IF(D47=1,SUMIFS(Benefits!$S$4:$S$703,Benefits!$B$4:$B$703,A47,Benefits!$F$4:$F$703,B47,Benefits!$R$4:$R$703,"avoided_cost_realised"),0) -> 0 | I47: =IF(D47=1,SUMIFS(Benefits!$S$4:$S$703,Benefits!$B$4:$B$703,A47,Benefits!$F$4:$F$703,B47,Benefits!$R$4:$R$703,"capacity_converted"),0) -> 18495.197 | J47: =SUM(F47:I47) -> 115282.7 | K47: =J47-E47 -> 103282.7 | L47: =IF(D47=1,L46+K47,0) -> -440244.52 | M47: =IF(D47=1,1/(1+Controls!$B$11)^B47,0) -> 0.95609908 | N47: =K47*M47 -> 98748.491 | O47: =IF(D47=1,O46+N47,0) -> -444380.67 | P47: =IF(AND(D47=1,L47<0),1,0) -> 1 | Q47: =IF(AND(D47=1,O47<0),1,0) -> 1
A48: init-002 | B48: 8 | C48: =IF(COUNTIF('Scenario inputs'!$A$4:$A$213,Controls!$B$3&"|"&A48)>0,1,0) -> 1 | D48: =IF(AND(C48=1,B48<Controls!$B$12),1,0) -> 1 | E48: =IF(D48=1,SUMPRODUCT((Costs!$B$4:$B$903=A48)*(Costs!$D$4:$D$903="planned")*(Costs!$J$4:$J$903<=B48)*(Costs!$K$4:$K$903>B48)*Costs!$E$4:$E$903),0) -> 12750 | F48: =IF(D48=1,SUMIFS(Benefits!$S$4:$S$703,Benefits!$B$4:$B$703,A48,Benefits!$F$4:$F$703,B48,Benefits!$R$4:$R$703,"cash"),0) -> 129050 | G48: =IF(D48=1,SUMIFS(Benefits!$S$4:$S$703,Benefits!$B$4:$B$703,A48,Benefits!$F$4:$F$703,B48,Benefits!$R$4:$R$703,"revenue"),0) -> 0 | H48: =IF(D48=1,SUMIFS(Benefits!$S$4:$S$703,Benefits!$B$4:$B$703,A48,Benefits!$F$4:$F$703,B48,Benefits!$R$4:$R$703,"avoided_cost_realised"),0) -> 0 | I48: =IF(D48=1,SUMIFS(Benefits!$S$4:$S$703,Benefits!$B$4:$B$703,A48,Benefits!$F$4:$F$703,B48,Benefits!$R$4:$R$703,"capacity_converted"),0) -> 25893.289 | J48: =SUM(F48:I48) -> 154943.29 | K48: =J48-E48 -> 142193.29 | L48: =IF(D48=1,L47+K48,0) -> -298051.23 | M48: =IF(D48=1,1/(1+Controls!$B$11)^B48,0) -> 0.94998686 | N48: =K48*M48 -> 135081.76 | O48: =IF(D48=1,O47+N48,0) -> -309298.91 | P48: =IF(AND(D48=1,L48<0),1,0) -> 1 | Q48: =IF(AND(D48=1,O48<0),1,0) -> 1
A49: init-002 | B49: 9 | C49: =IF(COUNTIF('Scenario inputs'!$A$4:$A$213,Controls!$B$3&"|"&A49)>0,1,0) -> 1 | D49: =IF(AND(C49=1,B49<Controls!$B$12),1,0) -> 1 | E49: =IF(D49=1,SUMPRODUCT((Costs!$B$4:$B$903=A49)*(Costs!$D$4:$D$903="planned")*(Costs!$J$4:$J$903<=B49)*(Costs!$K$4:$K$903>B49)*Costs!$E$4:$E$903),0) -> 12750 | F49: =IF(D49=1,SUMIFS(Benefits!$S$4:$S$703,Benefits!$B$4:$B$703,A49,Benefits!$F$4:$F$703,B49,Benefits!$R$4:$R$703,"cash"),0) -> 129050 | G49: =IF(D49=1,SUMIFS(Benefits!$S$4:$S$703,Benefits!$B$4:$B$703,A49,Benefits!$F$4:$F$703,B49,Benefits!$R$4:$R$703,"revenue"),0) -> 0 | H49: =IF(D49=1,SUMIFS(Benefits!$S$4:$S$703,Benefits!$B$4:$B$703,A49,Benefits!$F$4:$F$703,B49,Benefits!$R$4:$R$703,"avoided_cost_realised"),0) -> 0 | I49: =IF(D49=1,SUMIFS(Benefits!$S$4:$S$703,Benefits!$B$4:$B$703,A49,Benefits!$F$4:$F$703,B49,Benefits!$R$4:$R$703,"capacity_converted"),0) -> 34524.386 | J49: =SUM(F49:I49) -> 163574.39 | K49: =J49-E49 -> 150824.39 | L49: =IF(D49=1,L48+K49,0) -> -147226.84 | M49: =IF(D49=1,1/(1+Controls!$B$11)^B49,0) -> 0.94391372 | N49: =K49*M49 -> 142365.21 | O49: =IF(D49=1,O48+N49,0) -> -166933.7 | P49: =IF(AND(D49=1,L49<0),1,0) -> 1 | Q49: =IF(AND(D49=1,O49<0),1,0) -> 1
A50: init-002 | B50: 10 | C50: =IF(COUNTIF('Scenario inputs'!$A$4:$A$213,Controls!$B$3&"|"&A50)>0,1,0) -> 1 | D50: =IF(AND(C50=1,B50<Controls!$B$12),1,0) -> 1 | E50: =IF(D50=1,SUMPRODUCT((Costs!$B$4:$B$903=A50)*(Costs!$D$4:$D$903="planned")*(Costs!$J$4:$J$903<=B50)*(Costs!$K$4:$K$903>B50)*Costs!$E$4:$E$903),0) -> 12750 | F50: =IF(D50=1,SUMIFS(Benefits!$S$4:$S$703,Benefits!$B$4:$B$703,A50,Benefits!$F$4:$F$703,B50,Benefits!$R$4:$R$703,"cash"),0) -> 129050 | G50: =IF(D50=1,SUMIFS(Benefits!$S$4:$S$703,Benefits!$B$4:$B$703,A50,Benefits!$F$4:$F$703,B50,Benefits!$R$4:$R$703,"revenue"),0) -> 0 | H50: =IF(D50=1,SUMIFS(Benefits!$S$4:$S$703,Benefits!$B$4:$B$703,A50,Benefits!$F$4:$F$703,B50,Benefits!$R$4:$R$703,"avoided_cost_realised"),0) -> 0 | I50: =IF(D50=1,SUMIFS(Benefits!$S$4:$S$703,Benefits!$B$4:$B$703,A50,Benefits!$F$4:$F$703,B50,Benefits!$R$4:$R$703,"capacity_converted"),0) -> 34524.386 | J50: =SUM(F50:I50) -> 163574.39 | K50: =J50-E50 -> 150824.39 | L50: =IF(D50=1,L49+K50,0) -> 3597.544 | M50: =IF(D50=1,1/(1+Controls!$B$11)^B50,0) -> 0.93787941 | N50: =K50*M50 -> 141455.09 | O50: =IF(D50=1,O49+N50,0) -> -25478.618 | P50: =IF(AND(D50=1,L50<0),1,0) -> 0 | Q50: =IF(AND(D50=1,O50<0),1,0) -> 1
A51: init-002 | B51: 11 | C51: =IF(COUNTIF('Scenario inputs'!$A$4:$A$213,Controls!$B$3&"|"&A51)>0,1,0) -> 1 | D51: =IF(AND(C51=1,B51<Controls!$B$12),1,0) -> 1 | E51: =IF(D51=1,SUMPRODUCT((Costs!$B$4:$B$903=A51)*(Costs!$D$4:$D$903="planned")*(Costs!$J$4:$J$903<=B51)*(Costs!$K$4:$K$903>B51)*Costs!$E$4:$E$903),0) -> 12750 | F51: =IF(D51=1,SUMIFS(Benefits!$S$4:$S$703,Benefits!$B$4:$B$703,A51,Benefits!$F$4:$F$703,B51,Benefits!$R$4:$R$703,"cash"),0) -> 129050 | G51: =IF(D51=1,SUMIFS(Benefits!$S$4:$S$703,Benefits!$B$4:$B$703,A51,Benefits!$F$4:$F$703,B51,Benefits!$R$4:$R$703,"revenue"),0) -> 0 | H51: =IF(D51=1,SUMIFS(Benefits!$S$4:$S$703,Benefits!$B$4:$B$703,A51,Benefits!$F$4:$F$703,B51,Benefits!$R$4:$R$703,"avoided_cost_realised"),0) -> 0 | I51: =IF(D51=1,SUMIFS(Benefits!$S$4:$S$703,Benefits!$B$4:$B$703,A51,Benefits!$F$4:$F$703,B51,Benefits!$R$4:$R$703,"capacity_converted"),0) -> 34524.386 | J51: =SUM(F51:I51) -> 163574.39 | K51: =J51-E51 -> 150824.39 | L51: =IF(D51=1,L50+K51,0) -> 154421.93 | M51: =IF(D51=1,1/(1+Controls!$B$11)^B51,0) -> 0.93188367 | N51: =K51*M51 -> 140550.78 | O51: =IF(D51=1,O50+N51,0) -> 115072.16 | P51: =IF(AND(D51=1,L51<0),1,0) -> 0 | Q51: =IF(AND(D51=1,O51<0),1,0) -> 0
A52: init-002 | B52: 12 | C52: =IF(COUNTIF('Scenario inputs'!$A$4:$A$213,Controls!$B$3&"|"&A52)>0,1,0) -> 1 | D52: =IF(AND(C52=1,B52<Controls!$B$12),1,0) -> 1 | E52: =IF(D52=1,SUMPRODUCT((Costs!$B$4:$B$903=A52)*(Costs!$D$4:$D$903="planned")*(Costs!$J$4:$J$903<=B52)*(Costs!$K$4:$K$903>B52)*Costs!$E$4:$E$903),0) -> 12750 | F52: =IF(D52=1,SUMIFS(Benefits!$S$4:$S$703,Benefits!$B$4:$B$703,A52,Benefits!$F$4:$F$703,B52,Benefits!$R$4:$R$703,"cash"),0) -> 129050 | G52: =IF(D52=1,SUMIFS(Benefits!$S$4:$S$703,Benefits!$B$4:$B$703,A52,Benefits!$F$4:$F$703,B52,Benefits!$R$4:$R$703,"revenue"),0) -> 0 | H52: =IF(D52=1,SUMIFS(Benefits!$S$4:$S$703,Benefits!$B$4:$B$703,A52,Benefits!$F$4:$F$703,B52,Benefits!$R$4:$R$703,"avoided_cost_realised"),0) -> 0 | I52: =IF(D52=1,SUMIFS(Benefits!$S$4:$S$703,Benefits!$B$4:$B$703,A52,Benefits!$F$4:$F$703,B52,Benefits!$R$4:$R$703,"capacity_converted"),0) -> 34524.386 | J52: =SUM(F52:I52) -> 163574.39 | K52: =J52-E52 -> 150824.39 | L52: =IF(D52=1,L51+K52,0) -> 305246.32 | M52: =IF(D52=1,1/(1+Controls!$B$11)^B52,0) -> 0.92592626 | N52: =K52*M52 -> 139652.26 | O52: =IF(D52=1,O51+N52,0) -> 254724.42 | P52: =IF(AND(D52=1,L52<0),1,0) -> 0 | Q52: =IF(AND(D52=1,O52<0),1,0) -> 0
... A75: init-002 | B75: 35 | C75: =IF(COUNTIF('Scenario inputs'!$A$4:$A$213,Controls!$B$3&"|"&A75)>0,1,0) -> 1 | D75: =IF(AND(C75=1,B75<Controls!$B$12),1,0) -> 1 | E75: =IF(D75=1,SUMPRODUCT((Costs!$B$4:$B$903=A75)*(Costs!$D$4:$D$903="planned")*(Costs!$J$4:$J$903<=B75)*(Costs!$K$4:$K$903>B75)*Costs!$E$4:$E$903),0) -> 0 | F75: =IF(D75=1,SUMIFS(Benefits!$S$4:$S$703,Benefits!$B$4:$B$703,A75,Benefits!$F$4:$F$703,B75,Benefits!$R$4:$R$703,"cash"),0) -> 0 | G75: =IF(D75=1,SUMIFS(Benefits!$S$4:$S$703,Benefits!$B$4:$B$703,A75,Benefits!$F$4:$F$703,B75,Benefits!$R$4:$R$703,"revenue"),0) -> 0 | H75: =IF(D75=1,SUMIFS(Benefits!$S$4:$S$703,Benefits!$B$4:$B$703,A75,Benefits!$F$4:$F$703,B75,Benefits!$R$4:$R$703,"avoided_cost_realised"),0) -> 0 | I75: =IF(D75=1,SUMIFS(Benefits!$S$4:$S$703,Benefits!$B$4:$B$703,A75,Benefits!$F$4:$F$703,B75,Benefits!$R$4:$R$703,"capacity_converted"),0) -> 0 | J75: =SUM(F75:I75) -> 0 | K75: =J75-E75 -> 0 | L75: =IF(D75=1,L74+K75,0) -> 477845.09 | M75: =IF(D75=1,1/(1+Controls!$B$11)^B75,0) -> 0.79894062 | N75: =K75*M75 -> 0 | O75: =IF(D75=1,O74+N75,0) -> 413388.43 | P75: =IF(AND(D75=1,L75<0),1,0) -> 0 | Q75: =IF(AND(D75=1,O75<0),1,0) -> 0
A76: init-003 | B76: 0 | C76: =IF(COUNTIF('Scenario inputs'!$A$4:$A$213,Controls!$B$3&"|"&A76)>0,1,0) -> 1 | D76: =IF(AND(C76=1,B76<Controls!$B$12),1,0) -> 1 | E76: =IF(D76=1,SUMPRODUCT((Costs!$B$4:$B$903=A76)*(Costs!$D$4:$D$903="planned")*(Costs!$J$4:$J$903<=B76)*(Costs!$K$4:$K$903>B76)*Costs!$E$4:$E$903),0) -> 10000 | F76: =IF(D76=1,SUMIFS(Benefits!$S$4:$S$703,Benefits!$B$4:$B$703,A76,Benefits!$F$4:$F$703,B76,Benefits!$R$4:$R$703,"cash"),0) -> 0 | G76: =IF(D76=1,SUMIFS(Benefits!$S$4:$S$703,Benefits!$B$4:$B$703,A76,Benefits!$F$4:$F$703,B76,Benefits!$R$4:$R$703,"revenue"),0) -> 0 | H76: =IF(D76=1,SUMIFS(Benefits!$S$4:$S$703,Benefits!$B$4:$B$703,A76,Benefits!$F$4:$F$703,B76,Benefits!$R$4:$R$703,"avoided_cost_realised"),0) -> 0 | I76: =IF(D76=1,SUMIFS(Benefits!$S$4:$S$703,Benefits!$B$4:$B$703,A76,Benefits!$F$4:$F$703,B76,Benefits!$R$4:$R$703,"capacity_converted"),0) -> 0 | J76: =SUM(F76:I76) -> 0 | K76: =J76-E76 -> -10000 | L76: =IF(D76=1,K76,0) -> -10000 | M76: =IF(D76=1,1/(1+Controls!$B$11)^B76,0) -> 1 | N76: =K76*M76 -> -10000 | O76: =IF(D76=1,N76,0) -> -10000 | P76: =IF(AND(D76=1,L76<0),1,0) -> 1 | Q76: =IF(AND(D76=1,O76<0),1,0) -> 1
A77: init-003 | B77: 1 | C77: =IF(COUNTIF('Scenario inputs'!$A$4:$A$213,Controls!$B$3&"|"&A77)>0,1,0) -> 1 | D77: =IF(AND(C77=1,B77<Controls!$B$12),1,0) -> 1 | E77: =IF(D77=1,SUMPRODUCT((Costs!$B$4:$B$903=A77)*(Costs!$D$4:$D$903="planned")*(Costs!$J$4:$J$903<=B77)*(Costs!$K$4:$K$903>B77)*Costs!$E$4:$E$903),0) -> 274950 | F77: =IF(D77=1,SUMIFS(Benefits!$S$4:$S$703,Benefits!$B$4:$B$703,A77,Benefits!$F$4:$F$703,B77,Benefits!$R$4:$R$703,"cash"),0) -> 0 | G77: =IF(D77=1,SUMIFS(Benefits!$S$4:$S$703,Benefits!$B$4:$B$703,A77,Benefits!$F$4:$F$703,B77,Benefits!$R$4:$R$703,"revenue"),0) -> 0 | H77: =IF(D77=1,SUMIFS(Benefits!$S$4:$S$703,Benefits!$B$4:$B$703,A77,Benefits!$F$4:$F$703,B77,Benefits!$R$4:$R$703,"avoided_cost_realised"),0) -> 0 | I77: =IF(D77=1,SUMIFS(Benefits!$S$4:$S$703,Benefits!$B$4:$B$703,A77,Benefits!$F$4:$F$703,B77,Benefits!$R$4:$R$703,"capacity_converted"),0) -> 0 | J77: =SUM(F77:I77) -> 0 | K77: =J77-E77 -> -274950 | L77: =IF(D77=1,L76+K77,0) -> -284950 | M77: =IF(D77=1,1/(1+Controls!$B$11)^B77,0) -> 0.99360713 | N77: =K77*M77 -> -273192.28 | O77: =IF(D77=1,O76+N77,0) -> -283192.28 | P77: =IF(AND(D77=1,L77<0),1,0) -> 1 | Q77: =IF(AND(D77=1,O77<0),1,0) -> 1
A78: init-003 | B78: 2 | C78: =IF(COUNTIF('Scenario inputs'!$A$4:$A$213,Controls!$B$3&"|"&A78)>0,1,0) -> 1 | D78: =IF(AND(C78=1,B78<Controls!$B$12),1,0) -> 1 | E78: =IF(D78=1,SUMPRODUCT((Costs!$B$4:$B$903=A78)*(Costs!$D$4:$D$903="planned")*(Costs!$J$4:$J$903<=B78)*(Costs!$K$4:$K$903>B78)*Costs!$E$4:$E$903),0) -> 152400 | F78: =IF(D78=1,SUMIFS(Benefits!$S$4:$S$703,Benefits!$B$4:$B$703,A78,Benefits!$F$4:$F$703,B78,Benefits!$R$4:$R$703,"cash"),0) -> 0 | G78: =IF(D78=1,SUMIFS(Benefits!$S$4:$S$703,Benefits!$B$4:$B$703,A78,Benefits!$F$4:$F$703,B78,Benefits!$R$4:$R$703,"revenue"),0) -> 0 | H78: =IF(D78=1,SUMIFS(Benefits!$S$4:$S$703,Benefits!$B$4:$B$703,A78,Benefits!$F$4:$F$703,B78,Benefits!$R$4:$R$703,"avoided_cost_realised"),0) -> 0 | I78: =IF(D78=1,SUMIFS(Benefits!$S$4:$S$703,Benefits!$B$4:$B$703,A78,Benefits!$F$4:$F$703,B78,Benefits!$R$4:$R$703,"capacity_converted"),0) -> 0 | J78: =SUM(F78:I78) -> 0 | K78: =J78-E78 -> -152400 | L78: =IF(D78=1,L77+K78,0) -> -437350 | M78: =IF(D78=1,1/(1+Controls!$B$11)^B78,0) -> 0.98725513 | N78: =K78*M78 -> -150457.68 | O78: =IF(D78=1,O77+N78,0) -> -433649.96 | P78: =IF(AND(D78=1,L78<0),1,0) -> 1 | Q78: =IF(AND(D78=1,O78<0),1,0) -> 1
A79: init-003 | B79: 3 | C79: =IF(COUNTIF('Scenario inputs'!$A$4:$A$213,Controls!$B$3&"|"&A79)>0,1,0) -> 1 | D79: =IF(AND(C79=1,B79<Controls!$B$12),1,0) -> 1 | E79: =IF(D79=1,SUMPRODUCT((Costs!$B$4:$B$903=A79)*(Costs!$D$4:$D$903="planned")*(Costs!$J$4:$J$903<=B79)*(Costs!$K$4:$K$903>B79)*Costs!$E$4:$E$903),0) -> 92650 | F79: =IF(D79=1,SUMIFS(Benefits!$S$4:$S$703,Benefits!$B$4:$B$703,A79,Benefits!$F$4:$F$703,B79,Benefits!$R$4:$R$703,"cash"),0) -> 2825.0226 | G79: =IF(D79=1,SUMIFS(Benefits!$S$4:$S$703,Benefits!$B$4:$B$703,A79,Benefits!$F$4:$F$703,B79,Benefits!$R$4:$R$703,"revenue"),0) -> 0 | H79: =IF(D79=1,SUMIFS(Benefits!$S$4:$S$703,Benefits!$B$4:$B$703,A79,Benefits!$F$4:$F$703,B79,Benefits!$R$4:$R$703,"avoided_cost_realised"),0) -> 0 | I79: =IF(D79=1,SUMIFS(Benefits!$S$4:$S$703,Benefits!$B$4:$B$703,A79,Benefits!$F$4:$F$703,B79,Benefits!$R$4:$R$703,"capacity_converted"),0) -> 0 | J79: =SUM(F79:I79) -> 2825.0226 | K79: =J79-E79 -> -89824.977 | L79: =IF(D79=1,L78+K79,0) -> -527174.98 | M79: =IF(D79=1,1/(1+Controls!$B$11)^B79,0) -> 0.98094374 | N79: =K79*M79 -> -88113.249 | O79: =IF(D79=1,O78+N79,0) -> -521763.21 | P79: =IF(AND(D79=1,L79<0),1,0) -> 1 | Q79: =IF(AND(D79=1,O79<0),1,0) -> 1
A80: init-003 | B80: 4 | C80: =IF(COUNTIF('Scenario inputs'!$A$4:$A$213,Controls!$B$3&"|"&A80)>0,1,0) -> 1 | D80: =IF(AND(C80=1,B80<Controls!$B$12),1,0) -> 1 | E80: =IF(D80=1,SUMPRODUCT((Costs!$B$4:$B$903=A80)*(Costs!$D$4:$D$903="planned")*(Costs!$J$4:$J$903<=B80)*(Costs!$K$4:$K$903>B80)*Costs!$E$4:$E$903),0) -> 10000 | F80: =IF(D80=1,SUMIFS(Benefits!$S$4:$S$703,Benefits!$B$4:$B$703,A80,Benefits!$F$4:$F$703,B80,Benefits!$R$4:$R$703,"cash"),0) -> 8474.9661 | G80: =IF(D80=1,SUMIFS(Benefits!$S$4:$S$703,Benefits!$B$4:$B$703,A80,Benefits!$F$4:$F$703,B80,Benefits!$R$4:$R$703,"revenue"),0) -> 0 | H80: =IF(D80=1,SUMIFS(Benefits!$S$4:$S$703,Benefits!$B$4:$B$703,A80,Benefits!$F$4:$F$703,B80,Benefits!$R$4:$R$703,"avoided_cost_realised"),0) -> 0 | I80: =IF(D80=1,SUMIFS(Benefits!$S$4:$S$703,Benefits!$B$4:$B$703,A80,Benefits!$F$4:$F$703,B80,Benefits!$R$4:$R$703,"capacity_converted"),0) -> 1248.575 | J80: =SUM(F80:I80) -> 9723.5411 | K80: =J80-E80 -> -276.45886 | L80: =IF(D80=1,L79+K80,0) -> -527451.44 | M80: =IF(D80=1,1/(1+Controls!$B$11)^B80,0) -> 0.9746727 | N80: =K80*M80 -> -269.4569 | O80: =IF(D80=1,O79+N80,0) -> -522032.67 | P80: =IF(AND(D80=1,L80<0),1,0) -> 1 | Q80: =IF(AND(D80=1,O80<0),1,0) -> 1
A81: init-003 | B81: 5 | C81: =IF(COUNTIF('Scenario inputs'!$A$4:$A$213,Controls!$B$3&"|"&A81)>0,1,0) -> 1 | D81: =IF(AND(C81=1,B81<Controls!$B$12),1,0) -> 1 | E81: =IF(D81=1,SUMPRODUCT((Costs!$B$4:$B$903=A81)*(Costs!$D$4:$D$903="planned")*(Costs!$J$4:$J$903<=B81)*(Costs!$K$4:$K$903>B81)*Costs!$E$4:$E$903),0) -> 10000 | F81: =IF(D81=1,SUMIFS(Benefits!$S$4:$S$703,Benefits!$B$4:$B$703,A81,Benefits!$F$4:$F$703,B81,Benefits!$R$4:$R$703,"cash"),0) -> 16950.034 | G81: =IF(D81=1,SUMIFS(Benefits!$S$4:$S$703,Benefits!$B$4:$B$703,A81,Benefits!$F$4:$F$703,B81,Benefits!$R$4:$R$703,"revenue"),0) -> 0 | H81: =IF(D81=1,SUMIFS(Benefits!$S$4:$S$703,Benefits!$B$4:$B$703,A81,Benefits!$F$4:$F$703,B81,Benefits!$R$4:$R$703,"avoided_cost_realised"),0) -> 0 | I81: =IF(D81=1,SUMIFS(Benefits!$S$4:$S$703,Benefits!$B$4:$B$703,A81,Benefits!$F$4:$F$703,B81,Benefits!$R$4:$R$703,"capacity_converted"),0) -> 3745.6802 | J81: =SUM(F81:I81) -> 20695.714 | K81: =J81-E81 -> 10695.714 | L81: =IF(D81=1,L80+K81,0) -> -516755.72 | M81: =IF(D81=1,1/(1+Controls!$B$11)^B81,0) -> 0.96844174 | N81: =K81*M81 -> 10358.176 | O81: =IF(D81=1,O80+N81,0) -> -511674.49 | P81: =IF(AND(D81=1,L81<0),1,0) -> 1 | Q81: =IF(AND(D81=1,O81<0),1,0) -> 1
A82: init-003 | B82: 6 | C82: =IF(COUNTIF('Scenario inputs'!$A$4:$A$213,Controls!$B$3&"|"&A82)>0,1,0) -> 1 | D82: =IF(AND(C82=1,B82<Controls!$B$12),1,0) -> 1 | E82: =IF(D82=1,SUMPRODUCT((Costs!$B$4:$B$903=A82)*(Costs!$D$4:$D$903="planned")*(Costs!$J$4:$J$903<=B82)*(Costs!$K$4:$K$903>B82)*Costs!$E$4:$E$903),0) -> 10000 | F82: =IF(D82=1,SUMIFS(Benefits!$S$4:$S$703,Benefits!$B$4:$B$703,A82,Benefits!$F$4:$F$703,B82,Benefits!$R$4:$R$703,"cash"),0) -> 28250.023 | G82: =IF(D82=1,SUMIFS(Benefits!$S$4:$S$703,Benefits!$B$4:$B$703,A82,Benefits!$F$4:$F$703,B82,Benefits!$R$4:$R$703,"revenue"),0) -> 0 | H82: =IF(D82=1,SUMIFS(Benefits!$S$4:$S$703,Benefits!$B$4:$B$703,A82,Benefits!$F$4:$F$703,B82,Benefits!$R$4:$R$703,"avoided_cost_realised"),0) -> 0 | I82: =IF(D82=1,SUMIFS(Benefits!$S$4:$S$703,Benefits!$B$4:$B$703,A82,Benefits!$F$4:$F$703,B82,Benefits!$R$4:$R$703,"capacity_converted"),0) -> 7491.4053 | J82: =SUM(F82:I82) -> 35741.428 | K82: =J82-E82 -> 25741.428 | L82: =IF(D82=1,L81+K82,0) -> -491014.29 | M82: =IF(D82=1,1/(1+Controls!$B$11)^B82,0) -> 0.96225062 | N82: =K82*M82 -> 24769.705 | O82: =IF(D82=1,O81+N82,0) -> -486904.79 | P82: =IF(AND(D82=1,L82<0),1,0) -> 1 | Q82: =IF(AND(D82=1,O82<0),1,0) -> 1
A83: init-003 | B83: 7 | C83: =IF(COUNTIF('Scenario inputs'!$A$4:$A$213,Controls!$B$3&"|"&A83)>0,1,0) -> 1 | D83: =IF(AND(C83=1,B83<Controls!$B$12),1,0) -> 1 | E83: =IF(D83=1,SUMPRODUCT((Costs!$B$4:$B$903=A83)*(Costs!$D$4:$D$903="planned")*(Costs!$J$4:$J$903<=B83)*(Costs!$K$4:$K$903>B83)*Costs!$E$4:$E$903),0) -> 10000 | F83: =IF(D83=1,SUMIFS(Benefits!$S$4:$S$703,Benefits!$B$4:$B$703,A83,Benefits!$F$4:$F$703,B83,Benefits!$R$4:$R$703,"cash"),0) -> 42375.034 | G83: =IF(D83=1,SUMIFS(Benefits!$S$4:$S$703,Benefits!$B$4:$B$703,A83,Benefits!$F$4:$F$703,B83,Benefits!$R$4:$R$703,"revenue"),0) -> 0 | H83: =IF(D83=1,SUMIFS(Benefits!$S$4:$S$703,Benefits!$B$4:$B$703,A83,Benefits!$F$4:$F$703,B83,Benefits!$R$4:$R$703,"avoided_cost_realised"),0) -> 0 | I83: =IF(D83=1,SUMIFS(Benefits!$S$4:$S$703,Benefits!$B$4:$B$703,A83,Benefits!$F$4:$F$703,B83,Benefits!$R$4:$R$703,"capacity_converted"),0) -> 12485.66 | J83: =SUM(F83:I83) -> 54860.694 | K83: =J83-E83 -> 44860.694 | L83: =IF(D83=1,L82+K83,0) -> -446153.6 | M83: =IF(D83=1,1/(1+Controls!$B$11)^B83,0) -> 0.95609908 | N83: =K83*M83 -> 42891.269 | O83: =IF(D83=1,O82+N83,0) -> -444013.52 | P83: =IF(AND(D83=1,L83<0),1,0) -> 1 | Q83: =IF(AND(D83=1,O83<0),1,0) -> 1
A84: init-003 | B84: 8 | C84: =IF(COUNTIF('Scenario inputs'!$A$4:$A$213,Controls!$B$3&"|"&A84)>0,1,0) -> 1 | D84: =IF(AND(C84=1,B84<Controls!$B$12),1,0) -> 1 | E84: =IF(D84=1,SUMPRODUCT((Costs!$B$4:$B$903=A84)*(Costs!$D$4:$D$903="planned")*(Costs!$J$4:$J$903<=B84)*(Costs!$K$4:$K$903>B84)*Costs!$E$4:$E$903),0) -> 10000 | F84: =IF(D84=1,SUMIFS(Benefits!$S$4:$S$703,Benefits!$B$4:$B$703,A84,Benefits!$F$4:$F$703,B84,Benefits!$R$4:$R$703,"cash"),0) -> 59324.966 | G84: =IF(D84=1,SUMIFS(Benefits!$S$4:$S$703,Benefits!$B$4:$B$703,A84,Benefits!$F$4:$F$703,B84,Benefits!$R$4:$R$703,"revenue"),0) -> 0 | H84: =IF(D84=1,SUMIFS(Benefits!$S$4:$S$703,Benefits!$B$4:$B$703,A84,Benefits!$F$4:$F$703,B84,Benefits!$R$4:$R$703,"avoided_cost_realised"),0) -> 0 | I84: =IF(D84=1,SUMIFS(Benefits!$S$4:$S$703,Benefits!$B$4:$B$703,A84,Benefits!$F$4:$F$703,B84,Benefits!$R$4:$R$703,"capacity_converted"),0) -> 18728.491 | J84: =SUM(F84:I84) -> 78053.457 | K84: =J84-E84 -> 68053.457 | L84: =IF(D84=1,L83+K84,0) -> -378100.14 | M84: =IF(D84=1,1/(1+Controls!$B$11)^B84,0) -> 0.94998686 | N84: =K84*M84 -> 64649.89 | O84: =IF(D84=1,O83+N84,0) -> -379363.63 | P84: =IF(AND(D84=1,L84<0),1,0) -> 1 | Q84: =IF(AND(D84=1,O84<0),1,0) -> 1
A85: init-003 | B85: 9 | C85: =IF(COUNTIF('Scenario inputs'!$A$4:$A$213,Controls!$B$3&"|"&A85)>0,1,0) -> 1 | D85: =IF(AND(C85=1,B85<Controls!$B$12),1,0) -> 1 | E85: =IF(D85=1,SUMPRODUCT((Costs!$B$4:$B$903=A85)*(Costs!$D$4:$D$903="planned")*(Costs!$J$4:$J$903<=B85)*(Costs!$K$4:$K$903>B85)*Costs!$E$4:$E$903),0) -> 10400 | F85: =IF(D85=1,SUMIFS(Benefits!$S$4:$S$703,Benefits!$B$4:$B$703,A85,Benefits!$F$4:$F$703,B85,Benefits!$R$4:$R$703,"cash"),0) -> 79100.023 | G85: =IF(D85=1,SUMIFS(Benefits!$S$4:$S$703,Benefits!$B$4:$B$703,A85,Benefits!$F$4:$F$703,B85,Benefits!$R$4:$R$703,"revenue"),0) -> 0 | H85: =IF(D85=1,SUMIFS(Benefits!$S$4:$S$703,Benefits!$B$4:$B$703,A85,Benefits!$F$4:$F$703,B85,Benefits!$R$4:$R$703,"avoided_cost_realised"),0) -> 0 | I85: =IF(D85=1,SUMIFS(Benefits!$S$4:$S$703,Benefits!$B$4:$B$703,A85,Benefits!$F$4:$F$703,B85,Benefits!$R$4:$R$703,"capacity_converted"),0) -> 26219.851 | J85: =SUM(F85:I85) -> 105319.87 | K85: =J85-E85 -> 94919.874 | L85: =IF(D85=1,L84+K85,0) -> -283180.27 | M85: =IF(D85=1,1/(1+Controls!$B$11)^B85,0) -> 0.94391372 | N85: =K85*M85 -> 89596.171 | O85: =IF(D85=1,O84+N85,0) -> -289767.46 | P85: =IF(AND(D85=1,L85<0),1,0) -> 1 | Q85: =IF(AND(D85=1,O85<0),1,0) -> 1
A86: init-003 | B86: 10 | C86: =IF(COUNTIF('Scenario inputs'!$A$4:$A$213,Controls!$B$3&"|"&A86)>0,1,0) -> 1 | D86: =IF(AND(C86=1,B86<Controls!$B$12),1,0) -> 1 | E86: =IF(D86=1,SUMPRODUCT((Costs!$B$4:$B$903=A86)*(Costs!$D$4:$D$903="planned")*(Costs!$J$4:$J$903<=B86)*(Costs!$K$4:$K$903>B86)*Costs!$E$4:$E$903),0) -> 10400 | F86: =IF(D86=1,SUMIFS(Benefits!$S$4:$S$703,Benefits!$B$4:$B$703,A86,Benefits!$F$4:$F$703,B86,Benefits!$R$4:$R$703,"cash"),0) -> 101700 | G86: =IF(D86=1,SUMIFS(Benefits!$S$4:$S$703,Benefits!$B$4:$B$703,A86,Benefits!$F$4:$F$703,B86,Benefits!$R$4:$R$703,"revenue"),0) -> 0 | H86: =IF(D86=1,SUMIFS(Benefits!$S$4:$S$703,Benefits!$B$4:$B$703,A86,Benefits!$F$4:$F$703,B86,Benefits!$R$4:$R$703,"avoided_cost_realised"),0) -> 0 | I86: =IF(D86=1,SUMIFS(Benefits!$S$4:$S$703,Benefits!$B$4:$B$703,A86,Benefits!$F$4:$F$703,B86,Benefits!$R$4:$R$703,"capacity_converted"),0) -> 34959.831 | J86: =SUM(F86:I86) -> 136659.83 | K86: =J86-E86 -> 126259.83 | L86: =IF(D86=1,L85+K86,0) -> -156920.44 | M86: =IF(D86=1,1/(1+Controls!$B$11)^B86,0) -> 0.93787941 | N86: =K86*M86 -> 118416.5 | O86: =IF(D86=1,O85+N86,0) -> -171350.96 | P86: =IF(AND(D86=1,L86<0),1,0) -> 1 | Q86: =IF(AND(D86=1,O86<0),1,0) -> 1
A87: init-003 | B87: 11 | C87: =IF(COUNTIF('Scenario inputs'!$A$4:$A$213,Controls!$B$3&"|"&A87)>0,1,0) -> 1 | D87: =IF(AND(C87=1,B87<Controls!$B$12),1,0) -> 1 | E87: =IF(D87=1,SUMPRODUCT((Costs!$B$4:$B$903=A87)*(Costs!$D$4:$D$903="planned")*(Costs!$J$4:$J$903<=B87)*(Costs!$K$4:$K$903>B87)*Costs!$E$4:$E$903),0) -> 10400 | F87: =IF(D87=1,SUMIFS(Benefits!$S$4:$S$703,Benefits!$B$4:$B$703,A87,Benefits!$F$4:$F$703,B87,Benefits!$R$4:$R$703,"cash"),0) -> 101700 | G87: =IF(D87=1,SUMIFS(Benefits!$S$4:$S$703,Benefits!$B$4:$B$703,A87,Benefits!$F$4:$F$703,B87,Benefits!$R$4:$R$703,"revenue"),0) -> 0 | H87: =IF(D87=1,SUMIFS(Benefits!$S$4:$S$703,Benefits!$B$4:$B$703,A87,Benefits!$F$4:$F$703,B87,Benefits!$R$4:$R$703,"avoided_cost_realised"),0) -> 0 | I87: =IF(D87=1,SUMIFS(Benefits!$S$4:$S$703,Benefits!$B$4:$B$703,A87,Benefits!$F$4:$F$703,B87,Benefits!$R$4:$R$703,"capacity_converted"),0) -> 44948.342 | J87: =SUM(F87:I87) -> 146648.34 | K87: =J87-E87 -> 136248.34 | L87: =IF(D87=1,L86+K87,0) -> -20672.096 | M87: =IF(D87=1,1/(1+Controls!$B$11)^B87,0) -> 0.93188367 | N87: =K87*M87 -> 126967.6 | O87: =IF(D87=1,O86+N87,0) -> -44383.358 | P87: =IF(AND(D87=1,L87<0),1,0) -> 1 | Q87: =IF(AND(D87=1,O87<0),1,0) -> 1
A88: init-003 | B88: 12 | C88: =IF(COUNTIF('Scenario inputs'!$A$4:$A$213,Controls!$B$3&"|"&A88)>0,1,0) -> 1 | D88: =IF(AND(C88=1,B88<Controls!$B$12),1,0) -> 1 | E88: =IF(D88=1,SUMPRODUCT((Costs!$B$4:$B$903=A88)*(Costs!$D$4:$D$903="planned")*(Costs!$J$4:$J$903<=B88)*(Costs!$K$4:$K$903>B88)*Costs!$E$4:$E$903),0) -> 10400 | F88: =IF(D88=1,SUMIFS(Benefits!$S$4:$S$703,Benefits!$B$4:$B$703,A88,Benefits!$F$4:$F$703,B88,Benefits!$R$4:$R$703,"cash"),0) -> 101700 | G88: =IF(D88=1,SUMIFS(Benefits!$S$4:$S$703,Benefits!$B$4:$B$703,A88,Benefits!$F$4:$F$703,B88,Benefits!$R$4:$R$703,"revenue"),0) -> 0 | H88: =IF(D88=1,SUMIFS(Benefits!$S$4:$S$703,Benefits!$B$4:$B$703,A88,Benefits!$F$4:$F$703,B88,Benefits!$R$4:$R$703,"avoided_cost_realised"),0) -> 0 | I88: =IF(D88=1,SUMIFS(Benefits!$S$4:$S$703,Benefits!$B$4:$B$703,A88,Benefits!$F$4:$F$703,B88,Benefits!$R$4:$R$703,"capacity_converted"),0) -> 44948.342 | J88: =SUM(F88:I88) -> 146648.34 | K88: =J88-E88 -> 136248.34 | L88: =IF(D88=1,L87+K88,0) -> 115576.25 | M88: =IF(D88=1,1/(1+Controls!$B$11)^B88,0) -> 0.92592626 | N88: =K88*M88 -> 126155.92 | O88: =IF(D88=1,O87+N88,0) -> 81772.559 | P88: =IF(AND(D88=1,L88<0),1,0) -> 0 | Q88: =IF(AND(D88=1,O88<0),1,0) -> 0
... A111: init-003 | B111: 35 | C111: =IF(COUNTIF('Scenario inputs'!$A$4:$A$213,Controls!$B$3&"|"&A111)>0,1,0) -> 1 | D111: =IF(AND(C111=1,B111<Controls!$B$12),1,0) -> 1 | E111: =IF(D111=1,SUMPRODUCT((Costs!$B$4:$B$903=A111)*(Costs!$D$4:$D$903="planned")*(Costs!$J$4:$J$903<=B111)*(Costs!$K$4:$K$903>B111)*Costs!$E$4:$E$903),0) -> 0 | F111: =IF(D111=1,SUMIFS(Benefits!$S$4:$S$703,Benefits!$B$4:$B$703,A111,Benefits!$F$4:$F$703,B111,Benefits!$R$4:$R$703,"cash"),0) -> 0 | G111: =IF(D111=1,SUMIFS(Benefits!$S$4:$S$703,Benefits!$B$4:$B$703,A111,Benefits!$F$4:$F$703,B111,Benefits!$R$4:$R$703,"revenue"),0) -> 0 | H111: =IF(D111=1,SUMIFS(Benefits!$S$4:$S$703,Benefits!$B$4:$B$703,A111,Benefits!$F$4:$F$703,B111,Benefits!$R$4:$R$703,"avoided_cost_realised"),0) -> 0 | I111: =IF(D111=1,SUMIFS(Benefits!$S$4:$S$703,Benefits!$B$4:$B$703,A111,Benefits!$F$4:$F$703,B111,Benefits!$R$4:$R$703,"capacity_converted"),0) -> 0 | J111: =SUM(F111:I111) -> 0 | K111: =J111-E111 -> 0 | L111: =IF(D111=1,L110+K111,0) -> 422621.27 | M111: =IF(D111=1,1/(1+Controls!$B$11)^B111,0) -> 0.79894062 | N111: =K111*M111 -> 0 | O111: =IF(D111=1,O110+N111,0) -> 363049.68 | P111: =IF(AND(D111=1,L111<0),1,0) -> 0 | Q111: =IF(AND(D111=1,O111<0),1,0) -> 0
A112: init-004 | B112: 0 | C112: =IF(COUNTIF('Scenario inputs'!$A$4:$A$213,Controls!$B$3&"|"&A112)>0,1,0) -> 1 | D112: =IF(AND(C112=1,B112<Controls!$B$12),1,0) -> 1 | E112: =IF(D112=1,SUMPRODUCT((Costs!$B$4:$B$903=A112)*(Costs!$D$4:$D$903="planned")*(Costs!$J$4:$J$903<=B112)*(Costs!$K$4:$K$903>B112)*Costs!$E$4:$E$903),0) -> 22000 | F112: =IF(D112=1,SUMIFS(Benefits!$S$4:$S$703,Benefits!$B$4:$B$703,A112,Benefits!$F$4:$F$703,B112,Benefits!$R$4:$R$703,"cash"),0) -> 0 | G112: =IF(D112=1,SUMIFS(Benefits!$S$4:$S$703,Benefits!$B$4:$B$703,A112,Benefits!$F$4:$F$703,B112,Benefits!$R$4:$R$703,"revenue"),0) -> 0 | H112: =IF(D112=1,SUMIFS(Benefits!$S$4:$S$703,Benefits!$B$4:$B$703,A112,Benefits!$F$4:$F$703,B112,Benefits!$R$4:$R$703,"avoided_cost_realised"),0) -> 0 | I112: =IF(D112=1,SUMIFS(Benefits!$S$4:$S$703,Benefits!$B$4:$B$703,A112,Benefits!$F$4:$F$703,B112,Benefits!$R$4:$R$703,"capacity_converted"),0) -> 0 | J112: =SUM(F112:I112) -> 0 | K112: =J112-E112 -> -22000 | L112: =IF(D112=1,K112,0) -> -22000 | M112: =IF(D112=1,1/(1+Controls!$B$11)^B112,0) -> 1 | N112: =K112*M112 -> -22000 | O112: =IF(D112=1,N112,0) -> -22000 | P112: =IF(AND(D112=1,L112<0),1,0) -> 1 | Q112: =IF(AND(D112=1,O112<0),1,0) -> 1
A113: init-004 | B113: 1 | C113: =IF(COUNTIF('Scenario inputs'!$A$4:$A$213,Controls!$B$3&"|"&A113)>0,1,0) -> 1 | D113: =IF(AND(C113=1,B113<Controls!$B$12),1,0) -> 1 | E113: =IF(D113=1,SUMPRODUCT((Costs!$B$4:$B$903=A113)*(Costs!$D$4:$D$903="planned")*(Costs!$J$4:$J$903<=B113)*(Costs!$K$4:$K$903>B113)*Costs!$E$4:$E$903),0) -> 0 | F113: =IF(D113=1,SUMIFS(Benefits!$S$4:$S$703,Benefits!$B$4:$B$703,A113,Benefits!$F$4:$F$703,B113,Benefits!$R$4:$R$703,"cash"),0) -> 0 | G113: =IF(D113=1,SUMIFS(Benefits!$S$4:$S$703,Benefits!$B$4:$B$703,A113,Benefits!$F$4:$F$703,B113,Benefits!$R$4:$R$703,"revenue"),0) -> 0 | H113: =IF(D113=1,SUMIFS(Benefits!$S$4:$S$703,Benefits!$B$4:$B$703,A113,Benefits!$F$4:$F$703,B113,Benefits!$R$4:$R$703,"avoided_cost_realised"),0) -> 0 | I113: =IF(D113=1,SUMIFS(Benefits!$S$4:$S$703,Benefits!$B$4:$B$703,A113,Benefits!$F$4:$F$703,B113,Benefits!$R$4:$R$703,"capacity_converted"),0) -> 0 | J113: =SUM(F113:I113) -> 0 | K113: =J113-E113 -> 0 | L113: =IF(D113=1,L112+K113,0) -> -22000 | M113: =IF(D113=1,1/(1+Controls!$B$11)^B113,0) -> 0.99360713 | N113: =K113*M113 -> 0 | O113: =IF(D113=1,O112+N113,0) -> -22000 | P113: =IF(AND(D113=1,L113<0),1,0) -> 1 | Q113: =IF(AND(D113=1,O113<0),1,0) -> 1
A114: init-004 | B114: 2 | C114: =IF(COUNTIF('Scenario inputs'!$A$4:$A$213,Controls!$B$3&"|"&A114)>0,1,0) -> 1 | D114: =IF(AND(C114=1,B114<Controls!$B$12),1,0) -> 1 | E114: =IF(D114=1,SUMPRODUCT((Costs!$B$4:$B$903=A114)*(Costs!$D$4:$D$903="planned")*(Costs!$J$4:$J$903<=B114)*(Costs!$K$4:$K$903>B114)*Costs!$E$4:$E$903),0) -> 163900 | F114: =IF(D114=1,SUMIFS(Benefits!$S$4:$S$703,Benefits!$B$4:$B$703,A114,Benefits!$F$4:$F$703,B114,Benefits!$R$4:$R$703,"cash"),0) -> 0 | G114: =IF(D114=1,SUMIFS(Benefits!$S$4:$S$703,Benefits!$B$4:$B$703,A114,Benefits!$F$4:$F$703,B114,Benefits!$R$4:$R$703,"revenue"),0) -> 0 | H114: =IF(D114=1,SUMIFS(Benefits!$S$4:$S$703,Benefits!$B$4:$B$703,A114,Benefits!$F$4:$F$703,B114,Benefits!$R$4:$R$703,"avoided_cost_realised"),0) -> 0 | I114: =IF(D114=1,SUMIFS(Benefits!$S$4:$S$703,Benefits!$B$4:$B$703,A114,Benefits!$F$4:$F$703,B114,Benefits!$R$4:$R$703,"capacity_converted"),0) -> 0 | J114: =SUM(F114:I114) -> 0 | K114: =J114-E114 -> -163900 | L114: =IF(D114=1,L113+K114,0) -> -185900 | M114: =IF(D114=1,1/(1+Controls!$B$11)^B114,0) -> 0.98725513 | N114: =K114*M114 -> -161811.12 | O114: =IF(D114=1,O113+N114,0) -> -183811.12 | P114: =IF(AND(D114=1,L114<0),1,0) -> 1 | Q114: =IF(AND(D114=1,O114<0),1,0) -> 1
A115: init-004 | B115: 3 | C115: =IF(COUNTIF('Scenario inputs'!$A$4:$A$213,Controls!$B$3&"|"&A115)>0,1,0) -> 1 | D115: =IF(AND(C115=1,B115<Controls!$B$12),1,0) -> 1 | E115: =IF(D115=1,SUMPRODUCT((Costs!$B$4:$B$903=A115)*(Costs!$D$4:$D$903="planned")*(Costs!$J$4:$J$903<=B115)*(Costs!$K$4:$K$903>B115)*Costs!$E$4:$E$903),0) -> 453800 | F115: =IF(D115=1,SUMIFS(Benefits!$S$4:$S$703,Benefits!$B$4:$B$703,A115,Benefits!$F$4:$F$703,B115,Benefits!$R$4:$R$703,"cash"),0) -> 0 | G115: =IF(D115=1,SUMIFS(Benefits!$S$4:$S$703,Benefits!$B$4:$B$703,A115,Benefits!$F$4:$F$703,B115,Benefits!$R$4:$R$703,"revenue"),0) -> 0 | H115: =IF(D115=1,SUMIFS(Benefits!$S$4:$S$703,Benefits!$B$4:$B$703,A115,Benefits!$F$4:$F$703,B115,Benefits!$R$4:$R$703,"avoided_cost_realised"),0) -> 0 | I115: =IF(D115=1,SUMIFS(Benefits!$S$4:$S$703,Benefits!$B$4:$B$703,A115,Benefits!$F$4:$F$703,B115,Benefits!$R$4:$R$703,"capacity_converted"),0) -> 0 | J115: =SUM(F115:I115) -> 0 | K115: =J115-E115 -> -453800 | L115: =IF(D115=1,L114+K115,0) -> -639700 | M115: =IF(D115=1,1/(1+Controls!$B$11)^B115,0) -> 0.98094374 | N115: =K115*M115 -> -445152.27 | O115: =IF(D115=1,O114+N115,0) -> -628963.39 | P115: =IF(AND(D115=1,L115<0),1,0) -> 1 | Q115: =IF(AND(D115=1,O115<0),1,0) -> 1
A116: init-004 | B116: 4 | C116: =IF(COUNTIF('Scenario inputs'!$A$4:$A$213,Controls!$B$3&"|"&A116)>0,1,0) -> 1 | D116: =IF(AND(C116=1,B116<Controls!$B$12),1,0) -> 1 | E116: =IF(D116=1,SUMPRODUCT((Costs!$B$4:$B$903=A116)*(Costs!$D$4:$D$903="planned")*(Costs!$J$4:$J$903<=B116)*(Costs!$K$4:$K$903>B116)*Costs!$E$4:$E$903),0) -> 515300 | F116: =IF(D116=1,SUMIFS(Benefits!$S$4:$S$703,Benefits!$B$4:$B$703,A116,Benefits!$F$4:$F$703,B116,Benefits!$R$4:$R$703,"cash"),0) -> 0 | G116: =IF(D116=1,SUMIFS(Benefits!$S$4:$S$703,Benefits!$B$4:$B$703,A116,Benefits!$F$4:$F$703,B116,Benefits!$R$4:$R$703,"revenue"),0) -> 0 | H116: =IF(D116=1,SUMIFS(Benefits!$S$4:$S$703,Benefits!$B$4:$B$703,A116,Benefits!$F$4:$F$703,B116,Benefits!$R$4:$R$703,"avoided_cost_realised"),0) -> 3133.3584 | I116: =IF(D116=1,SUMIFS(Benefits!$S$4:$S$703,Benefits!$B$4:$B$703,A116,Benefits!$F$4:$F$703,B116,Benefits!$R$4:$R$703,"capacity_converted"),0) -> 0 | J116: =SUM(F116:I116) -> 3133.3584 | K116: =J116-E116 -> -512166.64 | L116: =IF(D116=1,L115+K116,0) -> -1151866.6 | M116: =IF(D116=1,1/(1+Controls!$B$11)^B116,0) -> 0.9746727 | N116: =K116*M116 -> -499194.84 | O116: =IF(D116=1,O115+N116,0) -> -1128158.2 | P116: =IF(AND(D116=1,L116<0),1,0) -> 1 | Q116: =IF(AND(D116=1,O116<0),1,0) -> 1
A117: init-004 | B117: 5 | C117: =IF(COUNTIF('Scenario inputs'!$A$4:$A$213,Controls!$B$3&"|"&A117)>0,1,0) -> 1 | D117: =IF(AND(C117=1,B117<Controls!$B$12),1,0) -> 1 | E117: =IF(D117=1,SUMPRODUCT((Costs!$B$4:$B$903=A117)*(Costs!$D$4:$D$903="planned")*(Costs!$J$4:$J$903<=B117)*(Costs!$K$4:$K$903>B117)*Costs!$E$4:$E$903),0) -> 22000 | F117: =IF(D117=1,SUMIFS(Benefits!$S$4:$S$703,Benefits!$B$4:$B$703,A117,Benefits!$F$4:$F$703,B117,Benefits!$R$4:$R$703,"cash"),0) -> 2563.9094 | G117: =IF(D117=1,SUMIFS(Benefits!$S$4:$S$703,Benefits!$B$4:$B$703,A117,Benefits!$F$4:$F$703,B117,Benefits!$R$4:$R$703,"revenue"),0) -> 0 | H117: =IF(D117=1,SUMIFS(Benefits!$S$4:$S$703,Benefits!$B$4:$B$703,A117,Benefits!$F$4:$F$703,B117,Benefits!$R$4:$R$703,"avoided_cost_realised"),0) -> 9399.9624 | I117: =IF(D117=1,SUMIFS(Benefits!$S$4:$S$703,Benefits!$B$4:$B$703,A117,Benefits!$F$4:$F$703,B117,Benefits!$R$4:$R$703,"capacity_converted"),0) -> 2100.2651 | J117: =SUM(F117:I117) -> 14064.137 | K117: =J117-E117 -> -7935.8631 | L117: =IF(D117=1,L116+K117,0) -> -1159802.5 | M117: =IF(D117=1,1/(1+Controls!$B$11)^B117,0) -> 0.96844174 | N117: =K117*M117 -> -7685.4211 | O117: =IF(D117=1,O116+N117,0) -> -1135843.6 | P117: =IF(AND(D117=1,L117<0),1,0) -> 1 | Q117: =IF(AND(D117=1,O117<0),1,0) -> 1
A118: init-004 | B118: 6 | C118: =IF(COUNTIF('Scenario inputs'!$A$4:$A$213,Controls!$B$3&"|"&A118)>0,1,0) -> 1 | D118: =IF(AND(C118=1,B118<Controls!$B$12),1,0) -> 1 | E118: =IF(D118=1,SUMPRODUCT((Costs!$B$4:$B$903=A118)*(Costs!$D$4:$D$903="planned")*(Costs!$J$4:$J$903<=B118)*(Costs!$K$4:$K$903>B118)*Costs!$E$4:$E$903),0) -> 22000 | F118: =IF(D118=1,SUMIFS(Benefits!$S$4:$S$703,Benefits!$B$4:$B$703,A118,Benefits!$F$4:$F$703,B118,Benefits!$R$4:$R$703,"cash"),0) -> 7691.6359 | G118: =IF(D118=1,SUMIFS(Benefits!$S$4:$S$703,Benefits!$B$4:$B$703,A118,Benefits!$F$4:$F$703,B118,Benefits!$R$4:$R$703,"revenue"),0) -> 0 | H118: =IF(D118=1,SUMIFS(Benefits!$S$4:$S$703,Benefits!$B$4:$B$703,A118,Benefits!$F$4:$F$703,B118,Benefits!$R$4:$R$703,"avoided_cost_realised"),0) -> 18800.038 | I118: =IF(D118=1,SUMIFS(Benefits!$S$4:$S$703,Benefits!$B$4:$B$703,A118,Benefits!$F$4:$F$703,B118,Benefits!$R$4:$R$703,"capacity_converted"),0) -> 6300.7196 | J118: =SUM(F118:I118) -> 32792.393 | K118: =J118-E118 -> 10792.393 | L118: =IF(D118=1,L117+K118,0) -> -1149010.1 | M118: =IF(D118=1,1/(1+Controls!$B$11)^B118,0) -> 0.96225062 | N118: =K118*M118 -> 10384.987 | O118: =IF(D118=1,O117+N118,0) -> -1125458.7 | P118: =IF(AND(D118=1,L118<0),1,0) -> 1 | Q118: =IF(AND(D118=1,O118<0),1,0) -> 1
A119: init-004 | B119: 7 | C119: =IF(COUNTIF('Scenario inputs'!$A$4:$A$213,Controls!$B$3&"|"&A119)>0,1,0) -> 1 | D119: =IF(AND(C119=1,B119<Controls!$B$12),1,0) -> 1 | E119: =IF(D119=1,SUMPRODUCT((Costs!$B$4:$B$903=A119)*(Costs!$D$4:$D$903="planned")*(Costs!$J$4:$J$903<=B119)*(Costs!$K$4:$K$903>B119)*Costs!$E$4:$E$903),0) -> 22000 | F119: =IF(D119=1,SUMIFS(Benefits!$S$4:$S$703,Benefits!$B$4:$B$703,A119,Benefits!$F$4:$F$703,B119,Benefits!$R$4:$R$703,"cash"),0) -> 15383.364 | G119: =IF(D119=1,SUMIFS(Benefits!$S$4:$S$703,Benefits!$B$4:$B$703,A119,Benefits!$F$4:$F$703,B119,Benefits!$R$4:$R$703,"revenue"),0) -> 0 | H119: =IF(D119=1,SUMIFS(Benefits!$S$4:$S$703,Benefits!$B$4:$B$703,A119,Benefits!$F$4:$F$703,B119,Benefits!$R$4:$R$703,"avoided_cost_realised"),0) -> 31333.358 | I119: =IF(D119=1,SUMIFS(Benefits!$S$4:$S$703,Benefits!$B$4:$B$703,A119,Benefits!$F$4:$F$703,B119,Benefits!$R$4:$R$703,"capacity_converted"),0) -> 12601.515 | J119: =SUM(F119:I119) -> 59318.237 | K119: =J119-E119 -> 37318.237 | L119: =IF(D119=1,L118+K119,0) -> -1111691.9 | M119: =IF(D119=1,1/(1+Controls!$B$11)^B119,0) -> 0.95609908 | N119: =K119*M119 -> 35679.932 | O119: =IF(D119=1,O118+N119,0) -> -1089778.7 | P119: =IF(AND(D119=1,L119<0),1,0) -> 1 | Q119: =IF(AND(D119=1,O119<0),1,0) -> 1
A120: init-004 | B120: 8 | C120: =IF(COUNTIF('Scenario inputs'!$A$4:$A$213,Controls!$B$3&"|"&A120)>0,1,0) -> 1 | D120: =IF(AND(C120=1,B120<Controls!$B$12),1,0) -> 1 | E120: =IF(D120=1,SUMPRODUCT((Costs!$B$4:$B$903=A120)*(Costs!$D$4:$D$903="planned")*(Costs!$J$4:$J$903<=B120)*(Costs!$K$4:$K$903>B120)*Costs!$E$4:$E$903),0) -> 22000 | F120: =IF(D120=1,SUMIFS(Benefits!$S$4:$S$703,Benefits!$B$4:$B$703,A120,Benefits!$F$4:$F$703,B120,Benefits!$R$4:$R$703,"cash"),0) -> 25638.909 | G120: =IF(D120=1,SUMIFS(Benefits!$S$4:$S$703,Benefits!$B$4:$B$703,A120,Benefits!$F$4:$F$703,B120,Benefits!$R$4:$R$703,"revenue"),0) -> 0 | H120: =IF(D120=1,SUMIFS(Benefits!$S$4:$S$703,Benefits!$B$4:$B$703,A120,Benefits!$F$4:$F$703,B120,Benefits!$R$4:$R$703,"avoided_cost_realised"),0) -> 47000.038 | I120: =IF(D120=1,SUMIFS(Benefits!$S$4:$S$703,Benefits!$B$4:$B$703,A120,Benefits!$F$4:$F$703,B120,Benefits!$R$4:$R$703,"capacity_converted"),0) -> 21002.499 | J120: =SUM(F120:I120) -> 93641.446 | K120: =J120-E120 -> 71641.446 | L120: =IF(D120=1,L119+K120,0) -> -1040050.4 | M120: =IF(D120=1,1/(1+Controls!$B$11)^B120,0) -> 0.94998686 | N120: =K120*M120 -> 68058.433 | O120: =IF(D120=1,O119+N120,0) -> -1021720.3 | P120: =IF(AND(D120=1,L120<0),1,0) -> 1 | Q120: =IF(AND(D120=1,O120<0),1,0) -> 1
A121: init-004 | B121: 9 | C121: =IF(COUNTIF('Scenario inputs'!$A$4:$A$213,Controls!$B$3&"|"&A121)>0,1,0) -> 1 | D121: =IF(AND(C121=1,B121<Controls!$B$12),1,0) -> 1 | E121: =IF(D121=1,SUMPRODUCT((Costs!$B$4:$B$903=A121)*(Costs!$D$4:$D$903="planned")*(Costs!$J$4:$J$903<=B121)*(Costs!$K$4:$K$903>B121)*Costs!$E$4:$E$903),0) -> 22000 | F121: =IF(D121=1,SUMIFS(Benefits!$S$4:$S$703,Benefits!$B$4:$B$703,A121,Benefits!$F$4:$F$703,B121,Benefits!$R$4:$R$703,"cash"),0) -> 38458.364 | G121: =IF(D121=1,SUMIFS(Benefits!$S$4:$S$703,Benefits!$B$4:$B$703,A121,Benefits!$F$4:$F$703,B121,Benefits!$R$4:$R$703,"revenue"),0) -> 0 | H121: =IF(D121=1,SUMIFS(Benefits!$S$4:$S$703,Benefits!$B$4:$B$703,A121,Benefits!$F$4:$F$703,B121,Benefits!$R$4:$R$703,"avoided_cost_realised"),0) -> 65799.962 | I121: =IF(D121=1,SUMIFS(Benefits!$S$4:$S$703,Benefits!$B$4:$B$703,A121,Benefits!$F$4:$F$703,B121,Benefits!$R$4:$R$703,"capacity_converted"),0) -> 31503.749 | J121: =SUM(F121:I121) -> 135762.08 | K121: =J121-E121 -> 113762.08 | L121: =IF(D121=1,L120+K121,0) -> -926288.35 | M121: =IF(D121=1,1/(1+Controls!$B$11)^B121,0) -> 0.94391372 | N121: =K121*M121 -> 107381.58 | O121: =IF(D121=1,O120+N121,0) -> -914338.71 | P121: =IF(AND(D121=1,L121<0),1,0) -> 1 | Q121: =IF(AND(D121=1,O121<0),1,0) -> 1
A122: init-004 | B122: 10 | C122: =IF(COUNTIF('Scenario inputs'!$A$4:$A$213,Controls!$B$3&"|"&A122)>0,1,0) -> 1 | D122: =IF(AND(C122=1,B122<Controls!$B$12),1,0) -> 1 | E122: =IF(D122=1,SUMPRODUCT((Costs!$B$4:$B$903=A122)*(Costs!$D$4:$D$903="planned")*(Costs!$J$4:$J$903<=B122)*(Costs!$K$4:$K$903>B122)*Costs!$E$4:$E$903),0) -> 22450 | F122: =IF(D122=1,SUMIFS(Benefits!$S$4:$S$703,Benefits!$B$4:$B$703,A122,Benefits!$F$4:$F$703,B122,Benefits!$R$4:$R$703,"cash"),0) -> 53841.636 | G122: =IF(D122=1,SUMIFS(Benefits!$S$4:$S$703,Benefits!$B$4:$B$703,A122,Benefits!$F$4:$F$703,B122,Benefits!$R$4:$R$703,"revenue"),0) -> 0 | H122: =IF(D122=1,SUMIFS(Benefits!$S$4:$S$703,Benefits!$B$4:$B$703,A122,Benefits!$F$4:$F$703,B122,Benefits!$R$4:$R$703,"avoided_cost_realised"),0) -> 87733.358 | I122: =IF(D122=1,SUMIFS(Benefits!$S$4:$S$703,Benefits!$B$4:$B$703,A122,Benefits!$F$4:$F$703,B122,Benefits!$R$4:$R$703,"capacity_converted"),0) -> 44105.188 | J122: =SUM(F122:I122) -> 185680.18 | K122: =J122-E122 -> 163230.18 | L122: =IF(D122=1,L121+K122,0) -> -763058.17 | M122: =IF(D122=1,1/(1+Controls!$B$11)^B122,0) -> 0.93787941 | N122: =K122*M122 -> 153090.23 | O122: =IF(D122=1,O121+N122,0) -> -761248.48 | P122: =IF(AND(D122=1,L122<0),1,0) -> 1 | Q122: =IF(AND(D122=1,O122<0),1,0) -> 1
A123: init-004 | B123: 11 | C123: =IF(COUNTIF('Scenario inputs'!$A$4:$A$213,Controls!$B$3&"|"&A123)>0,1,0) -> 1 | D123: =IF(AND(C123=1,B123<Controls!$B$12),1,0) -> 1 | E123: =IF(D123=1,SUMPRODUCT((Costs!$B$4:$B$903=A123)*(Costs!$D$4:$D$903="planned")*(Costs!$J$4:$J$903<=B123)*(Costs!$K$4:$K$903>B123)*Costs!$E$4:$E$903),0) -> 22450 | F123: =IF(D123=1,SUMIFS(Benefits!$S$4:$S$703,Benefits!$B$4:$B$703,A123,Benefits!$F$4:$F$703,B123,Benefits!$R$4:$R$703,"cash"),0) -> 71788.909 | G123: =IF(D123=1,SUMIFS(Benefits!$S$4:$S$703,Benefits!$B$4:$B$703,A123,Benefits!$F$4:$F$703,B123,Benefits!$R$4:$R$703,"revenue"),0) -> 0 | H123: =IF(D123=1,SUMIFS(Benefits!$S$4:$S$703,Benefits!$B$4:$B$703,A123,Benefits!$F$4:$F$703,B123,Benefits!$R$4:$R$703,"avoided_cost_realised"),0) -> 112800 | I123: =IF(D123=1,SUMIFS(Benefits!$S$4:$S$703,Benefits!$B$4:$B$703,A123,Benefits!$F$4:$F$703,B123,Benefits!$R$4:$R$703,"capacity_converted"),0) -> 58806.968 | J123: =SUM(F123:I123) -> 243395.88 | K123: =J123-E123 -> 220945.88 | L123: =IF(D123=1,L122+K123,0) -> -542112.29 | M123: =IF(D123=1,1/(1+Controls!$B$11)^B123,0) -> 0.93188367 | N123: =K123*M123 -> 205895.85 | O123: =IF(D123=1,O122+N123,0) -> -555352.63 | P123: =IF(AND(D123=1,L123<0),1,0) -> 1 | Q123: =IF(AND(D123=1,O123<0),1,0) -> 1
A124: init-004 | B124: 12 | C124: =IF(COUNTIF('Scenario inputs'!$A$4:$A$213,Controls!$B$3&"|"&A124)>0,1,0) -> 1 | D124: =IF(AND(C124=1,B124<Controls!$B$12),1,0) -> 1 | E124: =IF(D124=1,SUMPRODUCT((Costs!$B$4:$B$903=A124)*(Costs!$D$4:$D$903="planned")*(Costs!$J$4:$J$903<=B124)*(Costs!$K$4:$K$903>B124)*Costs!$E$4:$E$903),0) -> 22450 | F124: =IF(D124=1,SUMIFS(Benefits!$S$4:$S$703,Benefits!$B$4:$B$703,A124,Benefits!$F$4:$F$703,B124,Benefits!$R$4:$R$703,"cash"),0) -> 92300 | G124: =IF(D124=1,SUMIFS(Benefits!$S$4:$S$703,Benefits!$B$4:$B$703,A124,Benefits!$F$4:$F$703,B124,Benefits!$R$4:$R$703,"revenue"),0) -> 0 | H124: =IF(D124=1,SUMIFS(Benefits!$S$4:$S$703,Benefits!$B$4:$B$703,A124,Benefits!$F$4:$F$703,B124,Benefits!$R$4:$R$703,"avoided_cost_realised"),0) -> 112800 | I124: =IF(D124=1,SUMIFS(Benefits!$S$4:$S$703,Benefits!$B$4:$B$703,A124,Benefits!$F$4:$F$703,B124,Benefits!$R$4:$R$703,"capacity_converted"),0) -> 75608.938 | J124: =SUM(F124:I124) -> 280708.94 | K124: =J124-E124 -> 258258.94 | L124: =IF(D124=1,L123+K124,0) -> -283853.35 | M124: =IF(D124=1,1/(1+Controls!$B$11)^B124,0) -> 0.92592626 | N124: =K124*M124 -> 239128.73 | O124: =IF(D124=1,O123+N124,0) -> -316223.9 | P124: =IF(AND(D124=1,L124<0),1,0) -> 1 | Q124: =IF(AND(D124=1,O124<0),1,0) -> 1
... A147: init-004 | B147: 35 | C147: =IF(COUNTIF('Scenario inputs'!$A$4:$A$213,Controls!$B$3&"|"&A147)>0,1,0) -> 1 | D147: =IF(AND(C147=1,B147<Controls!$B$12),1,0) -> 1 | E147: =IF(D147=1,SUMPRODUCT((Costs!$B$4:$B$903=A147)*(Costs!$D$4:$D$903="planned")*(Costs!$J$4:$J$903<=B147)*(Costs!$K$4:$K$903>B147)*Costs!$E$4:$E$903),0) -> 0 | F147: =IF(D147=1,SUMIFS(Benefits!$S$4:$S$703,Benefits!$B$4:$B$703,A147,Benefits!$F$4:$F$703,B147,Benefits!$R$4:$R$703,"cash"),0) -> 0 | G147: =IF(D147=1,SUMIFS(Benefits!$S$4:$S$703,Benefits!$B$4:$B$703,A147,Benefits!$F$4:$F$703,B147,Benefits!$R$4:$R$703,"revenue"),0) -> 0 | H147: =IF(D147=1,SUMIFS(Benefits!$S$4:$S$703,Benefits!$B$4:$B$703,A147,Benefits!$F$4:$F$703,B147,Benefits!$R$4:$R$703,"avoided_cost_realised"),0) -> 0 | I147: =IF(D147=1,SUMIFS(Benefits!$S$4:$S$703,Benefits!$B$4:$B$703,A147,Benefits!$F$4:$F$703,B147,Benefits!$R$4:$R$703,"capacity_converted"),0) -> 0 | J147: =SUM(F147:I147) -> 0 | K147: =J147-E147 -> 0 | L147: =IF(D147=1,L146+K147,0) -> 636382.4 | M147: =IF(D147=1,1/(1+Controls!$B$11)^B147,0) -> 0.79894062 | N147: =K147*M147 -> 0 | O147: =IF(D147=1,O146+N147,0) -> 523302.08 | P147: =IF(AND(D147=1,L147<0),1,0) -> 0 | Q147: =IF(AND(D147=1,O147<0),1,0) -> 0
A148: init-005 | B148: 0 | C148: =IF(COUNTIF('Scenario inputs'!$A$4:$A$213,Controls!$B$3&"|"&A148)>0,1,0) -> 1 | D148: =IF(AND(C148=1,B148<Controls!$B$12),1,0) -> 1 | E148: =IF(D148=1,SUMPRODUCT((Costs!$B$4:$B$903=A148)*(Costs!$D$4:$D$903="planned")*(Costs!$J$4:$J$903<=B148)*(Costs!$K$4:$K$903>B148)*Costs!$E$4:$E$903),0) -> 14000 | F148: =IF(D148=1,SUMIFS(Benefits!$S$4:$S$703,Benefits!$B$4:$B$703,A148,Benefits!$F$4:$F$703,B148,Benefits!$R$4:$R$703,"cash"),0) -> 0 | G148: =IF(D148=1,SUMIFS(Benefits!$S$4:$S$703,Benefits!$B$4:$B$703,A148,Benefits!$F$4:$F$703,B148,Benefits!$R$4:$R$703,"revenue"),0) -> 0 | H148: =IF(D148=1,SUMIFS(Benefits!$S$4:$S$703,Benefits!$B$4:$B$703,A148,Benefits!$F$4:$F$703,B148,Benefits!$R$4:$R$703,"avoided_cost_realised"),0) -> 0 | I148: =IF(D148=1,SUMIFS(Benefits!$S$4:$S$703,Benefits!$B$4:$B$703,A148,Benefits!$F$4:$F$703,B148,Benefits!$R$4:$R$703,"capacity_converted"),0) -> 0 | J148: =SUM(F148:I148) -> 0 | K148: =J148-E148 -> -14000 | L148: =IF(D148=1,K148,0) -> -14000 | M148: =IF(D148=1,1/(1+Controls!$B$11)^B148,0) -> 1 | N148: =K148*M148 -> -14000 | O148: =IF(D148=1,N148,0) -> -14000 | P148: =IF(AND(D148=1,L148<0),1,0) -> 1 | Q148: =IF(AND(D148=1,O148<0),1,0) -> 1
A149: init-005 | B149: 1 | C149: =IF(COUNTIF('Scenario inputs'!$A$4:$A$213,Controls!$B$3&"|"&A149)>0,1,0) -> 1 | D149: =IF(AND(C149=1,B149<Controls!$B$12),1,0) -> 1 | E149: =IF(D149=1,SUMPRODUCT((Costs!$B$4:$B$903=A149)*(Costs!$D$4:$D$903="planned")*(Costs!$J$4:$J$903<=B149)*(Costs!$K$4:$K$903>B149)*Costs!$E$4:$E$903),0) -> 0 | F149: =IF(D149=1,SUMIFS(Benefits!$S$4:$S$703,Benefits!$B$4:$B$703,A149,Benefits!$F$4:$F$703,B149,Benefits!$R$4:$R$703,"cash"),0) -> 0 | G149: =IF(D149=1,SUMIFS(Benefits!$S$4:$S$703,Benefits!$B$4:$B$703,A149,Benefits!$F$4:$F$703,B149,Benefits!$R$4:$R$703,"revenue"),0) -> 0 | H149: =IF(D149=1,SUMIFS(Benefits!$S$4:$S$703,Benefits!$B$4:$B$703,A149,Benefits!$F$4:$F$703,B149,Benefits!$R$4:$R$703,"avoided_cost_realised"),0) -> 0 | I149: =IF(D149=1,SUMIFS(Benefits!$S$4:$S$703,Benefits!$B$4:$B$703,A149,Benefits!$F$4:$F$703,B149,Benefits!$R$4:$R$703,"capacity_converted"),0) -> 0 | J149: =SUM(F149:I149) -> 0 | K149: =J149-E149 -> 0 | L149: =IF(D149=1,L148+K149,0) -> -14000 | M149: =IF(D149=1,1/(1+Controls!$B$11)^B149,0) -> 0.99360713 | N149: =K149*M149 -> 0 | O149: =IF(D149=1,O148+N149,0) -> -14000 | P149: =IF(AND(D149=1,L149<0),1,0) -> 1 | Q149: =IF(AND(D149=1,O149<0),1,0) -> 1
A150: init-005 | B150: 2 | C150: =IF(COUNTIF('Scenario inputs'!$A$4:$A$213,Controls!$B$3&"|"&A150)>0,1,0) -> 1 | D150: =IF(AND(C150=1,B150<Controls!$B$12),1,0) -> 1 | E150: =IF(D150=1,SUMPRODUCT((Costs!$B$4:$B$903=A150)*(Costs!$D$4:$D$903="planned")*(Costs!$J$4:$J$903<=B150)*(Costs!$K$4:$K$903>B150)*Costs!$E$4:$E$903),0) -> 0 | F150: =IF(D150=1,SUMIFS(Benefits!$S$4:$S$703,Benefits!$B$4:$B$703,A150,Benefits!$F$4:$F$703,B150,Benefits!$R$4:$R$703,"cash"),0) -> 0 | G150: =IF(D150=1,SUMIFS(Benefits!$S$4:$S$703,Benefits!$B$4:$B$703,A150,Benefits!$F$4:$F$703,B150,Benefits!$R$4:$R$703,"revenue"),0) -> 0 | H150: =IF(D150=1,SUMIFS(Benefits!$S$4:$S$703,Benefits!$B$4:$B$703,A150,Benefits!$F$4:$F$703,B150,Benefits!$R$4:$R$703,"avoided_cost_realised"),0) -> 0 | I150: =IF(D150=1,SUMIFS(Benefits!$S$4:$S$703,Benefits!$B$4:$B$703,A150,Benefits!$F$4:$F$703,B150,Benefits!$R$4:$R$703,"capacity_converted"),0) -> 0 | J150: =SUM(F150:I150) -> 0 | K150: =J150-E150 -> 0 | L150: =IF(D150=1,L149+K150,0) -> -14000 | M150: =IF(D150=1,1/(1+Controls!$B$11)^B150,0) -> 0.98725513 | N150: =K150*M150 -> 0 | O150: =IF(D150=1,O149+N150,0) -> -14000 | P150: =IF(AND(D150=1,L150<0),1,0) -> 1 | Q150: =IF(AND(D150=1,O150<0),1,0) -> 1
A151: init-005 | B151: 3 | C151: =IF(COUNTIF('Scenario inputs'!$A$4:$A$213,Controls!$B$3&"|"&A151)>0,1,0) -> 1 | D151: =IF(AND(C151=1,B151<Controls!$B$12),1,0) -> 1 | E151: =IF(D151=1,SUMPRODUCT((Costs!$B$4:$B$903=A151)*(Costs!$D$4:$D$903="planned")*(Costs!$J$4:$J$903<=B151)*(Costs!$K$4:$K$903>B151)*Costs!$E$4:$E$903),0) -> 0 | F151: =IF(D151=1,SUMIFS(Benefits!$S$4:$S$703,Benefits!$B$4:$B$703,A151,Benefits!$F$4:$F$703,B151,Benefits!$R$4:$R$703,"cash"),0) -> 0 | G151: =IF(D151=1,SUMIFS(Benefits!$S$4:$S$703,Benefits!$B$4:$B$703,A151,Benefits!$F$4:$F$703,B151,Benefits!$R$4:$R$703,"revenue"),0) -> 0 | H151: =IF(D151=1,SUMIFS(Benefits!$S$4:$S$703,Benefits!$B$4:$B$703,A151,Benefits!$F$4:$F$703,B151,Benefits!$R$4:$R$703,"avoided_cost_realised"),0) -> 0 | I151: =IF(D151=1,SUMIFS(Benefits!$S$4:$S$703,Benefits!$B$4:$B$703,A151,Benefits!$F$4:$F$703,B151,Benefits!$R$4:$R$703,"capacity_converted"),0) -> 0 | J151: =SUM(F151:I151) -> 0 | K151: =J151-E151 -> 0 | L151: =IF(D151=1,L150+K151,0) -> -14000 | M151: =IF(D151=1,1/(1+Controls!$B$11)^B151,0) -> 0.98094374 | N151: =K151*M151 -> 0 | O151: =IF(D151=1,O150+N151,0) -> -14000 | P151: =IF(AND(D151=1,L151<0),1,0) -> 1 | Q151: =IF(AND(D151=1,O151<0),1,0) -> 1
A152: init-005 | B152: 4 | C152: =IF(COUNTIF('Scenario inputs'!$A$4:$A$213,Controls!$B$3&"|"&A152)>0,1,0) -> 1 | D152: =IF(AND(C152=1,B152<Controls!$B$12),1,0) -> 1 | E152: =IF(D152=1,SUMPRODUCT((Costs!$B$4:$B$903=A152)*(Costs!$D$4:$D$903="planned")*(Costs!$J$4:$J$903<=B152)*(Costs!$K$4:$K$903>B152)*Costs!$E$4:$E$903),0) -> 0 | F152: =IF(D152=1,SUMIFS(Benefits!$S$4:$S$703,Benefits!$B$4:$B$703,A152,Benefits!$F$4:$F$703,B152,Benefits!$R$4:$R$703,"cash"),0) -> 0 | G152: =IF(D152=1,SUMIFS(Benefits!$S$4:$S$703,Benefits!$B$4:$B$703,A152,Benefits!$F$4:$F$703,B152,Benefits!$R$4:$R$703,"revenue"),0) -> 0 | H152: =IF(D152=1,SUMIFS(Benefits!$S$4:$S$703,Benefits!$B$4:$B$703,A152,Benefits!$F$4:$F$703,B152,Benefits!$R$4:$R$703,"avoided_cost_realised"),0) -> 0 | I152: =IF(D152=1,SUMIFS(Benefits!$S$4:$S$703,Benefits!$B$4:$B$703,A152,Benefits!$F$4:$F$703,B152,Benefits!$R$4:$R$703,"capacity_converted"),0) -> 0 | J152: =SUM(F152:I152) -> 0 | K152: =J152-E152 -> 0 | L152: =IF(D152=1,L151+K152,0) -> -14000 | M152: =IF(D152=1,1/(1+Controls!$B$11)^B152,0) -> 0.9746727 | N152: =K152*M152 -> 0 | O152: =IF(D152=1,O151+N152,0) -> -14000 | P152: =IF(AND(D152=1,L152<0),1,0) -> 1 | Q152: =IF(AND(D152=1,O152<0),1,0) -> 1
A153: init-005 | B153: 5 | C153: =IF(COUNTIF('Scenario inputs'!$A$4:$A$213,Controls!$B$3&"|"&A153)>0,1,0) -> 1 | D153: =IF(AND(C153=1,B153<Controls!$B$12),1,0) -> 1 | E153: =IF(D153=1,SUMPRODUCT((Costs!$B$4:$B$903=A153)*(Costs!$D$4:$D$903="planned")*(Costs!$J$4:$J$903<=B153)*(Costs!$K$4:$K$903>B153)*Costs!$E$4:$E$903),0) -> 0 | F153: =IF(D153=1,SUMIFS(Benefits!$S$4:$S$703,Benefits!$B$4:$B$703,A153,Benefits!$F$4:$F$703,B153,Benefits!$R$4:$R$703,"cash"),0) -> 0 | G153: =IF(D153=1,SUMIFS(Benefits!$S$4:$S$703,Benefits!$B$4:$B$703,A153,Benefits!$F$4:$F$703,B153,Benefits!$R$4:$R$703,"revenue"),0) -> 0 | H153: =IF(D153=1,SUMIFS(Benefits!$S$4:$S$703,Benefits!$B$4:$B$703,A153,Benefits!$F$4:$F$703,B153,Benefits!$R$4:$R$703,"avoided_cost_realised"),0) -> 0 | I153: =IF(D153=1,SUMIFS(Benefits!$S$4:$S$703,Benefits!$B$4:$B$703,A153,Benefits!$F$4:$F$703,B153,Benefits!$R$4:$R$703,"capacity_converted"),0) -> 0 | J153: =SUM(F153:I153) -> 0 | K153: =J153-E153 -> 0 | L153: =IF(D153=1,L152+K153,0) -> -14000 | M153: =IF(D153=1,1/(1+Controls!$B$11)^B153,0) -> 0.96844174 | N153: =K153*M153 -> 0 | O153: =IF(D153=1,O152+N153,0) -> -14000 | P153: =IF(AND(D153=1,L153<0),1,0) -> 1 | Q153: =IF(AND(D153=1,O153<0),1,0) -> 1
A154: init-005 | B154: 6 | C154: =IF(COUNTIF('Scenario inputs'!$A$4:$A$213,Controls!$B$3&"|"&A154)>0,1,0) -> 1 | D154: =IF(AND(C154=1,B154<Controls!$B$12),1,0) -> 1 | E154: =IF(D154=1,SUMPRODUCT((Costs!$B$4:$B$903=A154)*(Costs!$D$4:$D$903="planned")*(Costs!$J$4:$J$903<=B154)*(Costs!$K$4:$K$903>B154)*Costs!$E$4:$E$903),0) -> 0 | F154: =IF(D154=1,SUMIFS(Benefits!$S$4:$S$703,Benefits!$B$4:$B$703,A154,Benefits!$F$4:$F$703,B154,Benefits!$R$4:$R$703,"cash"),0) -> 0 | G154: =IF(D154=1,SUMIFS(Benefits!$S$4:$S$703,Benefits!$B$4:$B$703,A154,Benefits!$F$4:$F$703,B154,Benefits!$R$4:$R$703,"revenue"),0) -> 0 | H154: =IF(D154=1,SUMIFS(Benefits!$S$4:$S$703,Benefits!$B$4:$B$703,A154,Benefits!$F$4:$F$703,B154,Benefits!$R$4:$R$703,"avoided_cost_realised"),0) -> 0 | I154: =IF(D154=1,SUMIFS(Benefits!$S$4:$S$703,Benefits!$B$4:$B$703,A154,Benefits!$F$4:$F$703,B154,Benefits!$R$4:$R$703,"capacity_converted"),0) -> 0 | J154: =SUM(F154:I154) -> 0 | K154: =J154-E154 -> 0 | L154: =IF(D154=1,L153+K154,0) -> -14000 | M154: =IF(D154=1,1/(1+Controls!$B$11)^B154,0) -> 0.96225062 | N154: =K154*M154 -> 0 | O154: =IF(D154=1,O153+N154,0) -> -14000 | P154: =IF(AND(D154=1,L154<0),1,0) -> 1 | Q154: =IF(AND(D154=1,O154<0),1,0) -> 1
A155: init-005 | B155: 7 | C155: =IF(COUNTIF('Scenario inputs'!$A$4:$A$213,Controls!$B$3&"|"&A155)>0,1,0) -> 1 | D155: =IF(AND(C155=1,B155<Controls!$B$12),1,0) -> 1 | E155: =IF(D155=1,SUMPRODUCT((Costs!$B$4:$B$903=A155)*(Costs!$D$4:$D$903="planned")*(Costs!$J$4:$J$903<=B155)*(Costs!$K$4:$K$903>B155)*Costs!$E$4:$E$903),0) -> 0 | F155: =IF(D155=1,SUMIFS(Benefits!$S$4:$S$703,Benefits!$B$4:$B$703,A155,Benefits!$F$4:$F$703,B155,Benefits!$R$4:$R$703,"cash"),0) -> 0 | G155: =IF(D155=1,SUMIFS(Benefits!$S$4:$S$703,Benefits!$B$4:$B$703,A155,Benefits!$F$4:$F$703,B155,Benefits!$R$4:$R$703,"revenue"),0) -> 0 | H155: =IF(D155=1,SUMIFS(Benefits!$S$4:$S$703,Benefits!$B$4:$B$703,A155,Benefits!$F$4:$F$703,B155,Benefits!$R$4:$R$703,"avoided_cost_realised"),0) -> 0 | I155: =IF(D155=1,SUMIFS(Benefits!$S$4:$S$703,Benefits!$B$4:$B$703,A155,Benefits!$F$4:$F$703,B155,Benefits!$R$4:$R$703,"capacity_converted"),0) -> 0 | J155: =SUM(F155:I155) -> 0 | K155: =J155-E155 -> 0 | L155: =IF(D155=1,L154+K155,0) -> -14000 | M155: =IF(D155=1,1/(1+Controls!$B$11)^B155,0) -> 0.95609908 | N155: =K155*M155 -> 0 | O155: =IF(D155=1,O154+N155,0) -> -14000 | P155: =IF(AND(D155=1,L155<0),1,0) -> 1 | Q155: =IF(AND(D155=1,O155<0),1,0) -> 1
A156: init-005 | B156: 8 | C156: =IF(COUNTIF('Scenario inputs'!$A$4:$A$213,Controls!$B$3&"|"&A156)>0,1,0) -> 1 | D156: =IF(AND(C156=1,B156<Controls!$B$12),1,0) -> 1 | E156: =IF(D156=1,SUMPRODUCT((Costs!$B$4:$B$903=A156)*(Costs!$D$4:$D$903="planned")*(Costs!$J$4:$J$903<=B156)*(Costs!$K$4:$K$903>B156)*Costs!$E$4:$E$903),0) -> 343650 | F156: =IF(D156=1,SUMIFS(Benefits!$S$4:$S$703,Benefits!$B$4:$B$703,A156,Benefits!$F$4:$F$703,B156,Benefits!$R$4:$R$703,"cash"),0) -> 0 | G156: =IF(D156=1,SUMIFS(Benefits!$S$4:$S$703,Benefits!$B$4:$B$703,A156,Benefits!$F$4:$F$703,B156,Benefits!$R$4:$R$703,"revenue"),0) -> 0 | H156: =IF(D156=1,SUMIFS(Benefits!$S$4:$S$703,Benefits!$B$4:$B$703,A156,Benefits!$F$4:$F$703,B156,Benefits!$R$4:$R$703,"avoided_cost_realised"),0) -> 0 | I156: =IF(D156=1,SUMIFS(Benefits!$S$4:$S$703,Benefits!$B$4:$B$703,A156,Benefits!$F$4:$F$703,B156,Benefits!$R$4:$R$703,"capacity_converted"),0) -> 0 | J156: =SUM(F156:I156) -> 0 | K156: =J156-E156 -> -343650 | L156: =IF(D156=1,L155+K156,0) -> -357650 | M156: =IF(D156=1,1/(1+Controls!$B$11)^B156,0) -> 0.94998686 | N156: =K156*M156 -> -326462.99 | O156: =IF(D156=1,O155+N156,0) -> -340462.99 | P156: =IF(AND(D156=1,L156<0),1,0) -> 1 | Q156: =IF(AND(D156=1,O156<0),1,0) -> 1
A157: init-005 | B157: 9 | C157: =IF(COUNTIF('Scenario inputs'!$A$4:$A$213,Controls!$B$3&"|"&A157)>0,1,0) -> 1 | D157: =IF(AND(C157=1,B157<Controls!$B$12),1,0) -> 1 | E157: =IF(D157=1,SUMPRODUCT((Costs!$B$4:$B$903=A157)*(Costs!$D$4:$D$903="planned")*(Costs!$J$4:$J$903<=B157)*(Costs!$K$4:$K$903>B157)*Costs!$E$4:$E$903),0) -> 176700 | F157: =IF(D157=1,SUMIFS(Benefits!$S$4:$S$703,Benefits!$B$4:$B$703,A157,Benefits!$F$4:$F$703,B157,Benefits!$R$4:$R$703,"cash"),0) -> 0 | G157: =IF(D157=1,SUMIFS(Benefits!$S$4:$S$703,Benefits!$B$4:$B$703,A157,Benefits!$F$4:$F$703,B157,Benefits!$R$4:$R$703,"revenue"),0) -> 0 | H157: =IF(D157=1,SUMIFS(Benefits!$S$4:$S$703,Benefits!$B$4:$B$703,A157,Benefits!$F$4:$F$703,B157,Benefits!$R$4:$R$703,"avoided_cost_realised"),0) -> 0 | I157: =IF(D157=1,SUMIFS(Benefits!$S$4:$S$703,Benefits!$B$4:$B$703,A157,Benefits!$F$4:$F$703,B157,Benefits!$R$4:$R$703,"capacity_converted"),0) -> 0 | J157: =SUM(F157:I157) -> 0 | K157: =J157-E157 -> -176700 | L157: =IF(D157=1,L156+K157,0) -> -534350 | M157: =IF(D157=1,1/(1+Controls!$B$11)^B157,0) -> 0.94391372 | N157: =K157*M157 -> -166789.55 | O157: =IF(D157=1,O156+N157,0) -> -507252.54 | P157: =IF(AND(D157=1,L157<0),1,0) -> 1 | Q157: =IF(AND(D157=1,O157<0),1,0) -> 1
A158: init-005 | B158: 10 | C158: =IF(COUNTIF('Scenario inputs'!$A$4:$A$213,Controls!$B$3&"|"&A158)>0,1,0) -> 1 | D158: =IF(AND(C158=1,B158<Controls!$B$12),1,0) -> 1 | E158: =IF(D158=1,SUMPRODUCT((Costs!$B$4:$B$903=A158)*(Costs!$D$4:$D$903="planned")*(Costs!$J$4:$J$903<=B158)*(Costs!$K$4:$K$903>B158)*Costs!$E$4:$E$903),0) -> 200650 | F158: =IF(D158=1,SUMIFS(Benefits!$S$4:$S$703,Benefits!$B$4:$B$703,A158,Benefits!$F$4:$F$703,B158,Benefits!$R$4:$R$703,"cash"),0) -> 8423.3754 | G158: =IF(D158=1,SUMIFS(Benefits!$S$4:$S$703,Benefits!$B$4:$B$703,A158,Benefits!$F$4:$F$703,B158,Benefits!$R$4:$R$703,"revenue"),0) -> 0 | H158: =IF(D158=1,SUMIFS(Benefits!$S$4:$S$703,Benefits!$B$4:$B$703,A158,Benefits!$F$4:$F$703,B158,Benefits!$R$4:$R$703,"avoided_cost_realised"),0) -> 0 | I158: =IF(D158=1,SUMIFS(Benefits!$S$4:$S$703,Benefits!$B$4:$B$703,A158,Benefits!$F$4:$F$703,B158,Benefits!$R$4:$R$703,"capacity_converted"),0) -> 0 | J158: =SUM(F158:I158) -> 8423.3754 | K158: =J158-E158 -> -192226.62 | L158: =IF(D158=1,L157+K158,0) -> -726576.62 | M158: =IF(D158=1,1/(1+Controls!$B$11)^B158,0) -> 0.93787941 | N158: =K158*M158 -> -180285.39 | O158: =IF(D158=1,O157+N158,0) -> -687537.93 | P158: =IF(AND(D158=1,L158<0),1,0) -> 1 | Q158: =IF(AND(D158=1,O158<0),1,0) -> 1
A159: init-005 | B159: 11 | C159: =IF(COUNTIF('Scenario inputs'!$A$4:$A$213,Controls!$B$3&"|"&A159)>0,1,0) -> 1 | D159: =IF(AND(C159=1,B159<Controls!$B$12),1,0) -> 1 | E159: =IF(D159=1,SUMPRODUCT((Costs!$B$4:$B$903=A159)*(Costs!$D$4:$D$903="planned")*(Costs!$J$4:$J$903<=B159)*(Costs!$K$4:$K$903>B159)*Costs!$E$4:$E$903),0) -> 14000 | F159: =IF(D159=1,SUMIFS(Benefits!$S$4:$S$703,Benefits!$B$4:$B$703,A159,Benefits!$F$4:$F$703,B159,Benefits!$R$4:$R$703,"cash"),0) -> 25270 | G159: =IF(D159=1,SUMIFS(Benefits!$S$4:$S$703,Benefits!$B$4:$B$703,A159,Benefits!$F$4:$F$703,B159,Benefits!$R$4:$R$703,"revenue"),0) -> 0 | H159: =IF(D159=1,SUMIFS(Benefits!$S$4:$S$703,Benefits!$B$4:$B$703,A159,Benefits!$F$4:$F$703,B159,Benefits!$R$4:$R$703,"avoided_cost_realised"),0) -> 0 | I159: =IF(D159=1,SUMIFS(Benefits!$S$4:$S$703,Benefits!$B$4:$B$703,A159,Benefits!$F$4:$F$703,B159,Benefits!$R$4:$R$703,"capacity_converted"),0) -> 0 | J159: =SUM(F159:I159) -> 25270 | K159: =J159-E159 -> 11270 | L159: =IF(D159=1,L158+K159,0) -> -715306.62 | M159: =IF(D159=1,1/(1+Controls!$B$11)^B159,0) -> 0.93188367 | N159: =K159*M159 -> 10502.329 | O159: =IF(D159=1,O158+N159,0) -> -677035.6 | P159: =IF(AND(D159=1,L159<0),1,0) -> 1 | Q159: =IF(AND(D159=1,O159<0),1,0) -> 1
A160: init-005 | B160: 12 | C160: =IF(COUNTIF('Scenario inputs'!$A$4:$A$213,Controls!$B$3&"|"&A160)>0,1,0) -> 1 | D160: =IF(AND(C160=1,B160<Controls!$B$12),1,0) -> 1 | E160: =IF(D160=1,SUMPRODUCT((Costs!$B$4:$B$903=A160)*(Costs!$D$4:$D$903="planned")*(Costs!$J$4:$J$903<=B160)*(Costs!$K$4:$K$903>B160)*Costs!$E$4:$E$903),0) -> 14000 | F160: =IF(D160=1,SUMIFS(Benefits!$S$4:$S$703,Benefits!$B$4:$B$703,A160,Benefits!$F$4:$F$703,B160,Benefits!$R$4:$R$703,"cash"),0) -> 50540 | G160: =IF(D160=1,SUMIFS(Benefits!$S$4:$S$703,Benefits!$B$4:$B$703,A160,Benefits!$F$4:$F$703,B160,Benefits!$R$4:$R$703,"revenue"),0) -> 0 | H160: =IF(D160=1,SUMIFS(Benefits!$S$4:$S$703,Benefits!$B$4:$B$703,A160,Benefits!$F$4:$F$703,B160,Benefits!$R$4:$R$703,"avoided_cost_realised"),0) -> 0 | I160: =IF(D160=1,SUMIFS(Benefits!$S$4:$S$703,Benefits!$B$4:$B$703,A160,Benefits!$F$4:$F$703,B160,Benefits!$R$4:$R$703,"capacity_converted"),0) -> 0 | J160: =SUM(F160:I160) -> 50540 | K160: =J160-E160 -> 36540 | L160: =IF(D160=1,L159+K160,0) -> -678766.62 | M160: =IF(D160=1,1/(1+Controls!$B$11)^B160,0) -> 0.92592626 | N160: =K160*M160 -> 33833.345 | O160: =IF(D160=1,O159+N160,0) -> -643202.26 | P160: =IF(AND(D160=1,L160<0),1,0) -> 1 | Q160: =IF(AND(D160=1,O160<0),1,0) -> 1
... A183: init-005 | B183: 35 | C183: =IF(COUNTIF('Scenario inputs'!$A$4:$A$213,Controls!$B$3&"|"&A183)>0,1,0) -> 1 | D183: =IF(AND(C183=1,B183<Controls!$B$12),1,0) -> 1 | E183: =IF(D183=1,SUMPRODUCT((Costs!$B$4:$B$903=A183)*(Costs!$D$4:$D$903="planned")*(Costs!$J$4:$J$903<=B183)*(Costs!$K$4:$K$903>B183)*Costs!$E$4:$E$903),0) -> 0 | F183: =IF(D183=1,SUMIFS(Benefits!$S$4:$S$703,Benefits!$B$4:$B$703,A183,Benefits!$F$4:$F$703,B183,Benefits!$R$4:$R$703,"cash"),0) -> 0 | G183: =IF(D183=1,SUMIFS(Benefits!$S$4:$S$703,Benefits!$B$4:$B$703,A183,Benefits!$F$4:$F$703,B183,Benefits!$R$4:$R$703,"revenue"),0) -> 0 | H183: =IF(D183=1,SUMIFS(Benefits!$S$4:$S$703,Benefits!$B$4:$B$703,A183,Benefits!$F$4:$F$703,B183,Benefits!$R$4:$R$703,"avoided_cost_realised"),0) -> 0 | I183: =IF(D183=1,SUMIFS(Benefits!$S$4:$S$703,Benefits!$B$4:$B$703,A183,Benefits!$F$4:$F$703,B183,Benefits!$R$4:$R$703,"capacity_converted"),0) -> 0 | J183: =SUM(F183:I183) -> 0 | K183: =J183-E183 -> 0 | L183: =IF(D183=1,L182+K183,0) -> 272066.75 | M183: =IF(D183=1,1/(1+Controls!$B$11)^B183,0) -> 0.79894062 | N183: =K183*M183 -> 0 | O183: =IF(D183=1,O182+N183,0) -> 209002.21 | P183: =IF(AND(D183=1,L183<0),1,0) -> 0 | Q183: =IF(AND(D183=1,O183<0),1,0) -> 0
A184: init-006 | B184: 0 | C184: =IF(COUNTIF('Scenario inputs'!$A$4:$A$213,Controls!$B$3&"|"&A184)>0,1,0) -> 1 | D184: =IF(AND(C184=1,B184<Controls!$B$12),1,0) -> 1 | E184: =IF(D184=1,SUMPRODUCT((Costs!$B$4:$B$903=A184)*(Costs!$D$4:$D$903="planned")*(Costs!$J$4:$J$903<=B184)*(Costs!$K$4:$K$903>B184)*Costs!$E$4:$E$903),0) -> 9000 | F184: =IF(D184=1,SUMIFS(Benefits!$S$4:$S$703,Benefits!$B$4:$B$703,A184,Benefits!$F$4:$F$703,B184,Benefits!$R$4:$R$703,"cash"),0) -> 0 | G184: =IF(D184=1,SUMIFS(Benefits!$S$4:$S$703,Benefits!$B$4:$B$703,A184,Benefits!$F$4:$F$703,B184,Benefits!$R$4:$R$703,"revenue"),0) -> 0 | H184: =IF(D184=1,SUMIFS(Benefits!$S$4:$S$703,Benefits!$B$4:$B$703,A184,Benefits!$F$4:$F$703,B184,Benefits!$R$4:$R$703,"avoided_cost_realised"),0) -> 0 | I184: =IF(D184=1,SUMIFS(Benefits!$S$4:$S$703,Benefits!$B$4:$B$703,A184,Benefits!$F$4:$F$703,B184,Benefits!$R$4:$R$703,"capacity_converted"),0) -> 0 | J184: =SUM(F184:I184) -> 0 | K184: =J184-E184 -> -9000 | L184: =IF(D184=1,K184,0) -> -9000 | M184: =IF(D184=1,1/(1+Controls!$B$11)^B184,0) -> 1 | N184: =K184*M184 -> -9000 | O184: =IF(D184=1,N184,0) -> -9000 | P184: =IF(AND(D184=1,L184<0),1,0) -> 1 | Q184: =IF(AND(D184=1,O184<0),1,0) -> 1
A185: init-006 | B185: 1 | C185: =IF(COUNTIF('Scenario inputs'!$A$4:$A$213,Controls!$B$3&"|"&A185)>0,1,0) -> 1 | D185: =IF(AND(C185=1,B185<Controls!$B$12),1,0) -> 1 | E185: =IF(D185=1,SUMPRODUCT((Costs!$B$4:$B$903=A185)*(Costs!$D$4:$D$903="planned")*(Costs!$J$4:$J$903<=B185)*(Costs!$K$4:$K$903>B185)*Costs!$E$4:$E$903),0) -> 0 | F185: =IF(D185=1,SUMIFS(Benefits!$S$4:$S$703,Benefits!$B$4:$B$703,A185,Benefits!$F$4:$F$703,B185,Benefits!$R$4:$R$703,"cash"),0) -> 0 | G185: =IF(D185=1,SUMIFS(Benefits!$S$4:$S$703,Benefits!$B$4:$B$703,A185,Benefits!$F$4:$F$703,B185,Benefits!$R$4:$R$703,"revenue"),0) -> 0 | H185: =IF(D185=1,SUMIFS(Benefits!$S$4:$S$703,Benefits!$B$4:$B$703,A185,Benefits!$F$4:$F$703,B185,Benefits!$R$4:$R$703,"avoided_cost_realised"),0) -> 0 | I185: =IF(D185=1,SUMIFS(Benefits!$S$4:$S$703,Benefits!$B$4:$B$703,A185,Benefits!$F$4:$F$703,B185,Benefits!$R$4:$R$703,"capacity_converted"),0) -> 0 | J185: =SUM(F185:I185) -> 0 | K185: =J185-E185 -> 0 | L185: =IF(D185=1,L184+K185,0) -> -9000 | M185: =IF(D185=1,1/(1+Controls!$B$11)^B185,0) -> 0.99360713 | N185: =K185*M185 -> 0 | O185: =IF(D185=1,O184+N185,0) -> -9000 | P185: =IF(AND(D185=1,L185<0),1,0) -> 1 | Q185: =IF(AND(D185=1,O185<0),1,0) -> 1
A186: init-006 | B186: 2 | C186: =IF(COUNTIF('Scenario inputs'!$A$4:$A$213,Controls!$B$3&"|"&A186)>0,1,0) -> 1 | D186: =IF(AND(C186=1,B186<Controls!$B$12),1,0) -> 1 | E186: =IF(D186=1,SUMPRODUCT((Costs!$B$4:$B$903=A186)*(Costs!$D$4:$D$903="planned")*(Costs!$J$4:$J$903<=B186)*(Costs!$K$4:$K$903>B186)*Costs!$E$4:$E$903),0) -> 0 | F186: =IF(D186=1,SUMIFS(Benefits!$S$4:$S$703,Benefits!$B$4:$B$703,A186,Benefits!$F$4:$F$703,B186,Benefits!$R$4:$R$703,"cash"),0) -> 0 | G186: =IF(D186=1,SUMIFS(Benefits!$S$4:$S$703,Benefits!$B$4:$B$703,A186,Benefits!$F$4:$F$703,B186,Benefits!$R$4:$R$703,"revenue"),0) -> 0 | H186: =IF(D186=1,SUMIFS(Benefits!$S$4:$S$703,Benefits!$B$4:$B$703,A186,Benefits!$F$4:$F$703,B186,Benefits!$R$4:$R$703,"avoided_cost_realised"),0) -> 0 | I186: =IF(D186=1,SUMIFS(Benefits!$S$4:$S$703,Benefits!$B$4:$B$703,A186,Benefits!$F$4:$F$703,B186,Benefits!$R$4:$R$703,"capacity_converted"),0) -> 0 | J186: =SUM(F186:I186) -> 0 | K186: =J186-E186 -> 0 | L186: =IF(D186=1,L185+K186,0) -> -9000 | M186: =IF(D186=1,1/(1+Controls!$B$11)^B186,0) -> 0.98725513 | N186: =K186*M186 -> 0 | O186: =IF(D186=1,O185+N186,0) -> -9000 | P186: =IF(AND(D186=1,L186<0),1,0) -> 1 | Q186: =IF(AND(D186=1,O186<0),1,0) -> 1
A187: init-006 | B187: 3 | C187: =IF(COUNTIF('Scenario inputs'!$A$4:$A$213,Controls!$B$3&"|"&A187)>0,1,0) -> 1 | D187: =IF(AND(C187=1,B187<Controls!$B$12),1,0) -> 1 | E187: =IF(D187=1,SUMPRODUCT((Costs!$B$4:$B$903=A187)*(Costs!$D$4:$D$903="planned")*(Costs!$J$4:$J$903<=B187)*(Costs!$K$4:$K$903>B187)*Costs!$E$4:$E$903),0) -> 0 | F187: =IF(D187=1,SUMIFS(Benefits!$S$4:$S$703,Benefits!$B$4:$B$703,A187,Benefits!$F$4:$F$703,B187,Benefits!$R$4:$R$703,"cash"),0) -> 0 | G187: =IF(D187=1,SUMIFS(Benefits!$S$4:$S$703,Benefits!$B$4:$B$703,A187,Benefits!$F$4:$F$703,B187,Benefits!$R$4:$R$703,"revenue"),0) -> 0 | H187: =IF(D187=1,SUMIFS(Benefits!$S$4:$S$703,Benefits!$B$4:$B$703,A187,Benefits!$F$4:$F$703,B187,Benefits!$R$4:$R$703,"avoided_cost_realised"),0) -> 0 | I187: =IF(D187=1,SUMIFS(Benefits!$S$4:$S$703,Benefits!$B$4:$B$703,A187,Benefits!$F$4:$F$703,B187,Benefits!$R$4:$R$703,"capacity_converted"),0) -> 0 | J187: =SUM(F187:I187) -> 0 | K187: =J187-E187 -> 0 | L187: =IF(D187=1,L186+K187,0) -> -9000 | M187: =IF(D187=1,1/(1+Controls!$B$11)^B187,0) -> 0.98094374 | N187: =K187*M187 -> 0 | O187: =IF(D187=1,O186+N187,0) -> -9000 | P187: =IF(AND(D187=1,L187<0),1,0) -> 1 | Q187: =IF(AND(D187=1,O187<0),1,0) -> 1
A188: init-006 | B188: 4 | C188: =IF(COUNTIF('Scenario inputs'!$A$4:$A$213,Controls!$B$3&"|"&A188)>0,1,0) -> 1 | D188: =IF(AND(C188=1,B188<Controls!$B$12),1,0) -> 1 | E188: =IF(D188=1,SUMPRODUCT((Costs!$B$4:$B$903=A188)*(Costs!$D$4:$D$903="planned")*(Costs!$J$4:$J$903<=B188)*(Costs!$K$4:$K$903>B188)*Costs!$E$4:$E$903),0) -> 0 | F188: =IF(D188=1,SUMIFS(Benefits!$S$4:$S$703,Benefits!$B$4:$B$703,A188,Benefits!$F$4:$F$703,B188,Benefits!$R$4:$R$703,"cash"),0) -> 0 | G188: =IF(D188=1,SUMIFS(Benefits!$S$4:$S$703,Benefits!$B$4:$B$703,A188,Benefits!$F$4:$F$703,B188,Benefits!$R$4:$R$703,"revenue"),0) -> 0 | H188: =IF(D188=1,SUMIFS(Benefits!$S$4:$S$703,Benefits!$B$4:$B$703,A188,Benefits!$F$4:$F$703,B188,Benefits!$R$4:$R$703,"avoided_cost_realised"),0) -> 0 | I188: =IF(D188=1,SUMIFS(Benefits!$S$4:$S$703,Benefits!$B$4:$B$703,A188,Benefits!$F$4:$F$703,B188,Benefits!$R$4:$R$703,"capacity_converted"),0) -> 0 | J188: =SUM(F188:I188) -> 0 | K188: =J188-E188 -> 0 | L188: =IF(D188=1,L187+K188,0) -> -9000 | M188: =IF(D188=1,1/(1+Controls!$B$11)^B188,0) -> 0.9746727 | N188: =K188*M188 -> 0 | O188: =IF(D188=1,O187+N188,0) -> -9000 | P188: =IF(AND(D188=1,L188<0),1,0) -> 1 | Q188: =IF(AND(D188=1,O188<0),1,0) -> 1
A189: init-006 | B189: 5 | C189: =IF(COUNTIF('Scenario inputs'!$A$4:$A$213,Controls!$B$3&"|"&A189)>0,1,0) -> 1 | D189: =IF(AND(C189=1,B189<Controls!$B$12),1,0) -> 1 | E189: =IF(D189=1,SUMPRODUCT((Costs!$B$4:$B$903=A189)*(Costs!$D$4:$D$903="planned")*(Costs!$J$4:$J$903<=B189)*(Costs!$K$4:$K$903>B189)*Costs!$E$4:$E$903),0) -> 0 | F189: =IF(D189=1,SUMIFS(Benefits!$S$4:$S$703,Benefits!$B$4:$B$703,A189,Benefits!$F$4:$F$703,B189,Benefits!$R$4:$R$703,"cash"),0) -> 0 | G189: =IF(D189=1,SUMIFS(Benefits!$S$4:$S$703,Benefits!$B$4:$B$703,A189,Benefits!$F$4:$F$703,B189,Benefits!$R$4:$R$703,"revenue"),0) -> 0 | H189: =IF(D189=1,SUMIFS(Benefits!$S$4:$S$703,Benefits!$B$4:$B$703,A189,Benefits!$F$4:$F$703,B189,Benefits!$R$4:$R$703,"avoided_cost_realised"),0) -> 0 | I189: =IF(D189=1,SUMIFS(Benefits!$S$4:$S$703,Benefits!$B$4:$B$703,A189,Benefits!$F$4:$F$703,B189,Benefits!$R$4:$R$703,"capacity_converted"),0) -> 0 | J189: =SUM(F189:I189) -> 0 | K189: =J189-E189 -> 0 | L189: =IF(D189=1,L188+K189,0) -> -9000 | M189: =IF(D189=1,1/(1+Controls!$B$11)^B189,0) -> 0.96844174 | N189: =K189*M189 -> 0 | O189: =IF(D189=1,O188+N189,0) -> -9000 | P189: =IF(AND(D189=1,L189<0),1,0) -> 1 | Q189: =IF(AND(D189=1,O189<0),1,0) -> 1
A190: init-006 | B190: 6 | C190: =IF(COUNTIF('Scenario inputs'!$A$4:$A$213,Controls!$B$3&"|"&A190)>0,1,0) -> 1 | D190: =IF(AND(C190=1,B190<Controls!$B$12),1,0) -> 1 | E190: =IF(D190=1,SUMPRODUCT((Costs!$B$4:$B$903=A190)*(Costs!$D$4:$D$903="planned")*(Costs!$J$4:$J$903<=B190)*(Costs!$K$4:$K$903>B190)*Costs!$E$4:$E$903),0) -> 0 | F190: =IF(D190=1,SUMIFS(Benefits!$S$4:$S$703,Benefits!$B$4:$B$703,A190,Benefits!$F$4:$F$703,B190,Benefits!$R$4:$R$703,"cash"),0) -> 0 | G190: =IF(D190=1,SUMIFS(Benefits!$S$4:$S$703,Benefits!$B$4:$B$703,A190,Benefits!$F$4:$F$703,B190,Benefits!$R$4:$R$703,"revenue"),0) -> 0 | H190: =IF(D190=1,SUMIFS(Benefits!$S$4:$S$703,Benefits!$B$4:$B$703,A190,Benefits!$F$4:$F$703,B190,Benefits!$R$4:$R$703,"avoided_cost_realised"),0) -> 0 | I190: =IF(D190=1,SUMIFS(Benefits!$S$4:$S$703,Benefits!$B$4:$B$703,A190,Benefits!$F$4:$F$703,B190,Benefits!$R$4:$R$703,"capacity_converted"),0) -> 0 | J190: =SUM(F190:I190) -> 0 | K190: =J190-E190 -> 0 | L190: =IF(D190=1,L189+K190,0) -> -9000 | M190: =IF(D190=1,1/(1+Controls!$B$11)^B190,0) -> 0.96225062 | N190: =K190*M190 -> 0 | O190: =IF(D190=1,O189+N190,0) -> -9000 | P190: =IF(AND(D190=1,L190<0),1,0) -> 1 | Q190: =IF(AND(D190=1,O190<0),1,0) -> 1
A191: init-006 | B191: 7 | C191: =IF(COUNTIF('Scenario inputs'!$A$4:$A$213,Controls!$B$3&"|"&A191)>0,1,0) -> 1 | D191: =IF(AND(C191=1,B191<Controls!$B$12),1,0) -> 1 | E191: =IF(D191=1,SUMPRODUCT((Costs!$B$4:$B$903=A191)*(Costs!$D$4:$D$903="planned")*(Costs!$J$4:$J$903<=B191)*(Costs!$K$4:$K$903>B191)*Costs!$E$4:$E$903),0) -> 0 | F191: =IF(D191=1,SUMIFS(Benefits!$S$4:$S$703,Benefits!$B$4:$B$703,A191,Benefits!$F$4:$F$703,B191,Benefits!$R$4:$R$703,"cash"),0) -> 0 | G191: =IF(D191=1,SUMIFS(Benefits!$S$4:$S$703,Benefits!$B$4:$B$703,A191,Benefits!$F$4:$F$703,B191,Benefits!$R$4:$R$703,"revenue"),0) -> 0 | H191: =IF(D191=1,SUMIFS(Benefits!$S$4:$S$703,Benefits!$B$4:$B$703,A191,Benefits!$F$4:$F$703,B191,Benefits!$R$4:$R$703,"avoided_cost_realised"),0) -> 0 | I191: =IF(D191=1,SUMIFS(Benefits!$S$4:$S$703,Benefits!$B$4:$B$703,A191,Benefits!$F$4:$F$703,B191,Benefits!$R$4:$R$703,"capacity_converted"),0) -> 0 | J191: =SUM(F191:I191) -> 0 | K191: =J191-E191 -> 0 | L191: =IF(D191=1,L190+K191,0) -> -9000 | M191: =IF(D191=1,1/(1+Controls!$B$11)^B191,0) -> 0.95609908 | N191: =K191*M191 -> 0 | O191: =IF(D191=1,O190+N191,0) -> -9000 | P191: =IF(AND(D191=1,L191<0),1,0) -> 1 | Q191: =IF(AND(D191=1,O191<0),1,0) -> 1
A192: init-006 | B192: 8 | C192: =IF(COUNTIF('Scenario inputs'!$A$4:$A$213,Controls!$B$3&"|"&A192)>0,1,0) -> 1 | D192: =IF(AND(C192=1,B192<Controls!$B$12),1,0) -> 1 | E192: =IF(D192=1,SUMPRODUCT((Costs!$B$4:$B$903=A192)*(Costs!$D$4:$D$903="planned")*(Costs!$J$4:$J$903<=B192)*(Costs!$K$4:$K$903>B192)*Costs!$E$4:$E$903),0) -> 0 | F192: =IF(D192=1,SUMIFS(Benefits!$S$4:$S$703,Benefits!$B$4:$B$703,A192,Benefits!$F$4:$F$703,B192,Benefits!$R$4:$R$703,"cash"),0) -> 0 | G192: =IF(D192=1,SUMIFS(Benefits!$S$4:$S$703,Benefits!$B$4:$B$703,A192,Benefits!$F$4:$F$703,B192,Benefits!$R$4:$R$703,"revenue"),0) -> 0 | H192: =IF(D192=1,SUMIFS(Benefits!$S$4:$S$703,Benefits!$B$4:$B$703,A192,Benefits!$F$4:$F$703,B192,Benefits!$R$4:$R$703,"avoided_cost_realised"),0) -> 0 | I192: =IF(D192=1,SUMIFS(Benefits!$S$4:$S$703,Benefits!$B$4:$B$703,A192,Benefits!$F$4:$F$703,B192,Benefits!$R$4:$R$703,"capacity_converted"),0) -> 0 | J192: =SUM(F192:I192) -> 0 | K192: =J192-E192 -> 0 | L192: =IF(D192=1,L191+K192,0) -> -9000 | M192: =IF(D192=1,1/(1+Controls!$B$11)^B192,0) -> 0.94998686 | N192: =K192*M192 -> 0 | O192: =IF(D192=1,O191+N192,0) -> -9000 | P192: =IF(AND(D192=1,L192<0),1,0) -> 1 | Q192: =IF(AND(D192=1,O192<0),1,0) -> 1
A193: init-006 | B193: 9 | C193: =IF(COUNTIF('Scenario inputs'!$A$4:$A$213,Controls!$B$3&"|"&A193)>0,1,0) -> 1 | D193: =IF(AND(C193=1,B193<Controls!$B$12),1,0) -> 1 | E193: =IF(D193=1,SUMPRODUCT((Costs!$B$4:$B$903=A193)*(Costs!$D$4:$D$903="planned")*(Costs!$J$4:$J$903<=B193)*(Costs!$K$4:$K$903>B193)*Costs!$E$4:$E$903),0) -> 0 | F193: =IF(D193=1,SUMIFS(Benefits!$S$4:$S$703,Benefits!$B$4:$B$703,A193,Benefits!$F$4:$F$703,B193,Benefits!$R$4:$R$703,"cash"),0) -> 0 | G193: =IF(D193=1,SUMIFS(Benefits!$S$4:$S$703,Benefits!$B$4:$B$703,A193,Benefits!$F$4:$F$703,B193,Benefits!$R$4:$R$703,"revenue"),0) -> 0 | H193: =IF(D193=1,SUMIFS(Benefits!$S$4:$S$703,Benefits!$B$4:$B$703,A193,Benefits!$F$4:$F$703,B193,Benefits!$R$4:$R$703,"avoided_cost_realised"),0) -> 0 | I193: =IF(D193=1,SUMIFS(Benefits!$S$4:$S$703,Benefits!$B$4:$B$703,A193,Benefits!$F$4:$F$703,B193,Benefits!$R$4:$R$703,"capacity_converted"),0) -> 0 | J193: =SUM(F193:I193) -> 0 | K193: =J193-E193 -> 0 | L193: =IF(D193=1,L192+K193,0) -> -9000 | M193: =IF(D193=1,1/(1+Controls!$B$11)^B193,0) -> 0.94391372 | N193: =K193*M193 -> 0 | O193: =IF(D193=1,O192+N193,0) -> -9000 | P193: =IF(AND(D193=1,L193<0),1,0) -> 1 | Q193: =IF(AND(D193=1,O193<0),1,0) -> 1
A194: init-006 | B194: 10 | C194: =IF(COUNTIF('Scenario inputs'!$A$4:$A$213,Controls!$B$3&"|"&A194)>0,1,0) -> 1 | D194: =IF(AND(C194=1,B194<Controls!$B$12),1,0) -> 1 | E194: =IF(D194=1,SUMPRODUCT((Costs!$B$4:$B$903=A194)*(Costs!$D$4:$D$903="planned")*(Costs!$J$4:$J$903<=B194)*(Costs!$K$4:$K$903>B194)*Costs!$E$4:$E$903),0) -> 0 | F194: =IF(D194=1,SUMIFS(Benefits!$S$4:$S$703,Benefits!$B$4:$B$703,A194,Benefits!$F$4:$F$703,B194,Benefits!$R$4:$R$703,"cash"),0) -> 0 | G194: =IF(D194=1,SUMIFS(Benefits!$S$4:$S$703,Benefits!$B$4:$B$703,A194,Benefits!$F$4:$F$703,B194,Benefits!$R$4:$R$703,"revenue"),0) -> 0 | H194: =IF(D194=1,SUMIFS(Benefits!$S$4:$S$703,Benefits!$B$4:$B$703,A194,Benefits!$F$4:$F$703,B194,Benefits!$R$4:$R$703,"avoided_cost_realised"),0) -> 0 | I194: =IF(D194=1,SUMIFS(Benefits!$S$4:$S$703,Benefits!$B$4:$B$703,A194,Benefits!$F$4:$F$703,B194,Benefits!$R$4:$R$703,"capacity_converted"),0) -> 0 | J194: =SUM(F194:I194) -> 0 | K194: =J194-E194 -> 0 | L194: =IF(D194=1,L193+K194,0) -> -9000 | M194: =IF(D194=1,1/(1+Controls!$B$11)^B194,0) -> 0.93787941 | N194: =K194*M194 -> 0 | O194: =IF(D194=1,O193+N194,0) -> -9000 | P194: =IF(AND(D194=1,L194<0),1,0) -> 1 | Q194: =IF(AND(D194=1,O194<0),1,0) -> 1
A195: init-006 | B195: 11 | C195: =IF(COUNTIF('Scenario inputs'!$A$4:$A$213,Controls!$B$3&"|"&A195)>0,1,0) -> 1 | D195: =IF(AND(C195=1,B195<Controls!$B$12),1,0) -> 1 | E195: =IF(D195=1,SUMPRODUCT((Costs!$B$4:$B$903=A195)*(Costs!$D$4:$D$903="planned")*(Costs!$J$4:$J$903<=B195)*(Costs!$K$4:$K$903>B195)*Costs!$E$4:$E$903),0) -> 0 | F195: =IF(D195=1,SUMIFS(Benefits!$S$4:$S$703,Benefits!$B$4:$B$703,A195,Benefits!$F$4:$F$703,B195,Benefits!$R$4:$R$703,"cash"),0) -> 0 | G195: =IF(D195=1,SUMIFS(Benefits!$S$4:$S$703,Benefits!$B$4:$B$703,A195,Benefits!$F$4:$F$703,B195,Benefits!$R$4:$R$703,"revenue"),0) -> 0 | H195: =IF(D195=1,SUMIFS(Benefits!$S$4:$S$703,Benefits!$B$4:$B$703,A195,Benefits!$F$4:$F$703,B195,Benefits!$R$4:$R$703,"avoided_cost_realised"),0) -> 0 | I195: =IF(D195=1,SUMIFS(Benefits!$S$4:$S$703,Benefits!$B$4:$B$703,A195,Benefits!$F$4:$F$703,B195,Benefits!$R$4:$R$703,"capacity_converted"),0) -> 0 | J195: =SUM(F195:I195) -> 0 | K195: =J195-E195 -> 0 | L195: =IF(D195=1,L194+K195,0) -> -9000 | M195: =IF(D195=1,1/(1+Controls!$B$11)^B195,0) -> 0.93188367 | N195: =K195*M195 -> 0 | O195: =IF(D195=1,O194+N195,0) -> -9000 | P195: =IF(AND(D195=1,L195<0),1,0) -> 1 | Q195: =IF(AND(D195=1,O195<0),1,0) -> 1
A196: init-006 | B196: 12 | C196: =IF(COUNTIF('Scenario inputs'!$A$4:$A$213,Controls!$B$3&"|"&A196)>0,1,0) -> 1 | D196: =IF(AND(C196=1,B196<Controls!$B$12),1,0) -> 1 | E196: =IF(D196=1,SUMPRODUCT((Costs!$B$4:$B$903=A196)*(Costs!$D$4:$D$903="planned")*(Costs!$J$4:$J$903<=B196)*(Costs!$K$4:$K$903>B196)*Costs!$E$4:$E$903),0) -> 150400 | F196: =IF(D196=1,SUMIFS(Benefits!$S$4:$S$703,Benefits!$B$4:$B$703,A196,Benefits!$F$4:$F$703,B196,Benefits!$R$4:$R$703,"cash"),0) -> 0 | G196: =IF(D196=1,SUMIFS(Benefits!$S$4:$S$703,Benefits!$B$4:$B$703,A196,Benefits!$F$4:$F$703,B196,Benefits!$R$4:$R$703,"revenue"),0) -> 0 | H196: =IF(D196=1,SUMIFS(Benefits!$S$4:$S$703,Benefits!$B$4:$B$703,A196,Benefits!$F$4:$F$703,B196,Benefits!$R$4:$R$703,"avoided_cost_realised"),0) -> 0 | I196: =IF(D196=1,SUMIFS(Benefits!$S$4:$S$703,Benefits!$B$4:$B$703,A196,Benefits!$F$4:$F$703,B196,Benefits!$R$4:$R$703,"capacity_converted"),0) -> 0 | J196: =SUM(F196:I196) -> 0 | K196: =J196-E196 -> -150400 | L196: =IF(D196=1,L195+K196,0) -> -159400 | M196: =IF(D196=1,1/(1+Controls!$B$11)^B196,0) -> 0.92592626 | N196: =K196*M196 -> -139259.31 | O196: =IF(D196=1,O195+N196,0) -> -148259.31 | P196: =IF(AND(D196=1,L196<0),1,0) -> 1 | Q196: =IF(AND(D196=1,O196<0),1,0) -> 1
... A219: init-006 | B219: 35 | C219: =IF(COUNTIF('Scenario inputs'!$A$4:$A$213,Controls!$B$3&"|"&A219)>0,1,0) -> 1 | D219: =IF(AND(C219=1,B219<Controls!$B$12),1,0) -> 1 | E219: =IF(D219=1,SUMPRODUCT((Costs!$B$4:$B$903=A219)*(Costs!$D$4:$D$903="planned")*(Costs!$J$4:$J$903<=B219)*(Costs!$K$4:$K$903>B219)*Costs!$E$4:$E$903),0) -> 0 | F219: =IF(D219=1,SUMIFS(Benefits!$S$4:$S$703,Benefits!$B$4:$B$703,A219,Benefits!$F$4:$F$703,B219,Benefits!$R$4:$R$703,"cash"),0) -> 0 | G219: =IF(D219=1,SUMIFS(Benefits!$S$4:$S$703,Benefits!$B$4:$B$703,A219,Benefits!$F$4:$F$703,B219,Benefits!$R$4:$R$703,"revenue"),0) -> 0 | H219: =IF(D219=1,SUMIFS(Benefits!$S$4:$S$703,Benefits!$B$4:$B$703,A219,Benefits!$F$4:$F$703,B219,Benefits!$R$4:$R$703,"avoided_cost_realised"),0) -> 0 | I219: =IF(D219=1,SUMIFS(Benefits!$S$4:$S$703,Benefits!$B$4:$B$703,A219,Benefits!$F$4:$F$703,B219,Benefits!$R$4:$R$703,"capacity_converted"),0) -> 0 | J219: =SUM(F219:I219) -> 0 | K219: =J219-E219 -> 0 | L219: =IF(D219=1,L218+K219,0) -> -588850 | M219: =IF(D219=1,1/(1+Controls!$B$11)^B219,0) -> 0.79894062 | N219: =K219*M219 -> 0 | O219: =IF(D219=1,O218+N219,0) -> -535631.92 | P219: =IF(AND(D219=1,L219<0),1,0) -> 1 | Q219: =IF(AND(D219=1,O219<0),1,0) -> 1
A220: init-007 | B220: 0 | C220: =IF(COUNTIF('Scenario inputs'!$A$4:$A$213,Controls!$B$3&"|"&A220)>0,1,0) -> 1 | D220: =IF(AND(C220=1,B220<Controls!$B$12),1,0) -> 1 | E220: =IF(D220=1,SUMPRODUCT((Costs!$B$4:$B$903=A220)*(Costs!$D$4:$D$903="planned")*(Costs!$J$4:$J$903<=B220)*(Costs!$K$4:$K$903>B220)*Costs!$E$4:$E$903),0) -> 1017700 | F220: =IF(D220=1,SUMIFS(Benefits!$S$4:$S$703,Benefits!$B$4:$B$703,A220,Benefits!$F$4:$F$703,B220,Benefits!$R$4:$R$703,"cash"),0) -> 0 | G220: =IF(D220=1,SUMIFS(Benefits!$S$4:$S$703,Benefits!$B$4:$B$703,A220,Benefits!$F$4:$F$703,B220,Benefits!$R$4:$R$703,"revenue"),0) -> 0 | H220: =IF(D220=1,SUMIFS(Benefits!$S$4:$S$703,Benefits!$B$4:$B$703,A220,Benefits!$F$4:$F$703,B220,Benefits!$R$4:$R$703,"avoided_cost_realised"),0) -> 0 | I220: =IF(D220=1,SUMIFS(Benefits!$S$4:$S$703,Benefits!$B$4:$B$703,A220,Benefits!$F$4:$F$703,B220,Benefits!$R$4:$R$703,"capacity_converted"),0) -> 0 | J220: =SUM(F220:I220) -> 0 | K220: =J220-E220 -> -1017700 | L220: =IF(D220=1,K220,0) -> -1017700 | M220: =IF(D220=1,1/(1+Controls!$B$11)^B220,0) -> 1 | N220: =K220*M220 -> -1017700 | O220: =IF(D220=1,N220,0) -> -1017700 | P220: =IF(AND(D220=1,L220<0),1,0) -> 1 | Q220: =IF(AND(D220=1,O220<0),1,0) -> 1
A221: init-007 | B221: 1 | C221: =IF(COUNTIF('Scenario inputs'!$A$4:$A$213,Controls!$B$3&"|"&A221)>0,1,0) -> 1 | D221: =IF(AND(C221=1,B221<Controls!$B$12),1,0) -> 1 | E221: =IF(D221=1,SUMPRODUCT((Costs!$B$4:$B$903=A221)*(Costs!$D$4:$D$903="planned")*(Costs!$J$4:$J$903<=B221)*(Costs!$K$4:$K$903>B221)*Costs!$E$4:$E$903),0) -> 572300 | F221: =IF(D221=1,SUMIFS(Benefits!$S$4:$S$703,Benefits!$B$4:$B$703,A221,Benefits!$F$4:$F$703,B221,Benefits!$R$4:$R$703,"cash"),0) -> 0 | G221: =IF(D221=1,SUMIFS(Benefits!$S$4:$S$703,Benefits!$B$4:$B$703,A221,Benefits!$F$4:$F$703,B221,Benefits!$R$4:$R$703,"revenue"),0) -> 8801.4593 | H221: =IF(D221=1,SUMIFS(Benefits!$S$4:$S$703,Benefits!$B$4:$B$703,A221,Benefits!$F$4:$F$703,B221,Benefits!$R$4:$R$703,"avoided_cost_realised"),0) -> 0 | I221: =IF(D221=1,SUMIFS(Benefits!$S$4:$S$703,Benefits!$B$4:$B$703,A221,Benefits!$F$4:$F$703,B221,Benefits!$R$4:$R$703,"capacity_converted"),0) -> 0 | J221: =SUM(F221:I221) -> 8801.4593 | K221: =J221-E221 -> -563498.54 | L221: =IF(D221=1,L220+K221,0) -> -1581198.5 | M221: =IF(D221=1,1/(1+Controls!$B$11)^B221,0) -> 0.99360713 | N221: =K221*M221 -> -559896.17 | O221: =IF(D221=1,O220+N221,0) -> -1577596.2 | P221: =IF(AND(D221=1,L221<0),1,0) -> 1 | Q221: =IF(AND(D221=1,O221<0),1,0) -> 1
A222: init-007 | B222: 2 | C222: =IF(COUNTIF('Scenario inputs'!$A$4:$A$213,Controls!$B$3&"|"&A222)>0,1,0) -> 1 | D222: =IF(AND(C222=1,B222<Controls!$B$12),1,0) -> 1 | E222: =IF(D222=1,SUMPRODUCT((Costs!$B$4:$B$903=A222)*(Costs!$D$4:$D$903="planned")*(Costs!$J$4:$J$903<=B222)*(Costs!$K$4:$K$903>B222)*Costs!$E$4:$E$903),0) -> 30000 | F222: =IF(D222=1,SUMIFS(Benefits!$S$4:$S$703,Benefits!$B$4:$B$703,A222,Benefits!$F$4:$F$703,B222,Benefits!$R$4:$R$703,"cash"),0) -> 0 | G222: =IF(D222=1,SUMIFS(Benefits!$S$4:$S$703,Benefits!$B$4:$B$703,A222,Benefits!$F$4:$F$703,B222,Benefits!$R$4:$R$703,"revenue"),0) -> 26404.061 | H222: =IF(D222=1,SUMIFS(Benefits!$S$4:$S$703,Benefits!$B$4:$B$703,A222,Benefits!$F$4:$F$703,B222,Benefits!$R$4:$R$703,"avoided_cost_realised"),0) -> 0 | I222: =IF(D222=1,SUMIFS(Benefits!$S$4:$S$703,Benefits!$B$4:$B$703,A222,Benefits!$F$4:$F$703,B222,Benefits!$R$4:$R$703,"capacity_converted"),0) -> 628.61253 | J222: =SUM(F222:I222) -> 27032.674 | K222: =J222-E222 -> -2967.3264 | L222: =IF(D222=1,L221+K222,0) -> -1584165.9 | M222: =IF(D222=1,1/(1+Controls!$B$11)^B222,0) -> 0.98725513 | N222: =K222*M222 -> -2929.5082 | O222: =IF(D222=1,O221+N222,0) -> -1580525.7 | P222: =IF(AND(D222=1,L222<0),1,0) -> 1 | Q222: =IF(AND(D222=1,O222<0),1,0) -> 1
A223: init-007 | B223: 3 | C223: =IF(COUNTIF('Scenario inputs'!$A$4:$A$213,Controls!$B$3&"|"&A223)>0,1,0) -> 1 | D223: =IF(AND(C223=1,B223<Controls!$B$12),1,0) -> 1 | E223: =IF(D223=1,SUMPRODUCT((Costs!$B$4:$B$903=A223)*(Costs!$D$4:$D$903="planned")*(Costs!$J$4:$J$903<=B223)*(Costs!$K$4:$K$903>B223)*Costs!$E$4:$E$903),0) -> 30000 | F223: =IF(D223=1,SUMIFS(Benefits!$S$4:$S$703,Benefits!$B$4:$B$703,A223,Benefits!$F$4:$F$703,B223,Benefits!$R$4:$R$703,"cash"),0) -> 0 | G223: =IF(D223=1,SUMIFS(Benefits!$S$4:$S$703,Benefits!$B$4:$B$703,A223,Benefits!$F$4:$F$703,B223,Benefits!$R$4:$R$703,"revenue"),0) -> 52808.439 | H223: =IF(D223=1,SUMIFS(Benefits!$S$4:$S$703,Benefits!$B$4:$B$703,A223,Benefits!$F$4:$F$703,B223,Benefits!$R$4:$R$703,"avoided_cost_realised"),0) -> 0 | I223: =IF(D223=1,SUMIFS(Benefits!$S$4:$S$703,Benefits!$B$4:$B$703,A223,Benefits!$F$4:$F$703,B223,Benefits!$R$4:$R$703,"capacity_converted"),0) -> 1885.815 | J223: =SUM(F223:I223) -> 54694.254 | K223: =J223-E223 -> 24694.254 | L223: =IF(D223=1,L222+K223,0) -> -1559471.6 | M223: =IF(D223=1,1/(1+Controls!$B$11)^B223,0) -> 0.98094374 | N223: =K223*M223 -> 24223.674 | O223: =IF(D223=1,O222+N223,0) -> -1556302 | P223: =IF(AND(D223=1,L223<0),1,0) -> 1 | Q223: =IF(AND(D223=1,O223<0),1,0) -> 1
A224: init-007 | B224: 4 | C224: =IF(COUNTIF('Scenario inputs'!$A$4:$A$213,Controls!$B$3&"|"&A224)>0,1,0) -> 1 | D224: =IF(AND(C224=1,B224<Controls!$B$12),1,0) -> 1 | E224: =IF(D224=1,SUMPRODUCT((Costs!$B$4:$B$903=A224)*(Costs!$D$4:$D$903="planned")*(Costs!$J$4:$J$903<=B224)*(Costs!$K$4:$K$903>B224)*Costs!$E$4:$E$903),0) -> 30000 | F224: =IF(D224=1,SUMIFS(Benefits!$S$4:$S$703,Benefits!$B$4:$B$703,A224,Benefits!$F$4:$F$703,B224,Benefits!$R$4:$R$703,"cash"),0) -> 0 | G224: =IF(D224=1,SUMIFS(Benefits!$S$4:$S$703,Benefits!$B$4:$B$703,A224,Benefits!$F$4:$F$703,B224,Benefits!$R$4:$R$703,"revenue"),0) -> 88013.959 | H224: =IF(D224=1,SUMIFS(Benefits!$S$4:$S$703,Benefits!$B$4:$B$703,A224,Benefits!$F$4:$F$703,B224,Benefits!$R$4:$R$703,"avoided_cost_realised"),0) -> 0 | I224: =IF(D224=1,SUMIFS(Benefits!$S$4:$S$703,Benefits!$B$4:$B$703,A224,Benefits!$F$4:$F$703,B224,Benefits!$R$4:$R$703,"capacity_converted"),0) -> 3771.6526 | J224: =SUM(F224:I224) -> 91785.612 | K224: =J224-E224 -> 61785.612 | L224: =IF(D224=1,L223+K224,0) -> -1497686 | M224: =IF(D224=1,1/(1+Controls!$B$11)^B224,0) -> 0.9746727 | N224: =K224*M224 -> 60220.749 | O224: =IF(D224=1,O223+N224,0) -> -1496081.3 | P224: =IF(AND(D224=1,L224<0),1,0) -> 1 | Q224: =IF(AND(D224=1,O224<0),1,0) -> 1
A225: init-007 | B225: 5 | C225: =IF(COUNTIF('Scenario inputs'!$A$4:$A$213,Controls!$B$3&"|"&A225)>0,1,0) -> 1 | D225: =IF(AND(C225=1,B225<Controls!$B$12),1,0) -> 1 | E225: =IF(D225=1,SUMPRODUCT((Costs!$B$4:$B$903=A225)*(Costs!$D$4:$D$903="planned")*(Costs!$J$4:$J$903<=B225)*(Costs!$K$4:$K$903>B225)*Costs!$E$4:$E$903),0) -> 30000 | F225: =IF(D225=1,SUMIFS(Benefits!$S$4:$S$703,Benefits!$B$4:$B$703,A225,Benefits!$F$4:$F$703,B225,Benefits!$R$4:$R$703,"cash"),0) -> 0 | G225: =IF(D225=1,SUMIFS(Benefits!$S$4:$S$703,Benefits!$B$4:$B$703,A225,Benefits!$F$4:$F$703,B225,Benefits!$R$4:$R$703,"revenue"),0) -> 132020.94 | H225: =IF(D225=1,SUMIFS(Benefits!$S$4:$S$703,Benefits!$B$4:$B$703,A225,Benefits!$F$4:$F$703,B225,Benefits!$R$4:$R$703,"avoided_cost_realised"),0) -> 0 | I225: =IF(D225=1,SUMIFS(Benefits!$S$4:$S$703,Benefits!$B$4:$B$703,A225,Benefits!$F$4:$F$703,B225,Benefits!$R$4:$R$703,"capacity_converted"),0) -> 6286.0801 | J225: =SUM(F225:I225) -> 138307.02 | K225: =J225-E225 -> 108307.02 | L225: =IF(D225=1,L224+K225,0) -> -1389379 | M225: =IF(D225=1,1/(1+Controls!$B$11)^B225,0) -> 0.96844174 | N225: =K225*M225 -> 104889.04 | O225: =IF(D225=1,O224+N225,0) -> -1391192.2 | P225: =IF(AND(D225=1,L225<0),1,0) -> 1 | Q225: =IF(AND(D225=1,O225<0),1,0) -> 1
A226: init-007 | B226: 6 | C226: =IF(COUNTIF('Scenario inputs'!$A$4:$A$213,Controls!$B$3&"|"&A226)>0,1,0) -> 1 | D226: =IF(AND(C226=1,B226<Controls!$B$12),1,0) -> 1 | E226: =IF(D226=1,SUMPRODUCT((Costs!$B$4:$B$903=A226)*(Costs!$D$4:$D$903="planned")*(Costs!$J$4:$J$903<=B226)*(Costs!$K$4:$K$903>B226)*Costs!$E$4:$E$903),0) -> 30000 | F226: =IF(D226=1,SUMIFS(Benefits!$S$4:$S$703,Benefits!$B$4:$B$703,A226,Benefits!$F$4:$F$703,B226,Benefits!$R$4:$R$703,"cash"),0) -> 0 | G226: =IF(D226=1,SUMIFS(Benefits!$S$4:$S$703,Benefits!$B$4:$B$703,A226,Benefits!$F$4:$F$703,B226,Benefits!$R$4:$R$703,"revenue"),0) -> 184829.06 | H226: =IF(D226=1,SUMIFS(Benefits!$S$4:$S$703,Benefits!$B$4:$B$703,A226,Benefits!$F$4:$F$703,B226,Benefits!$R$4:$R$703,"avoided_cost_realised"),0) -> 0 | I226: =IF(D226=1,SUMIFS(Benefits!$S$4:$S$703,Benefits!$B$4:$B$703,A226,Benefits!$F$4:$F$703,B226,Benefits!$R$4:$R$703,"capacity_converted"),0) -> 9429.1201 | J226: =SUM(F226:I226) -> 194258.18 | K226: =J226-E226 -> 164258.18 | L226: =IF(D226=1,L225+K226,0) -> -1225120.8 | M226: =IF(D226=1,1/(1+Controls!$B$11)^B226,0) -> 0.96225062 | N226: =K226*M226 -> 158057.54 | O226: =IF(D226=1,O225+N226,0) -> -1233134.7 | P226: =IF(AND(D226=1,L226<0),1,0) -> 1 | Q226: =IF(AND(D226=1,O226<0),1,0) -> 1
A227: init-007 | B227: 7 | C227: =IF(COUNTIF('Scenario inputs'!$A$4:$A$213,Controls!$B$3&"|"&A227)>0,1,0) -> 1 | D227: =IF(AND(C227=1,B227<Controls!$B$12),1,0) -> 1 | E227: =IF(D227=1,SUMPRODUCT((Costs!$B$4:$B$903=A227)*(Costs!$D$4:$D$903="planned")*(Costs!$J$4:$J$903<=B227)*(Costs!$K$4:$K$903>B227)*Costs!$E$4:$E$903),0) -> 31650 | F227: =IF(D227=1,SUMIFS(Benefits!$S$4:$S$703,Benefits!$B$4:$B$703,A227,Benefits!$F$4:$F$703,B227,Benefits!$R$4:$R$703,"cash"),0) -> 0 | G227: =IF(D227=1,SUMIFS(Benefits!$S$4:$S$703,Benefits!$B$4:$B$703,A227,Benefits!$F$4:$F$703,B227,Benefits!$R$4:$R$703,"revenue"),0) -> 246438.96 | H227: =IF(D227=1,SUMIFS(Benefits!$S$4:$S$703,Benefits!$B$4:$B$703,A227,Benefits!$F$4:$F$703,B227,Benefits!$R$4:$R$703,"avoided_cost_realised"),0) -> 0 | I227: =IF(D227=1,SUMIFS(Benefits!$S$4:$S$703,Benefits!$B$4:$B$703,A227,Benefits!$F$4:$F$703,B227,Benefits!$R$4:$R$703,"capacity_converted"),0) -> 13200.75 | J227: =SUM(F227:I227) -> 259639.71 | K227: =J227-E227 -> 227989.71 | L227: =IF(D227=1,L226+K227,0) -> -997131.09 | M227: =IF(D227=1,1/(1+Controls!$B$11)^B227,0) -> 0.95609908 | N227: =K227*M227 -> 217980.75 | O227: =IF(D227=1,O226+N227,0) -> -1015153.9 | P227: =IF(AND(D227=1,L227<0),1,0) -> 1 | Q227: =IF(AND(D227=1,O227<0),1,0) -> 1
A228: init-007 | B228: 8 | C228: =IF(COUNTIF('Scenario inputs'!$A$4:$A$213,Controls!$B$3&"|"&A228)>0,1,0) -> 1 | D228: =IF(AND(C228=1,B228<Controls!$B$12),1,0) -> 1 | E228: =IF(D228=1,SUMPRODUCT((Costs!$B$4:$B$903=A228)*(Costs!$D$4:$D$903="planned")*(Costs!$J$4:$J$903<=B228)*(Costs!$K$4:$K$903>B228)*Costs!$E$4:$E$903),0) -> 31650 | F228: =IF(D228=1,SUMIFS(Benefits!$S$4:$S$703,Benefits!$B$4:$B$703,A228,Benefits!$F$4:$F$703,B228,Benefits!$R$4:$R$703,"cash"),0) -> 0 | G228: =IF(D228=1,SUMIFS(Benefits!$S$4:$S$703,Benefits!$B$4:$B$703,A228,Benefits!$F$4:$F$703,B228,Benefits!$R$4:$R$703,"revenue"),0) -> 316850 | H228: =IF(D228=1,SUMIFS(Benefits!$S$4:$S$703,Benefits!$B$4:$B$703,A228,Benefits!$F$4:$F$703,B228,Benefits!$R$4:$R$703,"avoided_cost_realised"),0) -> 0 | I228: =IF(D228=1,SUMIFS(Benefits!$S$4:$S$703,Benefits!$B$4:$B$703,A228,Benefits!$F$4:$F$703,B228,Benefits!$R$4:$R$703,"capacity_converted"),0) -> 17601.015 | J228: =SUM(F228:I228) -> 334451.02 | K228: =J228-E228 -> 302801.02 | L228: =IF(D228=1,L227+K228,0) -> -694330.08 | M228: =IF(D228=1,1/(1+Controls!$B$11)^B228,0) -> 0.94998686 | N228: =K228*M228 -> 287656.99 | O228: =IF(D228=1,O227+N228,0) -> -727496.94 | P228: =IF(AND(D228=1,L228<0),1,0) -> 1 | Q228: =IF(AND(D228=1,O228<0),1,0) -> 1
A229: init-007 | B229: 9 | C229: =IF(COUNTIF('Scenario inputs'!$A$4:$A$213,Controls!$B$3&"|"&A229)>0,1,0) -> 1 | D229: =IF(AND(C229=1,B229<Controls!$B$12),1,0) -> 1 | E229: =IF(D229=1,SUMPRODUCT((Costs!$B$4:$B$903=A229)*(Costs!$D$4:$D$903="planned")*(Costs!$J$4:$J$903<=B229)*(Costs!$K$4:$K$903>B229)*Costs!$E$4:$E$903),0) -> 31650 | F229: =IF(D229=1,SUMIFS(Benefits!$S$4:$S$703,Benefits!$B$4:$B$703,A229,Benefits!$F$4:$F$703,B229,Benefits!$R$4:$R$703,"cash"),0) -> 0 | G229: =IF(D229=1,SUMIFS(Benefits!$S$4:$S$703,Benefits!$B$4:$B$703,A229,Benefits!$F$4:$F$703,B229,Benefits!$R$4:$R$703,"revenue"),0) -> 316850 | H229: =IF(D229=1,SUMIFS(Benefits!$S$4:$S$703,Benefits!$B$4:$B$703,A229,Benefits!$F$4:$F$703,B229,Benefits!$R$4:$R$703,"avoided_cost_realised"),0) -> 0 | I229: =IF(D229=1,SUMIFS(Benefits!$S$4:$S$703,Benefits!$B$4:$B$703,A229,Benefits!$F$4:$F$703,B229,Benefits!$R$4:$R$703,"capacity_converted"),0) -> 22629.87 | J229: =SUM(F229:I229) -> 339479.87 | K229: =J229-E229 -> 307829.87 | L229: =IF(D229=1,L228+K229,0) -> -386500.21 | M229: =IF(D229=1,1/(1+Controls!$B$11)^B229,0) -> 0.94391372 | N229: =K229*M229 -> 290564.84 | O229: =IF(D229=1,O228+N229,0) -> -436932.1 | P229: =IF(AND(D229=1,L229<0),1,0) -> 1 | Q229: =IF(AND(D229=1,O229<0),1,0) -> 1
A230: init-007 | B230: 10 | C230: =IF(COUNTIF('Scenario inputs'!$A$4:$A$213,Controls!$B$3&"|"&A230)>0,1,0) -> 1 | D230: =IF(AND(C230=1,B230<Controls!$B$12),1,0) -> 1 | E230: =IF(D230=1,SUMPRODUCT((Costs!$B$4:$B$903=A230)*(Costs!$D$4:$D$903="planned")*(Costs!$J$4:$J$903<=B230)*(Costs!$K$4:$K$903>B230)*Costs!$E$4:$E$903),0) -> 31650 | F230: =IF(D230=1,SUMIFS(Benefits!$S$4:$S$703,Benefits!$B$4:$B$703,A230,Benefits!$F$4:$F$703,B230,Benefits!$R$4:$R$703,"cash"),0) -> 0 | G230: =IF(D230=1,SUMIFS(Benefits!$S$4:$S$703,Benefits!$B$4:$B$703,A230,Benefits!$F$4:$F$703,B230,Benefits!$R$4:$R$703,"revenue"),0) -> 316850 | H230: =IF(D230=1,SUMIFS(Benefits!$S$4:$S$703,Benefits!$B$4:$B$703,A230,Benefits!$F$4:$F$703,B230,Benefits!$R$4:$R$703,"avoided_cost_realised"),0) -> 0 | I230: =IF(D230=1,SUMIFS(Benefits!$S$4:$S$703,Benefits!$B$4:$B$703,A230,Benefits!$F$4:$F$703,B230,Benefits!$R$4:$R$703,"capacity_converted"),0) -> 22629.87 | J230: =SUM(F230:I230) -> 339479.87 | K230: =J230-E230 -> 307829.87 | L230: =IF(D230=1,L229+K230,0) -> -78670.336 | M230: =IF(D230=1,1/(1+Controls!$B$11)^B230,0) -> 0.93787941 | N230: =K230*M230 -> 288707.3 | O230: =IF(D230=1,O229+N230,0) -> -148224.81 | P230: =IF(AND(D230=1,L230<0),1,0) -> 1 | Q230: =IF(AND(D230=1,O230<0),1,0) -> 1
A231: init-007 | B231: 11 | C231: =IF(COUNTIF('Scenario inputs'!$A$4:$A$213,Controls!$B$3&"|"&A231)>0,1,0) -> 1 | D231: =IF(AND(C231=1,B231<Controls!$B$12),1,0) -> 1 | E231: =IF(D231=1,SUMPRODUCT((Costs!$B$4:$B$903=A231)*(Costs!$D$4:$D$903="planned")*(Costs!$J$4:$J$903<=B231)*(Costs!$K$4:$K$903>B231)*Costs!$E$4:$E$903),0) -> 31650 | F231: =IF(D231=1,SUMIFS(Benefits!$S$4:$S$703,Benefits!$B$4:$B$703,A231,Benefits!$F$4:$F$703,B231,Benefits!$R$4:$R$703,"cash"),0) -> 0 | G231: =IF(D231=1,SUMIFS(Benefits!$S$4:$S$703,Benefits!$B$4:$B$703,A231,Benefits!$F$4:$F$703,B231,Benefits!$R$4:$R$703,"revenue"),0) -> 316850 | H231: =IF(D231=1,SUMIFS(Benefits!$S$4:$S$703,Benefits!$B$4:$B$703,A231,Benefits!$F$4:$F$703,B231,Benefits!$R$4:$R$703,"avoided_cost_realised"),0) -> 0 | I231: =IF(D231=1,SUMIFS(Benefits!$S$4:$S$703,Benefits!$B$4:$B$703,A231,Benefits!$F$4:$F$703,B231,Benefits!$R$4:$R$703,"capacity_converted"),0) -> 22629.87 | J231: =SUM(F231:I231) -> 339479.87 | K231: =J231-E231 -> 307829.87 | L231: =IF(D231=1,L230+K231,0) -> 229159.53 | M231: =IF(D231=1,1/(1+Controls!$B$11)^B231,0) -> 0.93188367 | N231: =K231*M231 -> 286861.63 | O231: =IF(D231=1,O230+N231,0) -> 138636.82 | P231: =IF(AND(D231=1,L231<0),1,0) -> 0 | Q231: =IF(AND(D231=1,O231<0),1,0) -> 0
A232: init-007 | B232: 12 | C232: =IF(COUNTIF('Scenario inputs'!$A$4:$A$213,Controls!$B$3&"|"&A232)>0,1,0) -> 1 | D232: =IF(AND(C232=1,B232<Controls!$B$12),1,0) -> 1 | E232: =IF(D232=1,SUMPRODUCT((Costs!$B$4:$B$903=A232)*(Costs!$D$4:$D$903="planned")*(Costs!$J$4:$J$903<=B232)*(Costs!$K$4:$K$903>B232)*Costs!$E$4:$E$903),0) -> 31650 | F232: =IF(D232=1,SUMIFS(Benefits!$S$4:$S$703,Benefits!$B$4:$B$703,A232,Benefits!$F$4:$F$703,B232,Benefits!$R$4:$R$703,"cash"),0) -> 0 | G232: =IF(D232=1,SUMIFS(Benefits!$S$4:$S$703,Benefits!$B$4:$B$703,A232,Benefits!$F$4:$F$703,B232,Benefits!$R$4:$R$703,"revenue"),0) -> 316850 | H232: =IF(D232=1,SUMIFS(Benefits!$S$4:$S$703,Benefits!$B$4:$B$703,A232,Benefits!$F$4:$F$703,B232,Benefits!$R$4:$R$703,"avoided_cost_realised"),0) -> 0 | I232: =IF(D232=1,SUMIFS(Benefits!$S$4:$S$703,Benefits!$B$4:$B$703,A232,Benefits!$F$4:$F$703,B232,Benefits!$R$4:$R$703,"capacity_converted"),0) -> 22629.87 | J232: =SUM(F232:I232) -> 339479.87 | K232: =J232-E232 -> 307829.87 | L232: =IF(D232=1,L231+K232,0) -> 536989.4 | M232: =IF(D232=1,1/(1+Controls!$B$11)^B232,0) -> 0.92592626 | N232: =K232*M232 -> 285027.76 | O232: =IF(D232=1,O231+N232,0) -> 423664.58 | P232: =IF(AND(D232=1,L232<0),1,0) -> 0 | Q232: =IF(AND(D232=1,O232<0),1,0) -> 0
...

Sheet Golden case
A1: The known answer (P09-GOLD-01) by hand, with formulas, against tests/fixtures/golden/expected.json
A2: Cost 1000 at period 0, net inflows 600 at periods 1 and 2, 10 % annual on annual periods. Blue cells are typed from the fixture; every figure in column C is a formula.
A3: input or figure | B3: value (typed) | C3: formula result | D3: expected.json / hand answer | E3: check
A4: rate per period (annual on annual periods) | B4: 0.1
A5: init-001 net cash flow at period 0 | B5: -1000
A6: init-001 net cash flow at period 1 (600 cash; the 400 capacity hours stay out) | B6: 600
A7: init-001 net cash flow at period 2 | B7: 600
A8: init-001 NPV = -1000 + 600/1.1 + 600/1.1^2 | C8: =B5+B6/(1+B4)+B7/(1+B4)^2 -> 41.322314 | D8: 41.32 | E8: =ROUND(C8,2)=D8 -> TRUE
A9: init-001 NPV exactly 5000/121 | C9: =5000/121 -> 41.322314 | E9: =ABS(C8-C9)<0.000000001 -> TRUE
A10: init-001 simple payback period (first period after the last negative cumulative) | C10: =IF(B5+B6<0,2,1) -> 2 | D10: 2 | E10: =C10=D10 -> TRUE
A11: init-001 simple payback, interpolated (t-1) + (-cum[t-1]) / (cum[t] - cum[t-1]) | C11: =1+(-(B5+B6))/((B5+B6+B7)-(B5+B6)) -> 1.6666667 | D11: 1.6667 | E11: =ROUND(C11,4)=D11 -> TRUE
A12: init-001 discounted payback period | C12: =IF(B5+B6/(1+B4)<0,2,1) -> 2 | D12: 2 | E12: =C12=D12 -> TRUE
A13: init-001 discounted payback, interpolated | C13: =1+(-(B5+B6/(1+B4)))/((B7/(1+B4)^2)) -> 1.9166667 | D13: 1.9167 | E13: =ROUND(C13,4)=D13 -> TRUE
A14: init-002 net cash flow at periods 0, 1, 2 (ramped) | B14: -500, 100, 425
A15: init-002 NPV = -500 + 100/1.1 + 425/1.1^2 = -7000/121 | C15: =-500+100/(1+B4)+425/(1+B4)^2 -> -57.85124 | D15: -57.85 | E15: =ROUND(C15,2)=D15 -> TRUE
A16: init-003 NPV = -800 + 150/1.1^2 = -81800/121 (never pays back) | C16: =-800+150/(1+B4)^2 -> -676.03306 | D16: -676.03 | E16: =ROUND(C16,2)=D16 -> TRUE
A17: sum of the three initiative NPVs = -83800/121 | C17: =C8+C15+C16 -> -692.56198 | D17: -692.56 | E17: =ROUND(C17,2)=D17 -> TRUE
A18: the 75.00 claimed twice (cost-line:CC-4410, period 2), present value 75/1.1^2 = 7500/121 | B18: 75 | C18: =B18/(1+B4)^2 -> 61.983471 | D18: 61.98 | E18: =ROUND(C18,2)=D18 -> TRUE
A19: attributable NPV = plain sum - present value counted twice = -8300/11 | C19: =C17-C18 -> -754.54545 | D19: -754.55 | E19: =ROUND(C19,2)=D19 -> TRUE
A20: simple and discounted paybacks are labelled separately and both are found for init-001 | C20: =AND(C10=2,C12=2,ROUND(C11,4)<>ROUND(C13,4)) -> TRUE | D20: =TRUE() -> TRUE | E20: =C20=D20 -> TRUE

Sheet Assumptions
A1: Assumptions and limits
A3: id | B3: statement
A4: A-01 | B4: Four benefit classes, never summed into one number (D-01): cash and revenue enter the net cash flow; avoided cost enters only with cash_realisation and a non-blank evidence_ref, otherwise it is reported beside the flow; capacity hours never enter unless the scenario's capacity_hourly_rate carries a staffing_change_evidence_ref, when each row becomes a separate derived cash item (hours x rate).
A5: A-02 | B5: A recurring cost is one row per period of its half-open range [start_period, end_period); a one-time cost sits in exactly its period_index (D-01, D-P9-16). Only planned rows enter the flow.
A6: A-03 | B6: NPV = sum over t < horizon of net_t / (1 + r)^t with r the period rate: the declared rate when its basis is the period basis, else the recorded 6-place monthly conversion (D-P9-06).
A7: A-04 | B7: Payback (simple and discounted, labelled separately) = the first period after the last negative cumulative, interpolated (t-1) + (-cum[t-1]) / (cum[t] - cum[t-1]); null with a reason (NO_INVESTMENT, NOT_RECOVERED, NO_FLOWS), never 0 (D-09 R9-12).
A8: A-05 | B8: Double count (D-01, R9-02, R9-03): money claims sharing a benefit_source_key in one period across two or more initiatives count once, at the largest (ties: the claim that enters the flow, then the smaller initiative and benefit id). The attributable NPV is the plain sum less the present value of the claims counted twice. Hours follow the same rule separately.
A9: A-06 | B9: The adoption ramp multiplies each benefit row from its own starts_period, the last value held (D-P9-02); the unramped plan is not shown here (it is in the domain's output).
A10: W-01 | B10: Observed, constructed and hypothetical results are kept apart: the NPVs and paybacks are plan estimates of one synthetic draw; the designed relationships are constructed; no real benefit is claimed.
A11: W-02 | B11: TYPED from the independent Python side, not replayed by formulas: which assumption version each scenario uses for each initiative (the pinned one, else the latest created by the scenario's created_at) and therefore its ramp and conversion rate (`Scenario inputs`). Every result is compared with the Python domain after recalculation.
A12: W-03 | B12: Recalculation: openpyxl writes formulas only; the delivered file was recalculated by LibreOffice headless and carries its cached values; Excel was NOT run. fullCalcOnLoad is set so Excel recalculates on open. Functions used: SUMIFS, COUNTIFS, COUNTIF, SUMPRODUCT, INDEX, MATCH, IF, IFERROR, ISNUMBER, AND, OR, NOT, MIN, MAX, SUM, ABS, ROUND, LEN, TRIM, DATE, YEAR, MONTH, DAY, N (no _xlfn functions).
A13: W-04 | B13: Spreadsheet arithmetic is binary floating point; the domain's figures are exact rationals rounded once. Money checks use a tolerance of 0.005 USD; the exact figures are in the SQL analysis and the domain.
A14: W-05 | B14: The rate override (Controls!B4) is an analyst's what-if: while it is set the checks against the domain stand down (they would compare different rates). The workbook has no macros, no external links and no credentials.
A15: W-06 | B15: Rows recorded after a scenario's created_at would not belong to it (R9-01); no row of the published world carries a recorded_at, so every row is used.

Sheet Benefits
A1: 700 benefit rows (typed) and their treatment in the selected scenario (formulas)
A2: row = the line of Scenario inputs for (Controls!B3, initiative), 0 when the initiative is not in the scenario; class follows D-01; money is USD (hours x rate for converted capacity); the double-count columns rank the claims of one source key in one period.
A3: benefit_id | B3: initiative_id | C3: init_no | D3: benefit_no | E3: benefit_type | F3: period_index | G3: starts_period | H3: amount | I3: cash_realisation | J3: evidence_ref | K3: benefit_source_key | L3: baseline_trend | M3: row | N3: in_scenario | O3: ramp_factor | P3: ramped | Q3: capacity_rate | R3: class | S3: money | T3: enters | U3: claim | V3: other_claimants | W3: claim_rank | X3: removed | Y3: removed_pv | Z3: hour_claim | AA3: hour_other | AB3: hour_rank | AC3: hours_removed
A4: b-0001 | B4: init-001 | C4: 1 | D4: 1 | E4: avoided_cost | F4: 1 | G4: 1 | H4: 74750 | I4: =TRUE() -> TRUE | J4: ev:budget-line-001-1 | K4: src-001-late-fee-avoidance | L4: 253.04 | M4: =IFERROR(MATCH(Controls!$B$3&"|"&B4,'Scenario inputs'!$A$4:$A$213,0),0) -> 132 | N4: =IF(M4=0,FALSE(),F4<Controls!$B$12) -> TRUE | O4: =IF(N4,IF(INDEX('Scenario inputs'!$E$4:$E$213,M4)=0,1,INDEX('Scenario inputs'!$F$4:$M$213,M4,MIN(MAX(F4-G4,0),INDEX('Scenario inputs'!$E$4:$E$213,M4)-1)+1)),0) -> 0.035714 | P4: =H4*O4 -> 2669.6215 | Q4: =IF(M4=0,"",IF(ISNUMBER(INDEX('Scenario inputs'!$N$4:$N$213,M4)),INDEX('Scenario inputs'!$N$4:$N$213,M4),"")) -> 31.74 | R4: =IF(NOT(N4),"",IF(OR(E4="cash",E4="revenue"),E4,IF(E4="avoided_cost",IF(AND(I4,LEN(TRIM(J4))>0),"avoided_cost_realised","avoided_cost_beside"),IF(ISNUMBER(Q4),"capacity_converted","capacity_hours")))) -> avoided_cost_realised | S4: =IF(OR(R4="",R4="capacity_hours"),0,IF(R4="capacity_converted",P4*Q4,P4)) -> 2669.6215 | T4: =IF(OR(R4="cash",R4="revenue",R4="avoided_cost_realised",R4="capacity_converted"),1,0) -> 1 | U4: =IF(AND(N4,R4<>"capacity_hours",LEN(K4)>0),1,0) -> 1 | V4: =IF(U4=1,SUMPRODUCT(($K$4:$K$703=K4)*($F$4:$F$703=F4)*($U$4:$U$703=1)*($B$4:$B$703<>B4)),0) -> 0 | W4: =IF(AND(U4=1,V4>0),1+SUMPRODUCT(($K$4:$K$703=K4)*($F$4:$F$703=F4)*($U$4:$U$703=1)*($S$4:$S$703>S4))+SUMPRODUCT(($K$4:$K$703=K4)*($F$4:$F$703=F4)*($U$4:$U$703=1)*($S$4:$S$703=S4)*($T$4:$T$703>T4))+SUMPRODUCT(($K$4:$K$703=K4)*($F$4:$F$703=F4)*($U$4:$U$703=1)*($S$4:$S$703=S4)*($T$4:$T$703=T4)*($C$4:$C$703<C4))+SUMPRODUCT(($K$4:$K$703=K4)*($F$4:$F$703=F4)*($U$4:$U$703=1)*($S$4:$S$703=S4)*($T$4:$T$703=T4)*($C$4:$C$703=C4)*($D$4:$D$703<D4)),0) -> 0 | X4: =IF(AND(U4=1,V4>0,W4>1),S4,0) -> 0 | Y4: =IF(T4=1,X4/(1+Controls!$B$11)^F4,0) -> 0 | Z4: =IF(AND(N4,E4="capacity",LEN(K4)>0),1,0) -> 0 | AA4: =IF(Z4=1,SUMPRODUCT(($K$4:$K$703=K4)*($F$4:$F$703=F4)*($Z$4:$Z$703=1)*($B$4:$B$703<>B4)),0) -> 0 | AB4: =IF(AND(Z4=1,AA4>0),1+SUMPRODUCT(($K$4:$K$703=K4)*($F$4:$F$703=F4)*($Z$4:$Z$703=1)*($P$4:$P$703>P4))+SUMPRODUCT(($K$4:$K$703=K4)*($F$4:$F$703=F4)*($Z$4:$Z$703=1)*($P$4:$P$703=P4)*($C$4:$C$703<C4))+SUMPRODUCT(($K$4:$K$703=K4)*($F$4:$F$703=F4)*($Z$4:$Z$703=1)*($P$4:$P$703=P4)*($C$4:$C$703=C4)*($D$4:$D$703<D4)),0) -> 0 | AC4: =IF(AND(Z4=1,AA4>0,AB4>1),P4,0) -> 0
A5: b-0002 | B5: init-001 | C5: 1 | D5: 2 | E5: avoided_cost | F5: 2 | G5: 1 | H5: 74750 | I5: =TRUE() -> TRUE | J5: ev:budget-line-001-1 | K5: src-001-late-fee-avoidance | L5: 782.86 | M5: =IFERROR(MATCH(Controls!$B$3&"|"&B5,'Scenario inputs'!$A$4:$A$213,0),0) -> 132 | N5: =IF(M5=0,FALSE(),F5<Controls!$B$12) -> TRUE | O5: =IF(N5,IF(INDEX('Scenario inputs'!$E$4:$E$213,M5)=0,1,INDEX('Scenario inputs'!$F$4:$M$213,M5,MIN(MAX(F5-G5,0),INDEX('Scenario inputs'!$E$4:$E$213,M5)-1)+1)),0) -> 0.107143 | P5: =H5*O5 -> 8008.9393 | Q5: =IF(M5=0,"",IF(ISNUMBER(INDEX('Scenario inputs'!$N$4:$N$213,M5)),INDEX('Scenario inputs'!$N$4:$N$213,M5),"")) -> 31.74 | R5: =IF(NOT(N5),"",IF(OR(E5="cash",E5="revenue"),E5,IF(E5="avoided_cost",IF(AND(I5,LEN(TRIM(J5))>0),"avoided_cost_realised","avoided_cost_beside"),IF(ISNUMBER(Q5),"capacity_converted","capacity_hours")))) -> avoided_cost_realised | S5: =IF(OR(R5="",R5="capacity_hours"),0,IF(R5="capacity_converted",P5*Q5,P5)) -> 8008.9393 | T5: =IF(OR(R5="cash",R5="revenue",R5="avoided_cost_realised",R5="capacity_converted"),1,0) -> 1 | U5: =IF(AND(N5,R5<>"capacity_hours",LEN(K5)>0),1,0) -> 1 | V5: =IF(U5=1,SUMPRODUCT(($K$4:$K$703=K5)*($F$4:$F$703=F5)*($U$4:$U$703=1)*($B$4:$B$703<>B5)),0) -> 0 | W5: =IF(AND(U5=1,V5>0),1+SUMPRODUCT(($K$4:$K$703=K5)*($F$4:$F$703=F5)*($U$4:$U$703=1)*($S$4:$S$703>S5))+SUMPRODUCT(($K$4:$K$703=K5)*($F$4:$F$703=F5)*($U$4:$U$703=1)*($S$4:$S$703=S5)*($T$4:$T$703>T5))+SUMPRODUCT(($K$4:$K$703=K5)*($F$4:$F$703=F5)*($U$4:$U$703=1)*($S$4:$S$703=S5)*($T$4:$T$703=T5)*($C$4:$C$703<C5))+SUMPRODUCT(($K$4:$K$703=K5)*($F$4:$F$703=F5)*($U$4:$U$703=1)*($S$4:$S$703=S5)*($T$4:$T$703=T5)*($C$4:$C$703=C5)*($D$4:$D$703<D5)),0) -> 0 | X5: =IF(AND(U5=1,V5>0,W5>1),S5,0) -> 0 | Y5: =IF(T5=1,X5/(1+Controls!$B$11)^F5,0) -> 0 | Z5: =IF(AND(N5,E5="capacity",LEN(K5)>0),1,0) -> 0 | AA5: =IF(Z5=1,SUMPRODUCT(($K$4:$K$703=K5)*($F$4:$F$703=F5)*($Z$4:$Z$703=1)*($B$4:$B$703<>B5)),0) -> 0 | AB5: =IF(AND(Z5=1,AA5>0),1+SUMPRODUCT(($K$4:$K$703=K5)*($F$4:$F$703=F5)*($Z$4:$Z$703=1)*($P$4:$P$703>P5))+SUMPRODUCT(($K$4:$K$703=K5)*($F$4:$F$703=F5)*($Z$4:$Z$703=1)*($P$4:$P$703=P5)*($C$4:$C$703<C5))+SUMPRODUCT(($K$4:$K$703=K5)*($F$4:$F$703=F5)*($Z$4:$Z$703=1)*($P$4:$P$703=P5)*($C$4:$C$703=C5)*($D$4:$D$703<D5)),0) -> 0 | AC5: =IF(AND(Z5=1,AA5>0,AB5>1),P5,0) -> 0
A6: b-0003 | B6: init-001 | C6: 1 | D6: 3 | E6: avoided_cost | F6: 3 | G6: 1 | H6: 74750 | I6: =TRUE() -> TRUE | J6: ev:budget-line-001-1 | K6: src-001-late-fee-avoidance | L6: 1534.09 | M6: =IFERROR(MATCH(Controls!$B$3&"|"&B6,'Scenario inputs'!$A$4:$A$213,0),0) -> 132 | N6: =IF(M6=0,FALSE(),F6<Controls!$B$12) -> TRUE | O6: =IF(N6,IF(INDEX('Scenario inputs'!$E$4:$E$213,M6)=0,1,INDEX('Scenario inputs'!$F$4:$M$213,M6,MIN(MAX(F6-G6,0),INDEX('Scenario inputs'!$E$4:$E$213,M6)-1)+1)),0) -> 0.214286 | P6: =H6*O6 -> 16017.879 | Q6: =IF(M6=0,"",IF(ISNUMBER(INDEX('Scenario inputs'!$N$4:$N$213,M6)),INDEX('Scenario inputs'!$N$4:$N$213,M6),"")) -> 31.74 | R6: =IF(NOT(N6),"",IF(OR(E6="cash",E6="revenue"),E6,IF(E6="avoided_cost",IF(AND(I6,LEN(TRIM(J6))>0),"avoided_cost_realised","avoided_cost_beside"),IF(ISNUMBER(Q6),"capacity_converted","capacity_hours")))) -> avoided_cost_realised | S6: =IF(OR(R6="",R6="capacity_hours"),0,IF(R6="capacity_converted",P6*Q6,P6)) -> 16017.879 | T6: =IF(OR(R6="cash",R6="revenue",R6="avoided_cost_realised",R6="capacity_converted"),1,0) -> 1 | U6: =IF(AND(N6,R6<>"capacity_hours",LEN(K6)>0),1,0) -> 1 | V6: =IF(U6=1,SUMPRODUCT(($K$4:$K$703=K6)*($F$4:$F$703=F6)*($U$4:$U$703=1)*($B$4:$B$703<>B6)),0) -> 0 | W6: =IF(AND(U6=1,V6>0),1+SUMPRODUCT(($K$4:$K$703=K6)*($F$4:$F$703=F6)*($U$4:$U$703=1)*($S$4:$S$703>S6))+SUMPRODUCT(($K$4:$K$703=K6)*($F$4:$F$703=F6)*($U$4:$U$703=1)*($S$4:$S$703=S6)*($T$4:$T$703>T6))+SUMPRODUCT(($K$4:$K$703=K6)*($F$4:$F$703=F6)*($U$4:$U$703=1)*($S$4:$S$703=S6)*($T$4:$T$703=T6)*($C$4:$C$703<C6))+SUMPRODUCT(($K$4:$K$703=K6)*($F$4:$F$703=F6)*($U$4:$U$703=1)*($S$4:$S$703=S6)*($T$4:$T$703=T6)*($C$4:$C$703=C6)*($D$4:$D$703<D6)),0) -> 0 | X6: =IF(AND(U6=1,V6>0,W6>1),S6,0) -> 0 | Y6: =IF(T6=1,X6/(1+Controls!$B$11)^F6,0) -> 0 | Z6: =IF(AND(N6,E6="capacity",LEN(K6)>0),1,0) -> 0 | AA6: =IF(Z6=1,SUMPRODUCT(($K$4:$K$703=K6)*($F$4:$F$703=F6)*($Z$4:$Z$703=1)*($B$4:$B$703<>B6)),0) -> 0 | AB6: =IF(AND(Z6=1,AA6>0),1+SUMPRODUCT(($K$4:$K$703=K6)*($F$4:$F$703=F6)*($Z$4:$Z$703=1)*($P$4:$P$703>P6))+SUMPRODUCT(($K$4:$K$703=K6)*($F$4:$F$703=F6)*($Z$4:$Z$703=1)*($P$4:$P$703=P6)*($C$4:$C$703<C6))+SUMPRODUCT(($K$4:$K$703=K6)*($F$4:$F$703=F6)*($Z$4:$Z$703=1)*($P$4:$P$703=P6)*($C$4:$C$703=C6)*($D$4:$D$703<D6)),0) -> 0 | AC6: =IF(AND(Z6=1,AA6>0,AB6>1),P6,0) -> 0
A7: b-0004 | B7: init-001 | C7: 1 | D7: 4 | E7: avoided_cost | F7: 4 | G7: 1 | H7: 74750 | I7: =TRUE() -> TRUE | J7: ev:budget-line-001-1 | K7: src-001-late-fee-avoidance | L7: 2714.98 | M7: =IFERROR(MATCH(Controls!$B$3&"|"&B7,'Scenario inputs'!$A$4:$A$213,0),0) -> 132 | N7: =IF(M7=0,FALSE(),F7<Controls!$B$12) -> TRUE | O7: =IF(N7,IF(INDEX('Scenario inputs'!$E$4:$E$213,M7)=0,1,INDEX('Scenario inputs'!$F$4:$M$213,M7,MIN(MAX(F7-G7,0),INDEX('Scenario inputs'!$E$4:$E$213,M7)-1)+1)),0) -> 0.357143 | P7: =H7*O7 -> 26696.439 | Q7: =IF(M7=0,"",IF(ISNUMBER(INDEX('Scenario inputs'!$N$4:$N$213,M7)),INDEX('Scenario inputs'!$N$4:$N$213,M7),"")) -> 31.74 | R7: =IF(NOT(N7),"",IF(OR(E7="cash",E7="revenue"),E7,IF(E7="avoided_cost",IF(AND(I7,LEN(TRIM(J7))>0),"avoided_cost_realised","avoided_cost_beside"),IF(ISNUMBER(Q7),"capacity_converted","capacity_hours")))) -> avoided_cost_realised | S7: =IF(OR(R7="",R7="capacity_hours"),0,IF(R7="capacity_converted",P7*Q7,P7)) -> 26696.439 | T7: =IF(OR(R7="cash",R7="revenue",R7="avoided_cost_realised",R7="capacity_converted"),1,0) -> 1 | U7: =IF(AND(N7,R7<>"capacity_hours",LEN(K7)>0),1,0) -> 1 | V7: =IF(U7=1,SUMPRODUCT(($K$4:$K$703=K7)*($F$4:$F$703=F7)*($U$4:$U$703=1)*($B$4:$B$703<>B7)),0) -> 0 | W7: =IF(AND(U7=1,V7>0),1+SUMPRODUCT(($K$4:$K$703=K7)*($F$4:$F$703=F7)*($U$4:$U$703=1)*($S$4:$S$703>S7))+SUMPRODUCT(($K$4:$K$703=K7)*($F$4:$F$703=F7)*($U$4:$U$703=1)*($S$4:$S$703=S7)*($T$4:$T$703>T7))+SUMPRODUCT(($K$4:$K$703=K7)*($F$4:$F$703=F7)*($U$4:$U$703=1)*($S$4:$S$703=S7)*($T$4:$T$703=T7)*($C$4:$C$703<C7))+SUMPRODUCT(($K$4:$K$703=K7)*($F$4:$F$703=F7)*($U$4:$U$703=1)*($S$4:$S$703=S7)*($T$4:$T$703=T7)*($C$4:$C$703=C7)*($D$4:$D$703<D7)),0) -> 0 | X7: =IF(AND(U7=1,V7>0,W7>1),S7,0) -> 0 | Y7: =IF(T7=1,X7/(1+Controls!$B$11)^F7,0) -> 0 | Z7: =IF(AND(N7,E7="capacity",LEN(K7)>0),1,0) -> 0 | AA7: =IF(Z7=1,SUMPRODUCT(($K$4:$K$703=K7)*($F$4:$F$703=F7)*($Z$4:$Z$703=1)*($B$4:$B$703<>B7)),0) -> 0 | AB7: =IF(AND(Z7=1,AA7>0),1+SUMPRODUCT(($K$4:$K$703=K7)*($F$4:$F$703=F7)*($Z$4:$Z$703=1)*($P$4:$P$703>P7))+SUMPRODUCT(($K$4:$K$703=K7)*($F$4:$F$703=F7)*($Z$4:$Z$703=1)*($P$4:$P$703=P7)*($C$4:$C$703<C7))+SUMPRODUCT(($K$4:$K$703=K7)*($F$4:$F$703=F7)*($Z$4:$Z$703=1)*($P$4:$P$703=P7)*($C$4:$C$703=C7)*($D$4:$D$703<D7)),0) -> 0 | AC7: =IF(AND(Z7=1,AA7>0,AB7>1),P7,0) -> 0
A8: b-0005 | B8: init-001 | C8: 1 | D8: 5 | E8: avoided_cost | F8: 5 | G8: 1 | H8: 74750 | I8: =TRUE() -> TRUE | J8: ev:budget-line-001-1 | K8: src-001-late-fee-avoidance | L8: 3795.69 | M8: =IFERROR(MATCH(Controls!$B$3&"|"&B8,'Scenario inputs'!$A$4:$A$213,0),0) -> 132 | N8: =IF(M8=0,FALSE(),F8<Controls!$B$12) -> TRUE | O8: =IF(N8,IF(INDEX('Scenario inputs'!$E$4:$E$213,M8)=0,1,INDEX('Scenario inputs'!$F$4:$M$213,M8,MIN(MAX(F8-G8,0),INDEX('Scenario inputs'!$E$4:$E$213,M8)-1)+1)),0) -> 0.535714 | P8: =H8*O8 -> 40044.622 | Q8: =IF(M8=0,"",IF(ISNUMBER(INDEX('Scenario inputs'!$N$4:$N$213,M8)),INDEX('Scenario inputs'!$N$4:$N$213,M8),"")) -> 31.74 | R8: =IF(NOT(N8),"",IF(OR(E8="cash",E8="revenue"),E8,IF(E8="avoided_cost",IF(AND(I8,LEN(TRIM(J8))>0),"avoided_cost_realised","avoided_cost_beside"),IF(ISNUMBER(Q8),"capacity_converted","capacity_hours")))) -> avoided_cost_realised | S8: =IF(OR(R8="",R8="capacity_hours"),0,IF(R8="capacity_converted",P8*Q8,P8)) -> 40044.622 | T8: =IF(OR(R8="cash",R8="revenue",R8="avoided_cost_realised",R8="capacity_converted"),1,0) -> 1 | U8: =IF(AND(N8,R8<>"capacity_hours",LEN(K8)>0),1,0) -> 1 | V8: =IF(U8=1,SUMPRODUCT(($K$4:$K$703=K8)*($F$4:$F$703=F8)*($U$4:$U$703=1)*($B$4:$B$703<>B8)),0) -> 0 | W8: =IF(AND(U8=1,V8>0),1+SUMPRODUCT(($K$4:$K$703=K8)*($F$4:$F$703=F8)*($U$4:$U$703=1)*($S$4:$S$703>S8))+SUMPRODUCT(($K$4:$K$703=K8)*($F$4:$F$703=F8)*($U$4:$U$703=1)*($S$4:$S$703=S8)*($T$4:$T$703>T8))+SUMPRODUCT(($K$4:$K$703=K8)*($F$4:$F$703=F8)*($U$4:$U$703=1)*($S$4:$S$703=S8)*($T$4:$T$703=T8)*($C$4:$C$703<C8))+SUMPRODUCT(($K$4:$K$703=K8)*($F$4:$F$703=F8)*($U$4:$U$703=1)*($S$4:$S$703=S8)*($T$4:$T$703=T8)*($C$4:$C$703=C8)*($D$4:$D$703<D8)),0) -> 0 | X8: =IF(AND(U8=1,V8>0,W8>1),S8,0) -> 0 | Y8: =IF(T8=1,X8/(1+Controls!$B$11)^F8,0) -> 0 | Z8: =IF(AND(N8,E8="capacity",LEN(K8)>0),1,0) -> 0 | AA8: =IF(Z8=1,SUMPRODUCT(($K$4:$K$703=K8)*($F$4:$F$703=F8)*($Z$4:$Z$703=1)*($B$4:$B$703<>B8)),0) -> 0 | AB8: =IF(AND(Z8=1,AA8>0),1+SUMPRODUCT(($K$4:$K$703=K8)*($F$4:$F$703=F8)*($Z$4:$Z$703=1)*($P$4:$P$703>P8))+SUMPRODUCT(($K$4:$K$703=K8)*($F$4:$F$703=F8)*($Z$4:$Z$703=1)*($P$4:$P$703=P8)*($C$4:$C$703<C8))+SUMPRODUCT(($K$4:$K$703=K8)*($F$4:$F$703=F8)*($Z$4:$Z$703=1)*($P$4:$P$703=P8)*($C$4:$C$703=C8)*($D$4:$D$703<D8)),0) -> 0 | AC8: =IF(AND(Z8=1,AA8>0,AB8>1),P8,0) -> 0
A9: b-0006 | B9: init-001 | C9: 1 | D9: 6 | E9: avoided_cost | F9: 6 | G9: 1 | H9: 74750 | I9: =TRUE() -> TRUE | J9: ev:budget-line-001-1 | K9: src-001-late-fee-avoidance | L9: 5590.74 | M9: =IFERROR(MATCH(Controls!$B$3&"|"&B9,'Scenario inputs'!$A$4:$A$213,0),0) -> 132 | N9: =IF(M9=0,FALSE(),F9<Controls!$B$12) -> TRUE | O9: =IF(N9,IF(INDEX('Scenario inputs'!$E$4:$E$213,M9)=0,1,INDEX('Scenario inputs'!$F$4:$M$213,M9,MIN(MAX(F9-G9,0),INDEX('Scenario inputs'!$E$4:$E$213,M9)-1)+1)),0) -> 0.75 | P9: =H9*O9 -> 56062.5 | Q9: =IF(M9=0,"",IF(ISNUMBER(INDEX('Scenario inputs'!$N$4:$N$213,M9)),INDEX('Scenario inputs'!$N$4:$N$213,M9),"")) -> 31.74 | R9: =IF(NOT(N9),"",IF(OR(E9="cash",E9="revenue"),E9,IF(E9="avoided_cost",IF(AND(I9,LEN(TRIM(J9))>0),"avoided_cost_realised","avoided_cost_beside"),IF(ISNUMBER(Q9),"capacity_converted","capacity_hours")))) -> avoided_cost_realised | S9: =IF(OR(R9="",R9="capacity_hours"),0,IF(R9="capacity_converted",P9*Q9,P9)) -> 56062.5 | T9: =IF(OR(R9="cash",R9="revenue",R9="avoided_cost_realised",R9="capacity_converted"),1,0) -> 1 | U9: =IF(AND(N9,R9<>"capacity_hours",LEN(K9)>0),1,0) -> 1 | V9: =IF(U9=1,SUMPRODUCT(($K$4:$K$703=K9)*($F$4:$F$703=F9)*($U$4:$U$703=1)*($B$4:$B$703<>B9)),0) -> 0 | W9: =IF(AND(U9=1,V9>0),1+SUMPRODUCT(($K$4:$K$703=K9)*($F$4:$F$703=F9)*($U$4:$U$703=1)*($S$4:$S$703>S9))+SUMPRODUCT(($K$4:$K$703=K9)*($F$4:$F$703=F9)*($U$4:$U$703=1)*($S$4:$S$703=S9)*($T$4:$T$703>T9))+SUMPRODUCT(($K$4:$K$703=K9)*($F$4:$F$703=F9)*($U$4:$U$703=1)*($S$4:$S$703=S9)*($T$4:$T$703=T9)*($C$4:$C$703<C9))+SUMPRODUCT(($K$4:$K$703=K9)*($F$4:$F$703=F9)*($U$4:$U$703=1)*($S$4:$S$703=S9)*($T$4:$T$703=T9)*($C$4:$C$703=C9)*($D$4:$D$703<D9)),0) -> 0 | X9: =IF(AND(U9=1,V9>0,W9>1),S9,0) -> 0 | Y9: =IF(T9=1,X9/(1+Controls!$B$11)^F9,0) -> 0 | Z9: =IF(AND(N9,E9="capacity",LEN(K9)>0),1,0) -> 0 | AA9: =IF(Z9=1,SUMPRODUCT(($K$4:$K$703=K9)*($F$4:$F$703=F9)*($Z$4:$Z$703=1)*($B$4:$B$703<>B9)),0) -> 0 | AB9: =IF(AND(Z9=1,AA9>0),1+SUMPRODUCT(($K$4:$K$703=K9)*($F$4:$F$703=F9)*($Z$4:$Z$703=1)*($P$4:$P$703>P9))+SUMPRODUCT(($K$4:$K$703=K9)*($F$4:$F$703=F9)*($Z$4:$Z$703=1)*($P$4:$P$703=P9)*($C$4:$C$703<C9))+SUMPRODUCT(($K$4:$K$703=K9)*($F$4:$F$703=F9)*($Z$4:$Z$703=1)*($P$4:$P$703=P9)*($C$4:$C$703=C9)*($D$4:$D$703<D9)),0) -> 0 | AC9: =IF(AND(Z9=1,AA9>0,AB9>1),P9,0) -> 0
A10: b-0007 | B10: init-001 | C10: 1 | D10: 7 | E10: avoided_cost | F10: 7 | G10: 1 | H10: 74750 | I10: =TRUE() -> TRUE | J10: ev:budget-line-001-1 | K10: src-001-late-fee-avoidance | L10: 7380.52 | M10: =IFERROR(MATCH(Controls!$B$3&"|"&B10,'Scenario inputs'!$A$4:$A$213,0),0) -> 132 | N10: =IF(M10=0,FALSE(),F10<Controls!$B$12) -> TRUE | O10: =IF(N10,IF(INDEX('Scenario inputs'!$E$4:$E$213,M10)=0,1,INDEX('Scenario inputs'!$F$4:$M$213,M10,MIN(MAX(F10-G10,0),INDEX('Scenario inputs'!$E$4:$E$213,M10)-1)+1)),0) -> 1 | P10: =H10*O10 -> 74750 | Q10: =IF(M10=0,"",IF(ISNUMBER(INDEX('Scenario inputs'!$N$4:$N$213,M10)),INDEX('Scenario inputs'!$N$4:$N$213,M10),"")) -> 31.74 | R10: =IF(NOT(N10),"",IF(OR(E10="cash",E10="revenue"),E10,IF(E10="avoided_cost",IF(AND(I10,LEN(TRIM(J10))>0),"avoided_cost_realised","avoided_cost_beside"),IF(ISNUMBER(Q10),"capacity_converted","capacity_hours")))) -> avoided_cost_realised | S10: =IF(OR(R10="",R10="capacity_hours"),0,IF(R10="capacity_converted",P10*Q10,P10)) -> 74750 | T10: =IF(OR(R10="cash",R10="revenue",R10="avoided_cost_realised",R10="capacity_converted"),1,0) -> 1 | U10: =IF(AND(N10,R10<>"capacity_hours",LEN(K10)>0),1,0) -> 1 | V10: =IF(U10=1,SUMPRODUCT(($K$4:$K$703=K10)*($F$4:$F$703=F10)*($U$4:$U$703=1)*($B$4:$B$703<>B10)),0) -> 0 | W10: =IF(AND(U10=1,V10>0),1+SUMPRODUCT(($K$4:$K$703=K10)*($F$4:$F$703=F10)*($U$4:$U$703=1)*($S$4:$S$703>S10))+SUMPRODUCT(($K$4:$K$703=K10)*($F$4:$F$703=F10)*($U$4:$U$703=1)*($S$4:$S$703=S10)*($T$4:$T$703>T10))+SUMPRODUCT(($K$4:$K$703=K10)*($F$4:$F$703=F10)*($U$4:$U$703=1)*($S$4:$S$703=S10)*($T$4:$T$703=T10)*($C$4:$C$703<C10))+SUMPRODUCT(($K$4:$K$703=K10)*($F$4:$F$703=F10)*($U$4:$U$703=1)*($S$4:$S$703=S10)*($T$4:$T$703=T10)*($C$4:$C$703=C10)*($D$4:$D$703<D10)),0) -> 0 | X10: =IF(AND(U10=1,V10>0,W10>1),S10,0) -> 0 | Y10: =IF(T10=1,X10/(1+Controls!$B$11)^F10,0) -> 0 | Z10: =IF(AND(N10,E10="capacity",LEN(K10)>0),1,0) -> 0 | AA10: =IF(Z10=1,SUMPRODUCT(($K$4:$K$703=K10)*($F$4:$F$703=F10)*($Z$4:$Z$703=1)*($B$4:$B$703<>B10)),0) -> 0 | AB10: =IF(AND(Z10=1,AA10>0),1+SUMPRODUCT(($K$4:$K$703=K10)*($F$4:$F$703=F10)*($Z$4:$Z$703=1)*($P$4:$P$703>P10))+SUMPRODUCT(($K$4:$K$703=K10)*($F$4:$F$703=F10)*($Z$4:$Z$703=1)*($P$4:$P$703=P10)*($C$4:$C$703<C10))+SUMPRODUCT(($K$4:$K$703=K10)*($F$4:$F$703=F10)*($Z$4:$Z$703=1)*($P$4:$P$703=P10)*($C$4:$C$703=C10)*($D$4:$D$703<D10)),0) -> 0 | AC10: =IF(AND(Z10=1,AA10>0,AB10>1),P10,0) -> 0
A11: b-0008 | B11: init-001 | C11: 1 | D11: 8 | E11: avoided_cost | F11: 8 | G11: 1 | H11: 74750 | I11: =TRUE() -> TRUE | J11: ev:budget-line-001-1 | K11: src-001-late-fee-avoidance | L11: 7232.91 | M11: =IFERROR(MATCH(Controls!$B$3&"|"&B11,'Scenario inputs'!$A$4:$A$213,0),0) -> 132 | N11: =IF(M11=0,FALSE(),F11<Controls!$B$12) -> TRUE | O11: =IF(N11,IF(INDEX('Scenario inputs'!$E$4:$E$213,M11)=0,1,INDEX('Scenario inputs'!$F$4:$M$213,M11,MIN(MAX(F11-G11,0),INDEX('Scenario inputs'!$E$4:$E$213,M11)-1)+1)),0) -> 1 | P11: =H11*O11 -> 74750 | Q11: =IF(M11=0,"",IF(ISNUMBER(INDEX('Scenario inputs'!$N$4:$N$213,M11)),INDEX('Scenario inputs'!$N$4:$N$213,M11),"")) -> 31.74 | R11: =IF(NOT(N11),"",IF(OR(E11="cash",E11="revenue"),E11,IF(E11="avoided_cost",IF(AND(I11,LEN(TRIM(J11))>0),"avoided_cost_realised","avoided_cost_beside"),IF(ISNUMBER(Q11),"capacity_converted","capacity_hours")))) -> avoided_cost_realised | S11: =IF(OR(R11="",R11="capacity_hours"),0,IF(R11="capacity_converted",P11*Q11,P11)) -> 74750 | T11: =IF(OR(R11="cash",R11="revenue",R11="avoided_cost_realised",R11="capacity_converted"),1,0) -> 1 | U11: =IF(AND(N11,R11<>"capacity_hours",LEN(K11)>0),1,0) -> 1 | V11: =IF(U11=1,SUMPRODUCT(($K$4:$K$703=K11)*($F$4:$F$703=F11)*($U$4:$U$703=1)*($B$4:$B$703<>B11)),0) -> 0 | W11: =IF(AND(U11=1,V11>0),1+SUMPRODUCT(($K$4:$K$703=K11)*($F$4:$F$703=F11)*($U$4:$U$703=1)*($S$4:$S$703>S11))+SUMPRODUCT(($K$4:$K$703=K11)*($F$4:$F$703=F11)*($U$4:$U$703=1)*($S$4:$S$703=S11)*($T$4:$T$703>T11))+SUMPRODUCT(($K$4:$K$703=K11)*($F$4:$F$703=F11)*($U$4:$U$703=1)*($S$4:$S$703=S11)*($T$4:$T$703=T11)*($C$4:$C$703<C11))+SUMPRODUCT(($K$4:$K$703=K11)*($F$4:$F$703=F11)*($U$4:$U$703=1)*($S$4:$S$703=S11)*($T$4:$T$703=T11)*($C$4:$C$703=C11)*($D$4:$D$703<D11)),0) -> 0 | X11: =IF(AND(U11=1,V11>0,W11>1),S11,0) -> 0 | Y11: =IF(T11=1,X11/(1+Controls!$B$11)^F11,0) -> 0 | Z11: =IF(AND(N11,E11="capacity",LEN(K11)>0),1,0) -> 0 | AA11: =IF(Z11=1,SUMPRODUCT(($K$4:$K$703=K11)*($F$4:$F$703=F11)*($Z$4:$Z$703=1)*($B$4:$B$703<>B11)),0) -> 0 | AB11: =IF(AND(Z11=1,AA11>0),1+SUMPRODUCT(($K$4:$K$703=K11)*($F$4:$F$703=F11)*($Z$4:$Z$703=1)*($P$4:$P$703>P11))+SUMPRODUCT(($K$4:$K$703=K11)*($F$4:$F$703=F11)*($Z$4:$Z$703=1)*($P$4:$P$703=P11)*($C$4:$C$703<C11))+SUMPRODUCT(($K$4:$K$703=K11)*($F$4:$F$703=F11)*($Z$4:$Z$703=1)*($P$4:$P$703=P11)*($C$4:$C$703=C11)*($D$4:$D$703<D11)),0) -> 0 | AC11: =IF(AND(Z11=1,AA11>0,AB11>1),P11,0) -> 0
A12: b-0009 | B12: init-001 | C12: 1 | D12: 9 | E12: avoided_cost | F12: 9 | G12: 1 | H12: 74750 | I12: =TRUE() -> TRUE | J12: ev:budget-line-001-1 | K12: src-001-late-fee-avoidance | L12: 8386.95 | M12: =IFERROR(MATCH(Controls!$B$3&"|"&B12,'Scenario inputs'!$A$4:$A$213,0),0) -> 132 | N12: =IF(M12=0,FALSE(),F12<Controls!$B$12) -> TRUE | O12: =IF(N12,IF(INDEX('Scenario inputs'!$E$4:$E$213,M12)=0,1,INDEX('Scenario inputs'!$F$4:$M$213,M12,MIN(MAX(F12-G12,0),INDEX('Scenario inputs'!$E$4:$E$213,M12)-1)+1)),0) -> 1 | P12: =H12*O12 -> 74750 | Q12: =IF(M12=0,"",IF(ISNUMBER(INDEX('Scenario inputs'!$N$4:$N$213,M12)),INDEX('Scenario inputs'!$N$4:$N$213,M12),"")) -> 31.74 | R12: =IF(NOT(N12),"",IF(OR(E12="cash",E12="revenue"),E12,IF(E12="avoided_cost",IF(AND(I12,LEN(TRIM(J12))>0),"avoided_cost_realised","avoided_cost_beside"),IF(ISNUMBER(Q12),"capacity_converted","capacity_hours")))) -> avoided_cost_realised | S12: =IF(OR(R12="",R12="capacity_hours"),0,IF(R12="capacity_converted",P12*Q12,P12)) -> 74750 | T12: =IF(OR(R12="cash",R12="revenue",R12="avoided_cost_realised",R12="capacity_converted"),1,0) -> 1 | U12: =IF(AND(N12,R12<>"capacity_hours",LEN(K12)>0),1,0) -> 1 | V12: =IF(U12=1,SUMPRODUCT(($K$4:$K$703=K12)*($F$4:$F$703=F12)*($U$4:$U$703=1)*($B$4:$B$703<>B12)),0) -> 0 | W12: =IF(AND(U12=1,V12>0),1+SUMPRODUCT(($K$4:$K$703=K12)*($F$4:$F$703=F12)*($U$4:$U$703=1)*($S$4:$S$703>S12))+SUMPRODUCT(($K$4:$K$703=K12)*($F$4:$F$703=F12)*($U$4:$U$703=1)*($S$4:$S$703=S12)*($T$4:$T$703>T12))+SUMPRODUCT(($K$4:$K$703=K12)*($F$4:$F$703=F12)*($U$4:$U$703=1)*($S$4:$S$703=S12)*($T$4:$T$703=T12)*($C$4:$C$703<C12))+SUMPRODUCT(($K$4:$K$703=K12)*($F$4:$F$703=F12)*($U$4:$U$703=1)*($S$4:$S$703=S12)*($T$4:$T$703=T12)*($C$4:$C$703=C12)*($D$4:$D$703<D12)),0) -> 0 | X12: =IF(AND(U12=1,V12>0,W12>1),S12,0) -> 0 | Y12: =IF(T12=1,X12/(1+Controls!$B$11)^F12,0) -> 0 | Z12: =IF(AND(N12,E12="capacity",LEN(K12)>0),1,0) -> 0 | AA12: =IF(Z12=1,SUMPRODUCT(($K$4:$K$703=K12)*($F$4:$F$703=F12)*($Z$4:$Z$703=1)*($B$4:$B$703<>B12)),0) -> 0 | AB12: =IF(AND(Z12=1,AA12>0),1+SUMPRODUCT(($K$4:$K$703=K12)*($F$4:$F$703=F12)*($Z$4:$Z$703=1)*($P$4:$P$703>P12))+SUMPRODUCT(($K$4:$K$703=K12)*($F$4:$F$703=F12)*($Z$4:$Z$703=1)*($P$4:$P$703=P12)*($C$4:$C$703<C12))+SUMPRODUCT(($K$4:$K$703=K12)*($F$4:$F$703=F12)*($Z$4:$Z$703=1)*($P$4:$P$703=P12)*($C$4:$C$703=C12)*($D$4:$D$703<D12)),0) -> 0 | AC12: =IF(AND(Z12=1,AA12>0,AB12>1),P12,0) -> 0
A13: b-0010 | B13: init-001 | C13: 1 | D13: 10 | E13: avoided_cost | F13: 10 | G13: 1 | H13: 74750 | I13: =TRUE() -> TRUE | J13: ev:budget-line-001-1 | K13: src-001-late-fee-avoidance | L13: 8386.95 | M13: =IFERROR(MATCH(Controls!$B$3&"|"&B13,'Scenario inputs'!$A$4:$A$213,0),0) -> 132 | N13: =IF(M13=0,FALSE(),F13<Controls!$B$12) -> TRUE | O13: =IF(N13,IF(INDEX('Scenario inputs'!$E$4:$E$213,M13)=0,1,INDEX('Scenario inputs'!$F$4:$M$213,M13,MIN(MAX(F13-G13,0),INDEX('Scenario inputs'!$E$4:$E$213,M13)-1)+1)),0) -> 1 | P13: =H13*O13 -> 74750 | Q13: =IF(M13=0,"",IF(ISNUMBER(INDEX('Scenario inputs'!$N$4:$N$213,M13)),INDEX('Scenario inputs'!$N$4:$N$213,M13),"")) -> 31.74 | R13: =IF(NOT(N13),"",IF(OR(E13="cash",E13="revenue"),E13,IF(E13="avoided_cost",IF(AND(I13,LEN(TRIM(J13))>0),"avoided_cost_realised","avoided_cost_beside"),IF(ISNUMBER(Q13),"capacity_converted","capacity_hours")))) -> avoided_cost_realised | S13: =IF(OR(R13="",R13="capacity_hours"),0,IF(R13="capacity_converted",P13*Q13,P13)) -> 74750 | T13: =IF(OR(R13="cash",R13="revenue",R13="avoided_cost_realised",R13="capacity_converted"),1,0) -> 1 | U13: =IF(AND(N13,R13<>"capacity_hours",LEN(K13)>0),1,0) -> 1 | V13: =IF(U13=1,SUMPRODUCT(($K$4:$K$703=K13)*($F$4:$F$703=F13)*($U$4:$U$703=1)*($B$4:$B$703<>B13)),0) -> 0 | W13: =IF(AND(U13=1,V13>0),1+SUMPRODUCT(($K$4:$K$703=K13)*($F$4:$F$703=F13)*($U$4:$U$703=1)*($S$4:$S$703>S13))+SUMPRODUCT(($K$4:$K$703=K13)*($F$4:$F$703=F13)*($U$4:$U$703=1)*($S$4:$S$703=S13)*($T$4:$T$703>T13))+SUMPRODUCT(($K$4:$K$703=K13)*($F$4:$F$703=F13)*($U$4:$U$703=1)*($S$4:$S$703=S13)*($T$4:$T$703=T13)*($C$4:$C$703<C13))+SUMPRODUCT(($K$4:$K$703=K13)*($F$4:$F$703=F13)*($U$4:$U$703=1)*($S$4:$S$703=S13)*($T$4:$T$703=T13)*($C$4:$C$703=C13)*($D$4:$D$703<D13)),0) -> 0 | X13: =IF(AND(U13=1,V13>0,W13>1),S13,0) -> 0 | Y13: =IF(T13=1,X13/(1+Controls!$B$11)^F13,0) -> 0 | Z13: =IF(AND(N13,E13="capacity",LEN(K13)>0),1,0) -> 0 | AA13: =IF(Z13=1,SUMPRODUCT(($K$4:$K$703=K13)*($F$4:$F$703=F13)*($Z$4:$Z$703=1)*($B$4:$B$703<>B13)),0) -> 0 | AB13: =IF(AND(Z13=1,AA13>0),1+SUMPRODUCT(($K$4:$K$703=K13)*($F$4:$F$703=F13)*($Z$4:$Z$703=1)*($P$4:$P$703>P13))+SUMPRODUCT(($K$4:$K$703=K13)*($F$4:$F$703=F13)*($Z$4:$Z$703=1)*($P$4:$P$703=P13)*($C$4:$C$703<C13))+SUMPRODUCT(($K$4:$K$703=K13)*($F$4:$F$703=F13)*($Z$4:$Z$703=1)*($P$4:$P$703=P13)*($C$4:$C$703=C13)*($D$4:$D$703<D13)),0) -> 0 | AC13: =IF(AND(Z13=1,AA13>0,AB13>1),P13,0) -> 0
A14: b-0011 | B14: init-001 | C14: 1 | D14: 11 | E14: avoided_cost | F14: 11 | G14: 1 | H14: 74750 | I14: =TRUE() -> TRUE | J14: ev:budget-line-001-1 | K14: src-001-late-fee-avoidance | L14: 8386.95 | M14: =IFERROR(MATCH(Controls!$B$3&"|"&B14,'Scenario inputs'!$A$4:$A$213,0),0) -> 132 | N14: =IF(M14=0,FALSE(),F14<Controls!$B$12) -> TRUE | O14: =IF(N14,IF(INDEX('Scenario inputs'!$E$4:$E$213,M14)=0,1,INDEX('Scenario inputs'!$F$4:$M$213,M14,MIN(MAX(F14-G14,0),INDEX('Scenario inputs'!$E$4:$E$213,M14)-1)+1)),0) -> 1 | P14: =H14*O14 -> 74750 | Q14: =IF(M14=0,"",IF(ISNUMBER(INDEX('Scenario inputs'!$N$4:$N$213,M14)),INDEX('Scenario inputs'!$N$4:$N$213,M14),"")) -> 31.74 | R14: =IF(NOT(N14),"",IF(OR(E14="cash",E14="revenue"),E14,IF(E14="avoided_cost",IF(AND(I14,LEN(TRIM(J14))>0),"avoided_cost_realised","avoided_cost_beside"),IF(ISNUMBER(Q14),"capacity_converted","capacity_hours")))) -> avoided_cost_realised | S14: =IF(OR(R14="",R14="capacity_hours"),0,IF(R14="capacity_converted",P14*Q14,P14)) -> 74750 | T14: =IF(OR(R14="cash",R14="revenue",R14="avoided_cost_realised",R14="capacity_converted"),1,0) -> 1 | U14: =IF(AND(N14,R14<>"capacity_hours",LEN(K14)>0),1,0) -> 1 | V14: =IF(U14=1,SUMPRODUCT(($K$4:$K$703=K14)*($F$4:$F$703=F14)*($U$4:$U$703=1)*($B$4:$B$703<>B14)),0) -> 0 | W14: =IF(AND(U14=1,V14>0),1+SUMPRODUCT(($K$4:$K$703=K14)*($F$4:$F$703=F14)*($U$4:$U$703=1)*($S$4:$S$703>S14))+SUMPRODUCT(($K$4:$K$703=K14)*($F$4:$F$703=F14)*($U$4:$U$703=1)*($S$4:$S$703=S14)*($T$4:$T$703>T14))+SUMPRODUCT(($K$4:$K$703=K14)*($F$4:$F$703=F14)*($U$4:$U$703=1)*($S$4:$S$703=S14)*($T$4:$T$703=T14)*($C$4:$C$703<C14))+SUMPRODUCT(($K$4:$K$703=K14)*($F$4:$F$703=F14)*($U$4:$U$703=1)*($S$4:$S$703=S14)*($T$4:$T$703=T14)*($C$4:$C$703=C14)*($D$4:$D$703<D14)),0) -> 0 | X14: =IF(AND(U14=1,V14>0,W14>1),S14,0) -> 0 | Y14: =IF(T14=1,X14/(1+Controls!$B$11)^F14,0) -> 0 | Z14: =IF(AND(N14,E14="capacity",LEN(K14)>0),1,0) -> 0 | AA14: =IF(Z14=1,SUMPRODUCT(($K$4:$K$703=K14)*($F$4:$F$703=F14)*($Z$4:$Z$703=1)*($B$4:$B$703<>B14)),0) -> 0 | AB14: =IF(AND(Z14=1,AA14>0),1+SUMPRODUCT(($K$4:$K$703=K14)*($F$4:$F$703=F14)*($Z$4:$Z$703=1)*($P$4:$P$703>P14))+SUMPRODUCT(($K$4:$K$703=K14)*($F$4:$F$703=F14)*($Z$4:$Z$703=1)*($P$4:$P$703=P14)*($C$4:$C$703<C14))+SUMPRODUCT(($K$4:$K$703=K14)*($F$4:$F$703=F14)*($Z$4:$Z$703=1)*($P$4:$P$703=P14)*($C$4:$C$703=C14)*($D$4:$D$703<D14)),0) -> 0 | AC14: =IF(AND(Z14=1,AA14>0,AB14>1),P14,0) -> 0
A15: b-0012 | B15: init-001 | C15: 1 | D15: 12 | E15: avoided_cost | F15: 12 | G15: 1 | H15: 74750 | I15: =TRUE() -> TRUE | J15: ev:budget-line-001-1 | K15: src-001-late-fee-avoidance | L15: 8386.95 | M15: =IFERROR(MATCH(Controls!$B$3&"|"&B15,'Scenario inputs'!$A$4:$A$213,0),0) -> 132 | N15: =IF(M15=0,FALSE(),F15<Controls!$B$12) -> TRUE | O15: =IF(N15,IF(INDEX('Scenario inputs'!$E$4:$E$213,M15)=0,1,INDEX('Scenario inputs'!$F$4:$M$213,M15,MIN(MAX(F15-G15,0),INDEX('Scenario inputs'!$E$4:$E$213,M15)-1)+1)),0) -> 1 | P15: =H15*O15 -> 74750 | Q15: =IF(M15=0,"",IF(ISNUMBER(INDEX('Scenario inputs'!$N$4:$N$213,M15)),INDEX('Scenario inputs'!$N$4:$N$213,M15),"")) -> 31.74 | R15: =IF(NOT(N15),"",IF(OR(E15="cash",E15="revenue"),E15,IF(E15="avoided_cost",IF(AND(I15,LEN(TRIM(J15))>0),"avoided_cost_realised","avoided_cost_beside"),IF(ISNUMBER(Q15),"capacity_converted","capacity_hours")))) -> avoided_cost_realised | S15: =IF(OR(R15="",R15="capacity_hours"),0,IF(R15="capacity_converted",P15*Q15,P15)) -> 74750 | T15: =IF(OR(R15="cash",R15="revenue",R15="avoided_cost_realised",R15="capacity_converted"),1,0) -> 1 | U15: =IF(AND(N15,R15<>"capacity_hours",LEN(K15)>0),1,0) -> 1 | V15: =IF(U15=1,SUMPRODUCT(($K$4:$K$703=K15)*($F$4:$F$703=F15)*($U$4:$U$703=1)*($B$4:$B$703<>B15)),0) -> 0 | W15: =IF(AND(U15=1,V15>0),1+SUMPRODUCT(($K$4:$K$703=K15)*($F$4:$F$703=F15)*($U$4:$U$703=1)*($S$4:$S$703>S15))+SUMPRODUCT(($K$4:$K$703=K15)*($F$4:$F$703=F15)*($U$4:$U$703=1)*($S$4:$S$703=S15)*($T$4:$T$703>T15))+SUMPRODUCT(($K$4:$K$703=K15)*($F$4:$F$703=F15)*($U$4:$U$703=1)*($S$4:$S$703=S15)*($T$4:$T$703=T15)*($C$4:$C$703<C15))+SUMPRODUCT(($K$4:$K$703=K15)*($F$4:$F$703=F15)*($U$4:$U$703=1)*($S$4:$S$703=S15)*($T$4:$T$703=T15)*($C$4:$C$703=C15)*($D$4:$D$703<D15)),0) -> 0 | X15: =IF(AND(U15=1,V15>0,W15>1),S15,0) -> 0 | Y15: =IF(T15=1,X15/(1+Controls!$B$11)^F15,0) -> 0 | Z15: =IF(AND(N15,E15="capacity",LEN(K15)>0),1,0) -> 0 | AA15: =IF(Z15=1,SUMPRODUCT(($K$4:$K$703=K15)*($F$4:$F$703=F15)*($Z$4:$Z$703=1)*($B$4:$B$703<>B15)),0) -> 0 | AB15: =IF(AND(Z15=1,AA15>0),1+SUMPRODUCT(($K$4:$K$703=K15)*($F$4:$F$703=F15)*($Z$4:$Z$703=1)*($P$4:$P$703>P15))+SUMPRODUCT(($K$4:$K$703=K15)*($F$4:$F$703=F15)*($Z$4:$Z$703=1)*($P$4:$P$703=P15)*($C$4:$C$703<C15))+SUMPRODUCT(($K$4:$K$703=K15)*($F$4:$F$703=F15)*($Z$4:$Z$703=1)*($P$4:$P$703=P15)*($C$4:$C$703=C15)*($D$4:$D$703<D15)),0) -> 0 | AC15: =IF(AND(Z15=1,AA15>0,AB15>1),P15,0) -> 0
A16: b-0013 | B16: init-001 | C16: 1 | D16: 13 | E16: cash | F16: 2 | G16: 2 | H16: 112150 | I16: =FALSE() -> FALSE | K16: src-001-early-payment-discounts | L16: 300.34 | M16: =IFERROR(MATCH(Controls!$B$3&"|"&B16,'Scenario inputs'!$A$4:$A$213,0),0) -> 132 | N16: =IF(M16=0,FALSE(),F16<Controls!$B$12) -> TRUE | O16: =IF(N16,IF(INDEX('Scenario inputs'!$E$4:$E$213,M16)=0,1,INDEX('Scenario inputs'!$F$4:$M$213,M16,MIN(MAX(F16-G16,0),INDEX('Scenario inputs'!$E$4:$E$213,M16)-1)+1)),0) -> 0.035714 | P16: =H16*O16 -> 4005.3251 | Q16: =IF(M16=0,"",IF(ISNUMBER(INDEX('Scenario inputs'!$N$4:$N$213,M16)),INDEX('Scenario inputs'!$N$4:$N$213,M16),"")) -> 31.74 | R16: =IF(NOT(N16),"",IF(OR(E16="cash",E16="revenue"),E16,IF(E16="avoided_cost",IF(AND(I16,LEN(TRIM(J16))>0),"avoided_cost_realised","avoided_cost_beside"),IF(ISNUMBER(Q16),"capacity_converted","capacity_hours")))) -> cash | S16: =IF(OR(R16="",R16="capacity_hours"),0,IF(R16="capacity_converted",P16*Q16,P16)) -> 4005.3251 | T16: =IF(OR(R16="cash",R16="revenue",R16="avoided_cost_realised",R16="capacity_converted"),1,0) -> 1 | U16: =IF(AND(N16,R16<>"capacity_hours",LEN(K16)>0),1,0) -> 1 | V16: =IF(U16=1,SUMPRODUCT(($K$4:$K$703=K16)*($F$4:$F$703=F16)*($U$4:$U$703=1)*($B$4:$B$703<>B16)),0) -> 0 | W16: =IF(AND(U16=1,V16>0),1+SUMPRODUCT(($K$4:$K$703=K16)*($F$4:$F$703=F16)*($U$4:$U$703=1)*($S$4:$S$703>S16))+SUMPRODUCT(($K$4:$K$703=K16)*($F$4:$F$703=F16)*($U$4:$U$703=1)*($S$4:$S$703=S16)*($T$4:$T$703>T16))+SUMPRODUCT(($K$4:$K$703=K16)*($F$4:$F$703=F16)*($U$4:$U$703=1)*($S$4:$S$703=S16)*($T$4:$T$703=T16)*($C$4:$C$703<C16))+SUMPRODUCT(($K$4:$K$703=K16)*($F$4:$F$703=F16)*($U$4:$U$703=1)*($S$4:$S$703=S16)*($T$4:$T$703=T16)*($C$4:$C$703=C16)*($D$4:$D$703<D16)),0) -> 0 | X16: =IF(AND(U16=1,V16>0,W16>1),S16,0) -> 0 | Y16: =IF(T16=1,X16/(1+Controls!$B$11)^F16,0) -> 0 | Z16: =IF(AND(N16,E16="capacity",LEN(K16)>0),1,0) -> 0 | AA16: =IF(Z16=1,SUMPRODUCT(($K$4:$K$703=K16)*($F$4:$F$703=F16)*($Z$4:$Z$703=1)*($B$4:$B$703<>B16)),0) -> 0 | AB16: =IF(AND(Z16=1,AA16>0),1+SUMPRODUCT(($K$4:$K$703=K16)*($F$4:$F$703=F16)*($Z$4:$Z$703=1)*($P$4:$P$703>P16))+SUMPRODUCT(($K$4:$K$703=K16)*($F$4:$F$703=F16)*($Z$4:$Z$703=1)*($P$4:$P$703=P16)*($C$4:$C$703<C16))+SUMPRODUCT(($K$4:$K$703=K16)*($F$4:$F$703=F16)*($Z$4:$Z$703=1)*($P$4:$P$703=P16)*($C$4:$C$703=C16)*($D$4:$D$703<D16)),0) -> 0 | AC16: =IF(AND(Z16=1,AA16>0,AB16>1),P16,0) -> 0
